Workbook

Sheet BASE_ABASTECIMENTO
A1: DATA | B1: SEMANA ANO | C1: PLATAFORMA | D1: VALOR | E1: EQUIPE | F1: CENTRO DE CUSTO | G1: PLACA | H1: OBS | I1: MÊS/ANO
A2: 46076 | B2: =WEEKNUM(A2,21) -> 9 | C2: TICKETLOG | D2: 80 | E2: MANFAC-1 | F2: =VLOOKUP(E2,BASE_VEICULOS!A:G,7,0) -> FAC - 140004 - MANUTENÇÃO PREDIAL DPSP 2025 | G2: =IFERROR(VLOOKUP(E2,BASE_VEICULOS!$A:$B,2,0),"") -> TEW9A25 | I2: =DATE(YEAR(A2),MONTH(A2),1) -> 46054
A3: 46076 | B3: =WEEKNUM(A3,21) -> 9 | C3: TICKETLOG | D3: 150 | E3: MANFAC-2 | F3: =VLOOKUP(E3,BASE_VEICULOS!A:G,7,0) -> PROF - 07001 - MANUTENÇÃO PREDIAL- PROFARMA-2025 | G3: =IFERROR(VLOOKUP(E3,BASE_VEICULOS!$A:$B,2,0),"") -> TEW9A28 | I3: =DATE(YEAR(A3),MONTH(A3),1) -> 46054
A4: 46076 | B4: =WEEKNUM(A4,21) -> 9 | C4: TICKETLOG | D4: 79.98 | E4: MANFAC-3 | F4: =VLOOKUP(E4,BASE_VEICULOS!A:G,7,0) -> FAC - 140004 - MANUTENÇÃO PREDIAL DPSP 2025 | G4: =IFERROR(VLOOKUP(E4,BASE_VEICULOS!$A:$B,2,0),"") -> FIL8C14 | I4: =DATE(YEAR(A4),MONTH(A4),1) -> 46054
A5: 46076 | B5: =WEEKNUM(A5,21) -> 9 | C5: TICKETLOG | D5: 79.98 | E5: MANFAC-4 | F5: =VLOOKUP(E5,BASE_VEICULOS!A:G,7,0) -> FAC - 140005 - SPOT MANUTENÇÃO DPSP 2025 | G5: =IFERROR(VLOOKUP(E5,BASE_VEICULOS!$A:$B,2,0),"") -> FGO3C61 | I5: =DATE(YEAR(A5),MONTH(A5),1) -> 46054
A6: 46076 | B6: =WEEKNUM(A6,21) -> 9 | C6: TICKETLOG | D6: 90 | E6: MANFAC-5 | F6: =VLOOKUP(E6,BASE_VEICULOS!A:G,7,0) -> FAC - 140004 - MANUTENÇÃO PREDIAL DPSP 2025 | G6: =IFERROR(VLOOKUP(E6,BASE_VEICULOS!$A:$B,2,0),"") -> FOK8A73 | I6: =DATE(YEAR(A6),MONTH(A6),1) -> 46054
A7: 46076 | B7: =WEEKNUM(A7,21) -> 9 | C7: TICKETLOG | D7: 70 | E7: MANFAC-6 | F7: =VLOOKUP(E7,BASE_VEICULOS!A:G,7,0) -> FAC - 140005 - SPOT MANUTENÇÃO DPSP 2025 | G7: =IFERROR(VLOOKUP(E7,BASE_VEICULOS!$A:$B,2,0),"") -> EWH1B84 | I7: =DATE(YEAR(A7),MONTH(A7),1) -> 46054
A8: 46076 | B8: =WEEKNUM(A8,21) -> 9 | C8: TICKETLOG | D8: 80 | E8: MANFAC-7 | F8: =VLOOKUP(E8,BASE_VEICULOS!A:G,7,0) -> FAC - 140005 - SPOT MANUTENÇÃO DPSP 2025 | G8: =IFERROR(VLOOKUP(E8,BASE_VEICULOS!$A:$B,2,0),"") -> TEW9A27 | I8: =DATE(YEAR(A8),MONTH(A8),1) -> 46054
A9: 46076 | B9: =WEEKNUM(A9,21) -> 9 | C9: TICKETLOG | D9: 119.97 | E9: MANFAC-8 | F9: =VLOOKUP(E9,BASE_VEICULOS!A:G,7,0) -> #N/A | G9: =IFERROR(VLOOKUP(E9,BASE_VEICULOS!$A:$B,2,0),"") | I9: =DATE(YEAR(A9),MONTH(A9),1) -> 46054
A10: 46076 | B10: =WEEKNUM(A10,21) -> 9 | C10: TICKETLOG | D10: 200 | E10: MANFAC-9 | F10: =VLOOKUP(E10,BASE_VEICULOS!A:G,7,0) -> FAC - 140004 - MANUTENÇÃO PREDIAL DPSP 2025 | G10: =IFERROR(VLOOKUP(E10,BASE_VEICULOS!$A:$B,2,0),"") -> TEW9A29 | I10: =DATE(YEAR(A10),MONTH(A10),1) -> 46054
A11: 46076 | B11: =WEEKNUM(A11,21) -> 9 | C11: TICKETLOG | D11: 160 | E11: MANFAC-11 | F11: =VLOOKUP(E11,BASE_VEICULOS!A:G,7,0) -> PROF - 07001 - MANUTENÇÃO PREDIAL- PROFARMA-2025 | G11: =IFERROR(VLOOKUP(E11,BASE_VEICULOS!$A:$B,2,0),"") -> TEW9A24 | I11: =DATE(YEAR(A11),MONTH(A11),1) -> 46054
A12: 46076 | B12: =WEEKNUM(A12,21) -> 9 | C12: TICKETLOG | D12: 80 | E12: MANFAC-12 | F12: =VLOOKUP(E12,BASE_VEICULOS!A:G,7,0) -> PROF - 07001 - MANUTENÇÃO PREDIAL- PROFARMA-2025 | G12: =IFERROR(VLOOKUP(E12,BASE_VEICULOS!$A:$B,2,0),"") -> TEW9A34 | I12: =DATE(YEAR(A12),MONTH(A12),1) -> 46054
A13: 46076 | B13: =WEEKNUM(A13,21) -> 9 | C13: TICKETLOG | D13: 80 | E13: MANFAC-13 | F13: =VLOOKUP(E13,BASE_VEICULOS!A:G,7,0) -> PROF - 07001 - MANUTENÇÃO PREDIAL- PROFARMA-2025 | G13: =IFERROR(VLOOKUP(E13,BASE_VEICULOS!$A:$B,2,0),"") -> TEW9A33 | I13: =DATE(YEAR(A13),MONTH(A13),1) -> 46054
... A37: 46077 | B37: =WEEKNUM(A37,21) -> 9 | C37: TICKETLOG | D37: 50 | E37: MANFAC-15 | F37: =VLOOKUP(E37,BASE_VEICULOS!A:G,7,0) -> PROF - 07001 - MANUTENÇÃO PREDIAL- PROFARMA-2025 | G37: =IFERROR(VLOOKUP(E37,BASE_VEICULOS!$A:$B,2,0),"") -> TEQ2I74 | I37: =DATE(YEAR(A37),MONTH(A37),1) -> 46054
A38: 46077 | B38: =WEEKNUM(A38,21) -> 9 | C38: TICKETLOG | D38: 80 | E38: MANFAC-20 | F38: =VLOOKUP(E38,BASE_VEICULOS!A:G,7,0) -> #N/A | G38: =IFERROR(VLOOKUP(E38,BASE_VEICULOS!$A:$B,2,0),"") | H38: Incluso 100,00 dia 24/02/2026 | I38: =DATE(YEAR(A38),MONTH(A38),1) -> 46054
A39: 46078 | B39: =WEEKNUM(A39,21) -> 9 | C39: TICKETLOG | D39: 140 | E39: MANFAC-1 | F39: =VLOOKUP(E39,BASE_VEICULOS!A:G,7,0) -> FAC - 140004 - MANUTENÇÃO PREDIAL DPSP 2025 | G39: =IFERROR(VLOOKUP(E39,BASE_VEICULOS!$A:$B,2,0),"") -> TEW9A25 | I39: =DATE(YEAR(A39),MONTH(A39),1) -> 46054
A40: 46078 | B40: =WEEKNUM(A40,21) -> 9 | C40: TICKETLOG | D40: 150.08 | E40: MANFAC-2 | F40: =VLOOKUP(E40,BASE_VEICULOS!A:G,7,0) -> PROF - 07001 - MANUTENÇÃO PREDIAL- PROFARMA-2025 | G40: =IFERROR(VLOOKUP(E40,BASE_VEICULOS!$A:$B,2,0),"") -> TEW9A28 | I40: =DATE(YEAR(A40),MONTH(A40),1) -> 46054
A41: 46078 | B41: =WEEKNUM(A41,21) -> 9 | C41: TICKETLOG | D41: 119.98 | E41: MANFAC-3 | F41: =VLOOKUP(E41,BASE_VEICULOS!A:G,7,0) -> FAC - 140004 - MANUTENÇÃO PREDIAL DPSP 2025 | G41: =IFERROR(VLOOKUP(E41,BASE_VEICULOS!$A:$B,2,0),"") -> FIL8C14 | I41: =DATE(YEAR(A41),MONTH(A41),1) -> 46054
A42: 46078 | B42: =WEEKNUM(A42,21) -> 9 | C42: TICKETLOG | D42: 79.97 | E42: MANFAC-4 | F42: =VLOOKUP(E42,BASE_VEICULOS!A:G,7,0) -> FAC - 140005 - SPOT MANUTENÇÃO DPSP 2025 | G42: =IFERROR(VLOOKUP(E42,BASE_VEICULOS!$A:$B,2,0),"") -> FGO3C61 | I42: =DATE(YEAR(A42),MONTH(A42),1) -> 46054
A43: 46078 | B43: =WEEKNUM(A43,21) -> 9 | C43: TICKETLOG | D43: 80 | E43: MANFAC-5 | F43: =VLOOKUP(E43,BASE_VEICULOS!A:G,7,0) -> FAC - 140004 - MANUTENÇÃO PREDIAL DPSP 2025 | G43: =IFERROR(VLOOKUP(E43,BASE_VEICULOS!$A:$B,2,0),"") -> FOK8A73 | I43: =DATE(YEAR(A43),MONTH(A43),1) -> 46054
A44: 46078 | B44: =WEEKNUM(A44,21) -> 9 | C44: TICKETLOG | D44: 70 | E44: MANFAC-6 | F44: =VLOOKUP(E44,BASE_VEICULOS!A:G,7,0) -> FAC - 140005 - SPOT MANUTENÇÃO DPSP 2025 | G44: =IFERROR(VLOOKUP(E44,BASE_VEICULOS!$A:$B,2,0),"") -> EWH1B84 | I44: =DATE(YEAR(A44),MONTH(A44),1) -> 46054
A45: 46078 | B45: =WEEKNUM(A45,21) -> 9 | C45: TICKETLOG | D45: 50 | E45: MANFAC-7 | F45: =VLOOKUP(E45,BASE_VEICULOS!A:G,7,0) -> FAC - 140005 - SPOT MANUTENÇÃO DPSP 2025 | G45: =IFERROR(VLOOKUP(E45,BASE_VEICULOS!$A:$B,2,0),"") -> TEW9A27 | I45: =DATE(YEAR(A45),MONTH(A45),1) -> 46054
A46: 46078 | B46: =WEEKNUM(A46,21) -> 9 | C46: TICKETLOG | D46: 120.03 | E46: MANFAC-8 | F46: =VLOOKUP(E46,BASE_VEICULOS!A:G,7,0) -> #N/A | G46: =IFERROR(VLOOKUP(E46,BASE_VEICULOS!$A:$B,2,0),"") | I46: =DATE(YEAR(A46),MONTH(A46),1) -> 46054
A47: 46078 | B47: =WEEKNUM(A47,21) -> 9 | C47: TICKETLOG | D47: 80 | E47: MANFAC-9 | F47: =VLOOKUP(E47,BASE_VEICULOS!A:G,7,0) -> FAC - 140004 - MANUTENÇÃO PREDIAL DPSP 2025 | G47: =IFERROR(VLOOKUP(E47,BASE_VEICULOS!$A:$B,2,0),"") -> TEW9A29 | I47: =DATE(YEAR(A47),MONTH(A47),1) -> 46054
A48: 46078 | B48: =WEEKNUM(A48,21) -> 9 | C48: TICKETLOG | D48: 100 | E48: MANFAC-11 | F48: =VLOOKUP(E48,BASE_VEICULOS!A:G,7,0) -> PROF - 07001 - MANUTENÇÃO PREDIAL- PROFARMA-2025 | G48: =IFERROR(VLOOKUP(E48,BASE_VEICULOS!$A:$B,2,0),"") -> TEW9A24 | I48: =DATE(YEAR(A48),MONTH(A48),1) -> 46054
A49: 46078 | B49: =WEEKNUM(A49,21) -> 9 | C49: TICKETLOG | D49: 80 | E49: MANFAC-12 | F49: =VLOOKUP(E49,BASE_VEICULOS!A:G,7,0) -> PROF - 07001 - MANUTENÇÃO PREDIAL- PROFARMA-2025 | G49: =IFERROR(VLOOKUP(E49,BASE_VEICULOS!$A:$B,2,0),"") -> TEW9A34 | I49: =DATE(YEAR(A49),MONTH(A49),1) -> 46054
A50: 46078 | B50: =WEEKNUM(A50,21) -> 9 | C50: TICKETLOG | D50: 100 | E50: MANFAC-13 | F50: =VLOOKUP(E50,BASE_VEICULOS!A:G,7,0) -> PROF - 07001 - MANUTENÇÃO PREDIAL- PROFARMA-2025 | G50: =IFERROR(VLOOKUP(E50,BASE_VEICULOS!$A:$B,2,0),"") -> TEW9A33 | I50: =DATE(YEAR(A50),MONTH(A50),1) -> 46054
... A290: 46094 | B290: =WEEKNUM(A290,21) -> 11 | C290: CAIXINHA | D290: 80 | E290: MANFAC-5 | F290: =VLOOKUP(E290,BASE_VEICULOS!A:G,7,0) -> FAC - 140004 - MANUTENÇÃO PREDIAL DPSP 2025 | G290: =IFERROR(VLOOKUP(E290,BASE_VEICULOS!$A:$B,2,0),"") -> FOK8A73 | I290: =DATE(YEAR(A290),MONTH(A290),1) -> 46082
A291: 46094 | B291: =WEEKNUM(A291,21) -> 11 | C291: CAIXINHA | E291: MANFAC-23 | F291: =VLOOKUP(E291,BASE_VEICULOS!A:G,7,0) -> #N/A | G291: =IFERROR(VLOOKUP(E291,BASE_VEICULOS!$A:$B,2,0),"") | I291: =DATE(YEAR(A291),MONTH(A291),1) -> 46082
A292: 46094 | B292: =WEEKNUM(A292,21) -> 11 | C292: CAIXINHA | E292: MANFAC-15 | F292: =VLOOKUP(E292,BASE_VEICULOS!A:G,7,0) -> PROF - 07001 - MANUTENÇÃO PREDIAL- PROFARMA-2025 | G292: =IFERROR(VLOOKUP(E292,BASE_VEICULOS!$A:$B,2,0),"") -> TEQ2I74 | I292: =DATE(YEAR(A292),MONTH(A292),1) -> 46082
A293: 46094 | B293: =WEEKNUM(A293,21) -> 11 | C293: CAIXINHA | E293: MANFAC-21 | F293: =VLOOKUP(E293,BASE_VEICULOS!A:G,7,0) -> PROF - 07001 - MANUTENÇÃO PREDIAL- PROFARMA-2025 | G293: =IFERROR(VLOOKUP(E293,BASE_VEICULOS!$A:$B,2,0),"") -> TEW9A23 | I293: =DATE(YEAR(A293),MONTH(A293),1) -> 46082
A294: 46094 | B294: =WEEKNUM(A294,21) -> 11 | C294: CAIXINHA | E294: MANFAC-18 | F294: =VLOOKUP(E294,BASE_VEICULOS!A:G,7,0) -> PROF - 07001 - MANUTENÇÃO PREDIAL- PROFARMA-2025 | G294: =IFERROR(VLOOKUP(E294,BASE_VEICULOS!$A:$B,2,0),"") -> TET5H37 | I294: =DATE(YEAR(A294),MONTH(A294),1) -> 46082
A295: 46094 | B295: =WEEKNUM(A295,21) -> 11 | C295: CAIXINHA | E295: MANFAC-4 | F295: =VLOOKUP(E295,BASE_VEICULOS!A:G,7,0) -> FAC - 140005 - SPOT MANUTENÇÃO DPSP 2025 | G295: =IFERROR(VLOOKUP(E295,BASE_VEICULOS!$A:$B,2,0),"") -> FGO3C61 | I295: =DATE(YEAR(A295),MONTH(A295),1) -> 46082
A296: 46094 | B296: =WEEKNUM(A296,21) -> 11 | C296: CAIXINHA | E296: MANFAC-22 | F296: =VLOOKUP(E296,BASE_VEICULOS!A:G,7,0) -> PROF - 07001 - MANUTENÇÃO PREDIAL- PROFARMA-2025 | G296: =IFERROR(VLOOKUP(E296,BASE_VEICULOS!$A:$B,2,0),"") -> TEW9A26 | I296: =DATE(YEAR(A296),MONTH(A296),1) -> 46082
A297: 46094 | B297: =WEEKNUM(A297,21) -> 11 | C297: CAIXINHA | E297: MANFAC-10 | F297: =VLOOKUP(E297,BASE_VEICULOS!A:G,7,0) -> PROF - 07001 - MANUTENÇÃO PREDIAL- PROFARMA-2025 | G297: =IFERROR(VLOOKUP(E297,BASE_VEICULOS!$A:$B,2,0),"") -> TEW9A30 | I297: =DATE(YEAR(A297),MONTH(A297),1) -> 46082
A298: 46094 | B298: =WEEKNUM(A298,21) -> 11 | C298: CAIXINHA | E298: MANFAC-20 | F298: =VLOOKUP(E298,BASE_VEICULOS!A:G,7,0) -> #N/A | G298: =IFERROR(VLOOKUP(E298,BASE_VEICULOS!$A:$B,2,0),"") | I298: =DATE(YEAR(A298),MONTH(A298),1) -> 46082
A299: 46094 | B299: =WEEKNUM(A299,21) -> 11 | C299: CAIXINHA | E299: MANFAC-2 | F299: =VLOOKUP(E299,BASE_VEICULOS!A:G,7,0) -> PROF - 07001 - MANUTENÇÃO PREDIAL- PROFARMA-2025 | G299: =IFERROR(VLOOKUP(E299,BASE_VEICULOS!$A:$B,2,0),"") -> TEW9A28 | I299: =DATE(YEAR(A299),MONTH(A299),1) -> 46082
A300: 46095 | B300: =WEEKNUM(A300,21) -> 11 | C300: CAIXINHA | E300: MANFAC-11 | F300: =VLOOKUP(E300,BASE_VEICULOS!A:G,7,0) -> PROF - 07001 - MANUTENÇÃO PREDIAL- PROFARMA-2025 | G300: =IFERROR(VLOOKUP(E300,BASE_VEICULOS!$A:$B,2,0),"") -> TEW9A24 | I300: =DATE(YEAR(A300),MONTH(A300),1) -> 46082
A301: 46095 | B301: =WEEKNUM(A301,21) -> 11 | C301: CAIXINHA | E301: MANFAC-19 | F301: =VLOOKUP(E301,BASE_VEICULOS!A:G,7,0) -> PROF - 07001 - MANUTENÇÃO PREDIAL- PROFARMA-2025 | G301: =IFERROR(VLOOKUP(E301,BASE_VEICULOS!$A:$B,2,0),"") -> TEH3I02 | I301: =DATE(YEAR(A301),MONTH(A301),1) -> 46082
A302: 46095 | B302: =WEEKNUM(A302,21) -> 11 | C302: CAIXINHA | E302: MANFAC-18 | F302: =VLOOKUP(E302,BASE_VEICULOS!A:G,7,0) -> PROF - 07001 - MANUTENÇÃO PREDIAL- PROFARMA-2025 | G302: =IFERROR(VLOOKUP(E302,BASE_VEICULOS!$A:$B,2,0),"") -> TET5H37 | I302: =DATE(YEAR(A302),MONTH(A302),1) -> 46082
... A407: 46104 | B407: =WEEKNUM(A407,21) -> 13 | C407: CAIXINHA | E407: MANFAC-20 | F407: =VLOOKUP(E407,BASE_VEICULOS!A:G,7,0) -> #N/A | G407: =IFERROR(VLOOKUP(E407,BASE_VEICULOS!$A:$B,2,0),"") | I407: =DATE(YEAR(A407),MONTH(A407),1) -> 46082
A408: 46104 | B408: =WEEKNUM(A408,21) -> 13 | C408: CAIXINHA | D408: 80 | E408: MANFAC-5 | F408: =VLOOKUP(E408,BASE_VEICULOS!A:G,7,0) -> FAC - 140004 - MANUTENÇÃO PREDIAL DPSP 2025 | G408: =IFERROR(VLOOKUP(E408,BASE_VEICULOS!$A:$B,2,0),"") -> FOK8A73 | I408: =DATE(YEAR(A408),MONTH(A408),1) -> 46082
A409: 46104 | B409: =WEEKNUM(A409,21) -> 13 | C409: CAIXINHA | D409: 100 | E409: MANFAC-18 | F409: =VLOOKUP(E409,BASE_VEICULOS!A:G,7,0) -> PROF - 07001 - MANUTENÇÃO PREDIAL- PROFARMA-2025 | G409: =IFERROR(VLOOKUP(E409,BASE_VEICULOS!$A:$B,2,0),"") -> TET5H37 | I409: =DATE(YEAR(A409),MONTH(A409),1) -> 46082
A410: 46104 | B410: =WEEKNUM(A410,21) -> 13 | C410: CAIXINHA | D410: 70 | E410: MANFAC-24 | F410: =VLOOKUP(E410,BASE_VEICULOS!A:G,7,0) -> PROF - 07001 - MANUTENÇÃO PREDIAL- PROFARMA-2025 | G410: =IFERROR(VLOOKUP(E410,BASE_VEICULOS!$A:$B,2,0),"") -> SRU8D16 | I410: =DATE(YEAR(A410),MONTH(A410),1) -> 46082
A411: 46104 | B411: =WEEKNUM(A411,21) -> 13 | C411: CAIXINHA | D411: 100 | E411: MANFAC-10 | F411: =VLOOKUP(E411,BASE_VEICULOS!A:G,7,0) -> PROF - 07001 - MANUTENÇÃO PREDIAL- PROFARMA-2025 | G411: =IFERROR(VLOOKUP(E411,BASE_VEICULOS!$A:$B,2,0),"") -> TEW9A30 | I411: =DATE(YEAR(A411),MONTH(A411),1) -> 46082
A412: 46104 | B412: =WEEKNUM(A412,21) -> 13 | C412: CAIXINHA | D412: 70 | E412: MANFAC-19 | F412: =VLOOKUP(E412,BASE_VEICULOS!A:G,7,0) -> PROF - 07001 - MANUTENÇÃO PREDIAL- PROFARMA-2025 | G412: =IFERROR(VLOOKUP(E412,BASE_VEICULOS!$A:$B,2,0),"") -> TEH3I02 | I412: =DATE(YEAR(A412),MONTH(A412),1) -> 46082
A413: 46104 | B413: =WEEKNUM(A413,21) -> 13 | C413: CAIXINHA | D413: 50 | E413: MANFAC-7 | F413: =VLOOKUP(E413,BASE_VEICULOS!A:G,7,0) -> FAC - 140005 - SPOT MANUTENÇÃO DPSP 2025 | G413: =IFERROR(VLOOKUP(E413,BASE_VEICULOS!$A:$B,2,0),"") -> TEW9A27 | I413: =DATE(YEAR(A413),MONTH(A413),1) -> 46082
A414: 46104 | B414: =WEEKNUM(A414,21) -> 13 | C414: CAIXINHA | D414: 80 | E414: MANFAC-3 | F414: =VLOOKUP(E414,BASE_VEICULOS!A:G,7,0) -> FAC - 140004 - MANUTENÇÃO PREDIAL DPSP 2025 | G414: =IFERROR(VLOOKUP(E414,BASE_VEICULOS!$A:$B,2,0),"") -> FIL8C14 | I414: =DATE(YEAR(A414),MONTH(A414),1) -> 46082
A415: 46104 | B415: =WEEKNUM(A415,21) -> 13 | C415: CAIXINHA | D415: 200 | E415: MANFAC-22 | F415: =VLOOKUP(E415,BASE_VEICULOS!A:G,7,0) -> PROF - 07001 - MANUTENÇÃO PREDIAL- PROFARMA-2025 | G415: =IFERROR(VLOOKUP(E415,BASE_VEICULOS!$A:$B,2,0),"") -> TEW9A26 | I415: =DATE(YEAR(A415),MONTH(A415),1) -> 46082
A416: 46104 | B416: =WEEKNUM(A416,21) -> 13 | C416: TICKETLOG | D416: 30 | E416: MANFAC-1 | F416: =VLOOKUP(E416,BASE_VEICULOS!A:G,7,0) -> FAC - 140004 - MANUTENÇÃO PREDIAL DPSP 2025 | G416: =IFERROR(VLOOKUP(E416,BASE_VEICULOS!$A:$B,2,0),"") -> TEW9A25 | I416: =DATE(YEAR(A416),MONTH(A416),1) -> 46082
A417: 46104 | B417: =WEEKNUM(A417,21) -> 13 | C417: TICKETLOG | D417: 40 | E417: MANFAC-12 | F417: =VLOOKUP(E417,BASE_VEICULOS!A:G,7,0) -> PROF - 07001 - MANUTENÇÃO PREDIAL- PROFARMA-2025 | G417: =IFERROR(VLOOKUP(E417,BASE_VEICULOS!$A:$B,2,0),"") -> TEW9A34 | I417: =DATE(YEAR(A417),MONTH(A417),1) -> 46082
A418: 46104 | B418: =WEEKNUM(A418,21) -> 13 | C418: TICKETLOG | D418: 100 | E418: MANFAC-15 | F418: =VLOOKUP(E418,BASE_VEICULOS!A:G,7,0) -> PROF - 07001 - MANUTENÇÃO PREDIAL- PROFARMA-2025 | G418: =IFERROR(VLOOKUP(E418,BASE_VEICULOS!$A:$B,2,0),"") -> TEQ2I74 | I418: =DATE(YEAR(A418),MONTH(A418),1) -> 46082
A419: 46104 | B419: =WEEKNUM(A419,21) -> 13 | C419: TICKETLOG | D419: 20 | E419: MANFAC-19 | F419: =VLOOKUP(E419,BASE_VEICULOS!A:G,7,0) -> PROF - 07001 - MANUTENÇÃO PREDIAL- PROFARMA-2025 | G419: =IFERROR(VLOOKUP(E419,BASE_VEICULOS!$A:$B,2,0),"") -> TEH3I02 | I419: =DATE(YEAR(A419),MONTH(A419),1) -> 46082
... A675: 46120 | B675: =WEEKNUM(A675,21) -> 15 | C675: CAIXINHA | D675: 100 | E675: MANFAC-15 | F675: =VLOOKUP(E675,BASE_VEICULOS!A:G,7,0) -> PROF - 07001 - MANUTENÇÃO PREDIAL- PROFARMA-2025 | G675: =IFERROR(VLOOKUP(E675,BASE_VEICULOS!$A:$B,2,0),"") -> TEQ2I74 | I675: =DATE(YEAR(A675),MONTH(A675),1) -> 46113
A676: 46120 | B676: =WEEKNUM(A676,21) -> 15 | D676: 75 | E676: MANFAC-13 | F676: =VLOOKUP(E676,BASE_VEICULOS!A:G,7,0) -> PROF - 07001 - MANUTENÇÃO PREDIAL- PROFARMA-2025 | G676: =IFERROR(VLOOKUP(E676,BASE_VEICULOS!$A:$B,2,0),"") -> TEW9A33 | I676: =DATE(YEAR(A676),MONTH(A676),1) -> 46113
A677: 46120 | B677: =WEEKNUM(A677,21) -> 15 | D677: 150 | E677: MANFAC-22 | F677: =VLOOKUP(E677,BASE_VEICULOS!A:G,7,0) -> PROF - 07001 - MANUTENÇÃO PREDIAL- PROFARMA-2025 | G677: =IFERROR(VLOOKUP(E677,BASE_VEICULOS!$A:$B,2,0),"") -> TEW9A26 | I677: =DATE(YEAR(A677),MONTH(A677),1) -> 46113
A678: 46120 | B678: =WEEKNUM(A678,21) -> 15 | D678: 50 | E678: MANFAC-2 | F678: =VLOOKUP(E678,BASE_VEICULOS!A:G,7,0) -> PROF - 07001 - MANUTENÇÃO PREDIAL- PROFARMA-2025 | G678: =IFERROR(VLOOKUP(E678,BASE_VEICULOS!$A:$B,2,0),"") -> TEW9A28 | I678: =DATE(YEAR(A678),MONTH(A678),1) -> 46113
A679: 46120 | B679: =WEEKNUM(A679,21) -> 15 | D679: 100 | E679: MANFAC-10 | F679: =VLOOKUP(E679,BASE_VEICULOS!A:G,7,0) -> PROF - 07001 - MANUTENÇÃO PREDIAL- PROFARMA-2025 | G679: =IFERROR(VLOOKUP(E679,BASE_VEICULOS!$A:$B,2,0),"") -> TEW9A30 | I679: =DATE(YEAR(A679),MONTH(A679),1) -> 46113
A680: 46120 | B680: =WEEKNUM(A680,21) -> 15 | D680: 100 | E680: MANFAC-4 | F680: =VLOOKUP(E680,BASE_VEICULOS!A:G,7,0) -> FAC - 140005 - SPOT MANUTENÇÃO DPSP 2025 | G680: =IFERROR(VLOOKUP(E680,BASE_VEICULOS!$A:$B,2,0),"") -> FGO3C61 | I680: =DATE(YEAR(A680),MONTH(A680),1) -> 46113
A681: 46120 | B681: =WEEKNUM(A681,21) -> 15 | D681: 45 | E681: MANFAC-15 | F681: =VLOOKUP(E681,BASE_VEICULOS!A:G,7,0) -> PROF - 07001 - MANUTENÇÃO PREDIAL- PROFARMA-2025 | G681: =IFERROR(VLOOKUP(E681,BASE_VEICULOS!$A:$B,2,0),"") -> TEQ2I74 | I681: =DATE(YEAR(A681),MONTH(A681),1) -> 46113
A682: 46120 | B682: =WEEKNUM(A682,21) -> 15 | D682: 60 | E682: MANFAC-13 | F682: =VLOOKUP(E682,BASE_VEICULOS!A:G,7,0) -> PROF - 07001 - MANUTENÇÃO PREDIAL- PROFARMA-2025 | G682: =IFERROR(VLOOKUP(E682,BASE_VEICULOS!$A:$B,2,0),"") -> TEW9A33 | I682: =DATE(YEAR(A682),MONTH(A682),1) -> 46113
A683: 46120 | B683: =WEEKNUM(A683,21) -> 15 | D683: 95 | E683: MANFAC-21 | F683: =VLOOKUP(E683,BASE_VEICULOS!A:G,7,0) -> PROF - 07001 - MANUTENÇÃO PREDIAL- PROFARMA-2025 | G683: =IFERROR(VLOOKUP(E683,BASE_VEICULOS!$A:$B,2,0),"") -> TEW9A23 | I683: =DATE(YEAR(A683),MONTH(A683),1) -> 46113
A684: 46121 | B684: =WEEKNUM(A684,21) -> 15 | C684: CAIXINHA | D684: 60 | E684: MANFAC-2 | F684: =VLOOKUP(E684,BASE_VEICULOS!A:G,7,0) -> PROF - 07001 - MANUTENÇÃO PREDIAL- PROFARMA-2025 | G684: =IFERROR(VLOOKUP(E684,BASE_VEICULOS!$A:$B,2,0),"") -> TEW9A28 | I684: =DATE(YEAR(A684),MONTH(A684),1) -> 46113
A685: 46120 | B685: =WEEKNUM(A685,21) -> 15 | D685: 100 | E685: MANFAC-19 | F685: =VLOOKUP(E685,BASE_VEICULOS!A:G,7,0) -> PROF - 07001 - MANUTENÇÃO PREDIAL- PROFARMA-2025 | G685: =IFERROR(VLOOKUP(E685,BASE_VEICULOS!$A:$B,2,0),"") -> TEH3I02 | I685: =DATE(YEAR(A685),MONTH(A685),1) -> 46113
A686: 46120 | B686: =WEEKNUM(A686,21) -> 15 | D686: 90 | E686: MANFAC-6 | F686: =VLOOKUP(E686,BASE_VEICULOS!A:G,7,0) -> FAC - 140005 - SPOT MANUTENÇÃO DPSP 2025 | G686: =IFERROR(VLOOKUP(E686,BASE_VEICULOS!$A:$B,2,0),"") -> EWH1B84 | I686: =DATE(YEAR(A686),MONTH(A686),1) -> 46113
A687: 46120 | B687: =WEEKNUM(A687,21) -> 15 | D687: 70 | E687: MANFAC-12 | F687: =VLOOKUP(E687,BASE_VEICULOS!A:G,7,0) -> PROF - 07001 - MANUTENÇÃO PREDIAL- PROFARMA-2025 | G687: =IFERROR(VLOOKUP(E687,BASE_VEICULOS!$A:$B,2,0),"") -> TEW9A34 | I687: =DATE(YEAR(A687),MONTH(A687),1) -> 46113
A688: 46120 | B688: =WEEKNUM(A688,21) -> 15 | D688: 95 | E688: MANFAC-1 | F688: =VLOOKUP(E688,BASE_VEICULOS!A:G,7,0) -> FAC - 140004 - MANUTENÇÃO PREDIAL DPSP 2025 | G688: =IFERROR(VLOOKUP(E688,BASE_VEICULOS!$A:$B,2,0),"") -> TEW9A25 | I688: =DATE(YEAR(A688),MONTH(A688),1) -> 46113
A689: 46121 | B689: =WEEKNUM(A689,21) -> 15 | C689: TICKETLOG | D689: 79.98 | E689: MANFAC-1 | F689: =VLOOKUP(E689,BASE_VEICULOS!A:G,7,0) -> FAC - 140004 - MANUTENÇÃO PREDIAL DPSP 2025 | G689: =IFERROR(VLOOKUP(E689,BASE_VEICULOS!$A:$B,2,0),"") -> TEW9A25 | I689: =DATE(YEAR(A689),MONTH(A689),1) -> 46113
A690: 46121 | B690: =WEEKNUM(A690,21) -> 15 | C690: TICKETLOG | D690: 100 | E690: MANFAC-21 | F690: =VLOOKUP(E690,BASE_VEICULOS!A:G,7,0) -> PROF - 07001 - MANUTENÇÃO PREDIAL- PROFARMA-2025 | G690: =IFERROR(VLOOKUP(E690,BASE_VEICULOS!$A:$B,2,0),"") -> TEW9A23 | I690: =DATE(YEAR(A690),MONTH(A690),1) -> 46113
A691: 46121 | B691: =WEEKNUM(A691,21) -> 15 | C691: TICKETLOG | D691: 100 | E691: MANFAC-8 | F691: =VLOOKUP(E691,BASE_VEICULOS!A:G,7,0) -> #N/A | G691: =IFERROR(VLOOKUP(E691,BASE_VEICULOS!$A:$B,2,0),"") | I691: =DATE(YEAR(A691),MONTH(A691),1) -> 46113
A692: 46121 | B692: =WEEKNUM(A692,21) -> 15 | C692: TICKETLOG | D692: 80 | E692: MANFAC-10 | F692: =VLOOKUP(E692,BASE_VEICULOS!A:G,7,0) -> PROF - 07001 - MANUTENÇÃO PREDIAL- PROFARMA-2025 | G692: =IFERROR(VLOOKUP(E692,BASE_VEICULOS!$A:$B,2,0),"") -> TEW9A30 | I692: =DATE(YEAR(A692),MONTH(A692),1) -> 46113
A693: 46121 | B693: =WEEKNUM(A693,21) -> 15 | C693: TICKETLOG | D693: 94.86 | E693: MANFAC-21 | F693: =VLOOKUP(E693,BASE_VEICULOS!A:G,7,0) -> PROF - 07001 - MANUTENÇÃO PREDIAL- PROFARMA-2025 | G693: =IFERROR(VLOOKUP(E693,BASE_VEICULOS!$A:$B,2,0),"") -> TEW9A23 | I693: =DATE(YEAR(A693),MONTH(A693),1) -> 46113
A694: 46121 | B694: =WEEKNUM(A694,21) -> 15 | C694: TICKETLOG | D694: 79.98 | E694: MANFAC-10 | F694: =VLOOKUP(E694,BASE_VEICULOS!A:G,7,0) -> PROF - 07001 - MANUTENÇÃO PREDIAL- PROFARMA-2025 | G694: =IFERROR(VLOOKUP(E694,BASE_VEICULOS!$A:$B,2,0),"") -> TEW9A30 | I694: =DATE(YEAR(A694),MONTH(A694),1) -> 46113
A695: 46121 | B695: =WEEKNUM(A695,21) -> 15 | C695: TICKETLOG | D695: 70 | E695: MANFAC-12 | F695: =VLOOKUP(E695,BASE_VEICULOS!A:G,7,0) -> PROF - 07001 - MANUTENÇÃO PREDIAL- PROFARMA-2025 | G695: =IFERROR(VLOOKUP(E695,BASE_VEICULOS!$A:$B,2,0),"") -> TEW9A34 | I695: =DATE(YEAR(A695),MONTH(A695),1) -> 46113
A696: 46121 | B696: =WEEKNUM(A696,21) -> 15 | C696: TICKETLOG | D696: 100 | E696: MANFAC-4 | F696: =VLOOKUP(E696,BASE_VEICULOS!A:G,7,0) -> FAC - 140005 - SPOT MANUTENÇÃO DPSP 2025 | G696: =IFERROR(VLOOKUP(E696,BASE_VEICULOS!$A:$B,2,0),"") -> FGO3C61 | I696: =DATE(YEAR(A696),MONTH(A696),1) -> 46113
A697: 46121 | B697: =WEEKNUM(A697,21) -> 15 | C697: TICKETLOG | D697: 50 | E697: MANFAC-13 | F697: =VLOOKUP(E697,BASE_VEICULOS!A:G,7,0) -> PROF - 07001 - MANUTENÇÃO PREDIAL- PROFARMA-2025 | G697: =IFERROR(VLOOKUP(E697,BASE_VEICULOS!$A:$B,2,0),"") -> TEW9A33 | I697: =DATE(YEAR(A697),MONTH(A697),1) -> 46113
A698: 46121 | B698: =WEEKNUM(A698,21) -> 15 | C698: TICKETLOG | D698: 50 | E698: MANFAC-15 | F698: =VLOOKUP(E698,BASE_VEICULOS!A:G,7,0) -> PROF - 07001 - MANUTENÇÃO PREDIAL- PROFARMA-2025 | G698: =IFERROR(VLOOKUP(E698,BASE_VEICULOS!$A:$B,2,0),"") -> TEQ2I74 | I698: =DATE(YEAR(A698),MONTH(A698),1) -> 46113
A699: 46121 | B699: =WEEKNUM(A699,21) -> 15 | C699: TICKETLOG | D699: 140 | E699: MANFAC-19 | F699: =VLOOKUP(E699,BASE_VEICULOS!A:G,7,0) -> PROF - 07001 - MANUTENÇÃO PREDIAL- PROFARMA-2025 | G699: =IFERROR(VLOOKUP(E699,BASE_VEICULOS!$A:$B,2,0),"") -> TEH3I02 | I699: =DATE(YEAR(A699),MONTH(A699),1) -> 46113
A700: 46121 | B700: =WEEKNUM(A700,21) -> 15 | C700: TICKETLOG | D700: 60 | E700: MANFAC-9 | F700: =VLOOKUP(E700,BASE_VEICULOS!A:G,7,0) -> FAC - 140004 - MANUTENÇÃO PREDIAL DPSP 2025 | G700: =IFERROR(VLOOKUP(E700,BASE_VEICULOS!$A:$B,2,0),"") -> TEW9A29 | I700: =DATE(YEAR(A700),MONTH(A700),1) -> 46113
... A1138: 46157 | B1138: =WEEKNUM(A1138,21) -> 20 | C1138: TICKETLOG | D1138: 59.98 | E1138: MANFAC-24 | F1138: =VLOOKUP(E1138,BASE_VEICULOS!A:G,7,0) -> PROF - 07001 - MANUTENÇÃO PREDIAL- PROFARMA-2025 | G1138: =IFERROR(VLOOKUP(E1138,BASE_VEICULOS!$A:$B,2,0),"") -> SRU8D16 | I1138: =DATE(YEAR(A1138),MONTH(A1138),1) -> 46143
B1139: =WEEKNUM(A1139,21) -> 52 | F1139: =VLOOKUP(E1139,BASE_VEICULOS!A:G,7,0) -> #N/A | G1139: =IFERROR(VLOOKUP(E1139,BASE_VEICULOS!$A:$B,2,0),"") | I1139: =DATE(YEAR(A1139),MONTH(A1139),1) -> 693932
B1140: =WEEKNUM(A1140,21) -> 52 | F1140: =VLOOKUP(E1140,BASE_VEICULOS!A:G,7,0) -> #N/A | G1140: =IFERROR(VLOOKUP(E1140,BASE_VEICULOS!$A:$B,2,0),"") | I1140: =DATE(YEAR(A1140),MONTH(A1140),1) -> 693932
B1141: =WEEKNUM(A1141,21) -> 52 | F1141: =VLOOKUP(E1141,BASE_VEICULOS!A:G,7,0) -> #N/A | G1141: =IFERROR(VLOOKUP(E1141,BASE_VEICULOS!$A:$B,2,0),"") | I1141: =DATE(YEAR(A1141),MONTH(A1141),1) -> 693932
B1142: =WEEKNUM(A1142,21) -> 52 | F1142: =VLOOKUP(E1142,BASE_VEICULOS!A:G,7,0) -> #N/A | G1142: =IFERROR(VLOOKUP(E1142,BASE_VEICULOS!$A:$B,2,0),"") | I1142: =DATE(YEAR(A1142),MONTH(A1142),1) -> 693932
B1143: =WEEKNUM(A1143,21) -> 52 | F1143: =VLOOKUP(E1143,BASE_VEICULOS!A:G,7,0) -> #N/A | G1143: =IFERROR(VLOOKUP(E1143,BASE_VEICULOS!$A:$B,2,0),"") | I1143: =DATE(YEAR(A1143),MONTH(A1143),1) -> 693932
B1144: =WEEKNUM(A1144,21) -> 52 | F1144: =VLOOKUP(E1144,BASE_VEICULOS!A:G,7,0) -> #N/A | G1144: =IFERROR(VLOOKUP(E1144,BASE_VEICULOS!$A:$B,2,0),"") | I1144: =DATE(YEAR(A1144),MONTH(A1144),1) -> 693932
B1145: =WEEKNUM(A1145,21) -> 52 | F1145: =VLOOKUP(E1145,BASE_VEICULOS!A:G,7,0) -> #N/A | G1145: =IFERROR(VLOOKUP(E1145,BASE_VEICULOS!$A:$B,2,0),"") | I1145: =DATE(YEAR(A1145),MONTH(A1145),1) -> 693932

Sheet DASH_DADOS
A2: Início mês | B2: =DATE(YEAR(B3),MONTH(B3),1) -> 46174 | D2: EQUIPE | E2: TODOS
A3: Fim mês | B3: =EOMONTH(B4,0) -> 46203 | D3: CENTRO DE CUSTO | E3: PROF - 07001 - MANUTENÇÃO PREDIAL- PROFARMA-2025
A4: Hoje | B4: =TODAY() -> 46184
A6: CONSUMO x PLANEJADO
A7: Semana (início) | B7: Semana (fim) | C7: Consumo (R$) | D7: Planejado (R$) | E7: Desvio (R$)
A8: =($B$2-WEEKDAY($B$2,2)+1) -> 46174 | B8: =A8+6 -> 46180 | C8: =IF(A8>$B$3,"",SUMIFS(BASE_ABASTECIMENTO!$D$2:$D$97,BASE_ABASTECIMENTO!$A$2:$A$145,">="&A8,BASE_ABASTECIMENTO!$A$2:$A$145,"<="&MIN(B8,$B$3,$B$4),BASE_ABASTECIMENTO!$E$2:$E$145,IF($E$2="TODOS","*",$E$2),BASE_ABASTECIMENTO!$F$2:$F$145,IF($E$3="TODOS","*",$E$3))) -> #VALUE! | D8: =IF(A8>$B$3,"",SUMIFS(BASE_PLANEJADO!$D$2:$D$1000,BASE_PLANEJADO!$B$2:$B$1000,DATE(YEAR($B$4),MONTH($B$4),1),BASE_PLANEJADO!$A$2:$A$1000,IF($E$3="TODOS","*",$E$3))) -> 0 | E8: =IF(C8="","",C8-D8) -> #VALUE!
A9: =A8+7 -> 46181 | B9: =A9+6 -> 46187 | C9: =IF(A9>$B$3,"",SUMIFS(BASE_ABASTECIMENTO!$D$2:$D$97,BASE_ABASTECIMENTO!$A$2:$A$145,">="&A9,BASE_ABASTECIMENTO!$A$2:$A$145,"<="&MIN(B9,$B$3,$B$4),BASE_ABASTECIMENTO!$E$2:$E$145,IF($E$2="TODOS","*",$E$2),BASE_ABASTECIMENTO!$F$2:$F$145,IF($E$3="TODOS","*",$E$3))) -> #VALUE! | D9: =IF(A9>$B$3,"",SUMIFS(BASE_PLANEJADO!$D$2:$D$1000,BASE_PLANEJADO!$B$2:$B$1000,DATE(YEAR($B$4),MONTH($B$4),1),BASE_PLANEJADO!$A$2:$A$1000,IF($E$3="TODOS","*",$E$3))) -> 0 | E9: =IF(C9="","",C9-D9) -> #VALUE!
A10: =A9+7 -> 46188 | B10: =A10+6 -> 46194 | C10: =IF(A10>$B$3,"",SUMIFS(BASE_ABASTECIMENTO!$D$2:$D$97,BASE_ABASTECIMENTO!$A$2:$A$145,">="&A10,BASE_ABASTECIMENTO!$A$2:$A$145,"<="&MIN(B10,$B$3,$B$4),BASE_ABASTECIMENTO!$E$2:$E$145,IF($E$2="TODOS","*",$E$2),BASE_ABASTECIMENTO!$F$2:$F$145,IF($E$3="TODOS","*",$E$3))) -> #VALUE! | D10: =IF(A10>$B$3,"",SUMIFS(BASE_PLANEJADO!$D$2:$D$1000,BASE_PLANEJADO!$B$2:$B$1000,DATE(YEAR($B$4),MONTH($B$4),1),BASE_PLANEJADO!$A$2:$A$1000,IF($E$3="TODOS","*",$E$3))) -> 0 | E10: =IF(C10="","",C10-D10) -> #VALUE!
A11: =A10+7 -> 46195 | B11: =A11+6 -> 46201 | C11: =IF(A11>$B$3,"",SUMIFS(BASE_ABASTECIMENTO!$D$2:$D$97,BASE_ABASTECIMENTO!$A$2:$A$145,">="&A11,BASE_ABASTECIMENTO!$A$2:$A$145,"<="&MIN(B11,$B$3,$B$4),BASE_ABASTECIMENTO!$E$2:$E$145,IF($E$2="TODOS","*",$E$2),BASE_ABASTECIMENTO!$F$2:$F$145,IF($E$3="TODOS","*",$E$3))) -> #VALUE! | D11: =IF(A11>$B$3,"",SUMIFS(BASE_PLANEJADO!$D$2:$D$1000,BASE_PLANEJADO!$B$2:$B$1000,DATE(YEAR($B$4),MONTH($B$4),1),BASE_PLANEJADO!$A$2:$A$1000,IF($E$3="TODOS","*",$E$3))) -> 0 | E11: =IF(C11="","",C11-D11) -> #VALUE!
A12: =A11+7 -> 46202 | B12: =A12+6 -> 46208 | C12: =IF(A12>$B$3,"",SUMIFS(BASE_ABASTECIMENTO!$D$2:$D$97,BASE_ABASTECIMENTO!$A$2:$A$145,">="&A12,BASE_ABASTECIMENTO!$A$2:$A$145,"<="&MIN(B12,$B$3,$B$4),BASE_ABASTECIMENTO!$E$2:$E$145,IF($E$2="TODOS","*",$E$2),BASE_ABASTECIMENTO!$F$2:$F$145,IF($E$3="TODOS","*",$E$3))) -> #VALUE! | D12: =IF(A12>$B$3,"",SUMIFS(BASE_PLANEJADO!$D$2:$D$1000,BASE_PLANEJADO!$B$2:$B$1000,DATE(YEAR($B$4),MONTH($B$4),1),BASE_PLANEJADO!$A$2:$A$1000,IF($E$3="TODOS","*",$E$3))) -> 0 | E12: =IF(C12="","",C12-D12) -> #VALUE!
A13: =A12+7 -> 46209 | B13: =A13+6 -> 46215 | C13: =IF(A13>$B$3,"",SUMIFS(BASE_ABASTECIMENTO!$D$2:$D$97,BASE_ABASTECIMENTO!$A$2:$A$145,">="&A13,BASE_ABASTECIMENTO!$A$2:$A$145,"<="&MIN(B13,$B$3,$B$4),BASE_ABASTECIMENTO!$E$2:$E$145,IF($E$2="TODOS","*",$E$2),BASE_ABASTECIMENTO!$F$2:$F$145,IF($E$3="TODOS","*",$E$3))) | D13: =IF(A13>$B$3,"",SUMIFS(BASE_PLANEJADO!$D$2:$D$1000,BASE_PLANEJADO!$B$2:$B$1000,DATE(YEAR($B$4),MONTH($B$4),1),BASE_PLANEJADO!$A$2:$A$1000,IF($E$3="TODOS","*",$E$3))) | E13: =IF(C13="","",C13-D13)
A15: TOP 10 CONSUMO COMBUSTÍVEL (POR EQUIPE) | G15: EQUIPE | H15: CENTRO DE CUSTO | I15: COMBUSTÍVEL | J15: PEDAGIO | K15: ESTACIONAMENTO | L15: MULTA | M15: MANUTENÇÃO | N15: CUSTO TOTAL FROTA | O15: KM CONTRATUAL | P15: ULTIMO KM | Q15: DESVIO KM
A16: #POS | B16: EQUIPE | C16: VALOR CONSUMIDO | G16: MANFAC-1 | H16: =IF(G16="","",IFERROR(VLOOKUP(G16,BASE_VEICULOS!$A:$G,7,FALSE),"")) -> FAC - 140004 - MANUTENÇÃO PREDIAL DPSP 2025 | I16: =SUMIFS(BASE_ABASTECIMENTO!D:D,BASE_ABASTECIMENTO!E:E,$G16,BASE_ABASTECIMENTO!A:A,">="&$B$2,BASE_ABASTECIMENTO!A:A,"<="&$B$3) -> 0 | J16: =SUMIFS(BASE_VELOE!$F:$F,BASE_VELOE!$B:$B,$G16,BASE_VELOE!$A:$A,">="&$B$2,BASE_VELOE!$A:$A,"<="&$B$3,BASE_VELOE!$D:$D,J$15) -> 0 | K16: =SUMIFS(BASE_VELOE!$F:$F,BASE_VELOE!$B:$B,$G16,BASE_VELOE!$A:$A,">="&$B$2,BASE_VELOE!$A:$A,"<="&$B$3,BASE_VELOE!$D:$D,K$15) -> 0 | N16: =SUM(I16:M16) -> 0 | O16: =IF(VLOOKUP(G16,BASE_VEICULOS!A:O,10,0)="CONTRATO FROTAS",($B$4-VLOOKUP(G16,BASE_VEICULOS!A:O,15,0))/30*VLOOKUP(G16,BASE_VEICULOS!A:O,12,0),"") -> 23100 | P16: =IFERROR(__xludf.DUMMYFUNCTION("IF(G16="""","""",IFERROR(MAX(FILTER(BASE_KM!$C$2:$C1000, BASE_KM!$B$2:$B1000=G16, BASE_KM!$A$2:$A1000=MAX(FILTER(BASE_KM!$A$2:$A1000, BASE_KM!$B$2:$B1000=G16)))),""""))"),25030.0) -> 25030 | Q16: =O16-P16 -> -1930
A17: =IFERROR(__xludf.DUMMYFUNCTION("IFERROR({SEQUENCE(10),SORTN(FILTER({$G$16:$G$41,$I$16:$I$41},$G$16:$G$41<>"""",$I$16:$I$41<>""""),10,0,2,FALSE)},"""")"),1.0) -> 1 | B17: =IFERROR(__xludf.DUMMYFUNCTION("""COMPUTED_VALUE"""),"MANFAC-1") -> MANFAC-1 | C17: =IFERROR(__xludf.DUMMYFUNCTION("""COMPUTED_VALUE"""),0.0) -> 0 | G17: MANFAC-2 | H17: =IF(G17="","",IFERROR(VLOOKUP(G17,BASE_VEICULOS!$A:$G,7,FALSE),"")) -> PROF - 07001 - MANUTENÇÃO PREDIAL- PROFARMA-2025 | I17: =SUMIFS(BASE_ABASTECIMENTO!D:D,BASE_ABASTECIMENTO!E:E,$G17,BASE_ABASTECIMENTO!A:A,">="&$B$2,BASE_ABASTECIMENTO!A:A,"<="&$B$3) -> 0 | J17: =SUMIFS(BASE_VELOE!F:F,BASE_VELOE!B:B,G17,BASE_VELOE!A:A,">="&$B$2,BASE_VELOE!A:A,"<="&$B$3,BASE_VELOE!D:D,J$15) -> 0 | K17: =SUMIFS(BASE_VELOE!$F:$F,BASE_VELOE!$B:$B,$G17,BASE_VELOE!$A:$A,">="&$B$2,BASE_VELOE!$A:$A,"<="&$B$3,BASE_VELOE!$D:$D,K$15) -> 0 | N17: =SUM(I17:M17) -> 0 | O17: =($B$4- VLOOKUP(G17,BASE_VEICULOS!A:O,15,0))/30*VLOOKUP(G17,BASE_VEICULOS!A:O,12,0) -> 21900 | P17: =IFERROR(__xludf.DUMMYFUNCTION("IF(G17="""","""",IFERROR(MAX(FILTER(BASE_KM!$C$2:$C1000, BASE_KM!$B$2:$B1000=G17, BASE_KM!$A$2:$A1000=MAX(FILTER(BASE_KM!$A$2:$A1000, BASE_KM!$B$2:$B1000=G17)))),""""))"),27226.0) -> 27226 | Q17: =O17-P17 -> -5326
A18: =IFERROR(__xludf.DUMMYFUNCTION("""COMPUTED_VALUE"""),2.0) -> 2 | B18: =IFERROR(__xludf.DUMMYFUNCTION("""COMPUTED_VALUE"""),"MANFAC-2") -> MANFAC-2 | C18: =IFERROR(__xludf.DUMMYFUNCTION("""COMPUTED_VALUE"""),0.0) -> 0 | G18: MANFAC-3 | H18: =IF(G18="","",IFERROR(VLOOKUP(G18,BASE_VEICULOS!$A:$G,7,FALSE),"")) -> FAC - 140004 - MANUTENÇÃO PREDIAL DPSP 2025 | I18: =SUMIFS(BASE_ABASTECIMENTO!D:D,BASE_ABASTECIMENTO!E:E,$G18,BASE_ABASTECIMENTO!A:A,">="&$B$2,BASE_ABASTECIMENTO!A:A,"<="&$B$3) -> 0 | J18: =SUMIFS(BASE_VELOE!F:F,BASE_VELOE!B:B,G18,BASE_VELOE!A:A,">="&$B$2,BASE_VELOE!A:A,"<="&$B$3,BASE_VELOE!D:D,J$15) -> 0 | K18: =SUMIFS(BASE_VELOE!$F:$F,BASE_VELOE!$B:$B,$G18,BASE_VELOE!$A:$A,">="&$B$2,BASE_VELOE!$A:$A,"<="&$B$3,BASE_VELOE!$D:$D,K$15) -> 0 | N18: =SUM(I18:M18) -> 0 | O18: =($B$4- VLOOKUP(G18,BASE_VEICULOS!A:O,15,0))/30*VLOOKUP(G18,BASE_VEICULOS!A:O,12,0) -> 100400 | P18: =IFERROR(__xludf.DUMMYFUNCTION("IF(G18="""","""",IFERROR(MAX(FILTER(BASE_KM!$C$2:$C1000, BASE_KM!$B$2:$B1000=G18, BASE_KM!$A$2:$A1000=MAX(FILTER(BASE_KM!$A$2:$A1000, BASE_KM!$B$2:$B1000=G18)))),""""))"),96713.0) -> 96713 | Q18: =O18-P18 -> 3687
A19: =IFERROR(__xludf.DUMMYFUNCTION("""COMPUTED_VALUE"""),3.0) -> 3 | B19: =IFERROR(__xludf.DUMMYFUNCTION("""COMPUTED_VALUE"""),"MANFAC-3") -> MANFAC-3 | C19: =IFERROR(__xludf.DUMMYFUNCTION("""COMPUTED_VALUE"""),0.0) -> 0 | G19: MANFAC-4 | H19: =IF(G19="","",IFERROR(VLOOKUP(G19,BASE_VEICULOS!$A:$G,7,FALSE),"")) -> FAC - 140005 - SPOT MANUTENÇÃO DPSP 2025 | I19: =SUMIFS(BASE_ABASTECIMENTO!D:D,BASE_ABASTECIMENTO!E:E,$G19,BASE_ABASTECIMENTO!A:A,">="&$B$2,BASE_ABASTECIMENTO!A:A,"<="&$B$3) -> 0 | J19: =SUMIFS(BASE_VELOE!F:F,BASE_VELOE!B:B,G19,BASE_VELOE!A:A,">="&$B$2,BASE_VELOE!A:A,"<="&$B$3,BASE_VELOE!D:D,J$15) -> 0 | K19: =SUMIFS(BASE_VELOE!$F:$F,BASE_VELOE!$B:$B,$G19,BASE_VELOE!$A:$A,">="&$B$2,BASE_VELOE!$A:$A,"<="&$B$3,BASE_VELOE!$D:$D,K$15) -> 0 | N19: =SUM(I19:M19) -> 0 | O19: =($B$4- VLOOKUP(G19,BASE_VEICULOS!A:O,15,0))/30*VLOOKUP(G19,BASE_VEICULOS!A:O,12,0) -> 105300 | P19: =IFERROR(__xludf.DUMMYFUNCTION("IF(G19="""","""",IFERROR(MAX(FILTER(BASE_KM!$C$2:$C1000, BASE_KM!$B$2:$B1000=G19, BASE_KM!$A$2:$A1000=MAX(FILTER(BASE_KM!$A$2:$A1000, BASE_KM!$B$2:$B1000=G19)))),""""))"),113188.0) -> 113188 | Q19: =O19-P19 -> -7888
A20: =IFERROR(__xludf.DUMMYFUNCTION("""COMPUTED_VALUE"""),4.0) -> 4 | B20: =IFERROR(__xludf.DUMMYFUNCTION("""COMPUTED_VALUE"""),"MANFAC-4") -> MANFAC-4 | C20: =IFERROR(__xludf.DUMMYFUNCTION("""COMPUTED_VALUE"""),0.0) -> 0 | G20: MANFAC-5 | H20: =IF(G20="","",IFERROR(VLOOKUP(G20,BASE_VEICULOS!$A:$G,7,FALSE),"")) -> FAC - 140004 - MANUTENÇÃO PREDIAL DPSP 2025 | I20: =SUMIFS(BASE_ABASTECIMENTO!D:D,BASE_ABASTECIMENTO!E:E,$G20,BASE_ABASTECIMENTO!A:A,">="&$B$2,BASE_ABASTECIMENTO!A:A,"<="&$B$3) -> 0 | J20: =SUMIFS(BASE_VELOE!F:F,BASE_VELOE!B:B,G20,BASE_VELOE!A:A,">="&$B$2,BASE_VELOE!A:A,"<="&$B$3,BASE_VELOE!D:D,J$15) -> 0 | K20: =SUMIFS(BASE_VELOE!$F:$F,BASE_VELOE!$B:$B,$G20,BASE_VELOE!$A:$A,">="&$B$2,BASE_VELOE!$A:$A,"<="&$B$3,BASE_VELOE!$D:$D,K$15) -> 0 | N20: =SUM(I20:M20) -> 0 | O20: =($B$4- VLOOKUP(G20,BASE_VEICULOS!A:O,15,0))/30*VLOOKUP(G20,BASE_VEICULOS!A:O,12,0) -> 105300 | P20: =IFERROR(__xludf.DUMMYFUNCTION("IF(G20="""","""",IFERROR(MAX(FILTER(BASE_KM!$C$2:$C1000, BASE_KM!$B$2:$B1000=G20, BASE_KM!$A$2:$A1000=MAX(FILTER(BASE_KM!$A$2:$A1000, BASE_KM!$B$2:$B1000=G20)))),""""))"),98530.0) -> 98530 | Q20: =O20-P20 -> 6770
A21: =IFERROR(__xludf.DUMMYFUNCTION("""COMPUTED_VALUE"""),5.0) -> 5 | B21: =IFERROR(__xludf.DUMMYFUNCTION("""COMPUTED_VALUE"""),"MANFAC-5") -> MANFAC-5 | C21: =IFERROR(__xludf.DUMMYFUNCTION("""COMPUTED_VALUE"""),0.0) -> 0 | G21: MANFAC-6 | H21: =IF(G21="","",IFERROR(VLOOKUP(G21,BASE_VEICULOS!$A:$G,7,FALSE),"")) -> FAC - 140005 - SPOT MANUTENÇÃO DPSP 2025 | I21: =SUMIFS(BASE_ABASTECIMENTO!D:D,BASE_ABASTECIMENTO!E:E,$G21,BASE_ABASTECIMENTO!A:A,">="&$B$2,BASE_ABASTECIMENTO!A:A,"<="&$B$3) -> 0 | J21: =SUMIFS(BASE_VELOE!F:F,BASE_VELOE!B:B,G21,BASE_VELOE!A:A,">="&$B$2,BASE_VELOE!A:A,"<="&$B$3,BASE_VELOE!D:D,J$15) -> 0 | K21: =SUMIFS(BASE_VELOE!$F:$F,BASE_VELOE!$B:$B,$G21,BASE_VELOE!$A:$A,">="&$B$2,BASE_VELOE!$A:$A,"<="&$B$3,BASE_VELOE!$D:$D,K$15) -> 0 | N21: =SUM(I21:M21) -> 0 | O21: =($B$4- VLOOKUP(G21,BASE_VEICULOS!A:O,15,0))/30*VLOOKUP(G21,BASE_VEICULOS!A:O,12,0) -> 94500 | P21: =IFERROR(__xludf.DUMMYFUNCTION("IF(G21="""","""",IFERROR(MAX(FILTER(BASE_KM!$C$2:$C1000, BASE_KM!$B$2:$B1000=G21, BASE_KM!$A$2:$A1000=MAX(FILTER(BASE_KM!$A$2:$A1000, BASE_KM!$B$2:$B1000=G21)))),""""))"),114223.0) -> 114223 | Q21: =O21-P21 -> -19723
A22: =IFERROR(__xludf.DUMMYFUNCTION("""COMPUTED_VALUE"""),6.0) -> 6 | B22: =IFERROR(__xludf.DUMMYFUNCTION("""COMPUTED_VALUE"""),"MANFAC-6") -> MANFAC-6 | C22: =IFERROR(__xludf.DUMMYFUNCTION("""COMPUTED_VALUE"""),0.0) -> 0 | G22: MANFAC-7 | H22: =IF(G22="","",IFERROR(VLOOKUP(G22,BASE_VEICULOS!$A:$G,7,FALSE),"")) -> FAC - 140005 - SPOT MANUTENÇÃO DPSP 2025 | I22: =SUMIFS(BASE_ABASTECIMENTO!D:D,BASE_ABASTECIMENTO!E:E,$G22,BASE_ABASTECIMENTO!A:A,">="&$B$2,BASE_ABASTECIMENTO!A:A,"<="&$B$3) -> 0 | J22: =SUMIFS(BASE_VELOE!F:F,BASE_VELOE!B:B,G22,BASE_VELOE!A:A,">="&$B$2,BASE_VELOE!A:A,"<="&$B$3,BASE_VELOE!D:D,J$15) -> 0 | K22: =SUMIFS(BASE_VELOE!$F:$F,BASE_VELOE!$B:$B,$G22,BASE_VELOE!$A:$A,">="&$B$2,BASE_VELOE!$A:$A,"<="&$B$3,BASE_VELOE!$D:$D,K$15) -> 0 | N22: =SUM(I22:M22) -> 0 | O22: =($B$4- VLOOKUP(G22,BASE_VEICULOS!A:O,15,0))/30*VLOOKUP(G22,BASE_VEICULOS!A:O,12,0) -> 21800 | P22: =IFERROR(__xludf.DUMMYFUNCTION("IF(G22="""","""",IFERROR(MAX(FILTER(BASE_KM!$C$2:$C1000, BASE_KM!$B$2:$B1000=G22, BASE_KM!$A$2:$A1000=MAX(FILTER(BASE_KM!$A$2:$A1000, BASE_KM!$B$2:$B1000=G22)))),""""))"),16032.0) -> 16032 | Q22: =O22-P22 -> 5768
A23: =IFERROR(__xludf.DUMMYFUNCTION("""COMPUTED_VALUE"""),7.0) -> 7 | B23: =IFERROR(__xludf.DUMMYFUNCTION("""COMPUTED_VALUE"""),"MANFAC-7") -> MANFAC-7 | C23: =IFERROR(__xludf.DUMMYFUNCTION("""COMPUTED_VALUE"""),0.0) -> 0 | G23: MANFAC-8 | H23: =IF(G23="","",IFERROR(VLOOKUP(G23,BASE_VEICULOS!$A:$G,7,FALSE),"")) | I23: =SUMIFS(BASE_ABASTECIMENTO!D:D,BASE_ABASTECIMENTO!E:E,$G23,BASE_ABASTECIMENTO!A:A,">="&$B$2,BASE_ABASTECIMENTO!A:A,"<="&$B$3) -> 0 | J23: =SUMIFS(BASE_VELOE!F:F,BASE_VELOE!B:B,G23,BASE_VELOE!A:A,">="&$B$2,BASE_VELOE!A:A,"<="&$B$3,BASE_VELOE!D:D,J$15) -> 0 | K23: =SUMIFS(BASE_VELOE!$F:$F,BASE_VELOE!$B:$B,$G23,BASE_VELOE!$A:$A,">="&$B$2,BASE_VELOE!$A:$A,"<="&$B$3,BASE_VELOE!$D:$D,K$15) -> 0 | N23: =SUM(I23:M23) -> 0 | O23: =($B$4- VLOOKUP(G23,BASE_VEICULOS!A:O,15,0))/30*VLOOKUP(G23,BASE_VEICULOS!A:O,12,0) -> #N/A | P23: =IFERROR(__xludf.DUMMYFUNCTION("IF(G23="""","""",IFERROR(MAX(FILTER(BASE_KM!$C$2:$C1000, BASE_KM!$B$2:$B1000=G23, BASE_KM!$A$2:$A1000=MAX(FILTER(BASE_KM!$A$2:$A1000, BASE_KM!$B$2:$B1000=G23)))),""""))"),17420.0) -> 17420 | Q23: =O23-P23 -> #N/A
A24: =IFERROR(__xludf.DUMMYFUNCTION("""COMPUTED_VALUE"""),8.0) -> 8 | B24: =IFERROR(__xludf.DUMMYFUNCTION("""COMPUTED_VALUE"""),"MANFAC-8") -> MANFAC-8 | C24: =IFERROR(__xludf.DUMMYFUNCTION("""COMPUTED_VALUE"""),0.0) -> 0 | G24: MANFAC-9 | H24: =IF(G24="","",IFERROR(VLOOKUP(G24,BASE_VEICULOS!$A:$G,7,FALSE),"")) -> FAC - 140004 - MANUTENÇÃO PREDIAL DPSP 2025 | I24: =SUMIFS(BASE_ABASTECIMENTO!D:D,BASE_ABASTECIMENTO!E:E,$G24,BASE_ABASTECIMENTO!A:A,">="&$B$2,BASE_ABASTECIMENTO!A:A,"<="&$B$3) -> 0 | J24: =SUMIFS(BASE_VELOE!F:F,BASE_VELOE!B:B,G24,BASE_VELOE!A:A,">="&$B$2,BASE_VELOE!A:A,"<="&$B$3,BASE_VELOE!D:D,J$15) -> 0 | K24: =SUMIFS(BASE_VELOE!$F:$F,BASE_VELOE!$B:$B,$G24,BASE_VELOE!$A:$A,">="&$B$2,BASE_VELOE!$A:$A,"<="&$B$3,BASE_VELOE!$D:$D,K$15) -> 0 | N24: =SUM(I24:M24) -> 0 | O24: =($B$4- VLOOKUP(G24,BASE_VEICULOS!A:O,15,0))/30*VLOOKUP(G24,BASE_VEICULOS!A:O,12,0) -> 23300 | P24: =IFERROR(__xludf.DUMMYFUNCTION("IF(G24="""","""",IFERROR(MAX(FILTER(BASE_KM!$C$2:$C1000, BASE_KM!$B$2:$B1000=G24, BASE_KM!$A$2:$A1000=MAX(FILTER(BASE_KM!$A$2:$A1000, BASE_KM!$B$2:$B1000=G24)))),""""))"),25035.0) -> 25035 | Q24: =O24-P24 -> -1735
A25: =IFERROR(__xludf.DUMMYFUNCTION("""COMPUTED_VALUE"""),9.0) -> 9 | B25: =IFERROR(__xludf.DUMMYFUNCTION("""COMPUTED_VALUE"""),"MANFAC-9") -> MANFAC-9 | C25: =IFERROR(__xludf.DUMMYFUNCTION("""COMPUTED_VALUE"""),0.0) -> 0 | G25: MANFAC-10 | H25: =IF(G25="","",IFERROR(VLOOKUP(G25,BASE_VEICULOS!$A:$G,7,FALSE),"")) -> PROF - 07001 - MANUTENÇÃO PREDIAL- PROFARMA-2025 | I25: =SUMIFS(BASE_ABASTECIMENTO!D:D,BASE_ABASTECIMENTO!E:E,$G25,BASE_ABASTECIMENTO!A:A,">="&$B$2,BASE_ABASTECIMENTO!A:A,"<="&$B$3) -> 0 | J25: =SUMIFS(BASE_VELOE!F:F,BASE_VELOE!B:B,G25,BASE_VELOE!A:A,">="&$B$2,BASE_VELOE!A:A,"<="&$B$3,BASE_VELOE!D:D,J$15) -> 0 | K25: =SUMIFS(BASE_VELOE!$F:$F,BASE_VELOE!$B:$B,$G25,BASE_VELOE!$A:$A,">="&$B$2,BASE_VELOE!$A:$A,"<="&$B$3,BASE_VELOE!$D:$D,K$15) -> 0 | N25: =SUM(I25:M25) -> 0 | O25: =($B$4- VLOOKUP(G25,BASE_VEICULOS!A:O,15,0))/30*VLOOKUP(G25,BASE_VEICULOS!A:O,12,0) -> 21200 | P25: =IFERROR(__xludf.DUMMYFUNCTION("IF(G25="""","""",IFERROR(MAX(FILTER(BASE_KM!$C$2:$C1000, BASE_KM!$B$2:$B1000=G25, BASE_KM!$A$2:$A1000=MAX(FILTER(BASE_KM!$A$2:$A1000, BASE_KM!$B$2:$B1000=G25)))),""""))"),22512.0) -> 22512 | Q25: =O25-P25 -> -1312
A26: =IFERROR(__xludf.DUMMYFUNCTION("""COMPUTED_VALUE"""),10.0) -> 10 | B26: =IFERROR(__xludf.DUMMYFUNCTION("""COMPUTED_VALUE"""),"MANFAC-10") -> MANFAC-10 | C26: =IFERROR(__xludf.DUMMYFUNCTION("""COMPUTED_VALUE"""),0.0) -> 0 | G26: MANFAC-11 | H26: =IF(G26="","",IFERROR(VLOOKUP(G26,BASE_VEICULOS!$A:$G,7,FALSE),"")) -> PROF - 07001 - MANUTENÇÃO PREDIAL- PROFARMA-2025 | I26: =SUMIFS(BASE_ABASTECIMENTO!D:D,BASE_ABASTECIMENTO!E:E,$G26,BASE_ABASTECIMENTO!A:A,">="&$B$2,BASE_ABASTECIMENTO!A:A,"<="&$B$3) -> 0 | J26: =SUMIFS(BASE_VELOE!F:F,BASE_VELOE!B:B,G26,BASE_VELOE!A:A,">="&$B$2,BASE_VELOE!A:A,"<="&$B$3,BASE_VELOE!D:D,J$15) -> 0 | K26: =SUMIFS(BASE_VELOE!$F:$F,BASE_VELOE!$B:$B,$G26,BASE_VELOE!$A:$A,">="&$B$2,BASE_VELOE!$A:$A,"<="&$B$3,BASE_VELOE!$D:$D,K$15) -> 0 | N26: =SUM(I26:M26) -> 0 | O26: =($B$4- VLOOKUP(G26,BASE_VEICULOS!A:O,15,0))/30*VLOOKUP(G26,BASE_VEICULOS!A:O,12,0) -> 23400 | P26: =IFERROR(__xludf.DUMMYFUNCTION("IF(G26="""","""",IFERROR(MAX(FILTER(BASE_KM!$C$2:$C1000, BASE_KM!$B$2:$B1000=G26, BASE_KM!$A$2:$A1000=MAX(FILTER(BASE_KM!$A$2:$A1000, BASE_KM!$B$2:$B1000=G26)))),""""))"),29003.0) -> 29003 | Q26: =O26-P26 -> -5603
G27: MANFAC-12 | H27: =IF(G27="","",IFERROR(VLOOKUP(G27,BASE_VEICULOS!$A:$G,7,FALSE),"")) -> PROF - 07001 - MANUTENÇÃO PREDIAL- PROFARMA-2025 | I27: =SUMIFS(BASE_ABASTECIMENTO!D:D,BASE_ABASTECIMENTO!E:E,$G27,BASE_ABASTECIMENTO!A:A,">="&$B$2,BASE_ABASTECIMENTO!A:A,"<="&$B$3) -> 0 | J27: =SUMIFS(BASE_VELOE!F:F,BASE_VELOE!B:B,G27,BASE_VELOE!A:A,">="&$B$2,BASE_VELOE!A:A,"<="&$B$3,BASE_VELOE!D:D,J$15) -> 0 | K27: =SUMIFS(BASE_VELOE!$F:$F,BASE_VELOE!$B:$B,$G27,BASE_VELOE!$A:$A,">="&$B$2,BASE_VELOE!$A:$A,"<="&$B$3,BASE_VELOE!$D:$D,K$15) -> 0 | N27: =SUM(I27:M27) -> 0 | O27: =($B$4- VLOOKUP(G27,BASE_VEICULOS!A:O,15,0))/30*VLOOKUP(G27,BASE_VEICULOS!A:O,12,0) -> 23300 | P27: =IFERROR(__xludf.DUMMYFUNCTION("IF(G27="""","""",IFERROR(MAX(FILTER(BASE_KM!$C$2:$C1000, BASE_KM!$B$2:$B1000=G27, BASE_KM!$A$2:$A1000=MAX(FILTER(BASE_KM!$A$2:$A1000, BASE_KM!$B$2:$B1000=G27)))),""""))"),23929.0) -> 23929 | Q27: =O27-P27 -> -629
A28: RANKING CONSUMO COMBUSTÍVEL (POR CC) | G28: MANFAC-13 | H28: =IF(G28="","",IFERROR(VLOOKUP(G28,BASE_VEICULOS!$A:$G,7,FALSE),"")) -> PROF - 07001 - MANUTENÇÃO PREDIAL- PROFARMA-2025 | I28: =SUMIFS(BASE_ABASTECIMENTO!D:D,BASE_ABASTECIMENTO!E:E,$G28,BASE_ABASTECIMENTO!A:A,">="&$B$2,BASE_ABASTECIMENTO!A:A,"<="&$B$3) -> 0 | J28: =SUMIFS(BASE_VELOE!F:F,BASE_VELOE!B:B,G28,BASE_VELOE!A:A,">="&$B$2,BASE_VELOE!A:A,"<="&$B$3,BASE_VELOE!D:D,J$15) -> 0 | K28: =SUMIFS(BASE_VELOE!$F:$F,BASE_VELOE!$B:$B,$G28,BASE_VELOE!$A:$A,">="&$B$2,BASE_VELOE!$A:$A,"<="&$B$3,BASE_VELOE!$D:$D,K$15) -> 0 | N28: =SUM(I28:M28) -> 0 | O28: =($B$4- VLOOKUP(G28,BASE_VEICULOS!A:O,15,0))/30*VLOOKUP(G28,BASE_VEICULOS!A:O,12,0) -> 23300 | P28: =IFERROR(__xludf.DUMMYFUNCTION("IF(G28="""","""",IFERROR(MAX(FILTER(BASE_KM!$C$2:$C1000, BASE_KM!$B$2:$B1000=G28, BASE_KM!$A$2:$A1000=MAX(FILTER(BASE_KM!$A$2:$A1000, BASE_KM!$B$2:$B1000=G28)))),""""))"),25563.0) -> 25563 | Q28: =O28-P28 -> -2263
A29: #POS | B29: EQUIPE | C29: VALOR CONSUMIDO | G29: MANFAC-15 | H29: =IF(G29="","",IFERROR(VLOOKUP(G29,BASE_VEICULOS!$A:$G,7,FALSE),"")) -> PROF - 07001 - MANUTENÇÃO PREDIAL- PROFARMA-2025 | I29: =SUMIFS(BASE_ABASTECIMENTO!D:D,BASE_ABASTECIMENTO!E:E,$G29,BASE_ABASTECIMENTO!A:A,">="&$B$2,BASE_ABASTECIMENTO!A:A,"<="&$B$3) -> 0 | J29: =SUMIFS(BASE_VELOE!F:F,BASE_VELOE!B:B,G29,BASE_VELOE!A:A,">="&$B$2,BASE_VELOE!A:A,"<="&$B$3,BASE_VELOE!D:D,J$15) -> 0 | K29: =SUMIFS(BASE_VELOE!$F:$F,BASE_VELOE!$B:$B,$G29,BASE_VELOE!$A:$A,">="&$B$2,BASE_VELOE!$A:$A,"<="&$B$3,BASE_VELOE!$D:$D,K$15) -> 0 | N29: =SUM(I29:M29) -> 0 | O29: =($B$4- VLOOKUP(G29,BASE_VEICULOS!A:O,15,0))/30*VLOOKUP(G29,BASE_VEICULOS!A:O,12,0) -> 10800 | P29: =IFERROR(__xludf.DUMMYFUNCTION("IF(G29="""","""",IFERROR(MAX(FILTER(BASE_KM!$C$2:$C1000, BASE_KM!$B$2:$B1000=G29, BASE_KM!$A$2:$A1000=MAX(FILTER(BASE_KM!$A$2:$A1000, BASE_KM!$B$2:$B1000=G29)))),""""))"),25331.0) -> 25331 | Q29: =O29-P29 -> -14531
A30: =IFERROR(__xludf.DUMMYFUNCTION("IFERROR({SEQUENCE(10),QUERY({$H$16:$H$41,IFERROR(VALUE(SUBSTITUTE(SUBSTITUTE(SUBSTITUTE($I$16:$I$41,""R$"",""""),""."",""""),"","",""."")),$I$16:$I$41)},""select Col1, sum(Col2) where Col1 is not null and Col1<>'' group by Col1 order by sum(Col2) desc lim"&"it 10 label sum(Col2) ''"",0)},"""")"),"")
G31: MANFAC-18 | H31: =IF(G31="","",IFERROR(VLOOKUP(G31,BASE_VEICULOS!$A:$G,7,FALSE),"")) -> PROF - 07001 - MANUTENÇÃO PREDIAL- PROFARMA-2025 | I31: =SUMIFS(BASE_ABASTECIMENTO!D:D,BASE_ABASTECIMENTO!E:E,$G31,BASE_ABASTECIMENTO!A:A,">="&$B$2,BASE_ABASTECIMENTO!A:A,"<="&$B$3) -> 0 | J31: =SUMIFS(BASE_VELOE!F:F,BASE_VELOE!B:B,G31,BASE_VELOE!A:A,">="&$B$2,BASE_VELOE!A:A,"<="&$B$3,BASE_VELOE!D:D,J$15) -> 0 | K31: =SUMIFS(BASE_VELOE!$F:$F,BASE_VELOE!$B:$B,$G31,BASE_VELOE!$A:$A,">="&$B$2,BASE_VELOE!$A:$A,"<="&$B$3,BASE_VELOE!$D:$D,K$15) -> 0 | N31: =SUM(I31:M31) -> 0 | O31: =($B$4- VLOOKUP(G31,BASE_VEICULOS!A:O,15,0))/30*VLOOKUP(G31,BASE_VEICULOS!A:O,12,0) -> 24400 | P31: =IFERROR(__xludf.DUMMYFUNCTION("IF(G31="""","""",IFERROR(MAX(FILTER(BASE_KM!$C$2:$C1000, BASE_KM!$B$2:$B1000=G31, BASE_KM!$A$2:$A1000=MAX(FILTER(BASE_KM!$A$2:$A1000, BASE_KM!$B$2:$B1000=G31)))),""""))"),38528.0) -> 38528 | Q31: =O31-P31 -> -14128
G32: MANFAC-19 | H32: =IF(G32="","",IFERROR(VLOOKUP(G32,BASE_VEICULOS!$A:$G,7,FALSE),"")) -> PROF - 07001 - MANUTENÇÃO PREDIAL- PROFARMA-2025 | I32: =SUMIFS(BASE_ABASTECIMENTO!D:D,BASE_ABASTECIMENTO!E:E,$G32,BASE_ABASTECIMENTO!A:A,">="&$B$2,BASE_ABASTECIMENTO!A:A,"<="&$B$3) -> 0 | J32: =SUMIFS(BASE_VELOE!F:F,BASE_VELOE!B:B,G32,BASE_VELOE!A:A,">="&$B$2,BASE_VELOE!A:A,"<="&$B$3,BASE_VELOE!D:D,J$15) -> 0 | K32: =SUMIFS(BASE_VELOE!$F:$F,BASE_VELOE!$B:$B,$G32,BASE_VELOE!$A:$A,">="&$B$2,BASE_VELOE!$A:$A,"<="&$B$3,BASE_VELOE!$D:$D,K$15) -> 0 | N32: =SUM(I32:M32) -> 0 | O32: =($B$4- VLOOKUP(G32,BASE_VEICULOS!A:O,15,0))/30*VLOOKUP(G32,BASE_VEICULOS!A:O,12,0) -> 9200 | P32: =IFERROR(__xludf.DUMMYFUNCTION("IF(G32="""","""",IFERROR(MAX(FILTER(BASE_KM!$C$2:$C1000, BASE_KM!$B$2:$B1000=G32, BASE_KM!$A$2:$A1000=MAX(FILTER(BASE_KM!$A$2:$A1000, BASE_KM!$B$2:$B1000=G32)))),""""))"),23062.0) -> 23062 | Q32: =O32-P32 -> -13862
G33: MANFAC-20 | H33: =IF(G33="","",IFERROR(VLOOKUP(G33,BASE_VEICULOS!$A:$G,7,FALSE),"")) | I33: =SUMIFS(BASE_ABASTECIMENTO!D:D,BASE_ABASTECIMENTO!E:E,$G33,BASE_ABASTECIMENTO!A:A,">="&$B$2,BASE_ABASTECIMENTO!A:A,"<="&$B$3) -> 0 | J33: =SUMIFS(BASE_VELOE!F:F,BASE_VELOE!B:B,G33,BASE_VELOE!A:A,">="&$B$2,BASE_VELOE!A:A,"<="&$B$3,BASE_VELOE!D:D,J$15) -> 0 | K33: =SUMIFS(BASE_VELOE!$F:$F,BASE_VELOE!$B:$B,$G33,BASE_VELOE!$A:$A,">="&$B$2,BASE_VELOE!$A:$A,"<="&$B$3,BASE_VELOE!$D:$D,K$15) -> 0 | N33: =SUM(I33:M33) -> 0 | O33: =($B$4- VLOOKUP(G33,BASE_VEICULOS!A:O,15,0))/30*VLOOKUP(G33,BASE_VEICULOS!A:O,12,0) -> #N/A | P33: =IFERROR(__xludf.DUMMYFUNCTION("IF(G33="""","""",IFERROR(MAX(FILTER(BASE_KM!$C$2:$C1000, BASE_KM!$B$2:$B1000=G33, BASE_KM!$A$2:$A1000=MAX(FILTER(BASE_KM!$A$2:$A1000, BASE_KM!$B$2:$B1000=G33)))),""""))"),26286.0) -> 26286 | Q33: =O33-P33 -> #N/A
G34: MANFAC-21 | H34: =IF(G34="","",IFERROR(VLOOKUP(G34,BASE_VEICULOS!$A:$G,7,FALSE),"")) -> PROF - 07001 - MANUTENÇÃO PREDIAL- PROFARMA-2025 | I34: =SUMIFS(BASE_ABASTECIMENTO!D:D,BASE_ABASTECIMENTO!E:E,$G34,BASE_ABASTECIMENTO!A:A,">="&$B$2,BASE_ABASTECIMENTO!A:A,"<="&$B$3) -> 0 | J34: =SUMIFS(BASE_VELOE!F:F,BASE_VELOE!B:B,G34,BASE_VELOE!A:A,">="&$B$2,BASE_VELOE!A:A,"<="&$B$3,BASE_VELOE!D:D,J$15) -> 0 | K34: =SUMIFS(BASE_VELOE!$F:$F,BASE_VELOE!$B:$B,$G34,BASE_VELOE!$A:$A,">="&$B$2,BASE_VELOE!$A:$A,"<="&$B$3,BASE_VELOE!$D:$D,K$15) -> 0 | N34: =SUM(I34:M34) -> 0 | O34: =($B$4- VLOOKUP(G34,BASE_VEICULOS!A:O,15,0))/30*VLOOKUP(G34,BASE_VEICULOS!A:O,12,0) -> 23300 | P34: =IFERROR(__xludf.DUMMYFUNCTION("IF(G34="""","""",IFERROR(MAX(FILTER(BASE_KM!$C$2:$C1000, BASE_KM!$B$2:$B1000=G34, BASE_KM!$A$2:$A1000=MAX(FILTER(BASE_KM!$A$2:$A1000, BASE_KM!$B$2:$B1000=G34)))),""""))"),23810.0) -> 23810 | Q34: =O34-P34 -> -510
G35: MANFAC-22 | H35: =IF(G35="","",IFERROR(VLOOKUP(G35,BASE_VEICULOS!$A:$G,7,FALSE),"")) -> PROF - 07001 - MANUTENÇÃO PREDIAL- PROFARMA-2025 | I35: =SUMIFS(BASE_ABASTECIMENTO!D:D,BASE_ABASTECIMENTO!E:E,$G35,BASE_ABASTECIMENTO!A:A,">="&$B$2,BASE_ABASTECIMENTO!A:A,"<="&$B$3) -> 0 | J35: =SUMIFS(BASE_VELOE!F:F,BASE_VELOE!B:B,G35,BASE_VELOE!A:A,">="&$B$2,BASE_VELOE!A:A,"<="&$B$3,BASE_VELOE!D:D,J$15) -> 0 | K35: =SUMIFS(BASE_VELOE!$F:$F,BASE_VELOE!$B:$B,$G35,BASE_VELOE!$A:$A,">="&$B$2,BASE_VELOE!$A:$A,"<="&$B$3,BASE_VELOE!$D:$D,K$15) -> 0 | N35: =SUM(I35:M35) -> 0 | O35: =($B$4- VLOOKUP(G35,BASE_VEICULOS!A:O,15,0))/30*VLOOKUP(G35,BASE_VEICULOS!A:O,12,0) -> 22700 | P35: =IFERROR(__xludf.DUMMYFUNCTION("IF(G35="""","""",IFERROR(MAX(FILTER(BASE_KM!$C$2:$C1000, BASE_KM!$B$2:$B1000=G35, BASE_KM!$A$2:$A1000=MAX(FILTER(BASE_KM!$A$2:$A1000, BASE_KM!$B$2:$B1000=G35)))),""""))"),24560.0) -> 24560 | Q35: =O35-P35 -> -1860
G36: MANFAC-23 | H36: =IF(G36="","",IFERROR(VLOOKUP(G36,BASE_VEICULOS!$A:$G,7,FALSE),"")) | I36: =SUMIFS(BASE_ABASTECIMENTO!D:D,BASE_ABASTECIMENTO!E:E,$G36,BASE_ABASTECIMENTO!A:A,">="&$B$2,BASE_ABASTECIMENTO!A:A,"<="&$B$3) -> 0 | J36: =SUMIFS(BASE_VELOE!F:F,BASE_VELOE!B:B,G36,BASE_VELOE!A:A,">="&$B$2,BASE_VELOE!A:A,"<="&$B$3,BASE_VELOE!D:D,J$15) -> 0 | K36: =SUMIFS(BASE_VELOE!$F:$F,BASE_VELOE!$B:$B,$G36,BASE_VELOE!$A:$A,">="&$B$2,BASE_VELOE!$A:$A,"<="&$B$3,BASE_VELOE!$D:$D,K$15) -> 0 | N36: =SUM(I36:M36) -> 0 | O36: =($B$4- VLOOKUP(G36,BASE_VEICULOS!A:O,15,0))/30*VLOOKUP(G36,BASE_VEICULOS!A:O,12,0) -> #N/A | P36: =IFERROR(__xludf.DUMMYFUNCTION("IF(G36="""","""",IFERROR(MAX(FILTER(BASE_KM!$C$2:$C1000, BASE_KM!$B$2:$B1000=G36, BASE_KM!$A$2:$A1000=MAX(FILTER(BASE_KM!$A$2:$A1000, BASE_KM!$B$2:$B1000=G36)))),""""))"),110390.0) -> 110390 | Q36: =O36-P36 -> #N/A
G37: MANFAC-24 | H37: =IF(G37="","",IFERROR(VLOOKUP(G37,BASE_VEICULOS!$A:$G,7,FALSE),"")) -> PROF - 07001 - MANUTENÇÃO PREDIAL- PROFARMA-2025 | I37: =SUMIFS(BASE_ABASTECIMENTO!D:D,BASE_ABASTECIMENTO!E:E,$G37,BASE_ABASTECIMENTO!A:A,">="&$B$2,BASE_ABASTECIMENTO!A:A,"<="&$B$3) -> 0 | J37: =SUMIFS(BASE_VELOE!F:F,BASE_VELOE!B:B,G37,BASE_VELOE!A:A,">="&$B$2,BASE_VELOE!A:A,"<="&$B$3,BASE_VELOE!D:D,J$15) -> 0 | K37: =SUMIFS(BASE_VELOE!$F:$F,BASE_VELOE!$B:$B,$G37,BASE_VELOE!$A:$A,">="&$B$2,BASE_VELOE!$A:$A,"<="&$B$3,BASE_VELOE!$D:$D,K$15) -> 0 | N37: =SUM(I37:M37) -> 0 | O37: =($B$4- VLOOKUP(G37,BASE_VEICULOS!A:O,15,0))/30*VLOOKUP(G37,BASE_VEICULOS!A:O,12,0) -> 4618400 | P37: =IFERROR(__xludf.DUMMYFUNCTION("IF(G37="""","""",IFERROR(MAX(FILTER(BASE_KM!$C$2:$C1000, BASE_KM!$B$2:$B1000=G37, BASE_KM!$A$2:$A1000=MAX(FILTER(BASE_KM!$A$2:$A1000, BASE_KM!$B$2:$B1000=G37)))),""""))"),63144.0) -> 63144 | Q37: =O37-P37 -> 4555256
G38: T-ANDERSON | H38: =IF(G38="","",IFERROR(VLOOKUP(G38,BASE_VEICULOS!$A:$G,7,FALSE),"")) | I38: =SUMIFS(BASE_ABASTECIMENTO!D:D,BASE_ABASTECIMENTO!E:E,$G38,BASE_ABASTECIMENTO!A:A,">="&$B$2,BASE_ABASTECIMENTO!A:A,"<="&$B$3) -> 0 | J38: =SUMIFS(BASE_VELOE!F:F,BASE_VELOE!B:B,G38,BASE_VELOE!A:A,">="&$B$2,BASE_VELOE!A:A,"<="&$B$3,BASE_VELOE!D:D,J$15) -> 0 | K38: =SUMIFS(BASE_VELOE!$F:$F,BASE_VELOE!$B:$B,$G38,BASE_VELOE!$A:$A,">="&$B$2,BASE_VELOE!$A:$A,"<="&$B$3,BASE_VELOE!$D:$D,K$15) -> 0 | N38: =SUM(I38:M38) -> 0 | O38: =($B$4- VLOOKUP(G38,BASE_VEICULOS!A:O,15,0))/30*VLOOKUP(G38,BASE_VEICULOS!A:O,12,0) -> #N/A | P38: =IFERROR(__xludf.DUMMYFUNCTION("IF(G38="""","""",IFERROR(MAX(FILTER(BASE_KM!$C$2:$C1000, BASE_KM!$B$2:$B1000=G38, BASE_KM!$A$2:$A1000=MAX(FILTER(BASE_KM!$A$2:$A1000, BASE_KM!$B$2:$B1000=G38)))),""""))"),17379.0) -> 17379 | Q38: =O38-P38 -> #N/A
G39: REINALDO | H39: =IF(G39="","",IFERROR(VLOOKUP(G39,BASE_VEICULOS!$A:$G,7,FALSE),"")) | I39: =SUMIFS(BASE_ABASTECIMENTO!D:D,BASE_ABASTECIMENTO!E:E,$G39,BASE_ABASTECIMENTO!A:A,">="&$B$2,BASE_ABASTECIMENTO!A:A,"<="&$B$3) -> 0 | J39: =SUMIFS(BASE_VELOE!F:F,BASE_VELOE!B:B,G39,BASE_VELOE!A:A,">="&$B$2,BASE_VELOE!A:A,"<="&$B$3,BASE_VELOE!D:D,J$15) -> 0 | K39: =SUMIFS(BASE_VELOE!$F:$F,BASE_VELOE!$B:$B,$G39,BASE_VELOE!$A:$A,">="&$B$2,BASE_VELOE!$A:$A,"<="&$B$3,BASE_VELOE!$D:$D,K$15) -> 0 | N39: =SUM(I39:M39) -> 0 | O39: =($B$4- VLOOKUP(G39,BASE_VEICULOS!A:O,15,0))/30*VLOOKUP(G39,BASE_VEICULOS!A:O,12,0) -> #N/A | P39: =IFERROR(__xludf.DUMMYFUNCTION("IF(G39="""","""",IFERROR(MAX(FILTER(BASE_KM!$C$2:$C1000, BASE_KM!$B$2:$B1000=G39, BASE_KM!$A$2:$A1000=MAX(FILTER(BASE_KM!$A$2:$A1000, BASE_KM!$B$2:$B1000=G39)))),""""))"),"") | Q39: =O39-P39 -> #N/A
G40: GABRIEL | H40: =IF(G40="","",IFERROR(VLOOKUP(G40,BASE_VEICULOS!$A:$G,7,FALSE),"")) | I40: =SUMIFS(BASE_ABASTECIMENTO!D:D,BASE_ABASTECIMENTO!E:E,$G40,BASE_ABASTECIMENTO!A:A,">="&$B$2,BASE_ABASTECIMENTO!A:A,"<="&$B$3) -> 0 | J40: =SUMIFS(BASE_VELOE!F:F,BASE_VELOE!B:B,G40,BASE_VELOE!A:A,">="&$B$2,BASE_VELOE!A:A,"<="&$B$3,BASE_VELOE!D:D,J$15) -> 0 | K40: =SUMIFS(BASE_VELOE!$F:$F,BASE_VELOE!$B:$B,$G40,BASE_VELOE!$A:$A,">="&$B$2,BASE_VELOE!$A:$A,"<="&$B$3,BASE_VELOE!$D:$D,K$15) -> 0 | N40: =SUM(I40:M40) -> 0 | O40: =($B$4- VLOOKUP(G40,BASE_VEICULOS!A:O,15,0))/30*VLOOKUP(G40,BASE_VEICULOS!A:O,12,0) -> #N/A | P40: =IFERROR(__xludf.DUMMYFUNCTION("IF(G40="""","""",IFERROR(MAX(FILTER(BASE_KM!$C$2:$C1000, BASE_KM!$B$2:$B1000=G40, BASE_KM!$A$2:$A1000=MAX(FILTER(BASE_KM!$A$2:$A1000, BASE_KM!$B$2:$B1000=G40)))),""""))"),"") | Q40: =O40-P40 -> #N/A
G41: YURI | H41: =IF(G41="","",IFERROR(VLOOKUP(G41,BASE_VEICULOS!$A:$G,7,FALSE),"")) -> FAC - 140005 - SPOT MANUTENÇÃO DPSP 2025 | I41: =SUMIFS(BASE_ABASTECIMENTO!D:D,BASE_ABASTECIMENTO!E:E,$G41,BASE_ABASTECIMENTO!A:A,">="&$B$2,BASE_ABASTECIMENTO!A:A,"<="&$B$3) -> 0 | J41: =SUMIFS(BASE_VELOE!F:F,BASE_VELOE!B:B,G41,BASE_VELOE!A:A,">="&$B$2,BASE_VELOE!A:A,"<="&$B$3,BASE_VELOE!D:D,J$15) -> 0 | K41: =SUMIFS(BASE_VELOE!$F:$F,BASE_VELOE!$B:$B,$G41,BASE_VELOE!$A:$A,">="&$B$2,BASE_VELOE!$A:$A,"<="&$B$3,BASE_VELOE!$D:$D,K$15) -> 0 | N41: =SUM(I41:M41) -> 0 | O41: =($B$4- VLOOKUP(G41,BASE_VEICULOS!A:O,15,0))/30*VLOOKUP(G41,BASE_VEICULOS!A:O,12,0) -> 3066.6667 | P41: =IFERROR(__xludf.DUMMYFUNCTION("IF(G41="""","""",IFERROR(MAX(FILTER(BASE_KM!$C$2:$C1000, BASE_KM!$B$2:$B1000=G41, BASE_KM!$A$2:$A1000=MAX(FILTER(BASE_KM!$A$2:$A1000, BASE_KM!$B$2:$B1000=G41)))),""""))"),"") | Q41: =O41-P41 -> 3066.6667

Sheet BASE_PLANEJADO
A1: CENTRO DE CUSTO | B1: MÊS COMPETÊNCIA | C1: VALOR PLANEJADO | D1: VALOR POR SEMANA
A2: FAC - 140004 - MANUTENÇÃO PREDIAL DPSP 2025 | B2: 46023 | C2: 15360 | D2: =C2/4 -> 3840
A3: FAC - 140004 - MANUTENÇÃO PREDIAL DPSP 2025 | B3: 46054 | C3: 15360 | D3: =C3/4 -> 3840
A4: FAC - 140004 - MANUTENÇÃO PREDIAL DPSP 2025 | B4: 46082 | C4: 15360 | D4: =C4/4 -> 3840
A5: PROF - 07001 - MANUTENÇÃO PREDIAL- PROFARMA-2025 | B5: 46023 | C5: 16160 | D5: =C5/4 -> 4040
A6: PROF - 07001 - MANUTENÇÃO PREDIAL- PROFARMA-2025 | B6: 46054 | C6: 16160 | D6: =C6/4 -> 4040
A7: PROF - 07001 - MANUTENÇÃO PREDIAL- PROFARMA-2025 | B7: 46082 | C7: 16160 | D7: =C7/4 -> 4040
A8: PROF - 07002 - SPOT MANUTENÇÃO PROFARMA | B8: 46023 | C8: 6560 | D8: =C8/4 -> 1640
A9: PROF - 07002 - SPOT MANUTENÇÃO PROFARMA | B9: 46054 | C9: 6560 | D9: =C9/4 -> 1640
A10: PROF - 07002 - SPOT MANUTENÇÃO PROFARMA | B10: 46082 | C10: 6560 | D10: =C10/4 -> 1640
A11: FAC - 140005 - SPOT MANUTENÇÃO DPSP 2025 | B11: 46023 | C11: 11200 | D11: =C11/4 -> 2800
A12: FAC - 140005 - SPOT MANUTENÇÃO DPSP 2025 | B12: 46054 | C12: 11200 | D12: =C12/4 -> 2800
A13: FAC - 140005 - SPOT MANUTENÇÃO DPSP 2025 | B13: 46082 | C13: 11200 | D13: =C13/4 -> 2800
... A16: EC - ESCRITORIO CENTRAL | B16: 46082 | C16: 2150 | D16: =C16/4 -> 537.5

Sheet BASE_MOTORISTAS
A1: EQUIPE | B1: STATUS | C1: COLABORADOR | D1: CENTRO DE CUSTO | E1: HABILITAÇÃO | F1: DATA EM QUE EXPIRA
A2: MANFAC-1 | B2: LIDER | C2: GABRIEL DE JESUS FIALHO MIRANDA | D2: FAC - 140004 - MANUTENÇÃO PREDIAL DPSP 2025 | E2: 8087985740 | F2: 48169
A3: MANFAC-10 | B3: LIDER | C3: NADSON SANTOS DE JESUS | D3: PROF - 07001 - MANUTENÇÃO PREDIAL- PROFARMA-2025 | E3: 4350350996 | F3: 47978
A4: MANFAC-11 | B4: LIDER | C4: MARCELO LOPES VIEIRA | D4: PROF - 07001 - MANUTENÇÃO PREDIAL- PROFARMA-2025 | E4: 5974391748 | F4: 46821
A5: MANFAC-12 | B5: LIDER | C5: ANDRE VINICIUS NAZARE ESCOBAR | D5: PROF - 07001 - MANUTENÇÃO PREDIAL- PROFARMA-2025 | E5: 9057636403 | F5: 46221
A6: MANFAC-13 | B6: LIDER | C6: CARLOS HENRIQUE SILVA MENDES | D6: PROF - 07001 - MANUTENÇÃO PREDIAL- PROFARMA-2025 | E6: 6273686368 | F6: 49080
A7: MANFAC-14 | D7: PROF - 07001 - MANUTENÇÃO PREDIAL- PROFARMA-2025 | E7: LIDER | F7: MANFAC-7
A8: MANFAC-15 | B8: LIDER | C8: ALDENIR TEIXIERA CARVALHO | D8: PROF - 07001 - MANUTENÇÃO PREDIAL- PROFARMA-2025 | E8: 7692354540 | F8: 49626
A9: MANFAC-7 | B9: LIDER | C9: HELENO ROVANE DOS SANTOS | D9: FAC - 140005 - SPOT MANUTENÇÃO DPSP 2025 | E9: 506291588
A10: MANFAC-17 | D10: PROF - 07001 - MANUTENÇÃO PREDIAL- PROFARMA-2025 | E10: LIDER | F10: MANFAC-10
A11: MANFAC-18 | B11: LIDER | C11: JORGE LUIZ DOS SANTOS VIEIRA | D11: FAC - 140004 - MANUTENÇÃO PREDIAL DPSP 2025 | E11: 1910272443 | F11: 48110
A12: MANFAC-19 | B12: LIDER | C12: CARLOS ARTHUR FERREIRA DE ANDRADE | D12: FAC - 140005 - SPOT MANUTENÇÃO DPSP 2025 | E12: LIDER | F12: MANFAC-12
A13: MANFAC-2 | B13: LIDER | C13: FABIO DA CONCEIÇÃO | D13: FAC - 140004 - MANUTENÇÃO PREDIAL DPSP 2025 | E13: 4350350996 | F13: 47978
A14: MANFAC-20 | B14: LIDER | C14: WEVERTON MIRANDA MATOS | D14: PROF - 07001 - MANUTENÇÃO PREDIAL- PROFARMA-2025 | E14: 8699424265 | F14: 48903
A15: MANFAC-21 | B15: LIDER | C15: MULLER GOMES DOS SANTOS | D15: PROF - 07001 - MANUTENÇÃO PREDIAL- PROFARMA-2025 | E15: 5550137007 | F15: 48181
A16: MANFAC-22 | B16: LIDER | C16: RICHARD GUIMARÃES FARIAS | D16: PROF - 07001 - MANUTENÇÃO PREDIAL- PROFARMA-2025 | E16: 4355440260 | F16: 48933
A17: MANFAC-23 | B17: LIDER | C17: DOUGLAS SIQUEIRA DOS SANTOS | D17: FAC - 140005 - SPOT MANUTENÇÃO DPSP 2025 | E17: LIDER | F17: MANFAC-17
A18: MANFAC-8 | C18: TIAGO LOURENÇO DOS SANTOS CONCEIÇÃO NUNES | D18: PROF - 07001 - MANUTENÇÃO PREDIAL- PROFARMA-2025 | E18: LIDER | F18: MANFAC-18
A19: MANFAC-3 | B19: LIDER | C19: AILTON HONORATO DOS SANTOS | D19: FAC - 140004 - MANUTENÇÃO PREDIAL DPSP 2025 | E19: 78247835 | F19: 48966
A20: MANFAC-4 | B20: LIDER | C20: MICHEL DA SILVA PINHEIRO | D20: FAC - 140005 - SPOT MANUTENÇÃO DPSP 2025 | E20: NÃO POSSUI
A21: MANFAC-5 | B21: LIDER | C21: RAFAEL SILVA DE OLIVEIRA | D21: FAC - 140004 - MANUTENÇÃO PREDIAL DPSP 2025 | E21: 7346753153 | F21: 49128
A22: MANFAC-20 | C22: WEVERTON MIRANDA MATOS | D22: PROF - 07001 - MANUTENÇÃO PREDIAL- PROFARMA-2025 | E22: LIDER | F22: MANFAC-22
A23: MANFAC-6 | B23: LIDER | C23: DIEGO DA SILVA OLIVEIRA | D23: FAC - 140005 - SPOT MANUTENÇÃO DPSP 2025 | E23: 7572524788 | F23: 49343
A24: MANFAC-8 | B24: LIDER | C24: ALAN DAVID SILVA DOS SANTOS | D24: PROF - 07001 - MANUTENÇÃO PREDIAL- PROFARMA-2025 | E24: 5454035601 | F24: 48111
A25: MANFAC-9 | B25: LIDER | C25: MARCELINO ALMEIDA DE CASTRO | D25: FAC - 140004 - MANUTENÇÃO PREDIAL DPSP 2025 | E25: 6660373002 | F25: 49706

Sheet BASE_VELOE
A1: DATA | B1: EQUIPE | C1: PLACA | D1: TIPO | E1: LOCAL | F1: VALOR | G1: =IFERROR(VLOOKUP(C2,BASE_VEICULOS!A:B,2, FALSE),"")
A2: 46076 | B2: MANFAC-19 | C2: =VLOOKUP(B2,BASE_VEICULOS!A:B,2,0) -> TEH3I02 | D2: PEDAGIO | E2: CONCESSIONARIA ECORIOMINAS | F2: 17.04
A3: 46076 | B3: MANFAC-19 | C3: =VLOOKUP(B3,BASE_VEICULOS!A:B,2,0) -> TEH3I02 | D3: PEDAGIO | E3: CONCESSIONARIA ROTA 116 S.A | F3: 9.6
A4: 46076 | B4: MANFAC-19 | C4: =VLOOKUP(B4,BASE_VEICULOS!A:B,2,0) -> TEH3I02 | D4: PEDAGIO | E4: CONCESSIONARIA ROTA 116 S.A | F4: 9.6
A5: 46076 | B5: MANFAC-19 | C5: =VLOOKUP(B5,BASE_VEICULOS!A:B,2,0) -> TEH3I02 | D5: PEDAGIO | E5: CONCESSIONARIA ECORIOMINAS | F5: 17.04
A6: 46076 | B6: MANFAC-21 | C6: =VLOOKUP(B6,BASE_VEICULOS!A:B,2,0) -> TEW9A23 | D6: PEDAGIO | E6: CONCESSIONARIA ECORIOMINAS | F6: 18.34
A7: 46076 | B7: MANFAC-21 | C7: =VLOOKUP(B7,BASE_VEICULOS!A:B,2,0) -> TEW9A23 | D7: PEDAGIO | E7: CONCESSIONARIA ECORIOMINAS | F7: 18.34
A8: 46076 | B8: MANFAC-21 | C8: =VLOOKUP(B8,BASE_VEICULOS!A:B,2,0) -> TEW9A23 | D8: PEDAGIO | E8: CONCESSIONARIA ROTA 116 S.A | F8: 9.6
A9: 46076 | B9: MANFAC-21 | C9: =VLOOKUP(B9,BASE_VEICULOS!A:B,2,0) -> TEW9A23 | D9: PEDAGIO | E9: CONCESSIONARIA ROTA 116 S.A | F9: 9.6
A10: 46076 | B10: MANFAC-8 | C10: =VLOOKUP(B10,BASE_VEICULOS!A:B,2,0) -> #N/A | D10: PEDAGIO | E10: CONCESSIONARIA ECORIOMINAS | F10: 12.69
A11: 46076 | B11: MANFAC-8 | C11: =VLOOKUP(B11,BASE_VEICULOS!A:B,2,0) -> #N/A | D11: PEDAGIO | E11: CONCESSIONARIA ECORIOMINAS | F11: 12.69
A12: 46076 | B12: MANFAC-15 | C12: =VLOOKUP(B12,BASE_VEICULOS!A:B,2,0) -> TEQ2I74 | D12: PEDAGIO | E12: CONCESSIONARIA PONTE RIO NITEROI S.A | F12: 6.8
A13: 46076 | B13: MANFAC-2 | C13: =VLOOKUP(B13,BASE_VEICULOS!A:B,2,0) -> TEW9A28 | D13: PEDAGIO | E13: CONCESSIONARIA DA RODOVIA DOS LAGOS S.A | F13: 18.4
... A213: 46089 | B213: MANFAC-15 | C213: =VLOOKUP(B213,BASE_VEICULOS!A:B,2,0) -> TEQ2I74 | D213: PEDAGIO | E213: CONCESSIONARIA ECORIOMINAS | F213: 19.1
A214: 46089 | C214: TEW9A20 | D214: PEDAGIO | E214: ELOVIAS S.A. | F214: 19.95
A215: 46089 | B215: MANFAC-7 | C215: =VLOOKUP(B215,BASE_VEICULOS!A:B,2,0) -> TEW9A27 | D215: PEDAGIO | E215: AUTOPISTA FLUMINENSE S.A | F215: 7.5
A216: 46089 | B216: MANFAC-7 | C216: =VLOOKUP(B216,BASE_VEICULOS!A:B,2,0) -> TEW9A27 | D216: PEDAGIO | E216: CONCESSIONARIA DA RODOVIA DOS LAGOS S.A | F216: 30.6
A217: 46089 | B217: MANFAC-9 | C217: =VLOOKUP(B217,BASE_VEICULOS!A:B,2,0) -> TEW9A29 | D217: PEDAGIO | E217: ELOVIAS S.A. | F217: 19.95
A218: 46089 | B218: MANFAC-13 | C218: =VLOOKUP(B218,BASE_VEICULOS!A:B,2,0) -> TEW9A33 | D218: PEDAGIO | E218: AUTOPISTA FLUMINENSE S.A | F218: 7.5
A219: 46090 | B219: MANFAC-6 | C219: =VLOOKUP(B219,BASE_VEICULOS!A:B,2,0) -> EWH1B84 | D219: PEDAGIO | E219: AUTOPISTA FLUMINENSE S.A | F219: 7.5
A220: 46090 | B220: MANFAC-6 | C220: =VLOOKUP(B220,BASE_VEICULOS!A:B,2,0) -> EWH1B84 | D220: PEDAGIO | E220: CONCESSIONARIA PONTE RIO NITEROI S.A | F220: 6.2
A221: 46090 | B221: MANFAC-2 | C221: =VLOOKUP(B221,BASE_VEICULOS!A:B,2,0) -> TEW9A28 | D221: PEDAGIO | E221: CONCESSIONARIA PONTE RIO NITEROI S.A | F221: 6.2
A222: 46090 | B222: REINALDO | C222: =VLOOKUP(B222,BASE_VEICULOS!A:B,2,0) -> #N/A | D222: PEDAGIO | E222: CONCESSIONARIA VIARIO S.A | F222: 8.95
A223: 46090 | B223: MANFAC-19 | C223: =VLOOKUP(B223,BASE_VEICULOS!A:B,2,0) -> TEH3I02 | D223: PEDAGIO | E223: CONCESSIONARIA VIARIO S.A | F223: 8.95
A224: 46090 | B224: MANFAC-19 | C224: =VLOOKUP(B224,BASE_VEICULOS!A:B,2,0) -> TEH3I02 | D224: PEDAGIO | E224: CONCESSIONARIA VIARIO S.A | F224: 8.95
A225: 46090 | B225: MANFAC-18 | C225: =VLOOKUP(B225,BASE_VEICULOS!A:B,2,0) -> TET5H37 | D225: PEDAGIO | E225: CONCESSIONARIA DA RODOVIA DOS LAGOS S.A | F225: 30.6
A226: 46090 | B226: MANFAC-18 | C226: =VLOOKUP(B226,BASE_VEICULOS!A:B,2,0) -> TET5H37 | D226: PEDAGIO | E226: CONCESSIONARIA PONTE RIO NITEROI S.A | F226: 6.2
... A411: 46099 | B411: GABRIEL VIDAL | C411: =VLOOKUP(B411,BASE_VEICULOS!A:B,2,0) -> #N/A | D411: PEDAGIO | E411: LINHA AMARELA S.A | F411: 3.8
A412: 46099 | C412: RNK | D412: PEDAGIO | E412: CONCESSIONARIA DO SISTEMA RODOVIARIO RIO SAO PAULO S.A | F412: 4.56
A413: 46099 | C413: RNK | D413: PEDAGIO | E413: CONCESSIONARIA DO SISTEMA RODOVIARIO RIO SAO PAULO S.A | F413: 4.56
A414: 46099 | B414: MANFAC-15 | C414: =VLOOKUP(B414,BASE_VEICULOS!A:B,2,0) -> TEQ2I74 | D414: PEDAGIO | E414: AUTOPISTA FLUMINENSE S.A | F414: 7.12
A415: 46099 | B415: MANFAC-15 | C415: =VLOOKUP(B415,BASE_VEICULOS!A:B,2,0) -> TEQ2I74 | D415: PEDAGIO | E415: AUTOPISTA FLUMINENSE S.A | F415: 7.12
A416: 46099 | B416: MANFAC-15 | C416: =VLOOKUP(B416,BASE_VEICULOS!A:B,2,0) -> TEQ2I74 | D416: PEDAGIO | E416: AUTOPISTA FLUMINENSE S.A | F416: 3.98
A417: 46099 | B417: MANFAC-24 | C417: =VLOOKUP(B417,BASE_VEICULOS!A:B,2,0) -> SRU8D16 | D417: PEDAGIO | E417: CONCESSIONARIA PONTE RIO NITEROI S.A | F417: 6.6
A418: 46099 | B418: MANFAC-7 | C418: =VLOOKUP(B418,BASE_VEICULOS!A:B,2,0) -> TEW9A27 | D418: PEDAGIO | E418: CONCESSIONARIA PONTE RIO NITEROI S.A | F418: 6.6
A419: 46099 | B419: REINALDO | C419: =VLOOKUP(B419,BASE_VEICULOS!A:B,2,0) -> #N/A | D419: PEDAGIO | E419: CONCESSIONARIA PONTE RIO NITEROI S.A | F419: 6.6
A420: 46099 | B420: MANFAC-19 | C420: =VLOOKUP(B420,BASE_VEICULOS!A:B,2,0) -> TEH3I02 | D420: ESTACIONAMENTO | E420: CONSORCIO PARKING NORTESHOPPING | F420: 20
A421: 46099 | B421: MANFAC-18 | C421: =VLOOKUP(B421,BASE_VEICULOS!A:B,2,0) -> TET5H37 | D421: PEDAGIO | E421: CONCESSIONARIA ECORIOMINAS | F421: 9.98
A422: 46099 | B422: MANFAC-18 | C422: =VLOOKUP(B422,BASE_VEICULOS!A:B,2,0) -> TET5H37 | D422: PEDAGIO | E422: CONCESSIONARIA DO SISTEMA RODOVIARIO RIO SAO PAULO S.A | F422: 4.56
A423: 46099 | B423: MANFAC-18 | C423: =VLOOKUP(B423,BASE_VEICULOS!A:B,2,0) -> TET5H37 | D423: PEDAGIO | E423: CONCESSIONARIA DO SISTEMA RODOVIARIO RIO SAO PAULO S.A | F423: 4.56
A424: 46099 | B424: MANFAC-18 | C424: =VLOOKUP(B424,BASE_VEICULOS!A:B,2,0) -> TET5H37 | D424: PEDAGIO | E424: CONCESSIONARIA DO SISTEMA RODOVIARIO RIO SAO PAULO S.A | F424: 4.56
A425: 46099 | B425: MANFAC-18 | C425: =VLOOKUP(B425,BASE_VEICULOS!A:B,2,0) -> TET5H37 | D425: PEDAGIO | E425: CONCESSIONARIA DO SISTEMA RODOVIARIO RIO SAO PAULO S.A | F425: 4.56
... A723: 46112 | B723: JOSÉ GUILHERME | C723: =VLOOKUP(B723,BASE_VEICULOS!A:B,2,0) -> TYK8C73 | D723: PEDAGIO | E723: LINHA AMARELA S.A | F723: 3.8

Sheet BASE_KM
A1: DATA | B1: EQUIPE | C1: KM | D1: PLACA | E1: KM RODADO
A2: 46076 | B2: MANFAC-1 | C2: 14236 | D2: =IFERROR(VLOOKUP(B2,BASE_VEICULOS!$A:$B,2,0),"") -> TEW9A25 | E2: =IFERROR(__xludf.DUMMYFUNCTION("IF(OR(A2="""",D2="""",C2=""""),"""",IFERROR(MAX(0,C2-MAX(FILTER($C$2:$C2,TRIM($D$2:$D2)=TRIM(D2),(($A$2:$A2<A2)+(($A$2:$A2=A2)*(ROW($A$2:$A2)<ROW(A2))))))),""""))"),"")
A3: 46076 | B3: MANFAC-11 | C3: 14715 | D3: =IFERROR(VLOOKUP(B3,BASE_VEICULOS!$A:$B,2,0),"") -> TEW9A24 | E3: =IFERROR(__xludf.DUMMYFUNCTION("IF(OR(A3="""",D3="""",C3=""""),"""",IFERROR(MAX(0,C3-MAX(FILTER($C$2:$C3,TRIM($D$2:$D3)=TRIM(D3),(($A$2:$A3<A3)+(($A$2:$A3=A3)*(ROW($A$2:$A3)<ROW(A3))))))),""""))"),"")
A4: 46076 | B4: MANFAC-24 | C4: 52136 | D4: =IFERROR(VLOOKUP(B4,BASE_VEICULOS!$A:$B,2,0),"") -> SRU8D16 | E4: =IFERROR(__xludf.DUMMYFUNCTION("IF(OR(A4="""",D4="""",C4=""""),"""",IFERROR(MAX(0,C4-MAX(FILTER($C$2:$C4,TRIM($D$2:$D4)=TRIM(D4),(($A$2:$A4<A4)+(($A$2:$A4=A4)*(ROW($A$2:$A4)<ROW(A4))))))),""""))"),"")
A5: 46076 | B5: MANFAC-12 | C5: 13756 | D5: =IFERROR(VLOOKUP(B5,BASE_VEICULOS!$A:$B,2,0),"") -> TEW9A34 | E5: =IFERROR(__xludf.DUMMYFUNCTION("IF(OR(A5="""",D5="""",C5=""""),"""",IFERROR(MAX(0,C5-MAX(FILTER($C$2:$C5,TRIM($D$2:$D5)=TRIM(D5),(($A$2:$A5<A5)+(($A$2:$A5=A5)*(ROW($A$2:$A5)<ROW(A5))))))),""""))"),"")
A6: 46076 | B6: MANFAC-13 | C6: 15391 | D6: =IFERROR(VLOOKUP(B6,BASE_VEICULOS!$A:$B,2,0),"") -> TEW9A33 | E6: =IFERROR(__xludf.DUMMYFUNCTION("IF(OR(A6="""",D6="""",C6=""""),"""",IFERROR(MAX(0,C6-MAX(FILTER($C$2:$C6,TRIM($D$2:$D6)=TRIM(D6),(($A$2:$A6<A6)+(($A$2:$A6=A6)*(ROW($A$2:$A6)<ROW(A6))))))),""""))"),"")
A7: 46076 | B7: MANFAC-18 | C7: 24327 | D7: =IFERROR(VLOOKUP(B7,BASE_VEICULOS!$A:$B,2,0),"") -> TET5H37 | E7: =IFERROR(__xludf.DUMMYFUNCTION("IF(OR(A7="""",D7="""",C7=""""),"""",IFERROR(MAX(0,C7-MAX(FILTER($C$2:$C7,TRIM($D$2:$D7)=TRIM(D7),(($A$2:$A7<A7)+(($A$2:$A7=A7)*(ROW($A$2:$A7)<ROW(A7))))))),""""))"),"")
A8: 46076 | B8: MANFAC-19 | C8: 14148 | D8: =IFERROR(VLOOKUP(B8,BASE_VEICULOS!$A:$B,2,0),"") -> TEH3I02 | E8: =IFERROR(__xludf.DUMMYFUNCTION("IF(OR(A8="""",D8="""",C8=""""),"""",IFERROR(MAX(0,C8-MAX(FILTER($C$2:$C8,TRIM($D$2:$D8)=TRIM(D8),(($A$2:$A8<A8)+(($A$2:$A8=A8)*(ROW($A$2:$A8)<ROW(A8))))))),""""))"),"")
A9: 46076 | B9: MANFAC-2 | C9: 93945 | D9: =IFERROR(VLOOKUP(B9,BASE_VEICULOS!$A:$B,2,0),"") -> TEW9A28 | E9: =IFERROR(__xludf.DUMMYFUNCTION("IF(OR(A9="""",D9="""",C9=""""),"""",IFERROR(MAX(0,C9-MAX(FILTER($C$2:$C9,TRIM($D$2:$D9)=TRIM(D9),(($A$2:$A9<A9)+(($A$2:$A9=A9)*(ROW($A$2:$A9)<ROW(A9))))))),""""))"),"")
A10: 46076 | B10: MANFAC-20 | C10: 16073 | D10: =IFERROR(VLOOKUP(B10,BASE_VEICULOS!$A:$B,2,0),"") | E10: =IFERROR(__xludf.DUMMYFUNCTION("IF(OR(A10="""",D10="""",C10=""""),"""",IFERROR(MAX(0,C10-MAX(FILTER($C$2:$C10,TRIM($D$2:$D10)=TRIM(D10),(($A$2:$A10<A10)+(($A$2:$A10=A10)*(ROW($A$2:$A10)<ROW(A10))))))),""""))"),"")
A11: 46076 | B11: MANFAC-21 | C11: 14187 | D11: =IFERROR(VLOOKUP(B11,BASE_VEICULOS!$A:$B,2,0),"") -> TEW9A23 | E11: =IFERROR(__xludf.DUMMYFUNCTION("IF(OR(A11="""",D11="""",C11=""""),"""",IFERROR(MAX(0,C11-MAX(FILTER($C$2:$C11,TRIM($D$2:$D11)=TRIM(D11),(($A$2:$A11<A11)+(($A$2:$A11=A11)*(ROW($A$2:$A11)<ROW(A11))))))),""""))"),"")
A12: 46076 | B12: MANFAC-22 | C12: 12552 | D12: =IFERROR(VLOOKUP(B12,BASE_VEICULOS!$A:$B,2,0),"") -> TEW9A26 | E12: =IFERROR(__xludf.DUMMYFUNCTION("IF(OR(A12="""",D12="""",C12=""""),"""",IFERROR(MAX(0,C12-MAX(FILTER($C$2:$C12,TRIM($D$2:$D12)=TRIM(D12),(($A$2:$A12<A12)+(($A$2:$A12=A12)*(ROW($A$2:$A12)<ROW(A12))))))),""""))"),"")
A13: 46076 | B13: MANFAC-23 | C13: 103981 | D13: =IFERROR(VLOOKUP(B13,BASE_VEICULOS!$A:$B,2,0),"") | E13: =IFERROR(__xludf.DUMMYFUNCTION("IF(OR(A13="""",D13="""",C13=""""),"""",IFERROR(MAX(0,C13-MAX(FILTER($C$2:$C13,TRIM($D$2:$D13)=TRIM(D13),(($A$2:$A13<A13)+(($A$2:$A13=A13)*(ROW($A$2:$A13)<ROW(A13))))))),""""))"),"")
A14: 46076 | B14: MANFAC-3 | C14: 87151 | D14: =IFERROR(VLOOKUP(B14,BASE_VEICULOS!$A:$B,2,0),"") -> FIL8C14 | E14: =IFERROR(__xludf.DUMMYFUNCTION("IF(OR(A14="""",D14="""",C14=""""),"""",IFERROR(MAX(0,C14-MAX(FILTER($C$2:$C14,TRIM($D$2:$D14)=TRIM(D14),(($A$2:$A14<A14)+(($A$2:$A14=A14)*(ROW($A$2:$A14)<ROW(A14))))))),""""))"),"")
A15: 46076 | B15: MANFAC-4 | C15: 103459 | D15: =IFERROR(VLOOKUP(B15,BASE_VEICULOS!$A:$B,2,0),"") -> FGO3C61 | E15: =IFERROR(__xludf.DUMMYFUNCTION("IF(OR(A15="""",D15="""",C15=""""),"""",IFERROR(MAX(0,C15-MAX(FILTER($C$2:$C15,TRIM($D$2:$D15)=TRIM(D15),(($A$2:$A15<A15)+(($A$2:$A15=A15)*(ROW($A$2:$A15)<ROW(A15))))))),""""))"),"")
A16: 46076 | B16: MANFAC-5 | C16: 87891 | D16: =IFERROR(VLOOKUP(B16,BASE_VEICULOS!$A:$B,2,0),"") -> FOK8A73 | E16: =IFERROR(__xludf.DUMMYFUNCTION("IF(OR(A16="""",D16="""",C16=""""),"""",IFERROR(MAX(0,C16-MAX(FILTER($C$2:$C16,TRIM($D$2:$D16)=TRIM(D16),(($A$2:$A16<A16)+(($A$2:$A16=A16)*(ROW($A$2:$A16)<ROW(A16))))))),""""))"),"")
A17: 46076 | B17: MANFAC-6 | C17: 105805 | D17: =IFERROR(VLOOKUP(B17,BASE_VEICULOS!$A:$B,2,0),"") -> EWH1B84 | E17: =IFERROR(__xludf.DUMMYFUNCTION("IF(OR(A17="""",D17="""",C17=""""),"""",IFERROR(MAX(0,C17-MAX(FILTER($C$2:$C17,TRIM($D$2:$D17)=TRIM(D17),(($A$2:$A17<A17)+(($A$2:$A17=A17)*(ROW($A$2:$A17)<ROW(A17))))))),""""))"),"")
A18: 46076 | B18: MANFAC-7 | C18: 9819 | D18: =IFERROR(VLOOKUP(B18,BASE_VEICULOS!$A:$B,2,0),"") -> TEW9A27 | E18: =IFERROR(__xludf.DUMMYFUNCTION("IF(OR(A18="""",D18="""",C18=""""),"""",IFERROR(MAX(0,C18-MAX(FILTER($C$2:$C18,TRIM($D$2:$D18)=TRIM(D18),(($A$2:$A18<A18)+(($A$2:$A18=A18)*(ROW($A$2:$A18)<ROW(A18))))))),""""))"),"")
A19: 46076 | B19: MANFAC-8 | C19: 10224 | D19: =IFERROR(VLOOKUP(B19,BASE_VEICULOS!$A:$B,2,0),"") | E19: =IFERROR(__xludf.DUMMYFUNCTION("IF(OR(A19="""",D19="""",C19=""""),"""",IFERROR(MAX(0,C19-MAX(FILTER($C$2:$C19,TRIM($D$2:$D19)=TRIM(D19),(($A$2:$A19<A19)+(($A$2:$A19=A19)*(ROW($A$2:$A19)<ROW(A19))))))),""""))"),"")
A20: 46076 | B20: MANFAC-9 | C20: 14263 | D20: =IFERROR(VLOOKUP(B20,BASE_VEICULOS!$A:$B,2,0),"") -> TEW9A29 | E20: =IFERROR(__xludf.DUMMYFUNCTION("IF(OR(A20="""",D20="""",C20=""""),"""",IFERROR(MAX(0,C20-MAX(FILTER($C$2:$C20,TRIM($D$2:$D20)=TRIM(D20),(($A$2:$A20<A20)+(($A$2:$A20=A20)*(ROW($A$2:$A20)<ROW(A20))))))),""""))"),"")
A21: 46077 | B21: MANFAC-1 | C21: 14453 | D21: =IFERROR(VLOOKUP(B21,BASE_VEICULOS!$A:$B,2,0),"") -> TEW9A25 | E21: =IFERROR(__xludf.DUMMYFUNCTION("IF(OR(A21="""",D21="""",C21=""""),"""",IFERROR(MAX(0,C21-MAX(FILTER($C$2:$C21,TRIM($D$2:$D21)=TRIM(D21),(($A$2:$A21<A21)+(($A$2:$A21=A21)*(ROW($A$2:$A21)<ROW(A21))))))),""""))"),217.0) -> 217
A22: 46077 | B22: MANFAC-11 | C22: 14822 | D22: =IFERROR(VLOOKUP(B22,BASE_VEICULOS!$A:$B,2,0),"") -> TEW9A24 | E22: =IFERROR(__xludf.DUMMYFUNCTION("IF(OR(A22="""",D22="""",C22=""""),"""",IFERROR(MAX(0,C22-MAX(FILTER($C$2:$C22,TRIM($D$2:$D22)=TRIM(D22),(($A$2:$A22<A22)+(($A$2:$A22=A22)*(ROW($A$2:$A22)<ROW(A22))))))),""""))"),107.0) -> 107
A23: 46077 | B23: MANFAC-12 | C23: 13891 | D23: =IFERROR(VLOOKUP(B23,BASE_VEICULOS!$A:$B,2,0),"") -> TEW9A34 | E23: =IFERROR(__xludf.DUMMYFUNCTION("IF(OR(A23="""",D23="""",C23=""""),"""",IFERROR(MAX(0,C23-MAX(FILTER($C$2:$C23,TRIM($D$2:$D23)=TRIM(D23),(($A$2:$A23<A23)+(($A$2:$A23=A23)*(ROW($A$2:$A23)<ROW(A23))))))),""""))"),135.0) -> 135
A24: 46077 | B24: MANFAC-13 | C24: 15463 | D24: =IFERROR(VLOOKUP(B24,BASE_VEICULOS!$A:$B,2,0),"") -> TEW9A33 | E24: =IFERROR(__xludf.DUMMYFUNCTION("IF(OR(A24="""",D24="""",C24=""""),"""",IFERROR(MAX(0,C24-MAX(FILTER($C$2:$C24,TRIM($D$2:$D24)=TRIM(D24),(($A$2:$A24<A24)+(($A$2:$A24=A24)*(ROW($A$2:$A24)<ROW(A24))))))),""""))"),72.0) -> 72
A25: 46077 | B25: MANFAC-19 | C25: 14292 | D25: =IFERROR(VLOOKUP(B25,BASE_VEICULOS!$A:$B,2,0),"") -> TEH3I02 | E25: =IFERROR(__xludf.DUMMYFUNCTION("IF(OR(A25="""",D25="""",C25=""""),"""",IFERROR(MAX(0,C25-MAX(FILTER($C$2:$C25,TRIM($D$2:$D25)=TRIM(D25),(($A$2:$A25<A25)+(($A$2:$A25=A25)*(ROW($A$2:$A25)<ROW(A25))))))),""""))"),144.0) -> 144
A26: 46077 | B26: MANFAC-20 | C26: 16186 | D26: =IFERROR(VLOOKUP(B26,BASE_VEICULOS!$A:$B,2,0),"") | E26: =IFERROR(__xludf.DUMMYFUNCTION("IF(OR(A26="""",D26="""",C26=""""),"""",IFERROR(MAX(0,C26-MAX(FILTER($C$2:$C26,TRIM($D$2:$D26)=TRIM(D26),(($A$2:$A26<A26)+(($A$2:$A26=A26)*(ROW($A$2:$A26)<ROW(A26))))))),""""))"),"")
A27: 46077 | B27: MANFAC-21 | C27: 14392 | D27: =IFERROR(VLOOKUP(B27,BASE_VEICULOS!$A:$B,2,0),"") -> TEW9A23 | E27: =IFERROR(__xludf.DUMMYFUNCTION("IF(OR(A27="""",D27="""",C27=""""),"""",IFERROR(MAX(0,C27-MAX(FILTER($C$2:$C27,TRIM($D$2:$D27)=TRIM(D27),(($A$2:$A27<A27)+(($A$2:$A27=A27)*(ROW($A$2:$A27)<ROW(A27))))))),""""))"),205.0) -> 205
A28: 46077 | B28: MANFAC-22 | C28: 12679 | D28: =IFERROR(VLOOKUP(B28,BASE_VEICULOS!$A:$B,2,0),"") -> TEW9A26 | E28: =IFERROR(__xludf.DUMMYFUNCTION("IF(OR(A28="""",D28="""",C28=""""),"""",IFERROR(MAX(0,C28-MAX(FILTER($C$2:$C28,TRIM($D$2:$D28)=TRIM(D28),(($A$2:$A28<A28)+(($A$2:$A28=A28)*(ROW($A$2:$A28)<ROW(A28))))))),""""))"),127.0) -> 127
A29: 46077 | B29: MANFAC-23 | C29: 104106 | D29: =IFERROR(VLOOKUP(B29,BASE_VEICULOS!$A:$B,2,0),"") | E29: =IFERROR(__xludf.DUMMYFUNCTION("IF(OR(A29="""",D29="""",C29=""""),"""",IFERROR(MAX(0,C29-MAX(FILTER($C$2:$C29,TRIM($D$2:$D29)=TRIM(D29),(($A$2:$A29<A29)+(($A$2:$A29=A29)*(ROW($A$2:$A29)<ROW(A29))))))),""""))"),"")
A30: 46077 | B30: MANFAC-15 | D30: =IFERROR(VLOOKUP(B30,BASE_VEICULOS!$A:$B,2,0),"") -> TEQ2I74 | E30: =IFERROR(__xludf.DUMMYFUNCTION("IF(OR(A30="""",D30="""",C30=""""),"""",IFERROR(MAX(0,C30-MAX(FILTER($C$2:$C30,TRIM($D$2:$D30)=TRIM(D30),(($A$2:$A30<A30)+(($A$2:$A30=A30)*(ROW($A$2:$A30)<ROW(A30))))))),""""))"),"")
A31: 46077 | B31: MANFAC-3 | C31: 87255 | D31: =IFERROR(VLOOKUP(B31,BASE_VEICULOS!$A:$B,2,0),"") -> FIL8C14 | E31: =IFERROR(__xludf.DUMMYFUNCTION("IF(OR(A31="""",D31="""",C31=""""),"""",IFERROR(MAX(0,C31-MAX(FILTER($C$2:$C31,TRIM($D$2:$D31)=TRIM(D31),(($A$2:$A31<A31)+(($A$2:$A31=A31)*(ROW($A$2:$A31)<ROW(A31))))))),""""))"),104.0) -> 104
A32: 46077 | B32: MANFAC-4 | C32: 103571 | D32: =IFERROR(VLOOKUP(B32,BASE_VEICULOS!$A:$B,2,0),"") -> FGO3C61 | E32: =IFERROR(__xludf.DUMMYFUNCTION("IF(OR(A32="""",D32="""",C32=""""),"""",IFERROR(MAX(0,C32-MAX(FILTER($C$2:$C32,TRIM($D$2:$D32)=TRIM(D32),(($A$2:$A32<A32)+(($A$2:$A32=A32)*(ROW($A$2:$A32)<ROW(A32))))))),""""))"),112.0) -> 112
A33: 46077 | B33: MANFAC-5 | C33: 88081 | D33: =IFERROR(VLOOKUP(B33,BASE_VEICULOS!$A:$B,2,0),"") -> FOK8A73 | E33: =IFERROR(__xludf.DUMMYFUNCTION("IF(OR(A33="""",D33="""",C33=""""),"""",IFERROR(MAX(0,C33-MAX(FILTER($C$2:$C33,TRIM($D$2:$D33)=TRIM(D33),(($A$2:$A33<A33)+(($A$2:$A33=A33)*(ROW($A$2:$A33)<ROW(A33))))))),""""))"),190.0) -> 190
A34: 46077 | B34: MANFAC-6 | C34: 105899 | D34: =IFERROR(VLOOKUP(B34,BASE_VEICULOS!$A:$B,2,0),"") -> EWH1B84 | E34: =IFERROR(__xludf.DUMMYFUNCTION("IF(OR(A34="""",D34="""",C34=""""),"""",IFERROR(MAX(0,C34-MAX(FILTER($C$2:$C34,TRIM($D$2:$D34)=TRIM(D34),(($A$2:$A34<A34)+(($A$2:$A34=A34)*(ROW($A$2:$A34)<ROW(A34))))))),""""))"),94.0) -> 94
A35: 46077 | B35: MANFAC-8 | C35: 10339 | D35: =IFERROR(VLOOKUP(B35,BASE_VEICULOS!$A:$B,2,0),"") | E35: =IFERROR(__xludf.DUMMYFUNCTION("IF(OR(A35="""",D35="""",C35=""""),"""",IFERROR(MAX(0,C35-MAX(FILTER($C$2:$C35,TRIM($D$2:$D35)=TRIM(D35),(($A$2:$A35<A35)+(($A$2:$A35=A35)*(ROW($A$2:$A35)<ROW(A35))))))),""""))"),"")
A36: 46077 | B36: T-ANDERSON | C36: 13566 | D36: =IFERROR(VLOOKUP(B36,BASE_VEICULOS!$A:$B,2,0),"") | E36: =IFERROR(__xludf.DUMMYFUNCTION("IF(OR(A36="""",D36="""",C36=""""),"""",IFERROR(MAX(0,C36-MAX(FILTER($C$2:$C36,TRIM($D$2:$D36)=TRIM(D36),(($A$2:$A36<A36)+(($A$2:$A36=A36)*(ROW($A$2:$A36)<ROW(A36))))))),""""))"),"")
A37: 46078 | B37: MANFAC-22 | C37: 12779 | D37: =IFERROR(VLOOKUP(B37,BASE_VEICULOS!$A:$B,2,0),"") -> TEW9A26 | E37: =IFERROR(__xludf.DUMMYFUNCTION("IF(OR(A37="""",D37="""",C37=""""),"""",IFERROR(MAX(0,C37-MAX(FILTER($C$2:$C37,TRIM($D$2:$D37)=TRIM(D37),(($A$2:$A37<A37)+(($A$2:$A37=A37)*(ROW($A$2:$A37)<ROW(A37))))))),""""))"),100.0) -> 100
A38: 46078 | B38: MANFAC-1 | C38: 14727 | D38: =IFERROR(VLOOKUP(B38,BASE_VEICULOS!$A:$B,2,0),"") -> TEW9A25 | E38: =IFERROR(__xludf.DUMMYFUNCTION("IF(OR(A38="""",D38="""",C38=""""),"""",IFERROR(MAX(0,C38-MAX(FILTER($C$2:$C38,TRIM($D$2:$D38)=TRIM(D38),(($A$2:$A38<A38)+(($A$2:$A38=A38)*(ROW($A$2:$A38)<ROW(A38))))))),""""))"),274.0) -> 274
A39: 46078 | B39: MANFAC-11 | C39: 14903 | D39: =IFERROR(VLOOKUP(B39,BASE_VEICULOS!$A:$B,2,0),"") -> TEW9A24 | E39: =IFERROR(__xludf.DUMMYFUNCTION("IF(OR(A39="""",D39="""",C39=""""),"""",IFERROR(MAX(0,C39-MAX(FILTER($C$2:$C39,TRIM($D$2:$D39)=TRIM(D39),(($A$2:$A39<A39)+(($A$2:$A39=A39)*(ROW($A$2:$A39)<ROW(A39))))))),""""))"),81.0) -> 81
A40: 46078 | B40: MANFAC-12 | C40: 14007 | D40: =IFERROR(VLOOKUP(B40,BASE_VEICULOS!$A:$B,2,0),"") -> TEW9A34 | E40: =IFERROR(__xludf.DUMMYFUNCTION("IF(OR(A40="""",D40="""",C40=""""),"""",IFERROR(MAX(0,C40-MAX(FILTER($C$2:$C40,TRIM($D$2:$D40)=TRIM(D40),(($A$2:$A40<A40)+(($A$2:$A40=A40)*(ROW($A$2:$A40)<ROW(A40))))))),""""))"),116.0) -> 116
A41: 46078 | B41: MANFAC-13 | C41: 15584 | D41: =IFERROR(VLOOKUP(B41,BASE_VEICULOS!$A:$B,2,0),"") -> TEW9A33 | E41: =IFERROR(__xludf.DUMMYFUNCTION("IF(OR(A41="""",D41="""",C41=""""),"""",IFERROR(MAX(0,C41-MAX(FILTER($C$2:$C41,TRIM($D$2:$D41)=TRIM(D41),(($A$2:$A41<A41)+(($A$2:$A41=A41)*(ROW($A$2:$A41)<ROW(A41))))))),""""))"),121.0) -> 121
A42: 46078 | B42: MANFAC-15 | C42: 70958 | D42: =IFERROR(VLOOKUP(B42,BASE_VEICULOS!$A:$B,2,0),"") -> TEQ2I74 | E42: =IFERROR(__xludf.DUMMYFUNCTION("IF(OR(A42="""",D42="""",C42=""""),"""",IFERROR(MAX(0,C42-MAX(FILTER($C$2:$C42,TRIM($D$2:$D42)=TRIM(D42),(($A$2:$A42<A42)+(($A$2:$A42=A42)*(ROW($A$2:$A42)<ROW(A42))))))),""""))"),70958.0) -> 70958
A43: 46078 | B43: MANFAC-18 | C43: 24560 | D43: =IFERROR(VLOOKUP(B43,BASE_VEICULOS!$A:$B,2,0),"") -> TET5H37 | E43: =IFERROR(__xludf.DUMMYFUNCTION("IF(OR(A43="""",D43="""",C43=""""),"""",IFERROR(MAX(0,C43-MAX(FILTER($C$2:$C43,TRIM($D$2:$D43)=TRIM(D43),(($A$2:$A43<A43)+(($A$2:$A43=A43)*(ROW($A$2:$A43)<ROW(A43))))))),""""))"),233.0) -> 233
A44: 46078 | B44: MANFAC-19 | C44: 14487 | D44: =IFERROR(VLOOKUP(B44,BASE_VEICULOS!$A:$B,2,0),"") -> TEH3I02 | E44: =IFERROR(__xludf.DUMMYFUNCTION("IF(OR(A44="""",D44="""",C44=""""),"""",IFERROR(MAX(0,C44-MAX(FILTER($C$2:$C44,TRIM($D$2:$D44)=TRIM(D44),(($A$2:$A44<A44)+(($A$2:$A44=A44)*(ROW($A$2:$A44)<ROW(A44))))))),""""))"),195.0) -> 195
A45: 46078 | B45: MANFAC-2 | C45: 94103 | D45: =IFERROR(VLOOKUP(B45,BASE_VEICULOS!$A:$B,2,0),"") -> TEW9A28 | E45: =IFERROR(__xludf.DUMMYFUNCTION("IF(OR(A45="""",D45="""",C45=""""),"""",IFERROR(MAX(0,C45-MAX(FILTER($C$2:$C45,TRIM($D$2:$D45)=TRIM(D45),(($A$2:$A45<A45)+(($A$2:$A45=A45)*(ROW($A$2:$A45)<ROW(A45))))))),""""))"),158.0) -> 158
A46: 46078 | B46: MANFAC-20 | C46: 16306 | D46: =IFERROR(VLOOKUP(B46,BASE_VEICULOS!$A:$B,2,0),"") | E46: =IFERROR(__xludf.DUMMYFUNCTION("IF(OR(A46="""",D46="""",C46=""""),"""",IFERROR(MAX(0,C46-MAX(FILTER($C$2:$C46,TRIM($D$2:$D46)=TRIM(D46),(($A$2:$A46<A46)+(($A$2:$A46=A46)*(ROW($A$2:$A46)<ROW(A46))))))),""""))"),"")
A47: 46078 | B47: MANFAC-21 | C47: 14599 | D47: =IFERROR(VLOOKUP(B47,BASE_VEICULOS!$A:$B,2,0),"") -> TEW9A23 | E47: =IFERROR(__xludf.DUMMYFUNCTION("IF(OR(A47="""",D47="""",C47=""""),"""",IFERROR(MAX(0,C47-MAX(FILTER($C$2:$C47,TRIM($D$2:$D47)=TRIM(D47),(($A$2:$A47<A47)+(($A$2:$A47=A47)*(ROW($A$2:$A47)<ROW(A47))))))),""""))"),207.0) -> 207
A48: 46078 | B48: MANFAC-23 | C48: 104121 | D48: =IFERROR(VLOOKUP(B48,BASE_VEICULOS!$A:$B,2,0),"") | E48: =IFERROR(__xludf.DUMMYFUNCTION("IF(OR(A48="""",D48="""",C48=""""),"""",IFERROR(MAX(0,C48-MAX(FILTER($C$2:$C48,TRIM($D$2:$D48)=TRIM(D48),(($A$2:$A48<A48)+(($A$2:$A48=A48)*(ROW($A$2:$A48)<ROW(A48))))))),""""))"),"")
A49: 46078 | B49: MANFAC-3 | C49: 87458 | D49: =IFERROR(VLOOKUP(B49,BASE_VEICULOS!$A:$B,2,0),"") -> FIL8C14 | E49: =IFERROR(__xludf.DUMMYFUNCTION("IF(OR(A49="""",D49="""",C49=""""),"""",IFERROR(MAX(0,C49-MAX(FILTER($C$2:$C49,TRIM($D$2:$D49)=TRIM(D49),(($A$2:$A49<A49)+(($A$2:$A49=A49)*(ROW($A$2:$A49)<ROW(A49))))))),""""))"),203.0) -> 203
A50: 46078 | B50: MANFAC-4 | C50: 103688 | D50: =IFERROR(VLOOKUP(B50,BASE_VEICULOS!$A:$B,2,0),"") -> FGO3C61 | E50: =IFERROR(__xludf.DUMMYFUNCTION("IF(OR(A50="""",D50="""",C50=""""),"""",IFERROR(MAX(0,C50-MAX(FILTER($C$2:$C50,TRIM($D$2:$D50)=TRIM(D50),(($A$2:$A50<A50)+(($A$2:$A50=A50)*(ROW($A$2:$A50)<ROW(A50))))))),""""))"),117.0) -> 117
A51: 46078 | B51: MANFAC-5 | C51: 88233 | D51: =IFERROR(VLOOKUP(B51,BASE_VEICULOS!$A:$B,2,0),"") -> FOK8A73 | E51: =IFERROR(__xludf.DUMMYFUNCTION("IF(OR(A51="""",D51="""",C51=""""),"""",IFERROR(MAX(0,C51-MAX(FILTER($C$2:$C51,TRIM($D$2:$D51)=TRIM(D51),(($A$2:$A51<A51)+(($A$2:$A51=A51)*(ROW($A$2:$A51)<ROW(A51))))))),""""))"),152.0) -> 152
A52: 46078 | B52: MANFAC-6 | C52: 105967 | D52: =IFERROR(VLOOKUP(B52,BASE_VEICULOS!$A:$B,2,0),"") -> EWH1B84 | E52: =IFERROR(__xludf.DUMMYFUNCTION("IF(OR(A52="""",D52="""",C52=""""),"""",IFERROR(MAX(0,C52-MAX(FILTER($C$2:$C52,TRIM($D$2:$D52)=TRIM(D52),(($A$2:$A52<A52)+(($A$2:$A52=A52)*(ROW($A$2:$A52)<ROW(A52))))))),""""))"),68.0) -> 68
A53: 46078 | B53: MANFAC-7 | C53: 10256 | D53: =IFERROR(VLOOKUP(B53,BASE_VEICULOS!$A:$B,2,0),"") -> TEW9A27 | E53: =IFERROR(__xludf.DUMMYFUNCTION("IF(OR(A53="""",D53="""",C53=""""),"""",IFERROR(MAX(0,C53-MAX(FILTER($C$2:$C53,TRIM($D$2:$D53)=TRIM(D53),(($A$2:$A53<A53)+(($A$2:$A53=A53)*(ROW($A$2:$A53)<ROW(A53))))))),""""))"),437.0) -> 437
A54: 46078 | B54: MANFAC-8 | C54: 10560 | D54: =IFERROR(VLOOKUP(B54,BASE_VEICULOS!$A:$B,2,0),"") | E54: =IFERROR(__xludf.DUMMYFUNCTION("IF(OR(A54="""",D54="""",C54=""""),"""",IFERROR(MAX(0,C54-MAX(FILTER($C$2:$C54,TRIM($D$2:$D54)=TRIM(D54),(($A$2:$A54<A54)+(($A$2:$A54=A54)*(ROW($A$2:$A54)<ROW(A54))))))),""""))"),"")
A55: 46078 | B55: MANFAC-9 | C55: 14430 | D55: =IFERROR(VLOOKUP(B55,BASE_VEICULOS!$A:$B,2,0),"") -> TEW9A29 | E55: =IFERROR(__xludf.DUMMYFUNCTION("IF(OR(A55="""",D55="""",C55=""""),"""",IFERROR(MAX(0,C55-MAX(FILTER($C$2:$C55,TRIM($D$2:$D55)=TRIM(D55),(($A$2:$A55<A55)+(($A$2:$A55=A55)*(ROW($A$2:$A55)<ROW(A55))))))),""""))"),167.0) -> 167
A56: 46079 | B56: MANFAC-1 | C56: 14890 | D56: =IFERROR(VLOOKUP(B56,BASE_VEICULOS!$A:$B,2,0),"") -> TEW9A25 | E56: =IFERROR(__xludf.DUMMYFUNCTION("IF(OR(A56="""",D56="""",C56=""""),"""",IFERROR(MAX(0,C56-MAX(FILTER($C$2:$C56,TRIM($D$2:$D56)=TRIM(D56),(($A$2:$A56<A56)+(($A$2:$A56=A56)*(ROW($A$2:$A56)<ROW(A56))))))),""""))"),163.0) -> 163
A57: 46079 | B57: MANFAC-11 | C57: 15165 | D57: =IFERROR(VLOOKUP(B57,BASE_VEICULOS!$A:$B,2,0),"") -> TEW9A24 | E57: =IFERROR(__xludf.DUMMYFUNCTION("IF(OR(A57="""",D57="""",C57=""""),"""",IFERROR(MAX(0,C57-MAX(FILTER($C$2:$C57,TRIM($D$2:$D57)=TRIM(D57),(($A$2:$A57<A57)+(($A$2:$A57=A57)*(ROW($A$2:$A57)<ROW(A57))))))),""""))"),262.0) -> 262
A58: 46079 | B58: MANFAC-12 | C58: 14217 | D58: =IFERROR(VLOOKUP(B58,BASE_VEICULOS!$A:$B,2,0),"") -> TEW9A34 | E58: =IFERROR(__xludf.DUMMYFUNCTION("IF(OR(A58="""",D58="""",C58=""""),"""",IFERROR(MAX(0,C58-MAX(FILTER($C$2:$C58,TRIM($D$2:$D58)=TRIM(D58),(($A$2:$A58<A58)+(($A$2:$A58=A58)*(ROW($A$2:$A58)<ROW(A58))))))),""""))"),210.0) -> 210
A59: 46079 | B59: MANFAC-13 | C59: 15673 | D59: =IFERROR(VLOOKUP(B59,BASE_VEICULOS!$A:$B,2,0),"") -> TEW9A33 | E59: =IFERROR(__xludf.DUMMYFUNCTION("IF(OR(A59="""",D59="""",C59=""""),"""",IFERROR(MAX(0,C59-MAX(FILTER($C$2:$C59,TRIM($D$2:$D59)=TRIM(D59),(($A$2:$A59<A59)+(($A$2:$A59=A59)*(ROW($A$2:$A59)<ROW(A59))))))),""""))"),89.0) -> 89
A60: 46079 | B60: MANFAC-17 | C60: 71106 | D60: SRN9C05 | E60: =IFERROR(__xludf.DUMMYFUNCTION("IF(OR(A60="""",D60="""",C60=""""),"""",IFERROR(MAX(0,C60-MAX(FILTER($C$2:$C60,TRIM($D$2:$D60)=TRIM(D60),(($A$2:$A60<A60)+(($A$2:$A60=A60)*(ROW($A$2:$A60)<ROW(A60))))))),""""))"),"")
A61: 46079 | B61: MANFAC-18 | C61: 24912 | D61: =IFERROR(VLOOKUP(B61,BASE_VEICULOS!$A:$B,2,0),"") -> TET5H37 | E61: =IFERROR(__xludf.DUMMYFUNCTION("IF(OR(A61="""",D61="""",C61=""""),"""",IFERROR(MAX(0,C61-MAX(FILTER($C$2:$C61,TRIM($D$2:$D61)=TRIM(D61),(($A$2:$A61<A61)+(($A$2:$A61=A61)*(ROW($A$2:$A61)<ROW(A61))))))),""""))"),352.0) -> 352
A62: 46079 | B62: MANFAC-19 | C62: 14797 | D62: =IFERROR(VLOOKUP(B62,BASE_VEICULOS!$A:$B,2,0),"") -> TEH3I02 | E62: =IFERROR(__xludf.DUMMYFUNCTION("IF(OR(A62="""",D62="""",C62=""""),"""",IFERROR(MAX(0,C62-MAX(FILTER($C$2:$C62,TRIM($D$2:$D62)=TRIM(D62),(($A$2:$A62<A62)+(($A$2:$A62=A62)*(ROW($A$2:$A62)<ROW(A62))))))),""""))"),310.0) -> 310
A63: 46079 | B63: MANFAC-2 | C63: 94276 | D63: =IFERROR(VLOOKUP(B63,BASE_VEICULOS!$A:$B,2,0),"") -> TEW9A28 | E63: =IFERROR(__xludf.DUMMYFUNCTION("IF(OR(A63="""",D63="""",C63=""""),"""",IFERROR(MAX(0,C63-MAX(FILTER($C$2:$C63,TRIM($D$2:$D63)=TRIM(D63),(($A$2:$A63<A63)+(($A$2:$A63=A63)*(ROW($A$2:$A63)<ROW(A63))))))),""""))"),173.0) -> 173
A64: 46079 | B64: MANFAC-20 | C64: 16412 | D64: =IFERROR(VLOOKUP(B64,BASE_VEICULOS!$A:$B,2,0),"") | E64: =IFERROR(__xludf.DUMMYFUNCTION("IF(OR(A64="""",D64="""",C64=""""),"""",IFERROR(MAX(0,C64-MAX(FILTER($C$2:$C64,TRIM($D$2:$D64)=TRIM(D64),(($A$2:$A64<A64)+(($A$2:$A64=A64)*(ROW($A$2:$A64)<ROW(A64))))))),""""))"),"")
A65: 46079 | B65: MANFAC-21 | C65: 14826 | D65: =IFERROR(VLOOKUP(B65,BASE_VEICULOS!$A:$B,2,0),"") -> TEW9A23 | E65: =IFERROR(__xludf.DUMMYFUNCTION("IF(OR(A65="""",D65="""",C65=""""),"""",IFERROR(MAX(0,C65-MAX(FILTER($C$2:$C65,TRIM($D$2:$D65)=TRIM(D65),(($A$2:$A65<A65)+(($A$2:$A65=A65)*(ROW($A$2:$A65)<ROW(A65))))))),""""))"),227.0) -> 227
A66: 46079 | B66: MANFAC-22 | C66: 12898 | D66: =IFERROR(VLOOKUP(B66,BASE_VEICULOS!$A:$B,2,0),"") -> TEW9A26 | E66: =IFERROR(__xludf.DUMMYFUNCTION("IF(OR(A66="""",D66="""",C66=""""),"""",IFERROR(MAX(0,C66-MAX(FILTER($C$2:$C66,TRIM($D$2:$D66)=TRIM(D66),(($A$2:$A66<A66)+(($A$2:$A66=A66)*(ROW($A$2:$A66)<ROW(A66))))))),""""))"),119.0) -> 119
A67: 46079 | B67: MANFAC-23 | C67: 104322 | D67: =IFERROR(VLOOKUP(B67,BASE_VEICULOS!$A:$B,2,0),"") | E67: =IFERROR(__xludf.DUMMYFUNCTION("IF(OR(A67="""",D67="""",C67=""""),"""",IFERROR(MAX(0,C67-MAX(FILTER($C$2:$C67,TRIM($D$2:$D67)=TRIM(D67),(($A$2:$A67<A67)+(($A$2:$A67=A67)*(ROW($A$2:$A67)<ROW(A67))))))),""""))"),"")
A68: 46079 | B68: MANFAC-3 | C68: 87559 | D68: =IFERROR(VLOOKUP(B68,BASE_VEICULOS!$A:$B,2,0),"") -> FIL8C14 | E68: =IFERROR(__xludf.DUMMYFUNCTION("IF(OR(A68="""",D68="""",C68=""""),"""",IFERROR(MAX(0,C68-MAX(FILTER($C$2:$C68,TRIM($D$2:$D68)=TRIM(D68),(($A$2:$A68<A68)+(($A$2:$A68=A68)*(ROW($A$2:$A68)<ROW(A68))))))),""""))"),101.0) -> 101
A69: 46079 | B69: MANFAC-4 | C69: 103804 | D69: =IFERROR(VLOOKUP(B69,BASE_VEICULOS!$A:$B,2,0),"") -> FGO3C61 | E69: =IFERROR(__xludf.DUMMYFUNCTION("IF(OR(A69="""",D69="""",C69=""""),"""",IFERROR(MAX(0,C69-MAX(FILTER($C$2:$C69,TRIM($D$2:$D69)=TRIM(D69),(($A$2:$A69<A69)+(($A$2:$A69=A69)*(ROW($A$2:$A69)<ROW(A69))))))),""""))"),116.0) -> 116
A70: 46079 | B70: MANFAC-5 | C70: 88361 | D70: =IFERROR(VLOOKUP(B70,BASE_VEICULOS!$A:$B,2,0),"") -> FOK8A73 | E70: =IFERROR(__xludf.DUMMYFUNCTION("IF(OR(A70="""",D70="""",C70=""""),"""",IFERROR(MAX(0,C70-MAX(FILTER($C$2:$C70,TRIM($D$2:$D70)=TRIM(D70),(($A$2:$A70<A70)+(($A$2:$A70=A70)*(ROW($A$2:$A70)<ROW(A70))))))),""""))"),128.0) -> 128
A71: 46079 | B71: MANFAC-6 | C71: 106167 | D71: =IFERROR(VLOOKUP(B71,BASE_VEICULOS!$A:$B,2,0),"") -> EWH1B84 | E71: =IFERROR(__xludf.DUMMYFUNCTION("IF(OR(A71="""",D71="""",C71=""""),"""",IFERROR(MAX(0,C71-MAX(FILTER($C$2:$C71,TRIM($D$2:$D71)=TRIM(D71),(($A$2:$A71<A71)+(($A$2:$A71=A71)*(ROW($A$2:$A71)<ROW(A71))))))),""""))"),200.0) -> 200
A72: 46079 | B72: MANFAC-7 | C72: 10363 | D72: =IFERROR(VLOOKUP(B72,BASE_VEICULOS!$A:$B,2,0),"") -> TEW9A27 | E72: =IFERROR(__xludf.DUMMYFUNCTION("IF(OR(A72="""",D72="""",C72=""""),"""",IFERROR(MAX(0,C72-MAX(FILTER($C$2:$C72,TRIM($D$2:$D72)=TRIM(D72),(($A$2:$A72<A72)+(($A$2:$A72=A72)*(ROW($A$2:$A72)<ROW(A72))))))),""""))"),107.0) -> 107
A73: 46079 | B73: MANFAC-8 | C73: 10652 | D73: =IFERROR(VLOOKUP(B73,BASE_VEICULOS!$A:$B,2,0),"") | E73: =IFERROR(__xludf.DUMMYFUNCTION("IF(OR(A73="""",D73="""",C73=""""),"""",IFERROR(MAX(0,C73-MAX(FILTER($C$2:$C73,TRIM($D$2:$D73)=TRIM(D73),(($A$2:$A73<A73)+(($A$2:$A73=A73)*(ROW($A$2:$A73)<ROW(A73))))))),""""))"),"")
A74: 46079 | B74: MANFAC-9 | C74: 14552 | D74: =IFERROR(VLOOKUP(B74,BASE_VEICULOS!$A:$B,2,0),"") -> TEW9A29 | E74: =IFERROR(__xludf.DUMMYFUNCTION("IF(OR(A74="""",D74="""",C74=""""),"""",IFERROR(MAX(0,C74-MAX(FILTER($C$2:$C74,TRIM($D$2:$D74)=TRIM(D74),(($A$2:$A74<A74)+(($A$2:$A74=A74)*(ROW($A$2:$A74)<ROW(A74))))))),""""))"),122.0) -> 122
A75: 46079 | B75: T-ANDERSON | C75: 13579 | D75: =IFERROR(VLOOKUP(B75,BASE_VEICULOS!$A:$B,2,0),"") | E75: =IFERROR(__xludf.DUMMYFUNCTION("IF(OR(A75="""",D75="""",C75=""""),"""",IFERROR(MAX(0,C75-MAX(FILTER($C$2:$C75,TRIM($D$2:$D75)=TRIM(D75),(($A$2:$A75<A75)+(($A$2:$A75=A75)*(ROW($A$2:$A75)<ROW(A75))))))),""""))"),"")
A76: 46079 | B76: MANFAC-15 | C76: 71133 | D76: =IFERROR(VLOOKUP(B76,BASE_VEICULOS!$A:$B,2,0),"") -> TEQ2I74 | E76: =IFERROR(__xludf.DUMMYFUNCTION("IF(OR(A76="""",D76="""",C76=""""),"""",IFERROR(MAX(0,C76-MAX(FILTER($C$2:$C76,TRIM($D$2:$D76)=TRIM(D76),(($A$2:$A76<A76)+(($A$2:$A76=A76)*(ROW($A$2:$A76)<ROW(A76))))))),""""))"),175.0) -> 175
A77: 46080 | B77: MANFAC-1 | C77: 15168 | D77: =IFERROR(VLOOKUP(B77,BASE_VEICULOS!$A:$B,2,0),"") -> TEW9A25 | E77: =IFERROR(__xludf.DUMMYFUNCTION("IF(OR(A77="""",D77="""",C77=""""),"""",IFERROR(MAX(0,C77-MAX(FILTER($C$2:$C77,TRIM($D$2:$D77)=TRIM(D77),(($A$2:$A77<A77)+(($A$2:$A77=A77)*(ROW($A$2:$A77)<ROW(A77))))))),""""))"),278.0) -> 278
A78: 46080 | B78: MANFAC-11 | C78: 15720 | D78: =IFERROR(VLOOKUP(B78,BASE_VEICULOS!$A:$B,2,0),"") -> TEW9A24 | E78: =IFERROR(__xludf.DUMMYFUNCTION("IF(OR(A78="""",D78="""",C78=""""),"""",IFERROR(MAX(0,C78-MAX(FILTER($C$2:$C78,TRIM($D$2:$D78)=TRIM(D78),(($A$2:$A78<A78)+(($A$2:$A78=A78)*(ROW($A$2:$A78)<ROW(A78))))))),""""))"),555.0) -> 555
A79: 46080 | B79: MANFAC-12 | C79: 14261 | D79: =IFERROR(VLOOKUP(B79,BASE_VEICULOS!$A:$B,2,0),"") -> TEW9A34 | E79: =IFERROR(__xludf.DUMMYFUNCTION("IF(OR(A79="""",D79="""",C79=""""),"""",IFERROR(MAX(0,C79-MAX(FILTER($C$2:$C79,TRIM($D$2:$D79)=TRIM(D79),(($A$2:$A79<A79)+(($A$2:$A79=A79)*(ROW($A$2:$A79)<ROW(A79))))))),""""))"),44.0) -> 44
A80: 46080 | B80: MANFAC-13 | C80: 15738 | D80: =IFERROR(VLOOKUP(B80,BASE_VEICULOS!$A:$B,2,0),"") -> TEW9A33 | E80: =IFERROR(__xludf.DUMMYFUNCTION("IF(OR(A80="""",D80="""",C80=""""),"""",IFERROR(MAX(0,C80-MAX(FILTER($C$2:$C80,TRIM($D$2:$D80)=TRIM(D80),(($A$2:$A80<A80)+(($A$2:$A80=A80)*(ROW($A$2:$A80)<ROW(A80))))))),""""))"),65.0) -> 65
A81: 46080 | B81: MANFAC-18 | C81: 25183 | D81: =IFERROR(VLOOKUP(B81,BASE_VEICULOS!$A:$B,2,0),"") -> TET5H37 | E81: =IFERROR(__xludf.DUMMYFUNCTION("IF(OR(A81="""",D81="""",C81=""""),"""",IFERROR(MAX(0,C81-MAX(FILTER($C$2:$C81,TRIM($D$2:$D81)=TRIM(D81),(($A$2:$A81<A81)+(($A$2:$A81=A81)*(ROW($A$2:$A81)<ROW(A81))))))),""""))"),271.0) -> 271
A82: 46080 | B82: MANFAC-19 | C82: 15017 | D82: =IFERROR(VLOOKUP(B82,BASE_VEICULOS!$A:$B,2,0),"") -> TEH3I02 | E82: =IFERROR(__xludf.DUMMYFUNCTION("IF(OR(A82="""",D82="""",C82=""""),"""",IFERROR(MAX(0,C82-MAX(FILTER($C$2:$C82,TRIM($D$2:$D82)=TRIM(D82),(($A$2:$A82<A82)+(($A$2:$A82=A82)*(ROW($A$2:$A82)<ROW(A82))))))),""""))"),220.0) -> 220
A83: 46080 | B83: MANFAC-2 | C83: 94481 | D83: =IFERROR(VLOOKUP(B83,BASE_VEICULOS!$A:$B,2,0),"") -> TEW9A28 | E83: =IFERROR(__xludf.DUMMYFUNCTION("IF(OR(A83="""",D83="""",C83=""""),"""",IFERROR(MAX(0,C83-MAX(FILTER($C$2:$C83,TRIM($D$2:$D83)=TRIM(D83),(($A$2:$A83<A83)+(($A$2:$A83=A83)*(ROW($A$2:$A83)<ROW(A83))))))),""""))"),205.0) -> 205
A84: 46080 | B84: MANFAC-20 | C84: 16572 | D84: =IFERROR(VLOOKUP(B84,BASE_VEICULOS!$A:$B,2,0),"") | E84: =IFERROR(__xludf.DUMMYFUNCTION("IF(OR(A84="""",D84="""",C84=""""),"""",IFERROR(MAX(0,C84-MAX(FILTER($C$2:$C84,TRIM($D$2:$D84)=TRIM(D84),(($A$2:$A84<A84)+(($A$2:$A84=A84)*(ROW($A$2:$A84)<ROW(A84))))))),""""))"),"")
A85: 46080 | B85: MANFAC-21 | C85: 14978 | D85: =IFERROR(VLOOKUP(B85,BASE_VEICULOS!$A:$B,2,0),"") -> TEW9A23 | E85: =IFERROR(__xludf.DUMMYFUNCTION("IF(OR(A85="""",D85="""",C85=""""),"""",IFERROR(MAX(0,C85-MAX(FILTER($C$2:$C85,TRIM($D$2:$D85)=TRIM(D85),(($A$2:$A85<A85)+(($A$2:$A85=A85)*(ROW($A$2:$A85)<ROW(A85))))))),""""))"),152.0) -> 152
A86: 46080 | B86: MANFAC-22 | C86: 12985 | D86: =IFERROR(VLOOKUP(B86,BASE_VEICULOS!$A:$B,2,0),"") -> TEW9A26 | E86: =IFERROR(__xludf.DUMMYFUNCTION("IF(OR(A86="""",D86="""",C86=""""),"""",IFERROR(MAX(0,C86-MAX(FILTER($C$2:$C86,TRIM($D$2:$D86)=TRIM(D86),(($A$2:$A86<A86)+(($A$2:$A86=A86)*(ROW($A$2:$A86)<ROW(A86))))))),""""))"),87.0) -> 87
A87: 46080 | B87: MANFAC-23 | C87: 104616 | D87: =IFERROR(VLOOKUP(B87,BASE_VEICULOS!$A:$B,2,0),"") | E87: =IFERROR(__xludf.DUMMYFUNCTION("IF(OR(A87="""",D87="""",C87=""""),"""",IFERROR(MAX(0,C87-MAX(FILTER($C$2:$C87,TRIM($D$2:$D87)=TRIM(D87),(($A$2:$A87<A87)+(($A$2:$A87=A87)*(ROW($A$2:$A87)<ROW(A87))))))),""""))"),"")
A88: 46080 | B88: MANFAC-15 | C88: 71254 | D88: =IFERROR(VLOOKUP(B88,BASE_VEICULOS!$A:$B,2,0),"") -> TEQ2I74 | E88: =IFERROR(__xludf.DUMMYFUNCTION("IF(OR(A88="""",D88="""",C88=""""),"""",IFERROR(MAX(0,C88-MAX(FILTER($C$2:$C88,TRIM($D$2:$D88)=TRIM(D88),(($A$2:$A88<A88)+(($A$2:$A88=A88)*(ROW($A$2:$A88)<ROW(A88))))))),""""))"),121.0) -> 121
A89: 46080 | B89: MANFAC-3 | C89: 87668 | D89: =IFERROR(VLOOKUP(B89,BASE_VEICULOS!$A:$B,2,0),"") -> FIL8C14 | E89: =IFERROR(__xludf.DUMMYFUNCTION("IF(OR(A89="""",D89="""",C89=""""),"""",IFERROR(MAX(0,C89-MAX(FILTER($C$2:$C89,TRIM($D$2:$D89)=TRIM(D89),(($A$2:$A89<A89)+(($A$2:$A89=A89)*(ROW($A$2:$A89)<ROW(A89))))))),""""))"),109.0) -> 109
A90: 46080 | B90: MANFAC-4 | C90: 103986 | D90: =IFERROR(VLOOKUP(B90,BASE_VEICULOS!$A:$B,2,0),"") -> FGO3C61 | E90: =IFERROR(__xludf.DUMMYFUNCTION("IF(OR(A90="""",D90="""",C90=""""),"""",IFERROR(MAX(0,C90-MAX(FILTER($C$2:$C90,TRIM($D$2:$D90)=TRIM(D90),(($A$2:$A90<A90)+(($A$2:$A90=A90)*(ROW($A$2:$A90)<ROW(A90))))))),""""))"),182.0) -> 182
A91: 46080 | B91: MANFAC-5 | C91: 88501 | D91: =IFERROR(VLOOKUP(B91,BASE_VEICULOS!$A:$B,2,0),"") -> FOK8A73 | E91: =IFERROR(__xludf.DUMMYFUNCTION("IF(OR(A91="""",D91="""",C91=""""),"""",IFERROR(MAX(0,C91-MAX(FILTER($C$2:$C91,TRIM($D$2:$D91)=TRIM(D91),(($A$2:$A91<A91)+(($A$2:$A91=A91)*(ROW($A$2:$A91)<ROW(A91))))))),""""))"),140.0) -> 140
A92: 46080 | B92: MANFAC-6 | C92: 106356 | D92: =IFERROR(VLOOKUP(B92,BASE_VEICULOS!$A:$B,2,0),"") -> EWH1B84 | E92: =IFERROR(__xludf.DUMMYFUNCTION("IF(OR(A92="""",D92="""",C92=""""),"""",IFERROR(MAX(0,C92-MAX(FILTER($C$2:$C92,TRIM($D$2:$D92)=TRIM(D92),(($A$2:$A92<A92)+(($A$2:$A92=A92)*(ROW($A$2:$A92)<ROW(A92))))))),""""))"),189.0) -> 189
A93: 46080 | B93: MANFAC-7 | C93: 10640 | D93: =IFERROR(VLOOKUP(B93,BASE_VEICULOS!$A:$B,2,0),"") -> TEW9A27 | E93: =IFERROR(__xludf.DUMMYFUNCTION("IF(OR(A93="""",D93="""",C93=""""),"""",IFERROR(MAX(0,C93-MAX(FILTER($C$2:$C93,TRIM($D$2:$D93)=TRIM(D93),(($A$2:$A93<A93)+(($A$2:$A93=A93)*(ROW($A$2:$A93)<ROW(A93))))))),""""))"),277.0) -> 277
A94: 46080 | B94: MANFAC-8 | C94: 10780 | D94: =IFERROR(VLOOKUP(B94,BASE_VEICULOS!$A:$B,2,0),"") | E94: =IFERROR(__xludf.DUMMYFUNCTION("IF(OR(A94="""",D94="""",C94=""""),"""",IFERROR(MAX(0,C94-MAX(FILTER($C$2:$C94,TRIM($D$2:$D94)=TRIM(D94),(($A$2:$A94<A94)+(($A$2:$A94=A94)*(ROW($A$2:$A94)<ROW(A94))))))),""""))"),"")
A95: 46080 | B95: MANFAC-9 | C95: 14697 | D95: =IFERROR(VLOOKUP(B95,BASE_VEICULOS!$A:$B,2,0),"") -> TEW9A29 | E95: =IFERROR(__xludf.DUMMYFUNCTION("IF(OR(A95="""",D95="""",C95=""""),"""",IFERROR(MAX(0,C95-MAX(FILTER($C$2:$C95,TRIM($D$2:$D95)=TRIM(D95),(($A$2:$A95<A95)+(($A$2:$A95=A95)*(ROW($A$2:$A95)<ROW(A95))))))),""""))"),145.0) -> 145
A96: 46081 | B96: MANFAC-11 | C96: 15750 | D96: =IFERROR(VLOOKUP(B96,BASE_VEICULOS!$A:$B,2,0),"") -> TEW9A24 | E96: =IFERROR(__xludf.DUMMYFUNCTION("IF(OR(A96="""",D96="""",C96=""""),"""",IFERROR(MAX(0,C96-MAX(FILTER($C$2:$C96,TRIM($D$2:$D96)=TRIM(D96),(($A$2:$A96<A96)+(($A$2:$A96=A96)*(ROW($A$2:$A96)<ROW(A96))))))),""""))"),30.0) -> 30
A97: 46081 | B97: MANFAC-19 | C97: 15255 | D97: =IFERROR(VLOOKUP(B97,BASE_VEICULOS!$A:$B,2,0),"") -> TEH3I02 | E97: =IFERROR(__xludf.DUMMYFUNCTION("IF(OR(A97="""",D97="""",C97=""""),"""",IFERROR(MAX(0,C97-MAX(FILTER($C$2:$C97,TRIM($D$2:$D97)=TRIM(D97),(($A$2:$A97<A97)+(($A$2:$A97=A97)*(ROW($A$2:$A97)<ROW(A97))))))),""""))"),238.0) -> 238
A98: 46081 | B98: MANFAC-20 | C98: 16685 | D98: =IFERROR(VLOOKUP(B98,BASE_VEICULOS!$A:$B,2,0),"") | E98: =IFERROR(__xludf.DUMMYFUNCTION("IF(OR(A98="""",D98="""",C98=""""),"""",IFERROR(MAX(0,C98-MAX(FILTER($C$2:$C98,TRIM($D$2:$D98)=TRIM(D98),(($A$2:$A98<A98)+(($A$2:$A98=A98)*(ROW($A$2:$A98)<ROW(A98))))))),""""))"),"")
A99: 46081 | B99: MANFAC-21 | C99: 15255 | D99: =IFERROR(VLOOKUP(B99,BASE_VEICULOS!$A:$B,2,0),"") -> TEW9A23 | E99: =IFERROR(__xludf.DUMMYFUNCTION("IF(OR(A99="""",D99="""",C99=""""),"""",IFERROR(MAX(0,C99-MAX(FILTER($C$2:$C99,TRIM($D$2:$D99)=TRIM(D99),(($A$2:$A99<A99)+(($A$2:$A99=A99)*(ROW($A$2:$A99)<ROW(A99))))))),""""))"),277.0) -> 277
A100: 46081 | B100: MANFAC-5 | C100: 88721 | D100: =IFERROR(VLOOKUP(B100,BASE_VEICULOS!$A:$B,2,0),"") -> FOK8A73 | E100: =IFERROR(__xludf.DUMMYFUNCTION("IF(OR(A100="""",D100="""",C100=""""),"""",IFERROR(MAX(0,C100-MAX(FILTER($C$2:$C100,TRIM($D$2:$D100)=TRIM(D100),(($A$2:$A100<A100)+(($A$2:$A100=A100)*(ROW($A$2:$A100)<ROW(A100))))))),""""))"),220.0) -> 220
...

Sheet BASE_VEICULOS
A2: EQUIPE | B2: PLACA | C2: MODELO | D2: RENAVAM | E2: CHASSI | F2: COR | G2: CENTRO DE CUSTO | H2: MOTORISTA | I2: OBS | J2: TIPO DE LOCAÇÃO | K2: FORNECEDOR | L2: FRANQUIA DE KM | M2: VALOR DE LOCAÇÃO | N2: PRAZO CONTRATO (MESES) | O2: DATA DE INÍCIO DO CONTRATO | P2: DATA DO FIM DO CONTRATO | Q2: CARTÃO TICKET LOG | R2: TAG VELOE
B3: FUR3I24 | C3: HB20 | D3: 1354465013 | E3: 9BHCN51AARP481338 | F3: BRANCO | G3: FAC - 140005 - SPOT MANUTENÇÃO DPSP 2025 | J3: CONTRATO FROTAS | K3: MAESTRO | L3: 3000 | M3: 2470.39 | N3: 36 | O3: 45131 | P3: 46226 | Q3: 2357 | R3: 1185466176
B4: EZX6C83 | C4: HB20 | D4: 1354464998 | E4: 9BHCN51AARP481339 | F4: BRANCO | G4: FAC - 140004 - MANUTENÇÃO PREDIAL DPSP 2025 | J4: CONTRATO FROTAS | K4: MAESTRO | L4: 3000 | M4: 2470.39 | N4: 36 | O4: 45131 | P4: 46226 | Q4: 806143 | R4: 1171264213
A5: MANFAC-3 | B5: FIL8C14 | C5: HB20 | D5: 1357609300 | E5: 9BHCN51AARP481345 | F5: BRANCO | G5: FAC - 140004 - MANUTENÇÃO PREDIAL DPSP 2025 | H5: AILTON HONORATO DOS SANTOS | J5: CONTRATO FROTAS | K5: MAESTRO | L5: 3000 | M5: 2469.15 | N5: 36 | O5: 45180 | P5: 46275 | Q5: 1605 | R5: 1177094700
A6: MANFAC-4 | B6: FGO3C61 | C6: HB20 | D6: 1354465030 | E6: 9BHCN51AARP478669 | F6: BRANCO | G6: FAC - 140005 - SPOT MANUTENÇÃO DPSP 2025 | H6: MICHEL PINHEIRO | J6: CONTRATO FROTAS | K6: MAESTRO | L6: 3000 | M6: 2470.39 | N6: 36 | O6: 45131 | P6: 46226 | Q6: 9628251 | R6: 1176651609
A7: MANFAC-5 | B7: FOK8A73 | C7: HB20 | D7: 1354464920 | E7: 9BHCN51AARP481343 | F7: BRANCO | G7: FAC - 140004 - MANUTENÇÃO PREDIAL DPSP 2025 | H7: RAFAEL SILVA DE OLIVEIRA | J7: CONTRATO FROTAS | K7: MAESTRO | L7: 3000 | M7: 2393.44 | N7: 36 | O7: 45131 | P7: 46226 | Q7: 695700 | R7: 1175599242
A8: MANFAC-6 | B8: EWH1B84 | C8: HB20 | D8: 1357609288 | E8: 9BHCN51AARP481286 | F8: BRANCO | G8: FAC - 140005 - SPOT MANUTENÇÃO DPSP 2025 | H8: DIEGO DA SILVA OLIVEIRA | J8: CONTRATO FROTAS | K8: MAESTRO | L8: 3000 | M8: 2469.15 | N8: 36 | O8: 45239 | P8: 46275 | Q8: 806598 | R8: 1175775665
A9: EDUARDO MAIA | B9: TCJ1G00 | C9: VIRTUS | F9: PRETO | G9: EC - ESCRITORIO CENTRAL | H9: EDUARDO MAIA | J9: CONTRATO FROTAS | K9: MAESTRO | L9: 3000 | M9: 3395 | N9: 36 | O9: 45566 | P9: 46660 | Q9: 1571 | R9: 1122315750
A10: MANFAC-18 | B10: TET5H37 | C10: FIAT MOBI LIKE | D10: 1445240820 | E10: 9BD341ACWSYA49652 | F10: BRANCO | G10: PROF - 07001 - MANUTENÇÃO PREDIAL- PROFARMA-2025 | H10: JORGE LUIZ DOS SANTOS VIEIRA | J10: LOCAÇÃO MENSAL | K10: BRASIL LOCAFACIL | L10: 3000 | M10: 2700 | N10: 1 | O10: 45940 | Q10: 973232 | R10: 1173593437
A11: JOSÉ GUILHERME | B11: TYK8C73 | C11: TERA | F11: VERMELHO | G11: EC - ESCRITORIO CENTRAL | H11: JOSÉ GUILHERME | J11: LOCAÇÃO MENSAL | K11: LOCALIZA | L11: 2500 | M11: 3500 | N11: 1 | O11: 45958 | Q11: 1589 | R11: 1112920117
A12: MANFAC-21 | B12: TEW9A23 | C12: ARGO DRIVE 1.0 | D12: 1448038399 | E12: 9BD358ATSTYP59767 | F12: BRANCO | G12: PROF - 07001 - MANUTENÇÃO PREDIAL- PROFARMA-2025 | H12: MULLER GOMES DOS SANTOS | J12: CONTRATO FROTAS | K12: MAESTRO | L12: 3000 | M12: 2989 | N12: 36 | O12: 45951 | P12: 47046 | Q12: 2705 | R12: 1177898618
A13: MANFAC-11 | B13: TEW9A24 | C13: ARGO DRIVE 1.0 | D13: 1448038402 | E13: 9BD358ATSTYP59797 | F13: BRANCO | G13: PROF - 07001 - MANUTENÇÃO PREDIAL- PROFARMA-2025 | H13: MARCELO LOPES VIEIRA | J13: CONTRATO FROTAS | K13: MAESTRO | L13: 3000 | M13: 2989 | N13: 36 | O13: 45950 | P13: 47045 | Q13: 2339 | R13: 1166514872
A14: MANFAC-1 | B14: TEW9A25 | C14: ARGO DRIVE 1.0 | D14: 1448038410 | E14: 9BD358ATSTYP59821 | F14: BRANCO | G14: FAC - 140004 - MANUTENÇÃO PREDIAL DPSP 2025 | H14: GABRIEL DE JESUS FIALHO MIRANDA | J14: CONTRATO FROTAS | K14: MAESTRO | L14: 3000 | M14: 2989 | N14: 36 | O14: 45953 | P14: 47048 | Q14: 6580 | R14: 1123931107
A15: MANFAC-22 | B15: TEW9A26 | C15: ARGO DRIVE 1.0 | D15: 1448038429 | E15: 9BD358ATSTYP59826 | F15: BRANCO | G15: PROF - 07001 - MANUTENÇÃO PREDIAL- PROFARMA-2025 | H15: RICHARD GUIMARÃES FARIAS | J15: CONTRATO FROTAS | K15: MAESTRO | L15: 3000 | M15: 2989 | N15: 36 | O15: 45957 | P15: 47052 | Q15: 2332 | R15: 1164571683
A16: MANFAC-12 | B16: TEW9A34 | C16: ARGO DRIVE 1.0 | D16: 1448038496 | E16: 9BD358ATSTYP65474 | F16: BRANCO | G16: PROF - 07001 - MANUTENÇÃO PREDIAL- PROFARMA-2025 | H16: ANDRE VINICIUS NAZARE ESCOBAR | J16: CONTRATO FROTAS | K16: MAESTRO | L16: 3000 | M16: 2989 | N16: 36 | O16: 45951 | P16: 47046 | Q16: 2313 | R16: 1137666461
A17: MANFAC-7 | B17: TEW9A27 | C17: ARGO DRIVE 1.0 | D17: 1448038437 | E17: 9BD358ATSTYP59841 | F17: BRANCO | G17: FAC - 140005 - SPOT MANUTENÇÃO DPSP 2025 | H17: HELENO ROVANE DOS SANTOS MELO | J17: CONTRATO FROTAS | K17: MAESTRO | L17: 3000 | M17: 2989 | N17: 36 | O17: 45966 | P17: 47061 | Q17: 1639 | R17: 1159575780
A18: MANFAC-2 | B18: TEW9A28 | C18: ARGO DRIVE 1.0 | D18: 1448038445 | E18: 9BD358ATSTYP60025 | F18: BRANCO | G18: PROF - 07001 - MANUTENÇÃO PREDIAL- PROFARMA-2025 | H18: LUIZ RODRIGO | J18: CONTRATO FROTAS | K18: MAESTRO | L18: 3000 | M18: 2989 | N18: 36 | O18: 45965 | P18: 47060 | Q18: 8151 | R18: 1110504952
A19: MANFAC-9 | B19: TEW9A29 | C19: ARGO DRIVE 1.0 | D19: 1448038453 | E19: 9BD358ATSTYP65020 | F19: BRANCO | G19: FAC - 140004 - MANUTENÇÃO PREDIAL DPSP 2025 | H19: MARCELINO ALMEIDA DE CASTRO | J19: CONTRATO FROTAS | K19: MAESTRO | L19: 3000 | M19: 2989 | N19: 36 | O19: 45951 | P19: 47046 | Q19: 4187 | R19: 1130417477
A20: MANFAC-10 | B20: TEW9A30 | C20: ARGO DRIVE 1.0 | D20: 1448005920 | E20: 9BD358ATSTYP65027 | F20: BRANCO | G20: PROF - 07001 - MANUTENÇÃO PREDIAL- PROFARMA-2025 | H20: NADSON SANTOS DE JESUS | J20: CONTRATO FROTAS | K20: MAESTRO | L20: 3000 | M20: 2989 | N20: 36 | O20: 45972 | P20: 47067 | Q20: 4153 | R20: 1148099343
A21: MANFAC-13 | B21: TEW9A33 | C21: ARGO DRIVE 1.0 | D21: 1448038488 | E21: 9BD358ATSTYP65358 | F21: BRANCO | G21: PROF - 07001 - MANUTENÇÃO PREDIAL- PROFARMA-2025 | H21: CARLOS HENRIQUE SILVA MENDES | J21: CONTRATO FROTAS | K21: MAESTRO | L21: 3000 | M21: 2989 | N21: 36 | O21: 45951 | P21: 47046 | Q21: 1984 | R21: 1155524837
A22: ALEX | B22: TEP5C93 | C22: ARGO DRIVE 1.0 | F22: BRANCO | G22: PROF - 07001 - MANUTENÇÃO PREDIAL- PROFARMA-2025 | H22: ALEX ARAUJO | J22: LOCAÇÃO MENSAL | K22: BRASIL LOCAFACIL | L22: 3000 | M22: 3200 | N22: 1 | O22: 46034 | Q22: 2340 | R22: 2159564773
A23: YURI | B23: UDA5B37 | C23: HB20 | D23: 1388078837 | E23: 9BD281AJHRYF17197 | F23: CINZA | G23: FAC - 140005 - SPOT MANUTENÇÃO DPSP 2025 | H23: YURI | J23: LOCAÇÃO MENSAL | K23: FOCO | L23: 4000 | M23: 2685 | N23: 1 | O23: 46161 | Q23: 502 | R23: 1133409223
A24: MANFAC-15 | B24: TEQ2I74 | C24: FIAT MOBI LIKE | D24: 1391954022 | E24: 93YRBB004SJ933541 | F24: BRANCO | G24: PROF - 07001 - MANUTENÇÃO PREDIAL- PROFARMA-2025 | H24: ALDENIR TEIXIERA CARVALHO | J24: LOCAÇÃO MENSAL | K24: BRASIL LOCAFACIL | L24: 3000 | M24: 2700 | N24: 1 | O24: 46076 | Q24: 2365 | R24: 2156453657
A25: MANFAC-10 | B25: SRK9F67 | C25: KWID ZEN | D25: 1391953069 | E25: 93YRBB004SJ933457 | F25: BRANCO | G25: PROF - 07001 - MANUTENÇÃO PREDIAL- PROFARMA-2025 | H25: NADSON SANTOS DE JESUS | J25: LOCAÇÃO MENSAL | K25: BRASIL LOCAFACIL | L25: 3000 | M25: 2700 | N25: 1 | O25: 46083 | Q25: 4599 | R25: 2156453657
A26: MANFAC-19 | B26: TEH3I02 | C26: ARGO DRIVE 1.0 | G26: PROF - 07001 - MANUTENÇÃO PREDIAL- PROFARMA-2025 | H26: CARLOS ANDRADE | J26: LOCAÇÃO MENSAL | K26: BRASIL LOCAFACIL | L26: 3000 | M26: 3200 | N26: 1 | O26: 46092
A27: MANFAC-24 | B27: SRU8D16 | C27: KWID ZEN | F27: CINZA | G27: PROF - 07001 - MANUTENÇÃO PREDIAL- PROFARMA-2025 | H27: VAGNER OLIVEIRA DOS SANTOS | J27: LOCAÇÃO MENSAL | K27: BRASIL LOCAFACIL | L27: 3000 | M27: 2700 | N27: 1 | Q27: 567
A28: ANDERSON CRUZ | B28: TEP5C33 | C28: ARGO DRIVE 1.0 | D28: 1388078837 | E28: 9BD281AJHRYF17197 | F28: BRANCO | G28: PROF - 07001 - MANUTENÇÃO PREDIAL- PROFARMA-2025 | H28: ANDERSON CRUZ DO AMARAL | J28: LOCAÇÃO MENSAL | K28: BRASIL LOCAFACIL | L28: 3000 | M28: 3200 | N28: 1 | Q28: 5678 | R28: 1185466176
A29: GABRUEL VIDAL | B29: SRI8F37 | C29: OROCH | F29: BRANCO | G29: EC - ESCRITORIO CENTRAL | H29: GABRIEL VIDAL | J29: LOCAÇÃO MENSAL | K29: BRASIL LOCAFACIL | M29: 3900 | N29: 1

Sheet DASHBOARD
A1: DATA ATUAL | B1: =TODAY() -> 46184
A2: SEMANA ATUAL | B2: =WEEKNUM(B1,21) -> 24
I5: VALOR COMBUSTIVEL
G6: RANKING POR EQUIPE | I6: KM RODADO
I7: CONSUMO
G8: QUAL CONSUMO POR VEICULO
G11: CONSUMO DE KM POR CONTRATO DE FROTAS

Sheet BASE_MULTAS
A1: DATA INFRAÇÃO | B1: EQUIPE | C1: PLACA | D1: AUTO DE INFRAÇÃO | E1: MOTORISTA | F1: VALOR | G1: MOTIVO | H1: LOCALIDADE | I1: IDENTIFICAÇÃO | J1: ENVIO DOCUMENTO | K1: STATUS DESCONTO
A2: 45856 | C2: RVK9C09 | D2: RA30206123 | F2: 281.74 | G2: AVANÇAR SINAL VERMELHO | H2: N/I | I2: SIM | J2: NÃO | K2: ?
A3: 45868 | C3: FOK8A73 | D3: RD31034942 | F3: R$ 130,16 | G3: DIRIGIR VEICULO UTILIZANDO TELEFONE CELULAR | H3: CAMPO DE SÃO CRISTOVÃO 246 | I3: NÃO | J3: NÃO | K3: ?
A4: 45874 | C4: RVK9C09 | D4: RD31054663 | F4: 187.42 | G4: ESTACIONAR EM DESACORDO COM A REGULAMENTAÇÃO | H4: N/I | I4: SIM | J4: NÃO | K4: ?
A5: 45876 | C5: RVK9C09 | D5: J003271364 | F5: 124.96 | G5: TRANSITAR EM VELOCIDADE SUPERIOR A MAXIMA PERMITIDA EM ATE 20% | H5: N/I | I5: SIM | J5: NÃO | K5: ?
A6: 45877 | C6: TCR8G79 | D6: RA40996281 | F6: 124.96 | G6: TRANSITAR EM VELOCIDADE SUPERIOR A MAXIMA PERMITIDA EM ATÉ 20% | H6: AV MENEZES CORTES, KM 5,4 ST JACAREPAGUA - RIO DE JANEIRO | I6: SIM | J6: NÃO | K6: ENVIADO AO DP
A7: 45880 | C7: GTN3F40 | D7: T29481238 | F7: 187.42 | G7: ESTACIONAR NO PASSEIO | H7: RUA MANOEL MADRUGA 4 - TERESOPOLIS | I7: SIM | J7: NÃO | K7: ENVIADO AO DP
A8: 45887 | C8: GTN3F40 | D8: J003505575 | F8: 124.96 | G8: TRANSITAR EM VELOCIDADE SUPERIOR A MAX PERMITIDA EM ATE 2 | H8: RJ-BR 116 -KM 182.09 - D - NOVA IGUAÇU | I8: SIM | J8: AGUARDANDO | K8: ENVIADO AO DP
A9: 45891 | C9: FGO3C61 | D9: J003583055 | F9: 156.18 | G9: TRANSITAR EM VELOCIDADE SUPERIOR A MAXIMA PERMITIDA EM MAIS DE 20% ATÉ 50% | H9: BR116, KM 36, 52 DECRESCENTE TERESOPOLIS RJ | I9: SIM | J9: NÃO | K9: ENVIADO AO DP
A10: 45896 | C10: GTN3F40 | D10: RA20967826 | F10: 281.74 | G10: AVANÇAR O SINAL VERMELHO | H10: AV BRAZ PINA PX2019 - ST LARGO DO BICAO - RJ | I10: SIM | J10: AGUARDANDO | K10: ENVIADO AO DP
A11: 45901 | C11: TDA2A99 | D11: Y35165236 | F11: 187.42 | G11: TRANSITAR EM VELOCIDADE SUPERIOR A MAX. PERMITIDA | H11: RJ-104, KM 18,5 - ST ITABORAI - SÃO GONÇALO -RJ | I11: SIM | J11: AGUARDANDO | K11: ENVIADO AO DP
A12: 45908 | C12: FGO3C61 | D12: T29484689 | F12: 156.18 | G12: ESTACIONAR NO PASSEIO | H12: RUA MANOEL MADRUGA 4 - TERESOPOLIS | I12: SIM | J12: NÃO | K12: ENVIADO AO DP
A13: 45917 | C13: EWH1B84 | D13: RD31101055 | F13: 130.16 | G13: ESTACIONAR EM DESACORDO CPM AS POSIÇÕES ESTABELECIDAS NO CTB | H13: RUA GENERAL OLIMPIO MOURÃO FILHO 10 - SÃO CONRADO | I13: SIM | J13: NÃO | K13: ENVIADO AO DP
A14: 45917 | C14: EWH1B84 | D14: RN00073334 | F14: R$ 208,26 | G14: MULTA POR NÃO IDENTIFCAR CONDUTOR | K14: ENVIADO AO DP
A15: 45922 | C15: TDC5I72 | D15: RD30824669 | F15: 124.96 | G15: ESTACIONAR EM LOCAL PROIBIDO | H15: RUA SAO LEOBALDO 1 - SAO CONRADO | K15: ENVIADO AO DP
A16: 45925 | C16: FGO3C61 | D16: N36080730 | G16: ESTACIONAR NO PASSEIO | H16: RUA SANTA ROSA PROXIMO AO N28 - NITEROI | K16: ENVIADO AO DP
A17: 45925 | C17: FGO3C61 | D17: N36080730 | F17: 156.18 | G17: ESTACIONAR EM DESACORDO COM REGULAMENTAÇÃO | H17: RUA SANTA ROSA, 28-NITERÓI RJ | I17: SIM | K17: ENVIADO AO DP
A18: 45925 | C18: GTN3F40 | D18: T29487832 | F18: 187.42 | G18: ESTACIONAR NO PASSEIO | H18: RUA MANOEL MADRUGA 4 - TERESOPOLIS | I18: SIM | J18: NÃO | K18: ENVIADO AO DP
A19: 45937 | C19: FGO3C61 | D19: X42616856 | F19: 234.77 | G19: AVANÇAR SINAL VERMELHO | H19: RJ-106, KM109 SENT NITEROI - ARARUAMA | K19: ENVIADO AO DP
A20: 45937 | C20: FGO3C61 | D20: X42616856 | G20: ESTACIONAR EM DESACORDO COM REGULAMENTAÇÃO | H20: RJ 106-KM 79,5 ST NITEROI- ARARUAMA RJ | I20: SIM | K20: ENVIADO AO DP
A21: 45949 | C21: FOK8A73 | D21: J004683144 | F21: 156.192 | G21: TRANSITAR EM VELOCIDADE SUPERIOR A 20% | H21: BR465, KM21,22 - NOVA IGUAÇÚ RJ | I21: SIM | K21: ENVIADO AO DP
A22: 45950 | C22: FGO3C61 | D22: L30464155 | F22: 156.18 | G22: ESTACIONAR EM DESACORDO COM REGULAMENTAÇÃO | H22: AV.CARDOSO MOREIRA, 946-ITAPERUNA RJ | I22: SIM | K22: ENVIADO AO DP
A23: 45952 | C23: FGO3C61 | D23: RD31131351 | F23: 293.47 | G23: ESTACIONAR EM DESACORDO COM REGULAMENTAÇÃO | K23: ENVIADO AO DP
A24: 45959 | C24: TEW9A25 | D24: L30517341 | F24: 156.18 | G24: ESTACIONAR EM DESACORDO COM REGULAMENTAÇÃO | I24: NÃO | K24: ENVIADO AO DP
A25: 45961 | C25: EWH1B84 | D25: RA41099745 | F25: 156.192 | G25: TRANSITAR EM VELOCIDADE SUPERIOR A 20% | H25: TN VICE PRES JOSE ALENCAR ST RECREIO | I25: SIM | K25: ENVIADO AO DP
A26: 45961 | C26: TET 5H37 | D26: N002538990 | F26: 1056.49 | G26: TRANSITAR PELO ACOSTAMENTO | H26: RJ BR116- KM173-D | I26: SIM | K26: ENVIADO AO DP
A27: 45973 | C27: TEW9A27 | D27: N36105951 | F27: 156.192 | G27: ESTACIONAR EM LOCAL PROIBIDO | H27: RUA SAO JOAO PX AO 114 | I27: SIM | K27: ENVIADO AO DP
A28: 45975 | C28: GTN3F40 | D28: RN 00082044 | F28: 586.94 | G28: MULTA POR NÃO IDENTIFCAR CONDUTOR | H28: RUA DOM MARCOS BARBOSA, CENTRO. | I28: SIM | J28: NÃO | K28: ENVIADO AO DP
A29: 45976 | C29: EWH1B84 | D29: RA41123782 | F29: R$ 293,47 | G29: AVANÇAR SINAL VERMELHO | H29: AV MIN. EDGAR ROMERO PX VICENTE DE CARVALHO - IRAJA | I29: SIM | J29: NÃO | K29: ENVIADO AO DP
A30: 45981 | C30: EWH1B84 | D30: RD31195687 | F30: 156.192 | G30: ESTACIONAR EM LOCAL PROIBIDO | H30: RUA VISC DE PIRAJA 514 IPANEMA | I30: SIM | K30: ENVIADO AO DP
A31: 45983 | C31: FOK8A73 | D31: RD31215511 | F31: 156.192 | G31: ESTACIONAR EM LOCAL PROIBIDO | H31: AV NOSSA SENHORA DE COPACABANA 266 | I31: SIM | K31: ENVIADO AO DP
A32: 45984 | C32: TEW9A20 | D32: RA41136772 | F32: 156.192 | G32: TRANSITAR EM VELOCIDADE SUPERIOR A 20% | H32: AV BRASIL KM 12,1 PCENTRAL - ST CENTRO | I32: SIM | K32: ENVIADO AO DP
A33: 45984 | C33: TEW9A34 | D33: RA21035720 | F33: 156.192 | G33: TRANSITAR EM VELOCIDADE SUPERIOR A 20% | H33: EST BARRA TIJUCA PX 436 SENT ITANHANGA | I33: SIM | K33: ENVIADO AO DP
A34: 45985 | C34: TEW9A23 | D34: N37498722 | F34: 156.192 | G34: ESTACIONAR EM LOCAL PROIBIDO | H34: AV MAL FLORIANO PEIXOTO NOVA IGUACU | I34: NÃO
A35: 45988 | C35: TEW9A29 | D35: N36113306 | F35: 156.192 | G35: ESTACIONAR EM LOCAL PROIBIDO | H35: NITEROI | I35: SIM | K35: ENVIADO AO DP
A36: 45993 | C36: TEW9A34 | D36: RA30329800 | F36: 352.164 | G36: AVANCAR SINAL VERMELHO | H36: RJJ SEABRA PX21 | I36: SIM | K36: ENVIADO AO DP
A37: 45999 | C37: EWH1B84 | D37: RD31241114 | F37: 293.47 | G37: DIRIGIR VEICULO UTILIZANDO TELEFONE CELULAR | H37: EST PORTELA 205 - MADUREIRA | I37: SIM | J37: NÃO | K37: ENVIADO AO DP
A38: 45999 | C38: TEW9A29 | D38: X41542510 | F38: 156.192 | G38: TRANSITAR EM VELOCIDADE SUPERIOR A 20% | H38: RJ-106 KM 19,3 SENT MACAE | I38: SIM | K38: ENVIADO AO DP
A39: 46002 | C39: FOK8A73 | D39: RD31240845 | F39: R$ 195,23 | G39: ESTACIONAR AO LADO DE OUTRO VEICULO EM FILA DUPLA | H39: RUA GUSTAVO SAMPAIO - COPACABANA | I39: SIM
A40: 46002 | C40: TEW9A29 | D40: S31498137 | F40: 156.192 | G40: ESTACIONAR EM LOCAL PROIBIDO | H40: SAO GONÇALO | I40: SIM | K40: ENVIADO AO DP
A41: 46006 | C41: FOK8A73 | D41: RD30951763 | F41: 195.23 | G41: ESTACIONAR AO LADO DE OUTRO VEICULO EM FILA DUPLA | H41: RUA MARIA QUITÉRIA, 83 - IPANEMA | I41: SIM | J41: NÃO | K41: ENVIADO AO DP
A42: 46007 | C42: FGO3C61 | D42: RN001420113 | F42: R$ 469,55 | G42: ESTACIONAR NAS VAGAS RES. A PESSOAS COM DEFICIÊNCIA
A43: 46014 | C43: TEW9A20 | D43: RD31263002 | F43: 156.192 | G43: ESTACIONAR EM LOCAL PROIBIDO | H43: AV VISCONDE DE PIRAJA | I43: SIM | K43: ENVIADO AO DP
A44: 46019 | C44: TEW9A34 | D44: RA41182264 | F44: 156.192 | G44: TRANSITAR EM VELOCIDADE SUPERIOR A 20% | H44: AV. BRASIL KM 12.1 | I44: SIM | J44: SIM | K44: ENVIADO AO DP
A45: 46020 | C45: TEH3I02 | D45: J005947306 | F45: R$ 156,19 | G45: TRANSITAR EM VELOCIDADE SUPERIOR A 20% | H45: RJ - BR 101 - KM 298.30- C | I45: SIM | J45: SIM | K45: ENVIADO AO DP
A46: 46022 | C46: FGO3C61 | D46: J005996520 | E46: MICHEL PINHEIRO | G46: TRANSITAR EM VELOCIDADE SUPERIOR A 50% | H46: BR 493 KM 19.22 - MAGÉ | I46: SIM | J46: NÃO
A47: 46029 | C47: FIL8C14 | D47: RD31277938 | F47: 130.16 | G47: ESTACIONAR EM LOCAL PROIBIDO | H47: RUA HILÁRIO GOUVEIA 33 - COPACABANA | I47: SIM | J47: NÃO | K47: ENVIADO AO DP
A48: 46040 | C48: TEW9A29 | D48: X41544064 | F48: 156.192 | G48: TRANSITAR EM VELOCIDADE SUPERIOR A 20% | H48: RJ-106 KM 18,8 SENT NITEROI | I48: SIM | K48: ENVIADO AO DP
A49: 46046 | C49: TET 5H37 | D49: J006558382 | E49: JORGE LUIZ DOS SANTOS VIEIRA | F49: 130.16 | G49: TRANSITAR EM VELOCIDADE SUPERIOR A 20% | H49: BR - 116 - KM 94.65 | I49: SIM | K49: ENVIADO AO DP
A50: 46048 | C50: TCJ1G00 | D50: J006612900 | E50: EDUARDO MAIA | F50: 130.16 | G50: TRANSITAR EM VELOCIDADE SUPERIOR A 20% | H50: BR 101 KM 415 - ITAGUAI
A51: 46049 | C51: EWH1B84 | D51: N36141833 | E51: DIEGO DA SILVA OLIVEIRA | F51: 156.18 | G51: ESTACIONAR EM DESACORDO COM A REGULAMENTAÇÃO | H51: AV. RUI BARBOSA 153 | K51: ENVIADO AO DP
A52: 46056 | C52: TEW9A26 | D52: RD31333218 | F52: 156.192 | G52: ESTACIONAR EM LOCAL PROIBIDO | H52: AV NOSSA SENHORA DE COPACABANA 876 | I52: SIM | J52: NÃO | K52: ENVIADO AO DP
A53: 46058 | C53: FGO3C61 | D53: K30743603 | E53: MICHEL PINHEIRO | F53: 156.19 | G53: ESTACIONAR EM LOCAL PROIBIDO | H53: RODOVIA AMARAL PEIXOTO 4879 | I53: SIM | K53: ENVIADO AO DP
A54: 46058 | C54: TEW9A27 | D54: N36146339 | E54: HELENO ROVANE DOS SANTOS MELO | F54: 156.18 | G54: ESTACIONAR EM DESACORDO COM A REGULAMENTAÇÃO | H54: RUA BELISARIO AUGUSTO PRÓXIMO AO 265 - NITERÓI | K54: ENVIADO AO DP
A55: 46059 | C55: TEW9A29 | D55: L30574947 | E55: MARCELINO ALMEIDA DE CASTRO | F55: 156.18 | G55: ESTACIONAR EM DESACORDO COM A REGULAMENTAÇÃO | H55: RUA PAULO BARBOSA - 125 - PETRÓPOLIS | I55: SIM | J55: NÃO | K55: ENVIADO AO DP
A56: 46060 | C56: TEW9A29 | D56: RA21126436 | E56: MARCELINO ALMEIDA DE CASTRO | F56: 130.16 | G56: TRANSITAR EM VELOCIDADE SUPERIOR A 20% | K56: ENVIADO AO DP
A57: 46062 | C57: FGO3C61 | D57: N36147921 | E57: MICHEL PINHEIRO | F57: 156.18 | G57: ESTACIONAR EM DESACORDO COM A REGULAMENTAÇÃO | K57: ENVIADO AO DP
A58: 46063 | C58: TEW9A24 | D58: Z54288066 | E58: MARCELO LOPES VIEIRA | F58: 352.16 | G58: AVANCAR SINAL VERMELHO | H58: RJ 216 SENTIDO CAMPOS DOS GOYTACAZES X FAROL DE SÃO THOME, KM08 | K58: ENVIADO AO DP
A59: 46063 | C59: TEW9A24 | D59: Z54288087 | E59: MARCELO LOPES VIEIRA | F59: R$ 1.056,49 | G59: DIRIGIR VEÍCULO SEM POSSUIR CNH/PPD/ACC | H59: RJ 216 SENTIDO CAMPOS DOS GOYTACAZES X FAROL DE SÃO THOME, KM08 | K59: ENVIADO AO DP
A60: 46064 | C60: TEW9A27 | D60: X41590241 | E60: HELENO ROVANE DOS SANTOS MELO | F60: 156.19 | G60: TRANSITAR EM VELOCIDADE SUPERIOR A 20% | H60: RJ 124, KM 1,2 ST BR -101. RIO BONITO | K60: ENVIADO AO DP
A61: 46065 | C61: TEP5C93 | D61: N004337238 | E61: ANDRE VINICIUS NAZARE ESCOBAR | F61: R$ 1.056,49 | G61: DIRIGIR VEÍCULO SEM POSSUIR CNH/PPD/ACC | H61: RJ - BR 116 - KM 171.00 | I61: SIM | J61: NÃO | K61: ENVIADO AO DP
A62: 46065 | C62: TEW9A28 | D62: N30845808 | E62: LUIZ FELIPE DA COSTA BARBOSA | F62: 156.18 | G62: ESTACIONAR EM DESACORDO COM A REGULAMENTAÇÃO | H62: RUA GAVIÃO PEIXOTO 123 - NITERÓI | K62: ENVIADO AO DP
A63: 46073 | C63: TEW9A29 | D63: RA21146928 | E63: MARCELINO ALMEIDA DE CASTRO | F63: 156.19 | G63: TRANSITAR EM VELOCIDADE SUPERIOR A MAXIMA PERMITIDA EM ATE 20% | H63: R BARONESA PX185-ST BRT PCA SECA | K63: ENVIADO AO DP
A64: 46079 | C64: TET5H37 | D64: J007267668 | E64: JORGE LUIZ DOS SANTOS VIEIRA | F64: 234.28 | G64: TRAN VELOC SUP MAX PERMITIDA EM MAIS DE 20% ATÉ 50% | H64: RJ - BR 116 - KM 108.17- C | K64: ENVIADO AO DP
A65: 46079 | C65: TET5H37 | D65: J007267561 | E65: JORGE LUIZ DOS SANTOS VIEIRA | F65: 234.28 | G65: TRAN VELOC SUP MAX PERMITIDA EM MAIS DE 20% ATÉ 50% | H65: RJ - BR 116 - KM 98.33- C | K65: ENVIADO AO DP
A66: 46080 | C66: SRN9C05 | D66: J007290141 | E66: ALDENIR TEIXIERA CARVALHO | F66: 156.19 | G66: TRANSITAR EM VELOCIDADE SUPERIOR A MAXIMA PERMITIDA EM ATE 20% | H66: RJ - BR 101 - KM 332.32 - C | K66: ENVIADO AO DP
A67: 46083 | C67: TET 5H37 | D67: RD31375531 | E67: JORGE LUIZ DOS SANTOS VIEIRA | F67: 156.18 | G67: VEICULO ESTACIONADO EM VAGA DE DEFICIENTE SEM PORTAR O SELO CONDUTOR AUSENTE | H67: Rua voluntários da Pátria - Botafogo | K67: ENVIADO AO DP
A68: 46083 | C68: TEW9A33 | D68: N36156647 | E68: CARLOS HENRIQUE SILVA MENDES | F68: 156.18 | G68: ESTACIONAR EM DESACORDO COM A REGULAMENTACAO - ESTACIONAMENTO ROTATIVO | H68: R. MARECHAL DEODORO PROXIMO AO 73 | K68: ENVIADO AO DP
A69: 46083 | C69: FUR3I24 | D69: RD31248545 | E69: DOUGLAS SIQUEIRA | F69: 156.19 | G69: ESTACIONAR EM LOCAL/HORARIO PROIBIDO ESPECIFICAMENTE PELA SINALIZACAO | H69: RUA SAO LEOBALDO 211, SÃO CONRADO | K69: ENVIADO AO DP
A70: 46084 | C70: EWH1B84 | D70: RA21164869 | E70: DIEGO DA SILVA OLIVEIRA | F70: 156.19 | G70: TRANSITAR EM VELOCIDADE SUPERIOR A MAXIMA PERMITIDA EM ATE 20% | H70: TN PREFMARCELOALENCAR PX PORTA05-STRODOVIARIA | K70: ENVIADO AO DP
A71: 46085 | C71: TET5H37 | D71: RA41264986 | E71: JORGE LUIZ DOS SANTOS VIEIRA | F71: 352.16 | G71: AVANCAR O SINAL DE PARADA OBRIGATORIA | H71: Av Nelson Cardoso Px R Mal Bevilaqua - St Praca Seca | K71: ENVIADO AO DP
A72: 46086 | C72: TCJ1G00 | D72: J007401871 | E72: EDUARDO MAIA | F72: R$ 130,16 | G72: TRANSITAR EM VELOCIDADE SUPERIOR A MAXIMA PERMITIDA EM ATE 20% | H72: RJ- BR 116- KM 173.46 - D | K72: ENVIADO AO DP
A73: 46087 | C73: SRU8D16 | D73: N30849757 | E73: DOUGLAS SIQUEIRA | F73: 156.19 | G73: ESTACIONAR EM LOCAL/HORARIO PROIBIDO ESPECIFICAMENTE PELA SINALIZACAO | H73: R. DOMINGUES DE SA 246 | K73: ENVIADO AO DP
A74: 46089 | C74: PVR9C55 | D74: RD31381373 | E74: EWERTON MIGUEL DA SILVA | F74: 293.47 | G74: DIRIGIR VEÍCULO MANUSEANDO TELEFONE CELULAR | K74: ENVIADO AO DP
A75: 46090 | C75: SRN9C05 | D75: N36159771 | E75: ALDENIR TEIXIERA CARVALHO | F75: 156.18 | G75: ESTACIONAR EM DESACORDO COM A REGULAMENTACAO - ESTACIONAMENTO ROTATIVO | H75: AV. RUI BARBOSA PROXIMO AO 159 | K75: ENVIADO AO DP
A76: 46091 | C76: TEP5C33 | D76: Q29991307 | E76: GABRIEL VIDAL | F76: R$ 234,28 | G76: ESTACIONAR O VEIC EM DESACORDO C AAS CONDIÇOES REGULAMENTADAS | H76: AV ASSUNÇÃO | K76: ENVIADO AO DP
A77: 46091 | C77: TEW9A29 | D77: RA21168865 | E77: MARCELINO ALMEIDA DE CASTRO | F77: 156.19 | G77: VELOCIDADE SUPERIOR ATÉ 20% DA PERMITIDA | H77: TN MARCELO ALENCAR
A78: 46091 | C78: SRN9C05 | D78: J007494807 | E78: ALDENIR TEIXIERA CARVALHO | F78: 156.19 | G78: VELOCIDADE SUPERIOR ATÉ 20% DA PERMITIDA | H78: : RJ - BR 101 - KM 325.60 - D | K78: ENVIADO AO DP
A79: 46093 | C79: TEW9A23 | D79: S31451696 | E79: MULLER GOMES DOS SANTOS | F79: 156.18 | G79: ESTACIONAR EM DESACORDO COM A REGULAMENTACAO - VAGA DE CARGA/DESCARGA | H79: RUA DOUTOR ANTONIO ALVES N:148 CENTRO - SÃO PEDRO DA ALDEIA | K79: ENVIADO AO DP
A80: 46093 | C80: EWH1B84 | D80: N36161227 | E80: DIEGO DA SILVA OLIVEIRA | F80: 156.18 | G80: ESTACIONAR EM DESACORDO COM A REGULAMENTACAO - ESTACIONAMENTO ROTATIVO | H80: R. JOSE CLEMENTE PROXIMO AO 17 | K80: ENVIADO AO DP
A81: 46093 | C81: SRN9C05 | D81: N36161406 | E81: ALDENIR TEIXIERA CARVALHO | F81: 234.28 | G81: ESTACIONAR EM DESACORDO COM A REGULAMENTACAO - ESTACIONAMENTO ROTATIVO | H81: R. OTAVIO CARNEIRO PROXIMO AO 18 | K81: ENVIADO AO DP
A82: 46094 | C82: TEW9A28 | D82: N36162153 | E82: LUIZ FELIPE DA COSTA BARBOSA | F82: R$ 195,23 | G82: ESTACIONAR EM DESACORDO COM A REGULAMENTACAO - ESTACIONAMENTO ROTATIVO | H82: R. ATOR PAULO GUSTAVO PROXIMO AО 371 | K82: ENVIADO AO DP
A83: 46094 | C83: TEW9A33 | D83: N36162192 | E83: CARLOS HENRIQUE SILVA MENDES | F83: R$ 195,23 | G83: ESTACIONAR EM DESACORDO COM A REGULAMENTACAO - ESTACIONAMENTO ROTATIVO | H83: R. SAO JOAO PROXIMO AO 42 | K83: ENVIADO AO DP
A84: 46094 | C84: EWH1B84 | D84: N36161990 | E84: DIEGO DA SILVA OLIVEIRA | F84: 156.18 | G84: ESTACIONAR EM DESACORDO COM A REGULAMENTACAO - ESTACIONAMENTO ROTATIVO | H84: R. AURELINO LEAL PROXIMO AO 2 | K84: ENVIADO AO DP
A85: 46094 | C85: EWH1B84 | D85: RA21164346 | E85: DIEGO DA SILVA OLIVEIRA | F85: 156.19 | G85: TRANSITAR EM VELOCIDADE SUPERIOR A MAXIMA PERMITIDA EM ATE 20% | H85: R HERCULANO PENA PX R MUCIO TEIXEIRA-ST PILARES | K85: ENVIADO AO DP
A86: 46095 | C86: TET5H37 | D86: RA21169715 | E86: JORGE LUIZ DOS SANTOS VIEIRA | F86: 156.19 | G86: VELOCIDADE SUPERIOR ATÉ 20% DA PERMITIDA | H86: : R FRANCISCO REAL PX1074- ST UNICO | K86: ENVIADO AO DP
A87: 46097 | C87: TET5I11 | D87: L30467484 | E87: ANDERSON CRUZ DO AMARAL | F87: 234.28 | G87: ESTACIONAR O VEIC EM DESACORDO C AAS CONDIÇOES REGULAMENTADAS | H87: AV. CARDOSO MORERA. 846 | K87: ENVIADO AO DP
A88: 46100 | C88: TEW9A26 | D88: RD31391427 | E88: RICHARD GUIMARÃES FARIAS | F88: 156.18 | G88: ESTACIONAR NAS RESERVADAS AS PESSOAS COM DEFICIENCIA, SEM CREDENCIAL | H88: ESTRADA ESTRADA DO PORTELA 51, - MADUREIRA | K88: ENVIADO AO DP
A89: 46101 | C89: TEW9A29 | D89: J007683606 | E89: MARCELINO ALMEIDA DE CASTRO | F89: R$ 130,16 | G89: TRANSITAR EM VELOCIDADE SUPERIOR A MAXIMA PERMITIDA EM ATE 20% | H89: RJ - BR 116 - KM 98.52 - D | K89: ENVIADO AO DP
A90: 46105 | C90: SRN9C05 | D90: X41617639 | E90: ALDENIR TEIXIERA CARVALHO | F90: R$ 130,16 | G90: TRANSITAR EM VELOCIDADE SUPERIOR A MAXIMA PERMITIDA EM ATE 20% | H90: RJ-124, KM 1,2 -ST BR-101
A91: 46107 | C91: FOK8A73 | D91: RD31410843 | E91: RAFAEL SILVA | F91: 195.23 | G91: ESTACIONAR EM DESACORDO COM A REGULAMENTACAO ESTACIONAMENTO ROTATIVo
A92: 46108 | C92: EWH1B84 | D92: RD31374120 | E92: DIEGO DA SILVA OLIVEIRA | F92: 130.16 | G92: ESTACIONAR EM DESACORDO COM AS POSICOES ESTABELECIDAS NO СТВ | H92: RUA AVENIDA LUIS DE VASCONCELOS 48, - CENTRO | K92: ENVIADO AO DP
A93: 46109 | C93: TET5H37 | D93: RD31415242 | E93: JORGE LUIZ DOS SANTOS VIEIRA | F93: R$ 234,28 | G93: ESTACIONAR O VEIC EM DESACORDO C AAS CONDIÇOES REGULAMENTADAS | H93: Avenida Nossa senhora de Copacabana 552 | K93: ENVIADO AO DP
A94: 46109 | C94: TET5I11 | D94: 031074363 | E94: ANDERSON CRUZ DO AMARAL | F94: 130.16 | G94: VELOCIDADE SUPERIOR ATÉ 20% DA PERMITIDA | H94: AV. JOSE ALVES MACHADO (LINHA VERDE) PX AV. ALUIZIO SILVA | K94: ENVIADO AO DP
A95: 46125 | C95: TEQ2I90 | D95: O30954962 | E95: CARLOS ARTHUR FERREIRA DE ANDRADE | F95: R$ 195,23 | G95: ESTACIONAR O VEICULO EM DESACORDO COM A REGULAMENTACAO VAGA DE CURTA DURACAO
A96: 46126 | C96: EWH1B84 | D96: RF50230840 | E96: DIEGO DA SILVA OLIVEIRA | F96: 88.38 | G96: EVADIR-SE DA COBRANCA PELO USO DE RODOVIAS E VIAS URBANAS PARA NAO EFETUAR SEU PAGAMENTO
A97: 46127 | C97: TEW9A23 | D97: J008191491 | E97: MULLER GOMES DOS SANTOS | F97: 130.16 | G97: VELOCIDADE SUPERIOR ATÉ 20% DA PERMITIDA
A98: 46127 | C98: FGO3C61 | D98: N36175235 | E98: MICHEL PINHEIRO | F98: 195.23 | G98: ESTACIONAR EM DESACORDO COM A REGULAMENTACAO ESTACIONAMENTO ROTATIVo
A99: 46129 | C99: FGO3C61 | D99: S31481092 | E99: MICHEL PINHEIRO | F99: 195.23 | G99: ESTACIONAR NO PASSEIO
A100: 46132 | C100: EZX6C83 | D100: N36177144 | E100: LUIZ RODRIGO | F100: 195.23 | G100: ESTACIONAR EM DESACORDO COM A REGULAMENTACAO ESTACIONAMENTO ROTATIVo
...

Sheet AUX
B4: TODOS
B5: MANFAC-1 | D5: TODOS
B6: MANFAC-2 | D6: FAC - 140004 - MANUTENÇÃO PREDIAL DPSP 2025
B7: MANFAC-3 | D7: PROF - 07001 - MANUTENÇÃO PREDIAL- PROFARMA-2025
B8: MANFAC-4 | D8: FAC - 140005 - SPOT MANUTENÇÃO DPSP 2025
B9: MANFAC-5 | D9: EC - ESCRITORIO CENTRAL
B10: MANFAC-6 | D10: PROF - 07002 - SPOT MANUTENÇÃO PROFARMA
B11: MANFAC-7
B12: MANFAC-8
B13: MANFAC-9
B14: MANFAC-10
B15: MANFAC-11
B16: MANFAC-12
B17: MANFAC-13
B18: MANFAC-15
B19: MANFAC-17
B20: MANFAC-18
B21: MANFAC-19
B22: MANFAC-20
... B30: YURI

Sheet MANUTENÇÃO PREVENTIVA
C2: MANUTENÇÃO PREVENTIVA
B5: PLACA | C5: VEÍCULO | D5: CENTRO DE CUSTO | E5: KM DA REVISÃO | F5: DATA REVISÃO | G5: PROXIMA REVISÃO | H5: CUSTO DE REVISÃO | I5: OBS | J5: STATUS
B6: FUR3I24 | C6: HB20 | D6: MANUTENÇÃO DPSP | E6: 102686 | F6: 45908 | G6: 110000 | H6: já esta imbutido no valor da locação | I6: Realizada Dia 10/02/2026
B7: EZX6C83 | C7: HB20 | D7: MANUTENÇÃO DPSP | E7: 91688 | F7: 45693 | G7: 100000 | H7: já esta imbutido no valor da locação
B8: FIL8C14 | C8: HB20 | D8: MANUTENÇÃO DPSP | E8: 85816 | F8: 45797 | G8: 90000 | H8: já esta imbutido no valor da locação
B9: FGO3C61 | C9: HB20 | D9: SPOT DPSP | E9: 101341 | F9: 45853 | G9: 110000 | H9: já esta imbutido no valor da locação | I9: Realizada Dia 11/02/2026
B10: FOK8A73 | C10: HB20 | D10: MANUTENÇÃO DPSP | E10: 85476 | F10: 45876 | G10: 100000 | H10: já esta imbutido no valor da locação
B11: EWH1B84 | C11: HB20 | D11: SPOT DPSP | E11: 104832 | F11: 45817 | G11: 110000 | H11: já esta imbutido no valor da locação
B12: TET5H37 | C12: FIAT MOBI LIKE | D12: MANUTENÇÃO DPSP | E12: VENCIDA | H12: já esta imbutido no valor da locação
H13: já esta imbutido no valor da locação
B14: TEW9A23 | C14: FIAT ARGO | D14: MANUTENÇÃO PROFARMA | E14: 12138 | G14: 20000 | H14: já esta imbutido no valor da locação
B15: TEW9A24 | C15: FIAT ARGO | D15: MANUTENÇÃO PROFARMA | E15: 12804 | G15: 20000 | H15: já esta imbutido no valor da locação
B16: TEW9A25 | C16: FIAT ARGO | D16: MANUTENÇÃO PROFARMA | E16: 12422 | G16: 20000 | H16: já esta imbutido no valor da locação
B17: TEW9A26 | C17: FIAT ARGO | D17: MANUTENÇÃO PROFARMA | E17: 11018 | G17: 20000 | H17: já esta imbutido no valor da locação | I17: Realizada Dia 09/02/2026
B18: TEW9A34 | C18: FIAT ARGO | D18: MANUTENÇÃO PROFARMA | E18: 13480 | G18: 20000 | H18: já esta imbutido no valor da locação
B19: TEW9A27 | C19: FIAT ARGO | D19: SPOT DPSP | E19: 10134 | G19: 20000 | H19: já esta imbutido no valor da locação | I19: Realizada Dia 25/02/2026
B20: TEW9A28 | C20: FIAT ARGO | D20: MANUTENÇÃO PROFARMA | E20: 13523 | G20: 19000 | H20: já esta imbutido no valor da locação
B21: TEW9A29 | C21: FIAT ARGO | D21: MANUTENÇÃO DPSP | E21: 12223 | G21: 19000 | H21: já esta imbutido no valor da locação
B22: TEW9A30 | C22: FIAT ARGO | D22: SPOT DPSP | E22: 10204 | G22: 20000 | H22: já esta imbutido no valor da locação | I22: Realizada Dia 24/02/2026
B23: TEW9A33 | C23: FIAT ARGO | D23: MANUTENÇÃO PROFARMA | E23: 13540 | G23: 19000 | H23: já esta imbutido no valor da locação
B24: TCJ1G00 | C24: VIRTUS | D24: ADM CENTRAL | E24: 19800 | F24: 45804 | G24: 29800 | H24: já esta imbutido no valor da locação
B25: RNK0B07 | C25: FIAT CRONOS | D25: ADM CENTRAL | E25: 50706 | F25: 45684 | G25: 60000 | H25: já esta imbutido no valor da locação
B26: TEP5C93 | C26: FIAT ARGO | D26: ADM CENTRAL | E26: 18255 | G26: 28255 | H26: já esta imbutido no valor da locação
B27: TEH3I02 | C27: FIAT MOBI LIKE | D27: SPOT DPSP | E27: 11623 | G27: 20000 | H27: já esta imbutido no valor da locação
B28: TEQ2I90 | C28: FIAT MOBI LIKE | D28: SPOT DPSP | E28: 11769 | G28: 20000 | H28: já esta imbutido no valor da locação
B29: SRN9C05 | C29: KWID | D29: MANUTENÇÃO PROFARMA | E29: 11769 | G29: 20000 | H29: já esta imbutido no valor da locação
B30: TYK8C73 | C30: TERA | D30: ADM CENTRAL | E30: 11769 | G30: 20000 | H30: já esta imbutido no valor da locação

Sheet DESCONTO DE SINISTROS
A1: PLACA | B1: DATA SINISTRO | C1: MOTORISTA | D1: VALOR SINISTRO | E1: DESCONTO | F1: OBSERVAÇÃO
C2: ANDRE VINICIUS | D2: 9400 | E2: NÃO
C3: ANDRE VINICIUS | D3: 350 | E3: NÃO
C4: MICHEL PINHEIRO | D4: 2132 | E4: NÃO
C5: MICHEL PINHEIRO | D5: 6000 | E5: NÃO
C6: HELENO | D6: 700 | E6: SIM
C7: HELENO | D7: 700 | E7: SIM | F7: JÁ DESCONTADO EM 2X
C8: DIEGO | D8: 900 | E8: NÃO
A9: TEW9A34 | C9: ANDRE VINICIUS | D9: R$ 300,00 | E9: SIM | F9: PORTA PAGO
A10: TEW9A34 | C10: ANDRE VINICIUS | D10: R$ 1.000 | E10: SIM | F10: TROCA DA PORTA PAGO
A11: FOK8A73 | C11: RAFAEL | D11: R$ 1.200 | E11: NÃO | F11: COMPRESSOR PAGO
A12: TEW9A27 | C12: HELENO | D12: R$ 742,84 | E12: NÃO | F12: RETROVISOR PAGO
A13: TEW9A34 | C13: ANDRE VINICIUS | D13: R$ 435,04 | E13: SIM | F13: VIDRO DA PORTA PAGO
A14: FGO3C61 | C14: MICHEL PINHEIRO | D14: R$ 357,00 | E14: SIM | F14: PARA-CHOQUE PAGO
A15: FGO3C61 | C15: MICHEL PINHEIRO | D15: R$ 290,00 | E15: SIM | F15: GRADE PARA-CHOQUE PAGO

Sheet CONTROLE DE VENC DE CNH
C3: CONTROLE DE VENCIMENTO DE CNH
B5: COLABORADOR | C5: DATA DE VENCIMENTO DA CNH | D5: PLACA DO VEÍCULO | E5: OBS
B6: GABRIEL MIRANDA | C6: 48169 | D6: TEW9A25
B8: FABIO DA CONCEIÇÃO | C8: 47978 | D8: EZX6C83
B10: AILTON HONORATO | C10: 48966 | D10: FIL8C14
B12: MICHEL PINHEIRO | C12: NÃO HABILITADO | D12: FGO3C61
B14: RAFAEL SILVA | C14: 49128 | D14: FOK8A73
B16: DIEGO OLIVEIRA | C16: 49343 | D16: EWH1B84
B18: HELENO HOVANE | C18: 46049 | D18: TEW9A27
B20: WEVERTON MIRANDA | C20: 48903 | D20: TEW9A28
B22: MARCELINO ALMEIDA DE CASTRO | C22: 49706 | D22: RVK9B93
B24: MARCELO LOPES VIEIRA | C24: 46821 | D24: SYD0J39
B26: ANDRÉ VINÍCIUS NAZARÉ ESCOBAR | C26: 46221 | D26: TCR8G41
B28: CARLOS HENRIQUE SILVA MENDES | C28: 49080 | D28: TCH0D80
B30: RICHARD GUIMARAES | C30: 48933 | D30: TEW9A26
B32: ALAN DAVI | C32: 48117 | D32: TEWA30
B34: MULLER | C34: 48181 | D34: TEW9A23
B36: DOUGLAS | C36: 49939 | D36: FUR3I24
B38: ANDERSON | C38: 48710 | D38: TET5I11

Sheet CONTROLE HIGIENIZAÇÃO
D3: CONTROLE DE HIGIENIZAÇÃO
B5: PLACA | C5: DATA DA ÚLTIMA HIGIENIZAÇÃO | D5: DATA DA PRÓXIMA HIGIENIZAÇÃO | E5: COLABORADOR | F5: OBS
B6: EZX6C83 | E6: FÁBIO DA CONCEIÇÃO
B7: FIL8C14 | E7: AILTON HONORATO
B8: FGO3C61 | E8: MICHEL PINHEIRO
B9: FOK8A73 | E9: RAFAEL SILVA
B10: EWH1B84 | E10: DIEGO DA SILVA
B11: TEW9A27 | E11: HELENO ROVANI
B12: TEW9A30 | E12: ALAN DAVI
B13: TEW9A29 | E13: MARCELINO ALMEIDA
B14: TEW9A24 | E14: MARCELO LOPES
B15: TEP5C93 | E15: ANDRÉ VINICIUS
B16: TEW9A33 | E16: CARLOS MENDES
B17: TET5H37 | E17: JORGE LUIZ
... B24: TET5I11 | E24: ANDERSON

Sheet RATEIO
C4: RATEIO
C6: ADM CENTRAL | D6: MANUTENÇÃO DPSP | E6: SPOT DPSP | F6: MANUTENÇÃO PROFARMA | G6: SPOT PROFARMA | H6: DATA DE VENCIMENTO | I6: NOTA DE DÉBITO | J6: VALOR E-MAIL
B7: LOCAÇÃO
B8: TAXA ADMINISTRATIVA
B9: MULTA
B10: JUROS DE PAGAMENTO
B11: MULTA DE PAGAMENTO
