Workbook
Name DataBase: PAINEL!$C$8
Name DataRef: PAINEL!$C$9
Name Feriados: LISTAS!$E$5:$E$24
Name FimObra: PAINEL!$C$10
Name RelSeg: RELATORIO_CLIENTE!$C$6
Name RelSex: RELATORIO_CLIENTE!$C$7

Sheet LEIA_ME
B1: SGO MANFAC – Sistema de Gestão, Controle e Comunicação de Obra
B2: Obra DP Macaé 3 (DPSP DS 1505) – base única: tudo é registrado uma vez e alimenta painel, relatórios e comunicação.
B5: COMO LER AS CORES
B6: Amarelo, texto azul | C6: Campo para preencher ou ajustar.
B7: Branco, texto preto | C7: Fórmula. Não sobrescrever.
B8: Cinza itálico | C8: Linha de exemplo (não entra em nenhum total).
B10: ABAS
B11: PAINEL | C11: Visão da gestão MANFAC: parâmetros, avanço, financeiro interno, pendências, comunicação e alertas automáticos.
B12: CRONOGRAMA | C12: 28 atividades (20 da frente estrutural + 8 da reforma light) com predecessoras, dias úteis, peso pelo valor do orçamento, status, % realizado e gráfico de barras semanal.
B13: ORCAMENTO | C13: REV_04 e LPU rev 2 na mesma tabela. Cada linha ligada a uma atividade (peso físico), com % medido, custo previsto e custo real vindo de COMPRAS e LOCACOES.
B14: CONFLITOS | C14: Nove sobreposições de escopo entre REV_04 e LPU, com valores e ação recomendada.
B15: RDO | C15: Registro diário do encarregado, validado pelo engenheiro. Base do informe diário ao cliente.
B16: COMPRAS / LOCACOES | C16: Pedidos, entregas e locações com custo acumulado por dia. Cada lançamento usa a chave de um item do orçamento.
B17: MEDICOES | C17: Ciclo medição → aprovação DPSP → NF → recebimento, com dias em aprovação.
B18: PENDENCIAS | C18: Travas, riscos, decisões do cliente e ajustes de escopo. Já carregada com 14 pontos da conferência de 23/10/2026.
B19: COMUNICACAO | C19: Agenda de envios gerada pelo cronograma (diários, semanais às sextas, mensais no último dia útil, fases e entrega) e histórico de envio, com situação automática.
B20: RELATORIO_CLIENTE | C20: Relatório semanal pronto para PDF, sem custos: avanço, concluídas, em andamento, próxima semana, decisões do cliente e fotos.
B21: CURVA_S | C21: Previsto x realizado por semana. O realizado é registrado toda sexta (copiar do PAINEL).
B22: LISTAS | C22: Listas suspensas e feriados usados no cálculo de dias úteis.
B24: ROTINA
B25: Diariamente | C25: Encarregado preenche o RDO → engenheiro valida → COP envia o informe diário e marca "Enviado?" = Sim e a data real em COMUNICACAO. Atualizar status e % no CRONOGRAMA.
B26: Sexta-feira | C26: Atualizar CRONOGRAMA e PENDENCIAS → GO avalia desvios no PAINEL → copiar avanço realizado na CURVA_S → salvar RELATORIO_CLIENTE em PDF e enviar.
B27: Último dia útil do mês | C27: Engenharia e Financeiro atualizam ORCAMENTO (% medido) e MEDICOES → GO valida → relatório mensal ao cliente.
B28: Exceção | C28: Risco de atraso, custo adicional ou decisão do cliente: comunicação imediata, registrada em COMUNICACAO (linhas amarelas no fim).
B30: PREMISSAS
B31: Datas | C31: Data-base 26/10/2026 (ajustável no PAINEL). Durações em dias úteis são estimativas MANFAC para validação do engenheiro.
B32: Peso físico | C32: Proporcional ao valor de venda vinculado a cada atividade. Indiretos (9.1–9.3) e imposto (9.4) do REV_04 ficam fora do peso.
B33: Situação atual | C33: Escoramento parcial: falta a viga principal. Demolições bloqueadas até o nº 6 ficar "Concluído". Status das atividades 1 a 5 a confirmar.
B34: Fontes | C34: REV_04 (orçamento estrutural), LPU Padrão Reforma Light DP Macaé 3 rev 2, Laudo EGUTI Rev.00 (09/06/2026), Layout aprovado Macaé RJ, Fases da Obra Macaé 3.

Sheet PAINEL
A1: SGO – Painel da Obra | DP Macaé 3 (DPSP DS 1505)
A2: Visão da gestão MANFAC. Uso interno: contém custos e margem. Para o cliente, use a aba RELATORIO_CLIENTE.
B4: PARÂMETROS DA OBRA | E4: FINANCEIRO (USO INTERNO)
B5: Obra | C5: DP Macaé 3 – Intervenção estrutural + reforma light | E5: Pedido estrutural – REV_04 | F5: =SUMIFS(ORCAMENTO!G:G,ORCAMENTO!A:A,"Estrutural REV_04") -> 292968
B6: Cliente | C6: Grupo DPSP – DS 1505 | E6: Pedido reforma light – LPU rev 2 | F6: =SUMIFS(ORCAMENTO!G:G,ORCAMENTO!A:A,"Reforma light LPU") -> 213372.41
B7: Endereço | C7: Rua Maria Francisca Borges Reid, s/nº – Glória, Macaé/RJ | E7: Total contratado | F7: =F5+F6 -> 506340.41
B8: Data-base do planejamento (início das atividades restantes) | C8: 46321 | E8: Medido acumulado (aba ORCAMENTO) | F8: =SUM(ORCAMENTO!K5:K200) -> 0
B9: Data de referência (hoje – pode fixar para fechar relatório) | C9: =TODAY() -> 46318 | E9: Medições apresentadas | F9: =SUM(MEDICOES!E6:E200) -> 0
B10: Previsão de término (cronograma) | C10: =MAX(CRONOGRAMA!K5:K32) -> 46415 | E10: Medições aprovadas | F10: =SUMIFS(MEDICOES!E6:E200,MEDICOES!H6:H200,"<>") -> 0
B11: Engenheiro responsável | E11: Faturado (NF emitida) | F11: =SUM(MEDICOES!L6:L200) -> 0
E12: Recebido | F12: =SUMIFS(MEDICOES!L6:L200,MEDICOES!M6:M200,"<>") -> 0
B13: PRAZO E AVANÇO FÍSICO | E13: Saldo a medir | F13: =F7-F8 -> 506340.41
B14: Avanço previsto até a data de referência | C14: =SUMPRODUCT(CRONOGRAMA!M5:M32,CRONOGRAMA!R5:R32) -> 0 | E14: Custo real (compras + locações) | F14: =SUMIFS(COMPRAS!G6:G500,COMPRAS!J6:J500,"<>Cancelado")+SUM(LOCACOES!I6:I200) -> 0
B15: Avanço realizado | C15: =SUMPRODUCT(CRONOGRAMA!M5:M32,CRONOGRAMA!O5:O32) -> 0 | E15: Resultado sobre o medido (medido – custo real) | F15: =F8-F14 -> 0
B16: Desvio (pontos percentuais) | C16: =(C15-C14)*100 -> 0 | E16: Exposição a glosa por sobreposição REV_04 x LPU (não resolvida) | F16: =SUMIFS(CONFLITOS!J5:J13,CONFLITOS!I5:I13,"<>Resolvido") -> 35912.64
B17: Atividades atrasadas ou com início atrasado | C17: =COUNTIF(CRONOGRAMA!T5:T32,"ATRASADA")+COUNTIF(CRONOGRAMA!T5:T32,"INÍCIO ATRASADO") -> 0
B18: Atividades concluídas | C18: =COUNTIF(CRONOGRAMA!N5:N32,"Concluído")&" de "&COUNTA(CRONOGRAMA!A5:A32) -> 0 de 28
B19: Trava estrutural (escoramento da viga principal) | C19: =IF(CRONOGRAMA!N10="Concluído","LIBERADA – demolições autorizadas","BLOQUEADA – demolições proibidas") -> BLOQUEADA – demolições proibidas
B21: PENDÊNCIAS, COMUNICAÇÃO E RECURSOS | E21: ALERTAS AUTOMÁTICOS
B22: Pendências em aberto | C22: =COUNTIFS(PENDENCIAS!C5:C200,"<>",PENDENCIAS!J5:J200,"<>Concluída") -> 14 | E22: =IF(CRONOGRAMA!N10<>"Concluído","Escoramento da viga principal pendente: nenhuma demolição pode começar.","") -> Escoramento da viga principal pendente: nenhuma demolição pode começar.
B23: Pendências vencidas | C23: =COUNTIF(PENDENCIAS!M5:M200,"VENCIDA") -> 0 | E23: =IF(C17>0,C17&" atividade(s) atrasada(s) – comunicar o cliente hoje, sem esperar o semanal.","")
B24: Decisões aguardando o cliente | C24: =COUNTIFS(PENDENCIAS!G5:G200,"Sim",PENDENCIAS!J5:J200,"<>Concluída",PENDENCIAS!C5:C200,"<>") -> 6 | E24: =IF(C16<-5,"Desvio acima de 5 p.p. – definir ação de recuperação e registrar no semanal.","")
B25: Comunicações ao cliente atrasadas | C25: =COUNTIF(COMUNICACAO!L5:L300,"ATRASADO") -> 0 | E25: =IF(C25>0,C25&" comunicação(ões) ao cliente atrasada(s).","")
B26: Próximo envio programado | C26: =_xlfn.MINIFS(COMUNICACAO!E5:E300,COMUNICACAO!F5:F300,"",COMUNICACAO!E5:E300,">="&DataRef) -> 46321 | E26: =IF(C24>0,C24&" decisão(ões) aguardando o cliente – cobrar no próximo informe.","") -> 6 decisão(ões) aguardando o cliente – cobrar no próximo informe.
B27: RDOs registrados | C27: =COUNT(RDO!A6:A500) -> 0 | E27: =IF(F16>0,"Exposição de R$ "&FIXED(F16,0)&" em escopo sobreposto REV_04 x LPU – resolver antes da 1ª medição.","") -> Exposição de R$ 35.913 em escopo sobreposto REV_04 x LPU – resolver antes da 1ª medição.
B28: RDOs registrados e não enviados ao cliente | C28: =COUNTIFS(RDO!A6:A500,"<>",RDO!Q6:Q500,"<>Sim") -> 0 | E28: =IF(C30>0,C30&" locação(ões) vencida(s) – custo correndo.","")
B29: Locações ativas | C29: =COUNTIF(LOCACOES!K6:K200,"Ativa")+COUNTIF(LOCACOES!K6:K200,"VENCIDA*") -> 0 | E29: =IF(C28>0,C28&" RDO(s) sem envio ao cliente.","")
B30: Locações vencidas (renovar ou devolver) | C30: =COUNTIF(LOCACOES!K6:K200,"VENCIDA*") -> 0
B31: Compras com entrega atrasada | C31: =COUNTIF(COMPRAS!L6:L500,"ATRASADA") -> 0

Sheet CRONOGRAMA
A1: Cronograma físico – atividades, travas e avanço
A2: Amarelo = preencher. Datas previstas calculadas por predecessoras e dias úteis (feriados na aba LISTAS). Peso = valor do orçamento vinculado à atividade.
Z3: Gráfico de barras por semana (segunda-feira)
A4: Nº | B4: Frente | C4: Etapa | D4: Atividade | E4: Saída / trava | F4: Pred. 1 | G4: Pred. 2 | H4: Dias úteis | I4: Responsável | J4: Início previsto | K4: Fim previsto | L4: Valor vinculado | M4: Peso | N4: Status | O4: % realizado | P4: Início real | Q4: Fim real | R4: % previsto (hoje) | S4: Desvio | T4: Situação | U4: % prev. data relatório | V4: aux1 | W4: aux2 | X4: aux3 | Z4: =DataBase-WEEKDAY(DataBase,2)+1+0 -> 46321 | AA4: =DataBase-WEEKDAY(DataBase,2)+1+7 -> 46328 | AB4: =DataBase-WEEKDAY(DataBase,2)+1+14 -> 46335 | AC4: =DataBase-WEEKDAY(DataBase,2)+1+21 -> 46342 | AD4: =DataBase-WEEKDAY(DataBase,2)+1+28 -> 46349 | AE4: =DataBase-WEEKDAY(DataBase,2)+1+35 -> 46356 | AF4: =DataBase-WEEKDAY(DataBase,2)+1+42 -> 46363 | AG4: =DataBase-WEEKDAY(DataBase,2)+1+49 -> 46370 | AH4: =DataBase-WEEKDAY(DataBase,2)+1+56 -> 46377 | AI4: =DataBase-WEEKDAY(DataBase,2)+1+63 -> 46384 | AJ4: =DataBase-WEEKDAY(DataBase,2)+1+70 -> 46391 | AK4: =DataBase-WEEKDAY(DataBase,2)+1+77 -> 46398 | AL4: =DataBase-WEEKDAY(DataBase,2)+1+84 -> 46405 | AM4: =DataBase-WEEKDAY(DataBase,2)+1+91 -> 46412 | AN4: =DataBase-WEEKDAY(DataBase,2)+1+98 -> 46419 | AO4: =DataBase-WEEKDAY(DataBase,2)+1+105 -> 46426 | AP4: =DataBase-WEEKDAY(DataBase,2)+1+112 -> 46433 | AQ4: =DataBase-WEEKDAY(DataBase,2)+1+119 -> 46440 | AR4: =DataBase-WEEKDAY(DataBase,2)+1+126 -> 46447 | AS4: =DataBase-WEEKDAY(DataBase,2)+1+133 -> 46454
A5: 1 | B5: Estrutural | C5: 1 – Mobilização e isolamento | D5: Reunião de partida no local: identificar P1–P4, treliça e faixa de piso afetada | E5: Mapa de frentes validado pelo RT | H5: 1 | J5: =IF(AND(F5="",G5=""),WORKDAY(DataBase-1,1,Feriados),WORKDAY(MAX(IFERROR(INDEX($K$5:$K$32,MATCH(F5,$A$5:$A$32,0)),0),IFERROR(INDEX($K$5:$K$32,MATCH(G5,$A$5:$A$32,0)),0)),1,Feriados)) -> 46321 | K5: =WORKDAY(J5,MAX(H5,1)-1,Feriados) -> 46321 | L5: =SUMIFS(ORCAMENTO!$G$5:$G$200,ORCAMENTO!$H$5:$H$200,A5) -> 6650 | M5: =IF(SUM($L$5:$L$32)=0,0,L5/SUM($L$5:$L$32)) -> 0.015190542 | N5: Não iniciado | R5: =IF(DataRef<J5,0,IF(DataRef>=K5,1,NETWORKDAYS(J5,DataRef,Feriados)/MAX(H5,1))) -> 0 | S5: =N(O5)-R5 -> 0 | T5: =IF(N5="Concluído","Concluída",IF(N5="Bloqueado","BLOQUEADA",IF(DataRef>K5,"ATRASADA",IF(AND(DataRef>=J5,N5="Não iniciado"),"INÍCIO ATRASADO","No prazo")))) -> No prazo | U5: =IF(RelSex<J5,0,IF(RelSex>=K5,1,NETWORKDAYS(J5,RelSex,Feriados)/MAX(H5,1))) -> 0 | V5: =IF(N5="Concluído",COUNTIF($N$5:N5,"Concluído"),"") | W5: =IF(N5="Em andamento",COUNTIF($N$5:N5,"Em andamento"),"") | X5: =IF(AND(N5<>"Concluído",J5<=RelSex+7,K5>RelSex),COUNTIFS($N$5:N5,"<>Concluído",$J$5:J5,"<="&(RelSex+7),$K$5:K5,">"&RelSex),"") -> 1 | Z5: =IF(AND(Z$4<=$K5,Z$4+4>=$J5),1,"") -> 1 | AA5: =IF(AND(AA$4<=$K5,AA$4+4>=$J5),1,"") | AB5: =IF(AND(AB$4<=$K5,AB$4+4>=$J5),1,"") | AC5: =IF(AND(AC$4<=$K5,AC$4+4>=$J5),1,"") | AD5: =IF(AND(AD$4<=$K5,AD$4+4>=$J5),1,"") | AE5: =IF(AND(AE$4<=$K5,AE$4+4>=$J5),1,"") | AF5: =IF(AND(AF$4<=$K5,AF$4+4>=$J5),1,"") | AG5: =IF(AND(AG$4<=$K5,AG$4+4>=$J5),1,"") | ... AS5: =IF(AND(AS$4<=$K5,AS$4+4>=$J5),1,"")
A6: 2 | B6: Estrutural | C6: 1 – Mobilização e isolamento | D6: Pontos de acompanhamento fotográfico, relatório "antes da obra" e marcos de nível | E6: Registro-base para medição e comparação | F6: 1 | H6: 2 | J6: =IF(AND(F6="",G6=""),WORKDAY(DataBase-1,1,Feriados),WORKDAY(MAX(IFERROR(INDEX($K$5:$K$32,MATCH(F6,$A$5:$A$32,0)),0),IFERROR(INDEX($K$5:$K$32,MATCH(G6,$A$5:$A$32,0)),0)),1,Feriados)) -> 46322 | K6: =WORKDAY(J6,MAX(H6,1)-1,Feriados) -> 46323 | L6: =SUMIFS(ORCAMENTO!$G$5:$G$200,ORCAMENTO!$H$5:$H$200,A6) -> 4500 | M6: =IF(SUM($L$5:$L$32)=0,0,L6/SUM($L$5:$L$32)) -> 0.010279314 | N6: Não iniciado | R6: =IF(DataRef<J6,0,IF(DataRef>=K6,1,NETWORKDAYS(J6,DataRef,Feriados)/MAX(H6,1))) -> 0 | S6: =N(O6)-R6 -> 0 | T6: =IF(N6="Concluído","Concluída",IF(N6="Bloqueado","BLOQUEADA",IF(DataRef>K6,"ATRASADA",IF(AND(DataRef>=J6,N6="Não iniciado"),"INÍCIO ATRASADO","No prazo")))) -> No prazo | U6: =IF(RelSex<J6,0,IF(RelSex>=K6,1,NETWORKDAYS(J6,RelSex,Feriados)/MAX(H6,1))) -> 0 | V6: =IF(N6="Concluído",COUNTIF($N$5:N6,"Concluído"),"") | W6: =IF(N6="Em andamento",COUNTIF($N$5:N6,"Em andamento"),"") | X6: =IF(AND(N6<>"Concluído",J6<=RelSex+7,K6>RelSex),COUNTIFS($N$5:N6,"<>Concluído",$J$5:J6,"<="&(RelSex+7),$K$5:K6,">"&RelSex),"") -> 2 | Z6: =IF(AND(Z$4<=$K6,Z$4+4>=$J6),1,"") -> 1 | AA6: =IF(AND(AA$4<=$K6,AA$4+4>=$J6),1,"") | AB6: =IF(AND(AB$4<=$K6,AB$4+4>=$J6),1,"") | AC6: =IF(AND(AC$4<=$K6,AC$4+4>=$J6),1,"") | AD6: =IF(AND(AD$4<=$K6,AD$4+4>=$J6),1,"") | AE6: =IF(AND(AE$4<=$K6,AE$4+4>=$J6),1,"") | AF6: =IF(AND(AF$4<=$K6,AF$4+4>=$J6),1,"") | AG6: =IF(AND(AG$4<=$K6,AG$4+4>=$J6),1,"") | ... AS6: =IF(AND(AS$4<=$K6,AS$4+4>=$J6),1,"")
A7: 3 | B7: Estrutural | C7: 1 – Mobilização e isolamento | D7: Instalar divisória de fechamento da área | E7: Área isolada e sinalizada | F7: 1 | H7: 2 | J7: =IF(AND(F7="",G7=""),WORKDAY(DataBase-1,1,Feriados),WORKDAY(MAX(IFERROR(INDEX($K$5:$K$32,MATCH(F7,$A$5:$A$32,0)),0),IFERROR(INDEX($K$5:$K$32,MATCH(G7,$A$5:$A$32,0)),0)),1,Feriados)) -> 46322 | K7: =WORKDAY(J7,MAX(H7,1)-1,Feriados) -> 46323 | L7: =SUMIFS(ORCAMENTO!$G$5:$G$200,ORCAMENTO!$H$5:$H$200,A7) -> 17869.2 | M7: =IF(SUM($L$5:$L$32)=0,0,L7/SUM($L$5:$L$32)) -> 0.04081847 | N7: Não iniciado | R7: =IF(DataRef<J7,0,IF(DataRef>=K7,1,NETWORKDAYS(J7,DataRef,Feriados)/MAX(H7,1))) -> 0 | S7: =N(O7)-R7 -> 0 | T7: =IF(N7="Concluído","Concluída",IF(N7="Bloqueado","BLOQUEADA",IF(DataRef>K7,"ATRASADA",IF(AND(DataRef>=J7,N7="Não iniciado"),"INÍCIO ATRASADO","No prazo")))) -> No prazo | U7: =IF(RelSex<J7,0,IF(RelSex>=K7,1,NETWORKDAYS(J7,RelSex,Feriados)/MAX(H7,1))) -> 0 | V7: =IF(N7="Concluído",COUNTIF($N$5:N7,"Concluído"),"") | W7: =IF(N7="Em andamento",COUNTIF($N$5:N7,"Em andamento"),"") | X7: =IF(AND(N7<>"Concluído",J7<=RelSex+7,K7>RelSex),COUNTIFS($N$5:N7,"<>Concluído",$J$5:J7,"<="&(RelSex+7),$K$5:K7,">"&RelSex),"") -> 3 | Z7: =IF(AND(Z$4<=$K7,Z$4+4>=$J7),1,"") -> 1 | AA7: =IF(AND(AA$4<=$K7,AA$4+4>=$J7),1,"") | AB7: =IF(AND(AB$4<=$K7,AB$4+4>=$J7),1,"") | AC7: =IF(AND(AC$4<=$K7,AC$4+4>=$J7),1,"") | AD7: =IF(AND(AD$4<=$K7,AD$4+4>=$J7),1,"") | AE7: =IF(AND(AE$4<=$K7,AE$4+4>=$J7),1,"") | AF7: =IF(AND(AF$4<=$K7,AF$4+4>=$J7),1,"") | AG7: =IF(AND(AG$4<=$K7,AG$4+4>=$J7),1,"") | ... AS7: =IF(AND(AS$4<=$K7,AS$4+4>=$J7),1,"")
A8: 4 | B8: Estrutural | C8: 1 – Mobilização e isolamento | D8: Remover produtos, virar o balcão e mudar o mobiliário da área afetada | E8: Frente de trabalho livre | F8: 3 | H8: 3 | J8: =IF(AND(F8="",G8=""),WORKDAY(DataBase-1,1,Feriados),WORKDAY(MAX(IFERROR(INDEX($K$5:$K$32,MATCH(F8,$A$5:$A$32,0)),0),IFERROR(INDEX($K$5:$K$32,MATCH(G8,$A$5:$A$32,0)),0)),1,Feriados)) -> 46324 | K8: =WORKDAY(J8,MAX(H8,1)-1,Feriados) -> 46329 | L8: =SUMIFS(ORCAMENTO!$G$5:$G$200,ORCAMENTO!$H$5:$H$200,A8) -> 5851 | M8: =IF(SUM($L$5:$L$32)=0,0,L8/SUM($L$5:$L$32)) -> 0.013365392 | N8: Não iniciado | R8: =IF(DataRef<J8,0,IF(DataRef>=K8,1,NETWORKDAYS(J8,DataRef,Feriados)/MAX(H8,1))) -> 0 | S8: =N(O8)-R8 -> 0 | T8: =IF(N8="Concluído","Concluída",IF(N8="Bloqueado","BLOQUEADA",IF(DataRef>K8,"ATRASADA",IF(AND(DataRef>=J8,N8="Não iniciado"),"INÍCIO ATRASADO","No prazo")))) -> No prazo | U8: =IF(RelSex<J8,0,IF(RelSex>=K8,1,NETWORKDAYS(J8,RelSex,Feriados)/MAX(H8,1))) -> 0 | V8: =IF(N8="Concluído",COUNTIF($N$5:N8,"Concluído"),"") | W8: =IF(N8="Em andamento",COUNTIF($N$5:N8,"Em andamento"),"") | X8: =IF(AND(N8<>"Concluído",J8<=RelSex+7,K8>RelSex),COUNTIFS($N$5:N8,"<>Concluído",$J$5:J8,"<="&(RelSex+7),$K$5:K8,">"&RelSex),"") -> 4 | Z8: =IF(AND(Z$4<=$K8,Z$4+4>=$J8),1,"") -> 1 | AA8: =IF(AND(AA$4<=$K8,AA$4+4>=$J8),1,"") -> 1 | AB8: =IF(AND(AB$4<=$K8,AB$4+4>=$J8),1,"") | AC8: =IF(AND(AC$4<=$K8,AC$4+4>=$J8),1,"") | AD8: =IF(AND(AD$4<=$K8,AD$4+4>=$J8),1,"") | AE8: =IF(AND(AE$4<=$K8,AE$4+4>=$J8),1,"") | AF8: =IF(AND(AF$4<=$K8,AF$4+4>=$J8),1,"") | AG8: =IF(AND(AG$4<=$K8,AG$4+4>=$J8),1,"") | ... AS8: =IF(AND(AS$4<=$K8,AS$4+4>=$J8),1,"")
A9: 5 | B9: Estrutural | C9: 1 – Mobilização e isolamento | D9: Aliviar a carga do mezanino (retirar estoque do depósito) | E9: Mezanino descarregado | F9: 3 | H9: 1 | J9: =IF(AND(F9="",G9=""),WORKDAY(DataBase-1,1,Feriados),WORKDAY(MAX(IFERROR(INDEX($K$5:$K$32,MATCH(F9,$A$5:$A$32,0)),0),IFERROR(INDEX($K$5:$K$32,MATCH(G9,$A$5:$A$32,0)),0)),1,Feriados)) -> 46324 | K9: =WORKDAY(J9,MAX(H9,1)-1,Feriados) -> 46324 | L9: =SUMIFS(ORCAMENTO!$G$5:$G$200,ORCAMENTO!$H$5:$H$200,A9) -> 0 | M9: =IF(SUM($L$5:$L$32)=0,0,L9/SUM($L$5:$L$32)) -> 0 | N9: Não iniciado | R9: =IF(DataRef<J9,0,IF(DataRef>=K9,1,NETWORKDAYS(J9,DataRef,Feriados)/MAX(H9,1))) -> 0 | S9: =N(O9)-R9 -> 0 | T9: =IF(N9="Concluído","Concluída",IF(N9="Bloqueado","BLOQUEADA",IF(DataRef>K9,"ATRASADA",IF(AND(DataRef>=J9,N9="Não iniciado"),"INÍCIO ATRASADO","No prazo")))) -> No prazo | U9: =IF(RelSex<J9,0,IF(RelSex>=K9,1,NETWORKDAYS(J9,RelSex,Feriados)/MAX(H9,1))) -> 0 | V9: =IF(N9="Concluído",COUNTIF($N$5:N9,"Concluído"),"") | W9: =IF(N9="Em andamento",COUNTIF($N$5:N9,"Em andamento"),"") | X9: =IF(AND(N9<>"Concluído",J9<=RelSex+7,K9>RelSex),COUNTIFS($N$5:N9,"<>Concluído",$J$5:J9,"<="&(RelSex+7),$K$5:K9,">"&RelSex),"") -> 5 | Z9: =IF(AND(Z$4<=$K9,Z$4+4>=$J9),1,"") -> 1 | AA9: =IF(AND(AA$4<=$K9,AA$4+4>=$J9),1,"") | AB9: =IF(AND(AB$4<=$K9,AB$4+4>=$J9),1,"") | AC9: =IF(AND(AC$4<=$K9,AC$4+4>=$J9),1,"") | AD9: =IF(AND(AD$4<=$K9,AD$4+4>=$J9),1,"") | AE9: =IF(AND(AE$4<=$K9,AE$4+4>=$J9),1,"") | AF9: =IF(AND(AF$4<=$K9,AF$4+4>=$J9),1,"") | AG9: =IF(AND(AG$4<=$K9,AG$4+4>=$J9),1,"") | ... AS9: =IF(AND(AS$4<=$K9,AS$4+4>=$J9),1,"")
A10: 6 | B10: Estrutural | C10: 2 – Estabilização | D10: Escoramento provisório sob a treliça (P2/P3 e vão P3–P4); macaco só para encunhar | E10: PARCIAL – falta a viga principal. Libera demolições. Manter até o nº 15 | F10: 5 | H10: 3 | J10: =IF(AND(F10="",G10=""),WORKDAY(DataBase-1,1,Feriados),WORKDAY(MAX(IFERROR(INDEX($K$5:$K$32,MATCH(F10,$A$5:$A$32,0)),0),IFERROR(INDEX($K$5:$K$32,MATCH(G10,$A$5:$A$32,0)),0)),1,Feriados)) -> 46325 | K10: =WORKDAY(J10,MAX(H10,1)-1,Feriados) -> 46330 | L10: =SUMIFS(ORCAMENTO!$G$5:$G$200,ORCAMENTO!$H$5:$H$200,A10) -> 15200 | M10: =IF(SUM($L$5:$L$32)=0,0,L10/SUM($L$5:$L$32)) -> 0.034721238 | N10: Em andamento | R10: =IF(DataRef<J10,0,IF(DataRef>=K10,1,NETWORKDAYS(J10,DataRef,Feriados)/MAX(H10,1))) -> 0 | S10: =N(O10)-R10 -> 0 | T10: =IF(N10="Concluído","Concluída",IF(N10="Bloqueado","BLOQUEADA",IF(DataRef>K10,"ATRASADA",IF(AND(DataRef>=J10,N10="Não iniciado"),"INÍCIO ATRASADO","No prazo")))) -> No prazo | U10: =IF(RelSex<J10,0,IF(RelSex>=K10,1,NETWORKDAYS(J10,RelSex,Feriados)/MAX(H10,1))) -> 0 | V10: =IF(N10="Concluído",COUNTIF($N$5:N10,"Concluído"),"") | W10: =IF(N10="Em andamento",COUNTIF($N$5:N10,"Em andamento"),"") -> 1 | X10: =IF(AND(N10<>"Concluído",J10<=RelSex+7,K10>RelSex),COUNTIFS($N$5:N10,"<>Concluído",$J$5:J10,"<="&(RelSex+7),$K$5:K10,">"&RelSex),"") -> 6 | Z10: =IF(AND(Z$4<=$K10,Z$4+4>=$J10),1,"") -> 1 | AA10: =IF(AND(AA$4<=$K10,AA$4+4>=$J10),1,"") -> 1 | AB10: =IF(AND(AB$4<=$K10,AB$4+4>=$J10),1,"") | AC10: =IF(AND(AC$4<=$K10,AC$4+4>=$J10),1,"") | AD10: =IF(AND(AD$4<=$K10,AD$4+4>=$J10),1,"") | AE10: =IF(AND(AE$4<=$K10,AE$4+4>=$J10),1,"") | AF10: =IF(AND(AF$4<=$K10,AF$4+4>=$J10),1,"") | AG10: =IF(AND(AG$4<=$K10,AG$4+4>=$J10),1,"") | ... AS10: =IF(AND(AS$4<=$K10,AS$4+4>=$J10),1,"")
A11: 7 | B11: Estrutural | C11: 3 – Investigação e projeto | D11: Levantamento topográfico de níveis e medição dos m² da faixa afetada | E11: Croqui com m² e cotas | F11: 6 | H11: 2 | J11: =IF(AND(F11="",G11=""),WORKDAY(DataBase-1,1,Feriados),WORKDAY(MAX(IFERROR(INDEX($K$5:$K$32,MATCH(F11,$A$5:$A$32,0)),0),IFERROR(INDEX($K$5:$K$32,MATCH(G11,$A$5:$A$32,0)),0)),1,Feriados)) -> 46331 | K11: =WORKDAY(J11,MAX(H11,1)-1,Feriados) -> 46332 | L11: =SUMIFS(ORCAMENTO!$G$5:$G$200,ORCAMENTO!$H$5:$H$200,A11) -> 11500 | M11: =IF(SUM($L$5:$L$32)=0,0,L11/SUM($L$5:$L$32)) -> 0.026269358 | N11: Não iniciado | R11: =IF(DataRef<J11,0,IF(DataRef>=K11,1,NETWORKDAYS(J11,DataRef,Feriados)/MAX(H11,1))) -> 0 | S11: =N(O11)-R11 -> 0 | T11: =IF(N11="Concluído","Concluída",IF(N11="Bloqueado","BLOQUEADA",IF(DataRef>K11,"ATRASADA",IF(AND(DataRef>=J11,N11="Não iniciado"),"INÍCIO ATRASADO","No prazo")))) -> No prazo | U11: =IF(RelSex<J11,0,IF(RelSex>=K11,1,NETWORKDAYS(J11,RelSex,Feriados)/MAX(H11,1))) -> 0 | V11: =IF(N11="Concluído",COUNTIF($N$5:N11,"Concluído"),"") | W11: =IF(N11="Em andamento",COUNTIF($N$5:N11,"Em andamento"),"") | X11: =IF(AND(N11<>"Concluído",J11<=RelSex+7,K11>RelSex),COUNTIFS($N$5:N11,"<>Concluído",$J$5:J11,"<="&(RelSex+7),$K$5:K11,">"&RelSex),"") | Z11: =IF(AND(Z$4<=$K11,Z$4+4>=$J11),1,"") | AA11: =IF(AND(AA$4<=$K11,AA$4+4>=$J11),1,"") -> 1 | AB11: =IF(AND(AB$4<=$K11,AB$4+4>=$J11),1,"") | AC11: =IF(AND(AC$4<=$K11,AC$4+4>=$J11),1,"") | AD11: =IF(AND(AD$4<=$K11,AD$4+4>=$J11),1,"") | AE11: =IF(AND(AE$4<=$K11,AE$4+4>=$J11),1,"") | AF11: =IF(AND(AF$4<=$K11,AF$4+4>=$J11),1,"") | AG11: =IF(AND(AG$4<=$K11,AG$4+4>=$J11),1,"") | ... AS11: =IF(AND(AS$4<=$K11,AS$4+4>=$J11),1,"")
A12: 8 | B12: Estrutural | C12: 3 – Investigação e projeto | D12: Estudo de solo: SPT e poço de inspeção com abertura localizada do piso | E12: Laudo de sondagem | F12: 6 | H12: 5 | J12: =IF(AND(F12="",G12=""),WORKDAY(DataBase-1,1,Feriados),WORKDAY(MAX(IFERROR(INDEX($K$5:$K$32,MATCH(F12,$A$5:$A$32,0)),0),IFERROR(INDEX($K$5:$K$32,MATCH(G12,$A$5:$A$32,0)),0)),1,Feriados)) -> 46331 | K12: =WORKDAY(J12,MAX(H12,1)-1,Feriados) -> 46337 | L12: =SUMIFS(ORCAMENTO!$G$5:$G$200,ORCAMENTO!$H$5:$H$200,A12) -> 38000 | M12: =IF(SUM($L$5:$L$32)=0,0,L12/SUM($L$5:$L$32)) -> 0.086803095 | N12: Não iniciado | R12: =IF(DataRef<J12,0,IF(DataRef>=K12,1,NETWORKDAYS(J12,DataRef,Feriados)/MAX(H12,1))) -> 0 | S12: =N(O12)-R12 -> 0 | T12: =IF(N12="Concluído","Concluída",IF(N12="Bloqueado","BLOQUEADA",IF(DataRef>K12,"ATRASADA",IF(AND(DataRef>=J12,N12="Não iniciado"),"INÍCIO ATRASADO","No prazo")))) -> No prazo | U12: =IF(RelSex<J12,0,IF(RelSex>=K12,1,NETWORKDAYS(J12,RelSex,Feriados)/MAX(H12,1))) -> 0 | V12: =IF(N12="Concluído",COUNTIF($N$5:N12,"Concluído"),"") | W12: =IF(N12="Em andamento",COUNTIF($N$5:N12,"Em andamento"),"") | X12: =IF(AND(N12<>"Concluído",J12<=RelSex+7,K12>RelSex),COUNTIFS($N$5:N12,"<>Concluído",$J$5:J12,"<="&(RelSex+7),$K$5:K12,">"&RelSex),"") | Z12: =IF(AND(Z$4<=$K12,Z$4+4>=$J12),1,"") | AA12: =IF(AND(AA$4<=$K12,AA$4+4>=$J12),1,"") -> 1 | AB12: =IF(AND(AB$4<=$K12,AB$4+4>=$J12),1,"") -> 1 | AC12: =IF(AND(AC$4<=$K12,AC$4+4>=$J12),1,"") | AD12: =IF(AND(AD$4<=$K12,AD$4+4>=$J12),1,"") | AE12: =IF(AND(AE$4<=$K12,AE$4+4>=$J12),1,"") | AF12: =IF(AND(AF$4<=$K12,AF$4+4>=$J12),1,"") | AG12: =IF(AND(AG$4<=$K12,AG$4+4>=$J12),1,"") | ... AS12: =IF(AND(AS$4<=$K12,AS$4+4>=$J12),1,"")
A13: 9 | B13: Estrutural | C13: 3 – Investigação e projeto | D13: Projeto estrutural de reforço (treliça, apoios e fundações) + ART | E13: Projeto executivo aprovado | F13: 8 | G13: 7 | H13: 10 | J13: =IF(AND(F13="",G13=""),WORKDAY(DataBase-1,1,Feriados),WORKDAY(MAX(IFERROR(INDEX($K$5:$K$32,MATCH(F13,$A$5:$A$32,0)),0),IFERROR(INDEX($K$5:$K$32,MATCH(G13,$A$5:$A$32,0)),0)),1,Feriados)) -> 46338 | K13: =WORKDAY(J13,MAX(H13,1)-1,Feriados) -> 46352 | L13: =SUMIFS(ORCAMENTO!$G$5:$G$200,ORCAMENTO!$H$5:$H$200,A13) -> 16293.44 | M13: =IF(SUM($L$5:$L$32)=0,0,L13/SUM($L$5:$L$32)) -> 0.037218974 | N13: Não iniciado | R13: =IF(DataRef<J13,0,IF(DataRef>=K13,1,NETWORKDAYS(J13,DataRef,Feriados)/MAX(H13,1))) -> 0 | S13: =N(O13)-R13 -> 0 | T13: =IF(N13="Concluído","Concluída",IF(N13="Bloqueado","BLOQUEADA",IF(DataRef>K13,"ATRASADA",IF(AND(DataRef>=J13,N13="Não iniciado"),"INÍCIO ATRASADO","No prazo")))) -> No prazo | U13: =IF(RelSex<J13,0,IF(RelSex>=K13,1,NETWORKDAYS(J13,RelSex,Feriados)/MAX(H13,1))) -> 0 | V13: =IF(N13="Concluído",COUNTIF($N$5:N13,"Concluído"),"") | W13: =IF(N13="Em andamento",COUNTIF($N$5:N13,"Em andamento"),"") | X13: =IF(AND(N13<>"Concluído",J13<=RelSex+7,K13>RelSex),COUNTIFS($N$5:N13,"<>Concluído",$J$5:J13,"<="&(RelSex+7),$K$5:K13,">"&RelSex),"") | Z13: =IF(AND(Z$4<=$K13,Z$4+4>=$J13),1,"") | AA13: =IF(AND(AA$4<=$K13,AA$4+4>=$J13),1,"") | AB13: =IF(AND(AB$4<=$K13,AB$4+4>=$J13),1,"") -> 1 | AC13: =IF(AND(AC$4<=$K13,AC$4+4>=$J13),1,"") -> 1 | AD13: =IF(AND(AD$4<=$K13,AD$4+4>=$J13),1,"") -> 1 | AE13: =IF(AND(AE$4<=$K13,AE$4+4>=$J13),1,"") | AF13: =IF(AND(AF$4<=$K13,AF$4+4>=$J13),1,"") | AG13: =IF(AND(AG$4<=$K13,AG$4+4>=$J13),1,"") | ... AS13: =IF(AND(AS$4<=$K13,AS$4+4>=$J13),1,"")
A14: 10 | B14: Estrutural | C14: 3 – Investigação e projeto | D14: Fechar quantitativos e revisar o orçamento da Fase 2 | E14: Escopo e valor aprovados pela DPSP | F14: 9 | H14: 5 | J14: =IF(AND(F14="",G14=""),WORKDAY(DataBase-1,1,Feriados),WORKDAY(MAX(IFERROR(INDEX($K$5:$K$32,MATCH(F14,$A$5:$A$32,0)),0),IFERROR(INDEX($K$5:$K$32,MATCH(G14,$A$5:$A$32,0)),0)),1,Feriados)) -> 46353 | K14: =WORKDAY(J14,MAX(H14,1)-1,Feriados) -> 46359 | L14: =SUMIFS(ORCAMENTO!$G$5:$G$200,ORCAMENTO!$H$5:$H$200,A14) -> 0 | M14: =IF(SUM($L$5:$L$32)=0,0,L14/SUM($L$5:$L$32)) -> 0 | N14: Não iniciado | R14: =IF(DataRef<J14,0,IF(DataRef>=K14,1,NETWORKDAYS(J14,DataRef,Feriados)/MAX(H14,1))) -> 0 | S14: =N(O14)-R14 -> 0 | T14: =IF(N14="Concluído","Concluída",IF(N14="Bloqueado","BLOQUEADA",IF(DataRef>K14,"ATRASADA",IF(AND(DataRef>=J14,N14="Não iniciado"),"INÍCIO ATRASADO","No prazo")))) -> No prazo | U14: =IF(RelSex<J14,0,IF(RelSex>=K14,1,NETWORKDAYS(J14,RelSex,Feriados)/MAX(H14,1))) -> 0 | V14: =IF(N14="Concluído",COUNTIF($N$5:N14,"Concluído"),"") | W14: =IF(N14="Em andamento",COUNTIF($N$5:N14,"Em andamento"),"") | X14: =IF(AND(N14<>"Concluído",J14<=RelSex+7,K14>RelSex),COUNTIFS($N$5:N14,"<>Concluído",$J$5:J14,"<="&(RelSex+7),$K$5:K14,">"&RelSex),"") | Z14: =IF(AND(Z$4<=$K14,Z$4+4>=$J14),1,"") | AA14: =IF(AND(AA$4<=$K14,AA$4+4>=$J14),1,"") | AB14: =IF(AND(AB$4<=$K14,AB$4+4>=$J14),1,"") | AC14: =IF(AND(AC$4<=$K14,AC$4+4>=$J14),1,"") | AD14: =IF(AND(AD$4<=$K14,AD$4+4>=$J14),1,"") -> 1 | AE14: =IF(AND(AE$4<=$K14,AE$4+4>=$J14),1,"") -> 1 | AF14: =IF(AND(AF$4<=$K14,AF$4+4>=$J14),1,"") | AG14: =IF(AND(AG$4<=$K14,AG$4+4>=$J14),1,"") | ... AS14: =IF(AND(AS$4<=$K14,AS$4+4>=$J14),1,"")
A15: 11 | B15: Estrutural | C15: 4 – Desmobilização e demolição | D15: Abertura de porta com retirada de vidro (logística de entulho e materiais) | E15: Acesso liberado | F15: 10 | H15: 1 | J15: =IF(AND(F15="",G15=""),WORKDAY(DataBase-1,1,Feriados),WORKDAY(MAX(IFERROR(INDEX($K$5:$K$32,MATCH(F15,$A$5:$A$32,0)),0),IFERROR(INDEX($K$5:$K$32,MATCH(G15,$A$5:$A$32,0)),0)),1,Feriados)) -> 46360 | K15: =WORKDAY(J15,MAX(H15,1)-1,Feriados) -> 46360 | L15: =SUMIFS(ORCAMENTO!$G$5:$G$200,ORCAMENTO!$H$5:$H$200,A15) -> 2100 | M15: =IF(SUM($L$5:$L$32)=0,0,L15/SUM($L$5:$L$32)) -> 0.0047970131 | N15: Não iniciado | R15: =IF(DataRef<J15,0,IF(DataRef>=K15,1,NETWORKDAYS(J15,DataRef,Feriados)/MAX(H15,1))) -> 0 | S15: =N(O15)-R15 -> 0 | T15: =IF(N15="Concluído","Concluída",IF(N15="Bloqueado","BLOQUEADA",IF(DataRef>K15,"ATRASADA",IF(AND(DataRef>=J15,N15="Não iniciado"),"INÍCIO ATRASADO","No prazo")))) -> No prazo | U15: =IF(RelSex<J15,0,IF(RelSex>=K15,1,NETWORKDAYS(J15,RelSex,Feriados)/MAX(H15,1))) -> 0 | V15: =IF(N15="Concluído",COUNTIF($N$5:N15,"Concluído"),"") | W15: =IF(N15="Em andamento",COUNTIF($N$5:N15,"Em andamento"),"") | X15: =IF(AND(N15<>"Concluído",J15<=RelSex+7,K15>RelSex),COUNTIFS($N$5:N15,"<>Concluído",$J$5:J15,"<="&(RelSex+7),$K$5:K15,">"&RelSex),"") | Z15: =IF(AND(Z$4<=$K15,Z$4+4>=$J15),1,"") | AA15: =IF(AND(AA$4<=$K15,AA$4+4>=$J15),1,"") | AB15: =IF(AND(AB$4<=$K15,AB$4+4>=$J15),1,"") | AC15: =IF(AND(AC$4<=$K15,AC$4+4>=$J15),1,"") | AD15: =IF(AND(AD$4<=$K15,AD$4+4>=$J15),1,"") | AE15: =IF(AND(AE$4<=$K15,AE$4+4>=$J15),1,"") -> 1 | AF15: =IF(AND(AF$4<=$K15,AF$4+4>=$J15),1,"") | AG15: =IF(AND(AG$4<=$K15,AG$4+4>=$J15),1,"") | ... AS15: =IF(AND(AS$4<=$K15,AS$4+4>=$J15),1,"")
A16: 12 | B16: Estrutural | C16: 4 – Desmobilização e demolição | D16: Descarte de gôndolas e geladeira | E16: Termo de baixa de patrimônio DPSP | F16: 10 | H16: 2 | J16: =IF(AND(F16="",G16=""),WORKDAY(DataBase-1,1,Feriados),WORKDAY(MAX(IFERROR(INDEX($K$5:$K$32,MATCH(F16,$A$5:$A$32,0)),0),IFERROR(INDEX($K$5:$K$32,MATCH(G16,$A$5:$A$32,0)),0)),1,Feriados)) -> 46360 | K16: =WORKDAY(J16,MAX(H16,1)-1,Feriados) -> 46363 | L16: =SUMIFS(ORCAMENTO!$G$5:$G$200,ORCAMENTO!$H$5:$H$200,A16) -> 1729 | M16: =IF(SUM($L$5:$L$32)=0,0,L16/SUM($L$5:$L$32)) -> 0.0039495408 | N16: Não iniciado | R16: =IF(DataRef<J16,0,IF(DataRef>=K16,1,NETWORKDAYS(J16,DataRef,Feriados)/MAX(H16,1))) -> 0 | S16: =N(O16)-R16 -> 0 | T16: =IF(N16="Concluído","Concluída",IF(N16="Bloqueado","BLOQUEADA",IF(DataRef>K16,"ATRASADA",IF(AND(DataRef>=J16,N16="Não iniciado"),"INÍCIO ATRASADO","No prazo")))) -> No prazo | U16: =IF(RelSex<J16,0,IF(RelSex>=K16,1,NETWORKDAYS(J16,RelSex,Feriados)/MAX(H16,1))) -> 0 | V16: =IF(N16="Concluído",COUNTIF($N$5:N16,"Concluído"),"") | W16: =IF(N16="Em andamento",COUNTIF($N$5:N16,"Em andamento"),"") | X16: =IF(AND(N16<>"Concluído",J16<=RelSex+7,K16>RelSex),COUNTIFS($N$5:N16,"<>Concluído",$J$5:J16,"<="&(RelSex+7),$K$5:K16,">"&RelSex),"") | Z16: =IF(AND(Z$4<=$K16,Z$4+4>=$J16),1,"") | AA16: =IF(AND(AA$4<=$K16,AA$4+4>=$J16),1,"") | AB16: =IF(AND(AB$4<=$K16,AB$4+4>=$J16),1,"") | AC16: =IF(AND(AC$4<=$K16,AC$4+4>=$J16),1,"") | AD16: =IF(AND(AD$4<=$K16,AD$4+4>=$J16),1,"") | AE16: =IF(AND(AE$4<=$K16,AE$4+4>=$J16),1,"") -> 1 | AF16: =IF(AND(AF$4<=$K16,AF$4+4>=$J16),1,"") -> 1 | AG16: =IF(AND(AG$4<=$K16,AG$4+4>=$J16),1,"") | ... AS16: =IF(AND(AS$4<=$K16,AS$4+4>=$J16),1,"")
A17: 13 | B17: Estrutural | C17: 4 – Desmobilização e demolição | D17: Desmobilização do banheiro | E17: Banheiro liberado para obra | F17: 10 | H17: 2 | J17: =IF(AND(F17="",G17=""),WORKDAY(DataBase-1,1,Feriados),WORKDAY(MAX(IFERROR(INDEX($K$5:$K$32,MATCH(F17,$A$5:$A$32,0)),0),IFERROR(INDEX($K$5:$K$32,MATCH(G17,$A$5:$A$32,0)),0)),1,Feriados)) -> 46360 | K17: =WORKDAY(J17,MAX(H17,1)-1,Feriados) -> 46363 | L17: =SUMIFS(ORCAMENTO!$G$5:$G$200,ORCAMENTO!$H$5:$H$200,A17) -> 438.68 | M17: =IF(SUM($L$5:$L$32)=0,0,L17/SUM($L$5:$L$32)) -> 0.0010020732 | N17: Não iniciado | R17: =IF(DataRef<J17,0,IF(DataRef>=K17,1,NETWORKDAYS(J17,DataRef,Feriados)/MAX(H17,1))) -> 0 | S17: =N(O17)-R17 -> 0 | T17: =IF(N17="Concluído","Concluída",IF(N17="Bloqueado","BLOQUEADA",IF(DataRef>K17,"ATRASADA",IF(AND(DataRef>=J17,N17="Não iniciado"),"INÍCIO ATRASADO","No prazo")))) -> No prazo | U17: =IF(RelSex<J17,0,IF(RelSex>=K17,1,NETWORKDAYS(J17,RelSex,Feriados)/MAX(H17,1))) -> 0 | V17: =IF(N17="Concluído",COUNTIF($N$5:N17,"Concluído"),"") | W17: =IF(N17="Em andamento",COUNTIF($N$5:N17,"Em andamento"),"") | X17: =IF(AND(N17<>"Concluído",J17<=RelSex+7,K17>RelSex),COUNTIFS($N$5:N17,"<>Concluído",$J$5:J17,"<="&(RelSex+7),$K$5:K17,">"&RelSex),"") | Z17: =IF(AND(Z$4<=$K17,Z$4+4>=$J17),1,"") | AA17: =IF(AND(AA$4<=$K17,AA$4+4>=$J17),1,"") | AB17: =IF(AND(AB$4<=$K17,AB$4+4>=$J17),1,"") | AC17: =IF(AND(AC$4<=$K17,AC$4+4>=$J17),1,"") | AD17: =IF(AND(AD$4<=$K17,AD$4+4>=$J17),1,"") | AE17: =IF(AND(AE$4<=$K17,AE$4+4>=$J17),1,"") -> 1 | AF17: =IF(AND(AF$4<=$K17,AF$4+4>=$J17),1,"") -> 1 | AG17: =IF(AND(AG$4<=$K17,AG$4+4>=$J17),1,"") | ... AS17: =IF(AND(AS$4<=$K17,AS$4+4>=$J17),1,"")
A18: 14 | B18: Estrutural | C18: 4 – Desmobilização e demolição | D18: Demolição do piso (revestimento, contrapiso e laje) + descarte com CTR | E18: Solo exposto na área delimitada | F18: 12 | G18: 13 | H18: 5 | J18: =IF(AND(F18="",G18=""),WORKDAY(DataBase-1,1,Feriados),WORKDAY(MAX(IFERROR(INDEX($K$5:$K$32,MATCH(F18,$A$5:$A$32,0)),0),IFERROR(INDEX($K$5:$K$32,MATCH(G18,$A$5:$A$32,0)),0)),1,Feriados)) -> 46364 | K18: =WORKDAY(J18,MAX(H18,1)-1,Feriados) -> 46370 | L18: =SUMIFS(ORCAMENTO!$G$5:$G$200,ORCAMENTO!$H$5:$H$200,A18) -> 23415.86 | M18: =IF(SUM($L$5:$L$32)=0,0,L18/SUM($L$5:$L$32)) -> 0.053488661 | N18: Não iniciado | R18: =IF(DataRef<J18,0,IF(DataRef>=K18,1,NETWORKDAYS(J18,DataRef,Feriados)/MAX(H18,1))) -> 0 | S18: =N(O18)-R18 -> 0 | T18: =IF(N18="Concluído","Concluída",IF(N18="Bloqueado","BLOQUEADA",IF(DataRef>K18,"ATRASADA",IF(AND(DataRef>=J18,N18="Não iniciado"),"INÍCIO ATRASADO","No prazo")))) -> No prazo | U18: =IF(RelSex<J18,0,IF(RelSex>=K18,1,NETWORKDAYS(J18,RelSex,Feriados)/MAX(H18,1))) -> 0 | V18: =IF(N18="Concluído",COUNTIF($N$5:N18,"Concluído"),"") | W18: =IF(N18="Em andamento",COUNTIF($N$5:N18,"Em andamento"),"") | X18: =IF(AND(N18<>"Concluído",J18<=RelSex+7,K18>RelSex),COUNTIFS($N$5:N18,"<>Concluído",$J$5:J18,"<="&(RelSex+7),$K$5:K18,">"&RelSex),"") | Z18: =IF(AND(Z$4<=$K18,Z$4+4>=$J18),1,"") | AA18: =IF(AND(AA$4<=$K18,AA$4+4>=$J18),1,"") | AB18: =IF(AND(AB$4<=$K18,AB$4+4>=$J18),1,"") | AC18: =IF(AND(AC$4<=$K18,AC$4+4>=$J18),1,"") | AD18: =IF(AND(AD$4<=$K18,AD$4+4>=$J18),1,"") | AE18: =IF(AND(AE$4<=$K18,AE$4+4>=$J18),1,"") | AF18: =IF(AND(AF$4<=$K18,AF$4+4>=$J18),1,"") -> 1 | AG18: =IF(AND(AG$4<=$K18,AG$4+4>=$J18),1,"") -> 1 | ... AS18: =IF(AND(AS$4<=$K18,AS$4+4>=$J18),1,"")
A19: 15 | B19: Estrutural | C19: 5 – Reforço e reconstrução | D19: Reforço das fundações de P2/P3 e da treliça, conforme projeto | E19: Estrutura reforçada e conferida pelo RT | F19: 14 | H19: 10 | J19: =IF(AND(F19="",G19=""),WORKDAY(DataBase-1,1,Feriados),WORKDAY(MAX(IFERROR(INDEX($K$5:$K$32,MATCH(F19,$A$5:$A$32,0)),0),IFERROR(INDEX($K$5:$K$32,MATCH(G19,$A$5:$A$32,0)),0)),1,Feriados)) -> 46371 | K19: =WORKDAY(J19,MAX(H19,1)-1,Feriados) -> 46385 | L19: =SUMIFS(ORCAMENTO!$G$5:$G$200,ORCAMENTO!$H$5:$H$200,A19) -> 49000 | M19: =IF(SUM($L$5:$L$32)=0,0,L19/SUM($L$5:$L$32)) -> 0.11193031 | N19: Não iniciado | R19: =IF(DataRef<J19,0,IF(DataRef>=K19,1,NETWORKDAYS(J19,DataRef,Feriados)/MAX(H19,1))) -> 0 | S19: =N(O19)-R19 -> 0 | T19: =IF(N19="Concluído","Concluída",IF(N19="Bloqueado","BLOQUEADA",IF(DataRef>K19,"ATRASADA",IF(AND(DataRef>=J19,N19="Não iniciado"),"INÍCIO ATRASADO","No prazo")))) -> No prazo | U19: =IF(RelSex<J19,0,IF(RelSex>=K19,1,NETWORKDAYS(J19,RelSex,Feriados)/MAX(H19,1))) -> 0 | V19: =IF(N19="Concluído",COUNTIF($N$5:N19,"Concluído"),"") | W19: =IF(N19="Em andamento",COUNTIF($N$5:N19,"Em andamento"),"") | X19: =IF(AND(N19<>"Concluído",J19<=RelSex+7,K19>RelSex),COUNTIFS($N$5:N19,"<>Concluído",$J$5:J19,"<="&(RelSex+7),$K$5:K19,">"&RelSex),"") | Z19: =IF(AND(Z$4<=$K19,Z$4+4>=$J19),1,"") | AA19: =IF(AND(AA$4<=$K19,AA$4+4>=$J19),1,"") | AB19: =IF(AND(AB$4<=$K19,AB$4+4>=$J19),1,"") | AC19: =IF(AND(AC$4<=$K19,AC$4+4>=$J19),1,"") | AD19: =IF(AND(AD$4<=$K19,AD$4+4>=$J19),1,"") | AE19: =IF(AND(AE$4<=$K19,AE$4+4>=$J19),1,"") | AF19: =IF(AND(AF$4<=$K19,AF$4+4>=$J19),1,"") | AG19: =IF(AND(AG$4<=$K19,AG$4+4>=$J19),1,"") -> 1 | ... AS19: =IF(AND(AS$4<=$K19,AS$4+4>=$J19),1,"")
A20: 16 | B20: Estrutural | C20: 5 – Reforço e reconstrução | D20: Remoção do solo inadequado, base de brita e compactação em camadas (máx. 20 cm) | E20: Base aprovada | F20: 14 | H20: 5 | J20: =IF(AND(F20="",G20=""),WORKDAY(DataBase-1,1,Feriados),WORKDAY(MAX(IFERROR(INDEX($K$5:$K$32,MATCH(F20,$A$5:$A$32,0)),0),IFERROR(INDEX($K$5:$K$32,MATCH(G20,$A$5:$A$32,0)),0)),1,Feriados)) -> 46371 | K20: =WORKDAY(J20,MAX(H20,1)-1,Feriados) -> 46377 | L20: =SUMIFS(ORCAMENTO!$G$5:$G$200,ORCAMENTO!$H$5:$H$200,A20) -> 19500 | M20: =IF(SUM($L$5:$L$32)=0,0,L20/SUM($L$5:$L$32)) -> 0.044543693 | N20: Não iniciado | R20: =IF(DataRef<J20,0,IF(DataRef>=K20,1,NETWORKDAYS(J20,DataRef,Feriados)/MAX(H20,1))) -> 0 | S20: =N(O20)-R20 -> 0 | T20: =IF(N20="Concluído","Concluída",IF(N20="Bloqueado","BLOQUEADA",IF(DataRef>K20,"ATRASADA",IF(AND(DataRef>=J20,N20="Não iniciado"),"INÍCIO ATRASADO","No prazo")))) -> No prazo | U20: =IF(RelSex<J20,0,IF(RelSex>=K20,1,NETWORKDAYS(J20,RelSex,Feriados)/MAX(H20,1))) -> 0 | V20: =IF(N20="Concluído",COUNTIF($N$5:N20,"Concluído"),"") | W20: =IF(N20="Em andamento",COUNTIF($N$5:N20,"Em andamento"),"") | X20: =IF(AND(N20<>"Concluído",J20<=RelSex+7,K20>RelSex),COUNTIFS($N$5:N20,"<>Concluído",$J$5:J20,"<="&(RelSex+7),$K$5:K20,">"&RelSex),"") | Z20: =IF(AND(Z$4<=$K20,Z$4+4>=$J20),1,"") | AA20: =IF(AND(AA$4<=$K20,AA$4+4>=$J20),1,"") | AB20: =IF(AND(AB$4<=$K20,AB$4+4>=$J20),1,"") | AC20: =IF(AND(AC$4<=$K20,AC$4+4>=$J20),1,"") | AD20: =IF(AND(AD$4<=$K20,AD$4+4>=$J20),1,"") | AE20: =IF(AND(AE$4<=$K20,AE$4+4>=$J20),1,"") | AF20: =IF(AND(AF$4<=$K20,AF$4+4>=$J20),1,"") | AG20: =IF(AND(AG$4<=$K20,AG$4+4>=$J20),1,"") -> 1 | ... AS20: =IF(AND(AS$4<=$K20,AS$4+4>=$J20),1,"")
A21: 17 | B21: Estrutural | C21: 5 – Reforço e reconstrução | D21: Nova laje de piso armada com nível final (inclui cura) | E21: Laje curada e nivelada | F21: 16 | G21: 15 | H21: 10 | J21: =IF(AND(F21="",G21=""),WORKDAY(DataBase-1,1,Feriados),WORKDAY(MAX(IFERROR(INDEX($K$5:$K$32,MATCH(F21,$A$5:$A$32,0)),0),IFERROR(INDEX($K$5:$K$32,MATCH(G21,$A$5:$A$32,0)),0)),1,Feriados)) -> 46386 | K21: =WORKDAY(J21,MAX(H21,1)-1,Feriados) -> 46400 | L21: =SUMIFS(ORCAMENTO!$G$5:$G$200,ORCAMENTO!$H$5:$H$200,A21) -> 9426 | M21: =IF(SUM($L$5:$L$32)=0,0,L21/SUM($L$5:$L$32)) -> 0.021531736 | N21: Não iniciado | R21: =IF(DataRef<J21,0,IF(DataRef>=K21,1,NETWORKDAYS(J21,DataRef,Feriados)/MAX(H21,1))) -> 0 | S21: =N(O21)-R21 -> 0 | T21: =IF(N21="Concluído","Concluída",IF(N21="Bloqueado","BLOQUEADA",IF(DataRef>K21,"ATRASADA",IF(AND(DataRef>=J21,N21="Não iniciado"),"INÍCIO ATRASADO","No prazo")))) -> No prazo | U21: =IF(RelSex<J21,0,IF(RelSex>=K21,1,NETWORKDAYS(J21,RelSex,Feriados)/MAX(H21,1))) -> 0 | V21: =IF(N21="Concluído",COUNTIF($N$5:N21,"Concluído"),"") | W21: =IF(N21="Em andamento",COUNTIF($N$5:N21,"Em andamento"),"") | X21: =IF(AND(N21<>"Concluído",J21<=RelSex+7,K21>RelSex),COUNTIFS($N$5:N21,"<>Concluído",$J$5:J21,"<="&(RelSex+7),$K$5:K21,">"&RelSex),"") | Z21: =IF(AND(Z$4<=$K21,Z$4+4>=$J21),1,"") | AA21: =IF(AND(AA$4<=$K21,AA$4+4>=$J21),1,"") | AB21: =IF(AND(AB$4<=$K21,AB$4+4>=$J21),1,"") | AC21: =IF(AND(AC$4<=$K21,AC$4+4>=$J21),1,"") | AD21: =IF(AND(AD$4<=$K21,AD$4+4>=$J21),1,"") | AE21: =IF(AND(AE$4<=$K21,AE$4+4>=$J21),1,"") | AF21: =IF(AND(AF$4<=$K21,AF$4+4>=$J21),1,"") | AG21: =IF(AND(AG$4<=$K21,AG$4+4>=$J21),1,"") | ... AS21: =IF(AND(AS$4<=$K21,AS$4+4>=$J21),1,"")
A22: 18 | B22: Estrutural | C22: 5 – Reforço e reconstrução | D22: Piso do banheiro e revestimento do salão | E22: Piso entregue | F22: 17 | H22: 8 | J22: =IF(AND(F22="",G22=""),WORKDAY(DataBase-1,1,Feriados),WORKDAY(MAX(IFERROR(INDEX($K$5:$K$32,MATCH(F22,$A$5:$A$32,0)),0),IFERROR(INDEX($K$5:$K$32,MATCH(G22,$A$5:$A$32,0)),0)),1,Feriados)) -> 46401 | K22: =WORKDAY(J22,MAX(H22,1)-1,Feriados) -> 46412 | L22: =SUMIFS(ORCAMENTO!$G$5:$G$200,ORCAMENTO!$H$5:$H$200,A22) -> 28000 | M22: =IF(SUM($L$5:$L$32)=0,0,L22/SUM($L$5:$L$32)) -> 0.063960175 | N22: Não iniciado | R22: =IF(DataRef<J22,0,IF(DataRef>=K22,1,NETWORKDAYS(J22,DataRef,Feriados)/MAX(H22,1))) -> 0 | S22: =N(O22)-R22 -> 0 | T22: =IF(N22="Concluído","Concluída",IF(N22="Bloqueado","BLOQUEADA",IF(DataRef>K22,"ATRASADA",IF(AND(DataRef>=J22,N22="Não iniciado"),"INÍCIO ATRASADO","No prazo")))) -> No prazo | U22: =IF(RelSex<J22,0,IF(RelSex>=K22,1,NETWORKDAYS(J22,RelSex,Feriados)/MAX(H22,1))) -> 0 | V22: =IF(N22="Concluído",COUNTIF($N$5:N22,"Concluído"),"") | W22: =IF(N22="Em andamento",COUNTIF($N$5:N22,"Em andamento"),"") | X22: =IF(AND(N22<>"Concluído",J22<=RelSex+7,K22>RelSex),COUNTIFS($N$5:N22,"<>Concluído",$J$5:J22,"<="&(RelSex+7),$K$5:K22,">"&RelSex),"") | Z22: =IF(AND(Z$4<=$K22,Z$4+4>=$J22),1,"") | AA22: =IF(AND(AA$4<=$K22,AA$4+4>=$J22),1,"") | AB22: =IF(AND(AB$4<=$K22,AB$4+4>=$J22),1,"") | AC22: =IF(AND(AC$4<=$K22,AC$4+4>=$J22),1,"") | AD22: =IF(AND(AD$4<=$K22,AD$4+4>=$J22),1,"") | AE22: =IF(AND(AE$4<=$K22,AE$4+4>=$J22),1,"") | AF22: =IF(AND(AF$4<=$K22,AF$4+4>=$J22),1,"") | AG22: =IF(AND(AG$4<=$K22,AG$4+4>=$J22),1,"") | ... AS22: =IF(AND(AS$4<=$K22,AS$4+4>=$J22),1,"")
A23: 19 | B23: Estrutural | C23: 6 – Acabamentos e entrega | D23: Recuperação do mezanino: drywall, piso cerâmico, copa e WCs | E23: Mezanino recuperado | F23: 15 | H23: 8 | J23: =IF(AND(F23="",G23=""),WORKDAY(DataBase-1,1,Feriados),WORKDAY(MAX(IFERROR(INDEX($K$5:$K$32,MATCH(F23,$A$5:$A$32,0)),0),IFERROR(INDEX($K$5:$K$32,MATCH(G23,$A$5:$A$32,0)),0)),1,Feriados)) -> 46386 | K23: =WORKDAY(J23,MAX(H23,1)-1,Feriados) -> 46398 | L23: =SUMIFS(ORCAMENTO!$G$5:$G$200,ORCAMENTO!$H$5:$H$200,A23) -> 20000 | M23: =IF(SUM($L$5:$L$32)=0,0,L23/SUM($L$5:$L$32)) -> 0.045685839 | N23: Não iniciado | R23: =IF(DataRef<J23,0,IF(DataRef>=K23,1,NETWORKDAYS(J23,DataRef,Feriados)/MAX(H23,1))) -> 0 | S23: =N(O23)-R23 -> 0 | T23: =IF(N23="Concluído","Concluída",IF(N23="Bloqueado","BLOQUEADA",IF(DataRef>K23,"ATRASADA",IF(AND(DataRef>=J23,N23="Não iniciado"),"INÍCIO ATRASADO","No prazo")))) -> No prazo | U23: =IF(RelSex<J23,0,IF(RelSex>=K23,1,NETWORKDAYS(J23,RelSex,Feriados)/MAX(H23,1))) -> 0 | V23: =IF(N23="Concluído",COUNTIF($N$5:N23,"Concluído"),"") | W23: =IF(N23="Em andamento",COUNTIF($N$5:N23,"Em andamento"),"") | X23: =IF(AND(N23<>"Concluído",J23<=RelSex+7,K23>RelSex),COUNTIFS($N$5:N23,"<>Concluído",$J$5:J23,"<="&(RelSex+7),$K$5:K23,">"&RelSex),"") | Z23: =IF(AND(Z$4<=$K23,Z$4+4>=$J23),1,"") | AA23: =IF(AND(AA$4<=$K23,AA$4+4>=$J23),1,"") | AB23: =IF(AND(AB$4<=$K23,AB$4+4>=$J23),1,"") | AC23: =IF(AND(AC$4<=$K23,AC$4+4>=$J23),1,"") | AD23: =IF(AND(AD$4<=$K23,AD$4+4>=$J23),1,"") | AE23: =IF(AND(AE$4<=$K23,AE$4+4>=$J23),1,"") | AF23: =IF(AND(AF$4<=$K23,AF$4+4>=$J23),1,"") | AG23: =IF(AND(AG$4<=$K23,AG$4+4>=$J23),1,"") | ... AS23: =IF(AND(AS$4<=$K23,AS$4+4>=$J23),1,"")
A24: 20 | B24: Estrutural | C24: 6 – Acabamentos e entrega | D24: Retirada do escoramento, conferência final de níveis, limpeza e liberação | E24: Loja liberada; relatório "depois" | F24: 18 | G24: 27 | H24: 3 | J24: =IF(AND(F24="",G24=""),WORKDAY(DataBase-1,1,Feriados),WORKDAY(MAX(IFERROR(INDEX($K$5:$K$32,MATCH(F24,$A$5:$A$32,0)),0),IFERROR(INDEX($K$5:$K$32,MATCH(G24,$A$5:$A$32,0)),0)),1,Feriados)) -> 46413 | K24: =WORKDAY(J24,MAX(H24,1)-1,Feriados) -> 46415 | L24: =SUMIFS(ORCAMENTO!$G$5:$G$200,ORCAMENTO!$H$5:$H$200,A24) -> 13656 | M24: =IF(SUM($L$5:$L$32)=0,0,L24/SUM($L$5:$L$32)) -> 0.031194291 | N24: Não iniciado | R24: =IF(DataRef<J24,0,IF(DataRef>=K24,1,NETWORKDAYS(J24,DataRef,Feriados)/MAX(H24,1))) -> 0 | S24: =N(O24)-R24 -> 0 | T24: =IF(N24="Concluído","Concluída",IF(N24="Bloqueado","BLOQUEADA",IF(DataRef>K24,"ATRASADA",IF(AND(DataRef>=J24,N24="Não iniciado"),"INÍCIO ATRASADO","No prazo")))) -> No prazo | U24: =IF(RelSex<J24,0,IF(RelSex>=K24,1,NETWORKDAYS(J24,RelSex,Feriados)/MAX(H24,1))) -> 0 | V24: =IF(N24="Concluído",COUNTIF($N$5:N24,"Concluído"),"") | W24: =IF(N24="Em andamento",COUNTIF($N$5:N24,"Em andamento"),"") | X24: =IF(AND(N24<>"Concluído",J24<=RelSex+7,K24>RelSex),COUNTIFS($N$5:N24,"<>Concluído",$J$5:J24,"<="&(RelSex+7),$K$5:K24,">"&RelSex),"") | Z24: =IF(AND(Z$4<=$K24,Z$4+4>=$J24),1,"") | AA24: =IF(AND(AA$4<=$K24,AA$4+4>=$J24),1,"") | AB24: =IF(AND(AB$4<=$K24,AB$4+4>=$J24),1,"") | AC24: =IF(AND(AC$4<=$K24,AC$4+4>=$J24),1,"") | AD24: =IF(AND(AD$4<=$K24,AD$4+4>=$J24),1,"") | AE24: =IF(AND(AE$4<=$K24,AE$4+4>=$J24),1,"") | AF24: =IF(AND(AF$4<=$K24,AF$4+4>=$J24),1,"") | AG24: =IF(AND(AG$4<=$K24,AG$4+4>=$J24),1,"") | ... AS24: =IF(AND(AS$4<=$K24,AS$4+4>=$J24),1,"")
A25: 21 | B25: Reforma light | C25: R – Reforma light | D25: Demolição de forro (250 m²) e drywall (100 m²) | E25: Somente após nº 6 concluído | F25: 6 | H25: 4 | J25: =IF(AND(F25="",G25=""),WORKDAY(DataBase-1,1,Feriados),WORKDAY(MAX(IFERROR(INDEX($K$5:$K$32,MATCH(F25,$A$5:$A$32,0)),0),IFERROR(INDEX($K$5:$K$32,MATCH(G25,$A$5:$A$32,0)),0)),1,Feriados)) -> 46331 | K25: =WORKDAY(J25,MAX(H25,1)-1,Feriados) -> 46336 | L25: =SUMIFS(ORCAMENTO!$G$5:$G$200,ORCAMENTO!$H$5:$H$200,A25) -> 2122.5 | M25: =IF(SUM($L$5:$L$32)=0,0,L25/SUM($L$5:$L$32)) -> 0.0048484097 | N25: Não iniciado | R25: =IF(DataRef<J25,0,IF(DataRef>=K25,1,NETWORKDAYS(J25,DataRef,Feriados)/MAX(H25,1))) -> 0 | S25: =N(O25)-R25 -> 0 | T25: =IF(N25="Concluído","Concluída",IF(N25="Bloqueado","BLOQUEADA",IF(DataRef>K25,"ATRASADA",IF(AND(DataRef>=J25,N25="Não iniciado"),"INÍCIO ATRASADO","No prazo")))) -> No prazo | U25: =IF(RelSex<J25,0,IF(RelSex>=K25,1,NETWORKDAYS(J25,RelSex,Feriados)/MAX(H25,1))) -> 0 | V25: =IF(N25="Concluído",COUNTIF($N$5:N25,"Concluído"),"") | W25: =IF(N25="Em andamento",COUNTIF($N$5:N25,"Em andamento"),"") | X25: =IF(AND(N25<>"Concluído",J25<=RelSex+7,K25>RelSex),COUNTIFS($N$5:N25,"<>Concluído",$J$5:J25,"<="&(RelSex+7),$K$5:K25,">"&RelSex),"") | Z25: =IF(AND(Z$4<=$K25,Z$4+4>=$J25),1,"") | AA25: =IF(AND(AA$4<=$K25,AA$4+4>=$J25),1,"") -> 1 | AB25: =IF(AND(AB$4<=$K25,AB$4+4>=$J25),1,"") -> 1 | AC25: =IF(AND(AC$4<=$K25,AC$4+4>=$J25),1,"") | AD25: =IF(AND(AD$4<=$K25,AD$4+4>=$J25),1,"") | AE25: =IF(AND(AE$4<=$K25,AE$4+4>=$J25),1,"") | AF25: =IF(AND(AF$4<=$K25,AF$4+4>=$J25),1,"") | AG25: =IF(AND(AG$4<=$K25,AG$4+4>=$J25),1,"") | ... AS25: =IF(AND(AS$4<=$K25,AS$4+4>=$J25),1,"")
A26: 22 | B26: Reforma light | C26: R – Reforma light | D26: Infraestrutura elétrica, rede, iluminação e ativações | E26: Circuitos testados | F26: 21 | H26: 10 | J26: =IF(AND(F26="",G26=""),WORKDAY(DataBase-1,1,Feriados),WORKDAY(MAX(IFERROR(INDEX($K$5:$K$32,MATCH(F26,$A$5:$A$32,0)),0),IFERROR(INDEX($K$5:$K$32,MATCH(G26,$A$5:$A$32,0)),0)),1,Feriados)) -> 46337 | K26: =WORKDAY(J26,MAX(H26,1)-1,Feriados) -> 46351 | L26: =SUMIFS(ORCAMENTO!$G$5:$G$200,ORCAMENTO!$H$5:$H$200,A26) -> 38254.25 | M26: =IF(SUM($L$5:$L$32)=0,0,L26/SUM($L$5:$L$32)) -> 0.087383876 | N26: Não iniciado | R26: =IF(DataRef<J26,0,IF(DataRef>=K26,1,NETWORKDAYS(J26,DataRef,Feriados)/MAX(H26,1))) -> 0 | S26: =N(O26)-R26 -> 0 | T26: =IF(N26="Concluído","Concluída",IF(N26="Bloqueado","BLOQUEADA",IF(DataRef>K26,"ATRASADA",IF(AND(DataRef>=J26,N26="Não iniciado"),"INÍCIO ATRASADO","No prazo")))) -> No prazo | U26: =IF(RelSex<J26,0,IF(RelSex>=K26,1,NETWORKDAYS(J26,RelSex,Feriados)/MAX(H26,1))) -> 0 | V26: =IF(N26="Concluído",COUNTIF($N$5:N26,"Concluído"),"") | W26: =IF(N26="Em andamento",COUNTIF($N$5:N26,"Em andamento"),"") | X26: =IF(AND(N26<>"Concluído",J26<=RelSex+7,K26>RelSex),COUNTIFS($N$5:N26,"<>Concluído",$J$5:J26,"<="&(RelSex+7),$K$5:K26,">"&RelSex),"") | Z26: =IF(AND(Z$4<=$K26,Z$4+4>=$J26),1,"") | AA26: =IF(AND(AA$4<=$K26,AA$4+4>=$J26),1,"") | AB26: =IF(AND(AB$4<=$K26,AB$4+4>=$J26),1,"") -> 1 | AC26: =IF(AND(AC$4<=$K26,AC$4+4>=$J26),1,"") -> 1 | AD26: =IF(AND(AD$4<=$K26,AD$4+4>=$J26),1,"") -> 1 | AE26: =IF(AND(AE$4<=$K26,AE$4+4>=$J26),1,"") | AF26: =IF(AND(AF$4<=$K26,AF$4+4>=$J26),1,"") | AG26: =IF(AND(AG$4<=$K26,AG$4+4>=$J26),1,"") | ... AS26: =IF(AND(AS$4<=$K26,AS$4+4>=$J26),1,"")
A27: 23 | B27: Reforma light | C27: R – Reforma light | D27: Ar-condicionado: retirada, reinstalação de splits e drenos | E27: Equipamentos operando | F27: 21 | H27: 5 | J27: =IF(AND(F27="",G27=""),WORKDAY(DataBase-1,1,Feriados),WORKDAY(MAX(IFERROR(INDEX($K$5:$K$32,MATCH(F27,$A$5:$A$32,0)),0),IFERROR(INDEX($K$5:$K$32,MATCH(G27,$A$5:$A$32,0)),0)),1,Feriados)) -> 46337 | K27: =WORKDAY(J27,MAX(H27,1)-1,Feriados) -> 46343 | L27: =SUMIFS(ORCAMENTO!$G$5:$G$200,ORCAMENTO!$H$5:$H$200,A27) -> 22042.6 | M27: =IF(SUM($L$5:$L$32)=0,0,L27/SUM($L$5:$L$32)) -> 0.050351734 | N27: Não iniciado | R27: =IF(DataRef<J27,0,IF(DataRef>=K27,1,NETWORKDAYS(J27,DataRef,Feriados)/MAX(H27,1))) -> 0 | S27: =N(O27)-R27 -> 0 | T27: =IF(N27="Concluído","Concluída",IF(N27="Bloqueado","BLOQUEADA",IF(DataRef>K27,"ATRASADA",IF(AND(DataRef>=J27,N27="Não iniciado"),"INÍCIO ATRASADO","No prazo")))) -> No prazo | U27: =IF(RelSex<J27,0,IF(RelSex>=K27,1,NETWORKDAYS(J27,RelSex,Feriados)/MAX(H27,1))) -> 0 | V27: =IF(N27="Concluído",COUNTIF($N$5:N27,"Concluído"),"") | W27: =IF(N27="Em andamento",COUNTIF($N$5:N27,"Em andamento"),"") | X27: =IF(AND(N27<>"Concluído",J27<=RelSex+7,K27>RelSex),COUNTIFS($N$5:N27,"<>Concluído",$J$5:J27,"<="&(RelSex+7),$K$5:K27,">"&RelSex),"") | Z27: =IF(AND(Z$4<=$K27,Z$4+4>=$J27),1,"") | AA27: =IF(AND(AA$4<=$K27,AA$4+4>=$J27),1,"") | AB27: =IF(AND(AB$4<=$K27,AB$4+4>=$J27),1,"") -> 1 | AC27: =IF(AND(AC$4<=$K27,AC$4+4>=$J27),1,"") -> 1 | AD27: =IF(AND(AD$4<=$K27,AD$4+4>=$J27),1,"") | AE27: =IF(AND(AE$4<=$K27,AE$4+4>=$J27),1,"") | AF27: =IF(AND(AF$4<=$K27,AF$4+4>=$J27),1,"") | AG27: =IF(AND(AG$4<=$K27,AG$4+4>=$J27),1,"") | ... AS27: =IF(AND(AS$4<=$K27,AS$4+4>=$J27),1,"")
A28: 24 | B28: Reforma light | C28: R – Reforma light | D28: Drywall novo (190 m²) com reforço em MDF | E28: No mezanino, só após nº 15 | F28: 22 | H28: 6 | J28: =IF(AND(F28="",G28=""),WORKDAY(DataBase-1,1,Feriados),WORKDAY(MAX(IFERROR(INDEX($K$5:$K$32,MATCH(F28,$A$5:$A$32,0)),0),IFERROR(INDEX($K$5:$K$32,MATCH(G28,$A$5:$A$32,0)),0)),1,Feriados)) -> 46352 | K28: =WORKDAY(J28,MAX(H28,1)-1,Feriados) -> 46359 | L28: =SUMIFS(ORCAMENTO!$G$5:$G$200,ORCAMENTO!$H$5:$H$200,A28) -> 24917.6 | M28: =IF(SUM($L$5:$L$32)=0,0,L28/SUM($L$5:$L$32)) -> 0.056919074 | N28: Não iniciado | R28: =IF(DataRef<J28,0,IF(DataRef>=K28,1,NETWORKDAYS(J28,DataRef,Feriados)/MAX(H28,1))) -> 0 | S28: =N(O28)-R28 -> 0 | T28: =IF(N28="Concluído","Concluída",IF(N28="Bloqueado","BLOQUEADA",IF(DataRef>K28,"ATRASADA",IF(AND(DataRef>=J28,N28="Não iniciado"),"INÍCIO ATRASADO","No prazo")))) -> No prazo | U28: =IF(RelSex<J28,0,IF(RelSex>=K28,1,NETWORKDAYS(J28,RelSex,Feriados)/MAX(H28,1))) -> 0 | V28: =IF(N28="Concluído",COUNTIF($N$5:N28,"Concluído"),"") | W28: =IF(N28="Em andamento",COUNTIF($N$5:N28,"Em andamento"),"") | X28: =IF(AND(N28<>"Concluído",J28<=RelSex+7,K28>RelSex),COUNTIFS($N$5:N28,"<>Concluído",$J$5:J28,"<="&(RelSex+7),$K$5:K28,">"&RelSex),"") | Z28: =IF(AND(Z$4<=$K28,Z$4+4>=$J28),1,"") | AA28: =IF(AND(AA$4<=$K28,AA$4+4>=$J28),1,"") | AB28: =IF(AND(AB$4<=$K28,AB$4+4>=$J28),1,"") | AC28: =IF(AND(AC$4<=$K28,AC$4+4>=$J28),1,"") | AD28: =IF(AND(AD$4<=$K28,AD$4+4>=$J28),1,"") -> 1 | AE28: =IF(AND(AE$4<=$K28,AE$4+4>=$J28),1,"") -> 1 | AF28: =IF(AND(AF$4<=$K28,AF$4+4>=$J28),1,"") | AG28: =IF(AND(AG$4<=$K28,AG$4+4>=$J28),1,"") | ... AS28: =IF(AND(AS$4<=$K28,AS$4+4>=$J28),1,"")
A29: 25 | B29: Reforma light | C29: R – Reforma light | D29: Forro mineral (250 m²) e abertura de luminárias | E29: Forro fechado | F29: 24 | G29: 23 | H29: 6 | J29: =IF(AND(F29="",G29=""),WORKDAY(DataBase-1,1,Feriados),WORKDAY(MAX(IFERROR(INDEX($K$5:$K$32,MATCH(F29,$A$5:$A$32,0)),0),IFERROR(INDEX($K$5:$K$32,MATCH(G29,$A$5:$A$32,0)),0)),1,Feriados)) -> 46360 | K29: =WORKDAY(J29,MAX(H29,1)-1,Feriados) -> 46367 | L29: =SUMIFS(ORCAMENTO!$G$5:$G$200,ORCAMENTO!$H$5:$H$200,A29) -> 35648.08 | M29: =IF(SUM($L$5:$L$32)=0,0,L29/SUM($L$5:$L$32)) -> 0.081430622 | N29: Não iniciado | R29: =IF(DataRef<J29,0,IF(DataRef>=K29,1,NETWORKDAYS(J29,DataRef,Feriados)/MAX(H29,1))) -> 0 | S29: =N(O29)-R29 -> 0 | T29: =IF(N29="Concluído","Concluída",IF(N29="Bloqueado","BLOQUEADA",IF(DataRef>K29,"ATRASADA",IF(AND(DataRef>=J29,N29="Não iniciado"),"INÍCIO ATRASADO","No prazo")))) -> No prazo | U29: =IF(RelSex<J29,0,IF(RelSex>=K29,1,NETWORKDAYS(J29,RelSex,Feriados)/MAX(H29,1))) -> 0 | V29: =IF(N29="Concluído",COUNTIF($N$5:N29,"Concluído"),"") | W29: =IF(N29="Em andamento",COUNTIF($N$5:N29,"Em andamento"),"") | X29: =IF(AND(N29<>"Concluído",J29<=RelSex+7,K29>RelSex),COUNTIFS($N$5:N29,"<>Concluído",$J$5:J29,"<="&(RelSex+7),$K$5:K29,">"&RelSex),"") | Z29: =IF(AND(Z$4<=$K29,Z$4+4>=$J29),1,"") | AA29: =IF(AND(AA$4<=$K29,AA$4+4>=$J29),1,"") | AB29: =IF(AND(AB$4<=$K29,AB$4+4>=$J29),1,"") | AC29: =IF(AND(AC$4<=$K29,AC$4+4>=$J29),1,"") | AD29: =IF(AND(AD$4<=$K29,AD$4+4>=$J29),1,"") | AE29: =IF(AND(AE$4<=$K29,AE$4+4>=$J29),1,"") -> 1 | AF29: =IF(AND(AF$4<=$K29,AF$4+4>=$J29),1,"") -> 1 | AG29: =IF(AND(AG$4<=$K29,AG$4+4>=$J29),1,"") | ... AS29: =IF(AND(AS$4<=$K29,AS$4+4>=$J29),1,"")
A30: 26 | B30: Reforma light | C30: R – Reforma light | D30: Portas, molas, grelhas, guia de porta de enrolar e fechadura | E30: Esquadrias instaladas | F30: 24 | H30: 4 | J30: =IF(AND(F30="",G30=""),WORKDAY(DataBase-1,1,Feriados),WORKDAY(MAX(IFERROR(INDEX($K$5:$K$32,MATCH(F30,$A$5:$A$32,0)),0),IFERROR(INDEX($K$5:$K$32,MATCH(G30,$A$5:$A$32,0)),0)),1,Feriados)) -> 46360 | K30: =WORKDAY(J30,MAX(H30,1)-1,Feriados) -> 46365 | L30: =SUMIFS(ORCAMENTO!$G$5:$G$200,ORCAMENTO!$H$5:$H$200,A30) -> 14246.2 | M30: =IF(SUM($L$5:$L$32)=0,0,L30/SUM($L$5:$L$32)) -> 0.03254248 | N30: Não iniciado | R30: =IF(DataRef<J30,0,IF(DataRef>=K30,1,NETWORKDAYS(J30,DataRef,Feriados)/MAX(H30,1))) -> 0 | S30: =N(O30)-R30 -> 0 | T30: =IF(N30="Concluído","Concluída",IF(N30="Bloqueado","BLOQUEADA",IF(DataRef>K30,"ATRASADA",IF(AND(DataRef>=J30,N30="Não iniciado"),"INÍCIO ATRASADO","No prazo")))) -> No prazo | U30: =IF(RelSex<J30,0,IF(RelSex>=K30,1,NETWORKDAYS(J30,RelSex,Feriados)/MAX(H30,1))) -> 0 | V30: =IF(N30="Concluído",COUNTIF($N$5:N30,"Concluído"),"") | W30: =IF(N30="Em andamento",COUNTIF($N$5:N30,"Em andamento"),"") | X30: =IF(AND(N30<>"Concluído",J30<=RelSex+7,K30>RelSex),COUNTIFS($N$5:N30,"<>Concluído",$J$5:J30,"<="&(RelSex+7),$K$5:K30,">"&RelSex),"") | Z30: =IF(AND(Z$4<=$K30,Z$4+4>=$J30),1,"") | AA30: =IF(AND(AA$4<=$K30,AA$4+4>=$J30),1,"") | AB30: =IF(AND(AB$4<=$K30,AB$4+4>=$J30),1,"") | AC30: =IF(AND(AC$4<=$K30,AC$4+4>=$J30),1,"") | AD30: =IF(AND(AD$4<=$K30,AD$4+4>=$J30),1,"") | AE30: =IF(AND(AE$4<=$K30,AE$4+4>=$J30),1,"") -> 1 | AF30: =IF(AND(AF$4<=$K30,AF$4+4>=$J30),1,"") -> 1 | AG30: =IF(AND(AG$4<=$K30,AG$4+4>=$J30),1,"") | ... AS30: =IF(AND(AS$4<=$K30,AS$4+4>=$J30),1,"")
A31: 27 | B31: Reforma light | C31: R – Reforma light | D31: Pintura (fundo, massa e acabamento) | E31: Pintura concluída | F31: 25 | G31: 19 | H31: 6 | J31: =IF(AND(F31="",G31=""),WORKDAY(DataBase-1,1,Feriados),WORKDAY(MAX(IFERROR(INDEX($K$5:$K$32,MATCH(F31,$A$5:$A$32,0)),0),IFERROR(INDEX($K$5:$K$32,MATCH(G31,$A$5:$A$32,0)),0)),1,Feriados)) -> 46399 | K31: =WORKDAY(J31,MAX(H31,1)-1,Feriados) -> 46406 | L31: =SUMIFS(ORCAMENTO!$G$5:$G$200,ORCAMENTO!$H$5:$H$200,A31) -> 13620 | M31: =IF(SUM($L$5:$L$32)=0,0,L31/SUM($L$5:$L$32)) -> 0.031112057 | N31: Não iniciado | R31: =IF(DataRef<J31,0,IF(DataRef>=K31,1,NETWORKDAYS(J31,DataRef,Feriados)/MAX(H31,1))) -> 0 | S31: =N(O31)-R31 -> 0 | T31: =IF(N31="Concluído","Concluída",IF(N31="Bloqueado","BLOQUEADA",IF(DataRef>K31,"ATRASADA",IF(AND(DataRef>=J31,N31="Não iniciado"),"INÍCIO ATRASADO","No prazo")))) -> No prazo | U31: =IF(RelSex<J31,0,IF(RelSex>=K31,1,NETWORKDAYS(J31,RelSex,Feriados)/MAX(H31,1))) -> 0 | V31: =IF(N31="Concluído",COUNTIF($N$5:N31,"Concluído"),"") | W31: =IF(N31="Em andamento",COUNTIF($N$5:N31,"Em andamento"),"") | X31: =IF(AND(N31<>"Concluído",J31<=RelSex+7,K31>RelSex),COUNTIFS($N$5:N31,"<>Concluído",$J$5:J31,"<="&(RelSex+7),$K$5:K31,">"&RelSex),"") | Z31: =IF(AND(Z$4<=$K31,Z$4+4>=$J31),1,"") | AA31: =IF(AND(AA$4<=$K31,AA$4+4>=$J31),1,"") | AB31: =IF(AND(AB$4<=$K31,AB$4+4>=$J31),1,"") | AC31: =IF(AND(AC$4<=$K31,AC$4+4>=$J31),1,"") | AD31: =IF(AND(AD$4<=$K31,AD$4+4>=$J31),1,"") | AE31: =IF(AND(AE$4<=$K31,AE$4+4>=$J31),1,"") | AF31: =IF(AND(AF$4<=$K31,AF$4+4>=$J31),1,"") | AG31: =IF(AND(AG$4<=$K31,AG$4+4>=$J31),1,"") | ... AS31: =IF(AND(AS$4<=$K31,AS$4+4>=$J31),1,"")
A32: 28 | B32: Reforma light | C32: R – Reforma light | D32: Fachada: fixação de vidros e pintura | E32: Fachada entregue | F32: 11 | H32: 3 | J32: =IF(AND(F32="",G32=""),WORKDAY(DataBase-1,1,Feriados),WORKDAY(MAX(IFERROR(INDEX($K$5:$K$32,MATCH(F32,$A$5:$A$32,0)),0),IFERROR(INDEX($K$5:$K$32,MATCH(G32,$A$5:$A$32,0)),0)),1,Feriados)) -> 46363 | K32: =WORKDAY(J32,MAX(H32,1)-1,Feriados) -> 46365 | L32: =SUMIFS(ORCAMENTO!$G$5:$G$200,ORCAMENTO!$H$5:$H$200,A32) -> 3792 | M32: =IF(SUM($L$5:$L$32)=0,0,L32/SUM($L$5:$L$32)) -> 0.0086620352 | N32: Não iniciado | R32: =IF(DataRef<J32,0,IF(DataRef>=K32,1,NETWORKDAYS(J32,DataRef,Feriados)/MAX(H32,1))) -> 0 | S32: =N(O32)-R32 -> 0 | T32: =IF(N32="Concluído","Concluída",IF(N32="Bloqueado","BLOQUEADA",IF(DataRef>K32,"ATRASADA",IF(AND(DataRef>=J32,N32="Não iniciado"),"INÍCIO ATRASADO","No prazo")))) -> No prazo | U32: =IF(RelSex<J32,0,IF(RelSex>=K32,1,NETWORKDAYS(J32,RelSex,Feriados)/MAX(H32,1))) -> 0 | V32: =IF(N32="Concluído",COUNTIF($N$5:N32,"Concluído"),"") | W32: =IF(N32="Em andamento",COUNTIF($N$5:N32,"Em andamento"),"") | X32: =IF(AND(N32<>"Concluído",J32<=RelSex+7,K32>RelSex),COUNTIFS($N$5:N32,"<>Concluído",$J$5:J32,"<="&(RelSex+7),$K$5:K32,">"&RelSex),"") | Z32: =IF(AND(Z$4<=$K32,Z$4+4>=$J32),1,"") | AA32: =IF(AND(AA$4<=$K32,AA$4+4>=$J32),1,"") | AB32: =IF(AND(AB$4<=$K32,AB$4+4>=$J32),1,"") | AC32: =IF(AND(AC$4<=$K32,AC$4+4>=$J32),1,"") | AD32: =IF(AND(AD$4<=$K32,AD$4+4>=$J32),1,"") | AE32: =IF(AND(AE$4<=$K32,AE$4+4>=$J32),1,"") | AF32: =IF(AND(AF$4<=$K32,AF$4+4>=$J32),1,"") -> 1 | AG32: =IF(AND(AG$4<=$K32,AG$4+4>=$J32),1,"") | ... AS32: =IF(AND(AS$4<=$K32,AS$4+4>=$J32),1,"")
D34: Total | L34: =SUM(L5:L32) -> 437772.41 | M34: =SUM(M5:M32) -> 1
D35: Valor de orçamento sem atividade (indiretos e imposto – fora do peso) | L35: =SUMIFS(ORCAMENTO!$G$5:$G$200,ORCAMENTO!$H$5:$H$200,0) -> 68568

Sheet CURVA_S
A1: Curva S – avanço previsto x realizado (semanal)
A2: Previsto calculado do cronograma. Realizado: toda sexta, copie aqui o avanço realizado do PAINEL (linha amarela).
B3: Sexta-feira | C3: =DataBase+MOD(5-WEEKDAY(DataBase,2),7)+0 -> 46325 | D3: =DataBase+MOD(5-WEEKDAY(DataBase,2),7)+7 -> 46332 | E3: =DataBase+MOD(5-WEEKDAY(DataBase,2),7)+14 -> 46339 | F3: =DataBase+MOD(5-WEEKDAY(DataBase,2),7)+21 -> 46346 | G3: =DataBase+MOD(5-WEEKDAY(DataBase,2),7)+28 -> 46353 | H3: =DataBase+MOD(5-WEEKDAY(DataBase,2),7)+35 -> 46360 | I3: =DataBase+MOD(5-WEEKDAY(DataBase,2),7)+42 -> 46367 | J3: =DataBase+MOD(5-WEEKDAY(DataBase,2),7)+49 -> 46374 | K3: =DataBase+MOD(5-WEEKDAY(DataBase,2),7)+56 -> 46381 | L3: =DataBase+MOD(5-WEEKDAY(DataBase,2),7)+63 -> 46388 | M3: =DataBase+MOD(5-WEEKDAY(DataBase,2),7)+70 -> 46395 | N3: =DataBase+MOD(5-WEEKDAY(DataBase,2),7)+77 -> 46402 | O3: =DataBase+MOD(5-WEEKDAY(DataBase,2),7)+84 -> 46409 | P3: =DataBase+MOD(5-WEEKDAY(DataBase,2),7)+91 -> 46416 | Q3: =DataBase+MOD(5-WEEKDAY(DataBase,2),7)+98 -> 46423 | R3: =DataBase+MOD(5-WEEKDAY(DataBase,2),7)+105 -> 46430 | S3: =DataBase+MOD(5-WEEKDAY(DataBase,2),7)+112 -> 46437 | T3: =DataBase+MOD(5-WEEKDAY(DataBase,2),7)+119 -> 46444 | U3: =DataBase+MOD(5-WEEKDAY(DataBase,2),7)+126 -> 46451 | V3: =DataBase+MOD(5-WEEKDAY(DataBase,2),7)+133 -> 46458
A5: =CRONOGRAMA!A5 -> 1 | B5: =CRONOGRAMA!D5 -> Reunião de partida no local: identificar P1–P4, treliça e faixa de piso afetada | C5: =CRONOGRAMA!$M5*IF(C$3<CRONOGRAMA!$J5,0,IF(C$3>=CRONOGRAMA!$K5,1,NETWORKDAYS(CRONOGRAMA!$J5,C$3,Feriados)/MAX(CRONOGRAMA!$H5,1))) -> 0.015190542 | D5: =CRONOGRAMA!$M5*IF(D$3<CRONOGRAMA!$J5,0,IF(D$3>=CRONOGRAMA!$K5,1,NETWORKDAYS(CRONOGRAMA!$J5,D$3,Feriados)/MAX(CRONOGRAMA!$H5,1))) -> 0.015190542 | E5: =CRONOGRAMA!$M5*IF(E$3<CRONOGRAMA!$J5,0,IF(E$3>=CRONOGRAMA!$K5,1,NETWORKDAYS(CRONOGRAMA!$J5,E$3,Feriados)/MAX(CRONOGRAMA!$H5,1))) -> 0.015190542 | F5: =CRONOGRAMA!$M5*IF(F$3<CRONOGRAMA!$J5,0,IF(F$3>=CRONOGRAMA!$K5,1,NETWORKDAYS(CRONOGRAMA!$J5,F$3,Feriados)/MAX(CRONOGRAMA!$H5,1))) -> 0.015190542 | G5: =CRONOGRAMA!$M5*IF(G$3<CRONOGRAMA!$J5,0,IF(G$3>=CRONOGRAMA!$K5,1,NETWORKDAYS(CRONOGRAMA!$J5,G$3,Feriados)/MAX(CRONOGRAMA!$H5,1))) -> 0.015190542 | H5: =CRONOGRAMA!$M5*IF(H$3<CRONOGRAMA!$J5,0,IF(H$3>=CRONOGRAMA!$K5,1,NETWORKDAYS(CRONOGRAMA!$J5,H$3,Feriados)/MAX(CRONOGRAMA!$H5,1))) -> 0.015190542 | I5: =CRONOGRAMA!$M5*IF(I$3<CRONOGRAMA!$J5,0,IF(I$3>=CRONOGRAMA!$K5,1,NETWORKDAYS(CRONOGRAMA!$J5,I$3,Feriados)/MAX(CRONOGRAMA!$H5,1))) -> 0.015190542 | J5: =CRONOGRAMA!$M5*IF(J$3<CRONOGRAMA!$J5,0,IF(J$3>=CRONOGRAMA!$K5,1,NETWORKDAYS(CRONOGRAMA!$J5,J$3,Feriados)/MAX(CRONOGRAMA!$H5,1))) -> 0.015190542 | ... V5: =CRONOGRAMA!$M5*IF(V$3<CRONOGRAMA!$J5,0,IF(V$3>=CRONOGRAMA!$K5,1,NETWORKDAYS(CRONOGRAMA!$J5,V$3,Feriados)/MAX(CRONOGRAMA!$H5,1))) -> 0.015190542
A6: =CRONOGRAMA!A6 -> 2 | B6: =CRONOGRAMA!D6 -> Pontos de acompanhamento fotográfico, relatório "antes da obra" e marcos de nível | C6: =CRONOGRAMA!$M6*IF(C$3<CRONOGRAMA!$J6,0,IF(C$3>=CRONOGRAMA!$K6,1,NETWORKDAYS(CRONOGRAMA!$J6,C$3,Feriados)/MAX(CRONOGRAMA!$H6,1))) -> 0.010279314 | D6: =CRONOGRAMA!$M6*IF(D$3<CRONOGRAMA!$J6,0,IF(D$3>=CRONOGRAMA!$K6,1,NETWORKDAYS(CRONOGRAMA!$J6,D$3,Feriados)/MAX(CRONOGRAMA!$H6,1))) -> 0.010279314 | E6: =CRONOGRAMA!$M6*IF(E$3<CRONOGRAMA!$J6,0,IF(E$3>=CRONOGRAMA!$K6,1,NETWORKDAYS(CRONOGRAMA!$J6,E$3,Feriados)/MAX(CRONOGRAMA!$H6,1))) -> 0.010279314 | F6: =CRONOGRAMA!$M6*IF(F$3<CRONOGRAMA!$J6,0,IF(F$3>=CRONOGRAMA!$K6,1,NETWORKDAYS(CRONOGRAMA!$J6,F$3,Feriados)/MAX(CRONOGRAMA!$H6,1))) -> 0.010279314 | G6: =CRONOGRAMA!$M6*IF(G$3<CRONOGRAMA!$J6,0,IF(G$3>=CRONOGRAMA!$K6,1,NETWORKDAYS(CRONOGRAMA!$J6,G$3,Feriados)/MAX(CRONOGRAMA!$H6,1))) -> 0.010279314 | H6: =CRONOGRAMA!$M6*IF(H$3<CRONOGRAMA!$J6,0,IF(H$3>=CRONOGRAMA!$K6,1,NETWORKDAYS(CRONOGRAMA!$J6,H$3,Feriados)/MAX(CRONOGRAMA!$H6,1))) -> 0.010279314 | I6: =CRONOGRAMA!$M6*IF(I$3<CRONOGRAMA!$J6,0,IF(I$3>=CRONOGRAMA!$K6,1,NETWORKDAYS(CRONOGRAMA!$J6,I$3,Feriados)/MAX(CRONOGRAMA!$H6,1))) -> 0.010279314 | J6: =CRONOGRAMA!$M6*IF(J$3<CRONOGRAMA!$J6,0,IF(J$3>=CRONOGRAMA!$K6,1,NETWORKDAYS(CRONOGRAMA!$J6,J$3,Feriados)/MAX(CRONOGRAMA!$H6,1))) -> 0.010279314 | ... V6: =CRONOGRAMA!$M6*IF(V$3<CRONOGRAMA!$J6,0,IF(V$3>=CRONOGRAMA!$K6,1,NETWORKDAYS(CRONOGRAMA!$J6,V$3,Feriados)/MAX(CRONOGRAMA!$H6,1))) -> 0.010279314
A7: =CRONOGRAMA!A7 -> 3 | B7: =CRONOGRAMA!D7 -> Instalar divisória de fechamento da área | C7: =CRONOGRAMA!$M7*IF(C$3<CRONOGRAMA!$J7,0,IF(C$3>=CRONOGRAMA!$K7,1,NETWORKDAYS(CRONOGRAMA!$J7,C$3,Feriados)/MAX(CRONOGRAMA!$H7,1))) -> 0.04081847 | D7: =CRONOGRAMA!$M7*IF(D$3<CRONOGRAMA!$J7,0,IF(D$3>=CRONOGRAMA!$K7,1,NETWORKDAYS(CRONOGRAMA!$J7,D$3,Feriados)/MAX(CRONOGRAMA!$H7,1))) -> 0.04081847 | E7: =CRONOGRAMA!$M7*IF(E$3<CRONOGRAMA!$J7,0,IF(E$3>=CRONOGRAMA!$K7,1,NETWORKDAYS(CRONOGRAMA!$J7,E$3,Feriados)/MAX(CRONOGRAMA!$H7,1))) -> 0.04081847 | F7: =CRONOGRAMA!$M7*IF(F$3<CRONOGRAMA!$J7,0,IF(F$3>=CRONOGRAMA!$K7,1,NETWORKDAYS(CRONOGRAMA!$J7,F$3,Feriados)/MAX(CRONOGRAMA!$H7,1))) -> 0.04081847 | G7: =CRONOGRAMA!$M7*IF(G$3<CRONOGRAMA!$J7,0,IF(G$3>=CRONOGRAMA!$K7,1,NETWORKDAYS(CRONOGRAMA!$J7,G$3,Feriados)/MAX(CRONOGRAMA!$H7,1))) -> 0.04081847 | H7: =CRONOGRAMA!$M7*IF(H$3<CRONOGRAMA!$J7,0,IF(H$3>=CRONOGRAMA!$K7,1,NETWORKDAYS(CRONOGRAMA!$J7,H$3,Feriados)/MAX(CRONOGRAMA!$H7,1))) -> 0.04081847 | I7: =CRONOGRAMA!$M7*IF(I$3<CRONOGRAMA!$J7,0,IF(I$3>=CRONOGRAMA!$K7,1,NETWORKDAYS(CRONOGRAMA!$J7,I$3,Feriados)/MAX(CRONOGRAMA!$H7,1))) -> 0.04081847 | J7: =CRONOGRAMA!$M7*IF(J$3<CRONOGRAMA!$J7,0,IF(J$3>=CRONOGRAMA!$K7,1,NETWORKDAYS(CRONOGRAMA!$J7,J$3,Feriados)/MAX(CRONOGRAMA!$H7,1))) -> 0.04081847 | ... V7: =CRONOGRAMA!$M7*IF(V$3<CRONOGRAMA!$J7,0,IF(V$3>=CRONOGRAMA!$K7,1,NETWORKDAYS(CRONOGRAMA!$J7,V$3,Feriados)/MAX(CRONOGRAMA!$H7,1))) -> 0.04081847
A8: =CRONOGRAMA!A8 -> 4 | B8: =CRONOGRAMA!D8 -> Remover produtos, virar o balcão e mudar o mobiliário da área afetada | C8: =CRONOGRAMA!$M8*IF(C$3<CRONOGRAMA!$J8,0,IF(C$3>=CRONOGRAMA!$K8,1,NETWORKDAYS(CRONOGRAMA!$J8,C$3,Feriados)/MAX(CRONOGRAMA!$H8,1))) -> 0.0089102615 | D8: =CRONOGRAMA!$M8*IF(D$3<CRONOGRAMA!$J8,0,IF(D$3>=CRONOGRAMA!$K8,1,NETWORKDAYS(CRONOGRAMA!$J8,D$3,Feriados)/MAX(CRONOGRAMA!$H8,1))) -> 0.013365392 | E8: =CRONOGRAMA!$M8*IF(E$3<CRONOGRAMA!$J8,0,IF(E$3>=CRONOGRAMA!$K8,1,NETWORKDAYS(CRONOGRAMA!$J8,E$3,Feriados)/MAX(CRONOGRAMA!$H8,1))) -> 0.013365392 | F8: =CRONOGRAMA!$M8*IF(F$3<CRONOGRAMA!$J8,0,IF(F$3>=CRONOGRAMA!$K8,1,NETWORKDAYS(CRONOGRAMA!$J8,F$3,Feriados)/MAX(CRONOGRAMA!$H8,1))) -> 0.013365392 | G8: =CRONOGRAMA!$M8*IF(G$3<CRONOGRAMA!$J8,0,IF(G$3>=CRONOGRAMA!$K8,1,NETWORKDAYS(CRONOGRAMA!$J8,G$3,Feriados)/MAX(CRONOGRAMA!$H8,1))) -> 0.013365392 | H8: =CRONOGRAMA!$M8*IF(H$3<CRONOGRAMA!$J8,0,IF(H$3>=CRONOGRAMA!$K8,1,NETWORKDAYS(CRONOGRAMA!$J8,H$3,Feriados)/MAX(CRONOGRAMA!$H8,1))) -> 0.013365392 | I8: =CRONOGRAMA!$M8*IF(I$3<CRONOGRAMA!$J8,0,IF(I$3>=CRONOGRAMA!$K8,1,NETWORKDAYS(CRONOGRAMA!$J8,I$3,Feriados)/MAX(CRONOGRAMA!$H8,1))) -> 0.013365392 | J8: =CRONOGRAMA!$M8*IF(J$3<CRONOGRAMA!$J8,0,IF(J$3>=CRONOGRAMA!$K8,1,NETWORKDAYS(CRONOGRAMA!$J8,J$3,Feriados)/MAX(CRONOGRAMA!$H8,1))) -> 0.013365392 | ... V8: =CRONOGRAMA!$M8*IF(V$3<CRONOGRAMA!$J8,0,IF(V$3>=CRONOGRAMA!$K8,1,NETWORKDAYS(CRONOGRAMA!$J8,V$3,Feriados)/MAX(CRONOGRAMA!$H8,1))) -> 0.013365392
A9: =CRONOGRAMA!A9 -> 5 | B9: =CRONOGRAMA!D9 -> Aliviar a carga do mezanino (retirar estoque do depósito) | C9: =CRONOGRAMA!$M9*IF(C$3<CRONOGRAMA!$J9,0,IF(C$3>=CRONOGRAMA!$K9,1,NETWORKDAYS(CRONOGRAMA!$J9,C$3,Feriados)/MAX(CRONOGRAMA!$H9,1))) -> 0 | D9: =CRONOGRAMA!$M9*IF(D$3<CRONOGRAMA!$J9,0,IF(D$3>=CRONOGRAMA!$K9,1,NETWORKDAYS(CRONOGRAMA!$J9,D$3,Feriados)/MAX(CRONOGRAMA!$H9,1))) -> 0 | E9: =CRONOGRAMA!$M9*IF(E$3<CRONOGRAMA!$J9,0,IF(E$3>=CRONOGRAMA!$K9,1,NETWORKDAYS(CRONOGRAMA!$J9,E$3,Feriados)/MAX(CRONOGRAMA!$H9,1))) -> 0 | F9: =CRONOGRAMA!$M9*IF(F$3<CRONOGRAMA!$J9,0,IF(F$3>=CRONOGRAMA!$K9,1,NETWORKDAYS(CRONOGRAMA!$J9,F$3,Feriados)/MAX(CRONOGRAMA!$H9,1))) -> 0 | G9: =CRONOGRAMA!$M9*IF(G$3<CRONOGRAMA!$J9,0,IF(G$3>=CRONOGRAMA!$K9,1,NETWORKDAYS(CRONOGRAMA!$J9,G$3,Feriados)/MAX(CRONOGRAMA!$H9,1))) -> 0 | H9: =CRONOGRAMA!$M9*IF(H$3<CRONOGRAMA!$J9,0,IF(H$3>=CRONOGRAMA!$K9,1,NETWORKDAYS(CRONOGRAMA!$J9,H$3,Feriados)/MAX(CRONOGRAMA!$H9,1))) -> 0 | I9: =CRONOGRAMA!$M9*IF(I$3<CRONOGRAMA!$J9,0,IF(I$3>=CRONOGRAMA!$K9,1,NETWORKDAYS(CRONOGRAMA!$J9,I$3,Feriados)/MAX(CRONOGRAMA!$H9,1))) -> 0 | J9: =CRONOGRAMA!$M9*IF(J$3<CRONOGRAMA!$J9,0,IF(J$3>=CRONOGRAMA!$K9,1,NETWORKDAYS(CRONOGRAMA!$J9,J$3,Feriados)/MAX(CRONOGRAMA!$H9,1))) -> 0 | ... V9: =CRONOGRAMA!$M9*IF(V$3<CRONOGRAMA!$J9,0,IF(V$3>=CRONOGRAMA!$K9,1,NETWORKDAYS(CRONOGRAMA!$J9,V$3,Feriados)/MAX(CRONOGRAMA!$H9,1))) -> 0
A10: =CRONOGRAMA!A10 -> 6 | B10: =CRONOGRAMA!D10 -> Escoramento provisório sob a treliça (P2/P3 e vão P3–P4); macaco só para encunhar | C10: =CRONOGRAMA!$M10*IF(C$3<CRONOGRAMA!$J10,0,IF(C$3>=CRONOGRAMA!$K10,1,NETWORKDAYS(CRONOGRAMA!$J10,C$3,Feriados)/MAX(CRONOGRAMA!$H10,1))) -> 0.011573746 | D10: =CRONOGRAMA!$M10*IF(D$3<CRONOGRAMA!$J10,0,IF(D$3>=CRONOGRAMA!$K10,1,NETWORKDAYS(CRONOGRAMA!$J10,D$3,Feriados)/MAX(CRONOGRAMA!$H10,1))) -> 0.034721238 | E10: =CRONOGRAMA!$M10*IF(E$3<CRONOGRAMA!$J10,0,IF(E$3>=CRONOGRAMA!$K10,1,NETWORKDAYS(CRONOGRAMA!$J10,E$3,Feriados)/MAX(CRONOGRAMA!$H10,1))) -> 0.034721238 | F10: =CRONOGRAMA!$M10*IF(F$3<CRONOGRAMA!$J10,0,IF(F$3>=CRONOGRAMA!$K10,1,NETWORKDAYS(CRONOGRAMA!$J10,F$3,Feriados)/MAX(CRONOGRAMA!$H10,1))) -> 0.034721238 | G10: =CRONOGRAMA!$M10*IF(G$3<CRONOGRAMA!$J10,0,IF(G$3>=CRONOGRAMA!$K10,1,NETWORKDAYS(CRONOGRAMA!$J10,G$3,Feriados)/MAX(CRONOGRAMA!$H10,1))) -> 0.034721238 | H10: =CRONOGRAMA!$M10*IF(H$3<CRONOGRAMA!$J10,0,IF(H$3>=CRONOGRAMA!$K10,1,NETWORKDAYS(CRONOGRAMA!$J10,H$3,Feriados)/MAX(CRONOGRAMA!$H10,1))) -> 0.034721238 | I10: =CRONOGRAMA!$M10*IF(I$3<CRONOGRAMA!$J10,0,IF(I$3>=CRONOGRAMA!$K10,1,NETWORKDAYS(CRONOGRAMA!$J10,I$3,Feriados)/MAX(CRONOGRAMA!$H10,1))) -> 0.034721238 | J10: =CRONOGRAMA!$M10*IF(J$3<CRONOGRAMA!$J10,0,IF(J$3>=CRONOGRAMA!$K10,1,NETWORKDAYS(CRONOGRAMA!$J10,J$3,Feriados)/MAX(CRONOGRAMA!$H10,1))) -> 0.034721238 | ... V10: =CRONOGRAMA!$M10*IF(V$3<CRONOGRAMA!$J10,0,IF(V$3>=CRONOGRAMA!$K10,1,NETWORKDAYS(CRONOGRAMA!$J10,V$3,Feriados)/MAX(CRONOGRAMA!$H10,1))) -> 0.034721238
A11: =CRONOGRAMA!A11 -> 7 | B11: =CRONOGRAMA!D11 -> Levantamento topográfico de níveis e medição dos m² da faixa afetada | C11: =CRONOGRAMA!$M11*IF(C$3<CRONOGRAMA!$J11,0,IF(C$3>=CRONOGRAMA!$K11,1,NETWORKDAYS(CRONOGRAMA!$J11,C$3,Feriados)/MAX(CRONOGRAMA!$H11,1))) -> 0 | D11: =CRONOGRAMA!$M11*IF(D$3<CRONOGRAMA!$J11,0,IF(D$3>=CRONOGRAMA!$K11,1,NETWORKDAYS(CRONOGRAMA!$J11,D$3,Feriados)/MAX(CRONOGRAMA!$H11,1))) -> 0.026269358 | E11: =CRONOGRAMA!$M11*IF(E$3<CRONOGRAMA!$J11,0,IF(E$3>=CRONOGRAMA!$K11,1,NETWORKDAYS(CRONOGRAMA!$J11,E$3,Feriados)/MAX(CRONOGRAMA!$H11,1))) -> 0.026269358 | F11: =CRONOGRAMA!$M11*IF(F$3<CRONOGRAMA!$J11,0,IF(F$3>=CRONOGRAMA!$K11,1,NETWORKDAYS(CRONOGRAMA!$J11,F$3,Feriados)/MAX(CRONOGRAMA!$H11,1))) -> 0.026269358 | G11: =CRONOGRAMA!$M11*IF(G$3<CRONOGRAMA!$J11,0,IF(G$3>=CRONOGRAMA!$K11,1,NETWORKDAYS(CRONOGRAMA!$J11,G$3,Feriados)/MAX(CRONOGRAMA!$H11,1))) -> 0.026269358 | H11: =CRONOGRAMA!$M11*IF(H$3<CRONOGRAMA!$J11,0,IF(H$3>=CRONOGRAMA!$K11,1,NETWORKDAYS(CRONOGRAMA!$J11,H$3,Feriados)/MAX(CRONOGRAMA!$H11,1))) -> 0.026269358 | I11: =CRONOGRAMA!$M11*IF(I$3<CRONOGRAMA!$J11,0,IF(I$3>=CRONOGRAMA!$K11,1,NETWORKDAYS(CRONOGRAMA!$J11,I$3,Feriados)/MAX(CRONOGRAMA!$H11,1))) -> 0.026269358 | J11: =CRONOGRAMA!$M11*IF(J$3<CRONOGRAMA!$J11,0,IF(J$3>=CRONOGRAMA!$K11,1,NETWORKDAYS(CRONOGRAMA!$J11,J$3,Feriados)/MAX(CRONOGRAMA!$H11,1))) -> 0.026269358 | ... V11: =CRONOGRAMA!$M11*IF(V$3<CRONOGRAMA!$J11,0,IF(V$3>=CRONOGRAMA!$K11,1,NETWORKDAYS(CRONOGRAMA!$J11,V$3,Feriados)/MAX(CRONOGRAMA!$H11,1))) -> 0.026269358
A12: =CRONOGRAMA!A12 -> 8 | B12: =CRONOGRAMA!D12 -> Estudo de solo: SPT e poço de inspeção com abertura localizada do piso | C12: =CRONOGRAMA!$M12*IF(C$3<CRONOGRAMA!$J12,0,IF(C$3>=CRONOGRAMA!$K12,1,NETWORKDAYS(CRONOGRAMA!$J12,C$3,Feriados)/MAX(CRONOGRAMA!$H12,1))) -> 0 | D12: =CRONOGRAMA!$M12*IF(D$3<CRONOGRAMA!$J12,0,IF(D$3>=CRONOGRAMA!$K12,1,NETWORKDAYS(CRONOGRAMA!$J12,D$3,Feriados)/MAX(CRONOGRAMA!$H12,1))) -> 0.034721238 | E12: =CRONOGRAMA!$M12*IF(E$3<CRONOGRAMA!$J12,0,IF(E$3>=CRONOGRAMA!$K12,1,NETWORKDAYS(CRONOGRAMA!$J12,E$3,Feriados)/MAX(CRONOGRAMA!$H12,1))) -> 0.086803095 | F12: =CRONOGRAMA!$M12*IF(F$3<CRONOGRAMA!$J12,0,IF(F$3>=CRONOGRAMA!$K12,1,NETWORKDAYS(CRONOGRAMA!$J12,F$3,Feriados)/MAX(CRONOGRAMA!$H12,1))) -> 0.086803095 | G12: =CRONOGRAMA!$M12*IF(G$3<CRONOGRAMA!$J12,0,IF(G$3>=CRONOGRAMA!$K12,1,NETWORKDAYS(CRONOGRAMA!$J12,G$3,Feriados)/MAX(CRONOGRAMA!$H12,1))) -> 0.086803095 | H12: =CRONOGRAMA!$M12*IF(H$3<CRONOGRAMA!$J12,0,IF(H$3>=CRONOGRAMA!$K12,1,NETWORKDAYS(CRONOGRAMA!$J12,H$3,Feriados)/MAX(CRONOGRAMA!$H12,1))) -> 0.086803095 | I12: =CRONOGRAMA!$M12*IF(I$3<CRONOGRAMA!$J12,0,IF(I$3>=CRONOGRAMA!$K12,1,NETWORKDAYS(CRONOGRAMA!$J12,I$3,Feriados)/MAX(CRONOGRAMA!$H12,1))) -> 0.086803095 | J12: =CRONOGRAMA!$M12*IF(J$3<CRONOGRAMA!$J12,0,IF(J$3>=CRONOGRAMA!$K12,1,NETWORKDAYS(CRONOGRAMA!$J12,J$3,Feriados)/MAX(CRONOGRAMA!$H12,1))) -> 0.086803095 | ... V12: =CRONOGRAMA!$M12*IF(V$3<CRONOGRAMA!$J12,0,IF(V$3>=CRONOGRAMA!$K12,1,NETWORKDAYS(CRONOGRAMA!$J12,V$3,Feriados)/MAX(CRONOGRAMA!$H12,1))) -> 0.086803095
A13: =CRONOGRAMA!A13 -> 9 | B13: =CRONOGRAMA!D13 -> Projeto estrutural de reforço (treliça, apoios e fundações) + ART | C13: =CRONOGRAMA!$M13*IF(C$3<CRONOGRAMA!$J13,0,IF(C$3>=CRONOGRAMA!$K13,1,NETWORKDAYS(CRONOGRAMA!$J13,C$3,Feriados)/MAX(CRONOGRAMA!$H13,1))) -> 0 | D13: =CRONOGRAMA!$M13*IF(D$3<CRONOGRAMA!$J13,0,IF(D$3>=CRONOGRAMA!$K13,1,NETWORKDAYS(CRONOGRAMA!$J13,D$3,Feriados)/MAX(CRONOGRAMA!$H13,1))) -> 0 | E13: =CRONOGRAMA!$M13*IF(E$3<CRONOGRAMA!$J13,0,IF(E$3>=CRONOGRAMA!$K13,1,NETWORKDAYS(CRONOGRAMA!$J13,E$3,Feriados)/MAX(CRONOGRAMA!$H13,1))) -> 0.0074437948 | F13: =CRONOGRAMA!$M13*IF(F$3<CRONOGRAMA!$J13,0,IF(F$3>=CRONOGRAMA!$K13,1,NETWORKDAYS(CRONOGRAMA!$J13,F$3,Feriados)/MAX(CRONOGRAMA!$H13,1))) -> 0.022331384 | G13: =CRONOGRAMA!$M13*IF(G$3<CRONOGRAMA!$J13,0,IF(G$3>=CRONOGRAMA!$K13,1,NETWORKDAYS(CRONOGRAMA!$J13,G$3,Feriados)/MAX(CRONOGRAMA!$H13,1))) -> 0.037218974 | H13: =CRONOGRAMA!$M13*IF(H$3<CRONOGRAMA!$J13,0,IF(H$3>=CRONOGRAMA!$K13,1,NETWORKDAYS(CRONOGRAMA!$J13,H$3,Feriados)/MAX(CRONOGRAMA!$H13,1))) -> 0.037218974 | I13: =CRONOGRAMA!$M13*IF(I$3<CRONOGRAMA!$J13,0,IF(I$3>=CRONOGRAMA!$K13,1,NETWORKDAYS(CRONOGRAMA!$J13,I$3,Feriados)/MAX(CRONOGRAMA!$H13,1))) -> 0.037218974 | J13: =CRONOGRAMA!$M13*IF(J$3<CRONOGRAMA!$J13,0,IF(J$3>=CRONOGRAMA!$K13,1,NETWORKDAYS(CRONOGRAMA!$J13,J$3,Feriados)/MAX(CRONOGRAMA!$H13,1))) -> 0.037218974 | ... V13: =CRONOGRAMA!$M13*IF(V$3<CRONOGRAMA!$J13,0,IF(V$3>=CRONOGRAMA!$K13,1,NETWORKDAYS(CRONOGRAMA!$J13,V$3,Feriados)/MAX(CRONOGRAMA!$H13,1))) -> 0.037218974
A14: =CRONOGRAMA!A14 -> 10 | B14: =CRONOGRAMA!D14 -> Fechar quantitativos e revisar o orçamento da Fase 2 | C14: =CRONOGRAMA!$M14*IF(C$3<CRONOGRAMA!$J14,0,IF(C$3>=CRONOGRAMA!$K14,1,NETWORKDAYS(CRONOGRAMA!$J14,C$3,Feriados)/MAX(CRONOGRAMA!$H14,1))) -> 0 | D14: =CRONOGRAMA!$M14*IF(D$3<CRONOGRAMA!$J14,0,IF(D$3>=CRONOGRAMA!$K14,1,NETWORKDAYS(CRONOGRAMA!$J14,D$3,Feriados)/MAX(CRONOGRAMA!$H14,1))) -> 0 | E14: =CRONOGRAMA!$M14*IF(E$3<CRONOGRAMA!$J14,0,IF(E$3>=CRONOGRAMA!$K14,1,NETWORKDAYS(CRONOGRAMA!$J14,E$3,Feriados)/MAX(CRONOGRAMA!$H14,1))) -> 0 | F14: =CRONOGRAMA!$M14*IF(F$3<CRONOGRAMA!$J14,0,IF(F$3>=CRONOGRAMA!$K14,1,NETWORKDAYS(CRONOGRAMA!$J14,F$3,Feriados)/MAX(CRONOGRAMA!$H14,1))) -> 0 | G14: =CRONOGRAMA!$M14*IF(G$3<CRONOGRAMA!$J14,0,IF(G$3>=CRONOGRAMA!$K14,1,NETWORKDAYS(CRONOGRAMA!$J14,G$3,Feriados)/MAX(CRONOGRAMA!$H14,1))) -> 0 | H14: =CRONOGRAMA!$M14*IF(H$3<CRONOGRAMA!$J14,0,IF(H$3>=CRONOGRAMA!$K14,1,NETWORKDAYS(CRONOGRAMA!$J14,H$3,Feriados)/MAX(CRONOGRAMA!$H14,1))) -> 0 | I14: =CRONOGRAMA!$M14*IF(I$3<CRONOGRAMA!$J14,0,IF(I$3>=CRONOGRAMA!$K14,1,NETWORKDAYS(CRONOGRAMA!$J14,I$3,Feriados)/MAX(CRONOGRAMA!$H14,1))) -> 0 | J14: =CRONOGRAMA!$M14*IF(J$3<CRONOGRAMA!$J14,0,IF(J$3>=CRONOGRAMA!$K14,1,NETWORKDAYS(CRONOGRAMA!$J14,J$3,Feriados)/MAX(CRONOGRAMA!$H14,1))) -> 0 | ... V14: =CRONOGRAMA!$M14*IF(V$3<CRONOGRAMA!$J14,0,IF(V$3>=CRONOGRAMA!$K14,1,NETWORKDAYS(CRONOGRAMA!$J14,V$3,Feriados)/MAX(CRONOGRAMA!$H14,1))) -> 0
A15: =CRONOGRAMA!A15 -> 11 | B15: =CRONOGRAMA!D15 -> Abertura de porta com retirada de vidro (logística de entulho e materiais) | C15: =CRONOGRAMA!$M15*IF(C$3<CRONOGRAMA!$J15,0,IF(C$3>=CRONOGRAMA!$K15,1,NETWORKDAYS(CRONOGRAMA!$J15,C$3,Feriados)/MAX(CRONOGRAMA!$H15,1))) -> 0 | D15: =CRONOGRAMA!$M15*IF(D$3<CRONOGRAMA!$J15,0,IF(D$3>=CRONOGRAMA!$K15,1,NETWORKDAYS(CRONOGRAMA!$J15,D$3,Feriados)/MAX(CRONOGRAMA!$H15,1))) -> 0 | E15: =CRONOGRAMA!$M15*IF(E$3<CRONOGRAMA!$J15,0,IF(E$3>=CRONOGRAMA!$K15,1,NETWORKDAYS(CRONOGRAMA!$J15,E$3,Feriados)/MAX(CRONOGRAMA!$H15,1))) -> 0 | F15: =CRONOGRAMA!$M15*IF(F$3<CRONOGRAMA!$J15,0,IF(F$3>=CRONOGRAMA!$K15,1,NETWORKDAYS(CRONOGRAMA!$J15,F$3,Feriados)/MAX(CRONOGRAMA!$H15,1))) -> 0 | G15: =CRONOGRAMA!$M15*IF(G$3<CRONOGRAMA!$J15,0,IF(G$3>=CRONOGRAMA!$K15,1,NETWORKDAYS(CRONOGRAMA!$J15,G$3,Feriados)/MAX(CRONOGRAMA!$H15,1))) -> 0 | H15: =CRONOGRAMA!$M15*IF(H$3<CRONOGRAMA!$J15,0,IF(H$3>=CRONOGRAMA!$K15,1,NETWORKDAYS(CRONOGRAMA!$J15,H$3,Feriados)/MAX(CRONOGRAMA!$H15,1))) -> 0.0047970131 | I15: =CRONOGRAMA!$M15*IF(I$3<CRONOGRAMA!$J15,0,IF(I$3>=CRONOGRAMA!$K15,1,NETWORKDAYS(CRONOGRAMA!$J15,I$3,Feriados)/MAX(CRONOGRAMA!$H15,1))) -> 0.0047970131 | J15: =CRONOGRAMA!$M15*IF(J$3<CRONOGRAMA!$J15,0,IF(J$3>=CRONOGRAMA!$K15,1,NETWORKDAYS(CRONOGRAMA!$J15,J$3,Feriados)/MAX(CRONOGRAMA!$H15,1))) -> 0.0047970131 | ... V15: =CRONOGRAMA!$M15*IF(V$3<CRONOGRAMA!$J15,0,IF(V$3>=CRONOGRAMA!$K15,1,NETWORKDAYS(CRONOGRAMA!$J15,V$3,Feriados)/MAX(CRONOGRAMA!$H15,1))) -> 0.0047970131
A16: =CRONOGRAMA!A16 -> 12 | B16: =CRONOGRAMA!D16 -> Descarte de gôndolas e geladeira | C16: =CRONOGRAMA!$M16*IF(C$3<CRONOGRAMA!$J16,0,IF(C$3>=CRONOGRAMA!$K16,1,NETWORKDAYS(CRONOGRAMA!$J16,C$3,Feriados)/MAX(CRONOGRAMA!$H16,1))) -> 0 | D16: =CRONOGRAMA!$M16*IF(D$3<CRONOGRAMA!$J16,0,IF(D$3>=CRONOGRAMA!$K16,1,NETWORKDAYS(CRONOGRAMA!$J16,D$3,Feriados)/MAX(CRONOGRAMA!$H16,1))) -> 0 | E16: =CRONOGRAMA!$M16*IF(E$3<CRONOGRAMA!$J16,0,IF(E$3>=CRONOGRAMA!$K16,1,NETWORKDAYS(CRONOGRAMA!$J16,E$3,Feriados)/MAX(CRONOGRAMA!$H16,1))) -> 0 | F16: =CRONOGRAMA!$M16*IF(F$3<CRONOGRAMA!$J16,0,IF(F$3>=CRONOGRAMA!$K16,1,NETWORKDAYS(CRONOGRAMA!$J16,F$3,Feriados)/MAX(CRONOGRAMA!$H16,1))) -> 0 | G16: =CRONOGRAMA!$M16*IF(G$3<CRONOGRAMA!$J16,0,IF(G$3>=CRONOGRAMA!$K16,1,NETWORKDAYS(CRONOGRAMA!$J16,G$3,Feriados)/MAX(CRONOGRAMA!$H16,1))) -> 0 | H16: =CRONOGRAMA!$M16*IF(H$3<CRONOGRAMA!$J16,0,IF(H$3>=CRONOGRAMA!$K16,1,NETWORKDAYS(CRONOGRAMA!$J16,H$3,Feriados)/MAX(CRONOGRAMA!$H16,1))) -> 0.0019747704 | I16: =CRONOGRAMA!$M16*IF(I$3<CRONOGRAMA!$J16,0,IF(I$3>=CRONOGRAMA!$K16,1,NETWORKDAYS(CRONOGRAMA!$J16,I$3,Feriados)/MAX(CRONOGRAMA!$H16,1))) -> 0.0039495408 | J16: =CRONOGRAMA!$M16*IF(J$3<CRONOGRAMA!$J16,0,IF(J$3>=CRONOGRAMA!$K16,1,NETWORKDAYS(CRONOGRAMA!$J16,J$3,Feriados)/MAX(CRONOGRAMA!$H16,1))) -> 0.0039495408 | ... V16: =CRONOGRAMA!$M16*IF(V$3<CRONOGRAMA!$J16,0,IF(V$3>=CRONOGRAMA!$K16,1,NETWORKDAYS(CRONOGRAMA!$J16,V$3,Feriados)/MAX(CRONOGRAMA!$H16,1))) -> 0.0039495408
... A32: =CRONOGRAMA!A32 -> 28 | B32: =CRONOGRAMA!D32 -> Fachada: fixação de vidros e pintura | C32: =CRONOGRAMA!$M32*IF(C$3<CRONOGRAMA!$J32,0,IF(C$3>=CRONOGRAMA!$K32,1,NETWORKDAYS(CRONOGRAMA!$J32,C$3,Feriados)/MAX(CRONOGRAMA!$H32,1))) -> 0 | D32: =CRONOGRAMA!$M32*IF(D$3<CRONOGRAMA!$J32,0,IF(D$3>=CRONOGRAMA!$K32,1,NETWORKDAYS(CRONOGRAMA!$J32,D$3,Feriados)/MAX(CRONOGRAMA!$H32,1))) -> 0 | E32: =CRONOGRAMA!$M32*IF(E$3<CRONOGRAMA!$J32,0,IF(E$3>=CRONOGRAMA!$K32,1,NETWORKDAYS(CRONOGRAMA!$J32,E$3,Feriados)/MAX(CRONOGRAMA!$H32,1))) -> 0 | F32: =CRONOGRAMA!$M32*IF(F$3<CRONOGRAMA!$J32,0,IF(F$3>=CRONOGRAMA!$K32,1,NETWORKDAYS(CRONOGRAMA!$J32,F$3,Feriados)/MAX(CRONOGRAMA!$H32,1))) -> 0 | G32: =CRONOGRAMA!$M32*IF(G$3<CRONOGRAMA!$J32,0,IF(G$3>=CRONOGRAMA!$K32,1,NETWORKDAYS(CRONOGRAMA!$J32,G$3,Feriados)/MAX(CRONOGRAMA!$H32,1))) -> 0 | H32: =CRONOGRAMA!$M32*IF(H$3<CRONOGRAMA!$J32,0,IF(H$3>=CRONOGRAMA!$K32,1,NETWORKDAYS(CRONOGRAMA!$J32,H$3,Feriados)/MAX(CRONOGRAMA!$H32,1))) -> 0 | I32: =CRONOGRAMA!$M32*IF(I$3<CRONOGRAMA!$J32,0,IF(I$3>=CRONOGRAMA!$K32,1,NETWORKDAYS(CRONOGRAMA!$J32,I$3,Feriados)/MAX(CRONOGRAMA!$H32,1))) -> 0.0086620352 | J32: =CRONOGRAMA!$M32*IF(J$3<CRONOGRAMA!$J32,0,IF(J$3>=CRONOGRAMA!$K32,1,NETWORKDAYS(CRONOGRAMA!$J32,J$3,Feriados)/MAX(CRONOGRAMA!$H32,1))) -> 0.0086620352 | ... V32: =CRONOGRAMA!$M32*IF(V$3<CRONOGRAMA!$J32,0,IF(V$3>=CRONOGRAMA!$K32,1,NETWORKDAYS(CRONOGRAMA!$J32,V$3,Feriados)/MAX(CRONOGRAMA!$H32,1))) -> 0.0086620352
B34: Previsto acumulado | C34: =SUM(C5:C32) -> 0.086772333 | D34: =SUM(D5:D32) -> 0.17778976 | E34: =SUM(E5:E32) -> 0.29616582 | F34: =SUM(F5:F32) -> 0.36614765 | G34: =SUM(G5:G32) -> 0.42622343 | H34: =SUM(H5:H32) -> 0.49314969 | I34: =SUM(I5:I32) -> 0.63934417 | J34: =SUM(J5:J32) -> 0.73044898 | ... V34: =SUM(V5:V32) -> 1
B35: Realizado acumulado

Sheet ORCAMENTO
A1: Orçamento consolidado – Estrutural REV_04 + Reforma light LPU rev 2
A2: Preços copiados das fontes (azul). Amarelo = vínculo com atividade, % medido e custo previsto. Atividade 0 = indireto/imposto (fora do peso físico). | C2: Conferência com as fontes: | D2: REV_04 | E2: 292968 | G2: =IF(ABS(SUMIFS(G5:G200,A5:A200,"Estrutural REV_04")-E2)<0.01,"OK","DIVERGENTE") -> OK | H2: LPU | J2: 213372.41 | K2: =IF(ABS(SUMIFS(G5:G200,A5:A200,"Reforma light LPU")-J2)<1,"OK","DIVERGENTE") -> OK
A4: Origem | B4: Item | C4: Descrição | D4: Un. | E4: Qtd. | F4: Preço unit. (R$) | G4: Total (R$) | H4: Ativ. nº | I4: Atividade | J4: % medido | K4: Valor medido | L4: Saldo a medir | M4: Custo previsto | N4: Custo real | O4: Resultado (medido – custo real) | Q4: Chave
A5: Estrutural REV_04 | B5: 1.1 | C5: Isolamento e sinalização da área (salão e mezanino) | D5: vb | E5: 1 | F5: 9500 | G5: =E5*F5 -> 9500 | H5: 3 | I5: =IF(H5=0,"Indireto / imposto",IFERROR(INDEX(CRONOGRAMA!$D$5:$D$32,MATCH(H5,CRONOGRAMA!$A$5:$A$32,0)),"nº inexistente")) -> Instalar divisória de fechamento da área | K5: =G5*N(J5) -> 0 | L5: =G5-K5 -> 9500 | N5: =SUMIFS(COMPRAS!$G$6:$G$500,COMPRAS!$D$6:$D$500,Q5,COMPRAS!$J$6:$J$500,"<>Cancelado")+SUMIFS(LOCACOES!$I$6:$I$200,LOCACOES!$J$6:$J$200,Q5) -> 0 | O5: =K5-N5 -> 0 | Q5: =IF(LEFT(A5,4)="Estr","REV","LPU")&"|"&B5 -> REV|1.1
A6: Estrutural REV_04 | B6: 1.2 | C6: Mobilização e desmobilização de equipe/ferramentas | D6: vb | E6: 1 | F6: 4500 | G6: =E6*F6 -> 4500 | H6: 1 | I6: =IF(H6=0,"Indireto / imposto",IFERROR(INDEX(CRONOGRAMA!$D$5:$D$32,MATCH(H6,CRONOGRAMA!$A$5:$A$32,0)),"nº inexistente")) -> Reunião de partida no local: identificar P1–P4, treliça e faixa de piso afetada | K6: =G6*N(J6) -> 0 | L6: =G6-K6 -> 4500 | N6: =SUMIFS(COMPRAS!$G$6:$G$500,COMPRAS!$D$6:$D$500,Q6,COMPRAS!$J$6:$J$500,"<>Cancelado")+SUMIFS(LOCACOES!$I$6:$I$200,LOCACOES!$J$6:$J$200,Q6) -> 0 | O6: =K6-N6 -> 0 | Q6: =IF(LEFT(A6,4)="Estr","REV","LPU")&"|"&B6 -> REV|1.2
A7: Estrutural REV_04 | B7: 1.3 | C7: Proteções provisórias e contenção de poeira/entulho | D7: vb | E7: 1 | F7: 1000 | G7: =E7*F7 -> 1000 | H7: 3 | I7: =IF(H7=0,"Indireto / imposto",IFERROR(INDEX(CRONOGRAMA!$D$5:$D$32,MATCH(H7,CRONOGRAMA!$A$5:$A$32,0)),"nº inexistente")) -> Instalar divisória de fechamento da área | K7: =G7*N(J7) -> 0 | L7: =G7-K7 -> 1000 | N7: =SUMIFS(COMPRAS!$G$6:$G$500,COMPRAS!$D$6:$D$500,Q7,COMPRAS!$J$6:$J$500,"<>Cancelado")+SUMIFS(LOCACOES!$I$6:$I$200,LOCACOES!$J$6:$J$200,Q7) -> 0 | O7: =K7-N7 -> 0 | Q7: =IF(LEFT(A7,4)="Estr","REV","LPU")&"|"&B7 -> REV|1.3
A8: Estrutural REV_04 | B8: 1.4 | C8: Remanejamento de gôndolas, estoque e mobiliário da área de intervenção (térreo e mezanino) | D8: vb | E8: 1 | F8: 2500 | G8: =E8*F8 -> 2500 | H8: 4 | I8: =IF(H8=0,"Indireto / imposto",IFERROR(INDEX(CRONOGRAMA!$D$5:$D$32,MATCH(H8,CRONOGRAMA!$A$5:$A$32,0)),"nº inexistente")) -> Remover produtos, virar o balcão e mudar o mobiliário da área afetada | K8: =G8*N(J8) -> 0 | L8: =G8-K8 -> 2500 | N8: =SUMIFS(COMPRAS!$G$6:$G$500,COMPRAS!$D$6:$D$500,Q8,COMPRAS!$J$6:$J$500,"<>Cancelado")+SUMIFS(LOCACOES!$I$6:$I$200,LOCACOES!$J$6:$J$200,Q8) -> 0 | O8: =K8-N8 -> 0 | Q8: =IF(LEFT(A8,4)="Estr","REV","LPU")&"|"&B8 -> REV|1.4
A9: Estrutural REV_04 | B9: 1.5 | C9: Adicional para trabalho fora do horário comercial (noturno/fim de semana) | D9: vb | E9: 1 | F9: 1200 | G9: =E9*F9 -> 1200 | H9: 14 | I9: =IF(H9=0,"Indireto / imposto",IFERROR(INDEX(CRONOGRAMA!$D$5:$D$32,MATCH(H9,CRONOGRAMA!$A$5:$A$32,0)),"nº inexistente")) -> Demolição do piso (revestimento, contrapiso e laje) + descarte com CTR | K9: =G9*N(J9) -> 0 | L9: =G9-K9 -> 1200 | N9: =SUMIFS(COMPRAS!$G$6:$G$500,COMPRAS!$D$6:$D$500,Q9,COMPRAS!$J$6:$J$500,"<>Cancelado")+SUMIFS(LOCACOES!$I$6:$I$200,LOCACOES!$J$6:$J$200,Q9) -> 0 | O9: =K9-N9 -> 0 | Q9: =IF(LEFT(A9,4)="Estr","REV","LPU")&"|"&B9 -> REV|1.5
A10: Estrutural REV_04 | B10: 2.1 | C10: Escoramento provisório sob a treliça principal – apoios P2/P3 e vão livre P3–P4 (10,00 m) | D10: vb | E10: 1 | F10: 5000 | G10: =E10*F10 -> 5000 | H10: 6 | I10: =IF(H10=0,"Indireto / imposto",IFERROR(INDEX(CRONOGRAMA!$D$5:$D$32,MATCH(H10,CRONOGRAMA!$A$5:$A$32,0)),"nº inexistente")) -> Escoramento provisório sob a treliça (P2/P3 e vão P3–P4); macaco só para encunhar | K10: =G10*N(J10) -> 0 | L10: =G10-K10 -> 5000 | N10: =SUMIFS(COMPRAS!$G$6:$G$500,COMPRAS!$D$6:$D$500,Q10,COMPRAS!$J$6:$J$500,"<>Cancelado")+SUMIFS(LOCACOES!$I$6:$I$200,LOCACOES!$J$6:$J$200,Q10) -> 0 | O10: =K10-N10 -> 0 | Q10: =IF(LEFT(A10,4)="Estr","REV","LPU")&"|"&B10 -> REV|2.1
A11: Estrutural REV_04 | B11: 2.2 | C11: Materiais para escoramento e travamento (escoras metálicas, vigas de distribuição, calços) | D11: vb | E11: 1 | F11: 7000 | G11: =E11*F11 -> 7000 | H11: 6 | I11: =IF(H11=0,"Indireto / imposto",IFERROR(INDEX(CRONOGRAMA!$D$5:$D$32,MATCH(H11,CRONOGRAMA!$A$5:$A$32,0)),"nº inexistente")) -> Escoramento provisório sob a treliça (P2/P3 e vão P3–P4); macaco só para encunhar | K11: =G11*N(J11) -> 0 | L11: =G11-K11 -> 7000 | N11: =SUMIFS(COMPRAS!$G$6:$G$500,COMPRAS!$D$6:$D$500,Q11,COMPRAS!$J$6:$J$500,"<>Cancelado")+SUMIFS(LOCACOES!$I$6:$I$200,LOCACOES!$J$6:$J$200,Q11) -> 0 | O11: =K11-N11 -> 0 | Q11: =IF(LEFT(A11,4)="Estr","REV","LPU")&"|"&B11 -> REV|2.2
A12: Estrutural REV_04 | B12: 2.3 | C12: Mão de obra especializada para montagem e desmontagem | D12: vb | E12: 1 | F12: 3200 | G12: =E12*F12 -> 3200 | H12: 6 | I12: =IF(H12=0,"Indireto / imposto",IFERROR(INDEX(CRONOGRAMA!$D$5:$D$32,MATCH(H12,CRONOGRAMA!$A$5:$A$32,0)),"nº inexistente")) -> Escoramento provisório sob a treliça (P2/P3 e vão P3–P4); macaco só para encunhar | K12: =G12*N(J12) -> 0 | L12: =G12-K12 -> 3200 | N12: =SUMIFS(COMPRAS!$G$6:$G$500,COMPRAS!$D$6:$D$500,Q12,COMPRAS!$J$6:$J$500,"<>Cancelado")+SUMIFS(LOCACOES!$I$6:$I$200,LOCACOES!$J$6:$J$200,Q12) -> 0 | O12: =K12-N12 -> 0 | Q12: =IF(LEFT(A12,4)="Estr","REV","LPU")&"|"&B12 -> REV|2.3
A13: Estrutural REV_04 | B13: 2.4 | C13: Monitoramento de recalque (marcos + leituras topográficas periódicas) durante a obra | D13: vb | E13: 1 | F13: 4500 | G13: =E13*F13 -> 4500 | H13: 2 | I13: =IF(H13=0,"Indireto / imposto",IFERROR(INDEX(CRONOGRAMA!$D$5:$D$32,MATCH(H13,CRONOGRAMA!$A$5:$A$32,0)),"nº inexistente")) -> Pontos de acompanhamento fotográfico, relatório "antes da obra" e marcos de nível | K13: =G13*N(J13) -> 0 | L13: =G13-K13 -> 4500 | N13: =SUMIFS(COMPRAS!$G$6:$G$500,COMPRAS!$D$6:$D$500,Q13,COMPRAS!$J$6:$J$500,"<>Cancelado")+SUMIFS(LOCACOES!$I$6:$I$200,LOCACOES!$J$6:$J$200,Q13) -> 0 | O13: =K13-N13 -> 0 | Q13: =IF(LEFT(A13,4)="Estr","REV","LPU")&"|"&B13 -> REV|2.4
A14: Estrutural REV_04 | B14: 3.1 | C14: Corte e abertura localizada do piso junto às bases de P2 e P3 | D14: vb | E14: 1 | F14: 8000 | G14: =E14*F14 -> 8000 | H14: 8 | I14: =IF(H14=0,"Indireto / imposto",IFERROR(INDEX(CRONOGRAMA!$D$5:$D$32,MATCH(H14,CRONOGRAMA!$A$5:$A$32,0)),"nº inexistente")) -> Estudo de solo: SPT e poço de inspeção com abertura localizada do piso | K14: =G14*N(J14) -> 0 | L14: =G14-K14 -> 8000 | N14: =SUMIFS(COMPRAS!$G$6:$G$500,COMPRAS!$D$6:$D$500,Q14,COMPRAS!$J$6:$J$500,"<>Cancelado")+SUMIFS(LOCACOES!$I$6:$I$200,LOCACOES!$J$6:$J$200,Q14) -> 0 | O14: =K14-N14 -> 0 | Q14: =IF(LEFT(A14,4)="Estr","REV","LPU")&"|"&B14 -> REV|3.1
A15: Estrutural REV_04 | B15: 3.2 | C15: Retirada de revestimento, contrapiso e laje de piso danificada | D15: vb | E15: 1 | F15: 6500 | G15: =E15*F15 -> 6500 | H15: 14 | I15: =IF(H15=0,"Indireto / imposto",IFERROR(INDEX(CRONOGRAMA!$D$5:$D$32,MATCH(H15,CRONOGRAMA!$A$5:$A$32,0)),"nº inexistente")) -> Demolição do piso (revestimento, contrapiso e laje) + descarte com CTR | K15: =G15*N(J15) -> 0 | L15: =G15-K15 -> 6500 | N15: =SUMIFS(COMPRAS!$G$6:$G$500,COMPRAS!$D$6:$D$500,Q15,COMPRAS!$J$6:$J$500,"<>Cancelado")+SUMIFS(LOCACOES!$I$6:$I$200,LOCACOES!$J$6:$J$200,Q15) -> 0 | O15: =K15-N15 -> 0 | Q15: =IF(LEFT(A15,4)="Estr","REV","LPU")&"|"&B15 -> REV|3.2
A16: Estrutural REV_04 | B16: 3.3 | C16: Carga, transporte e descarte de entulho (com CTR) | D16: vb | E16: 1 | F16: 4500 | G16: =E16*F16 -> 4500 | H16: 14 | I16: =IF(H16=0,"Indireto / imposto",IFERROR(INDEX(CRONOGRAMA!$D$5:$D$32,MATCH(H16,CRONOGRAMA!$A$5:$A$32,0)),"nº inexistente")) -> Demolição do piso (revestimento, contrapiso e laje) + descarte com CTR | K16: =G16*N(J16) -> 0 | L16: =G16-K16 -> 4500 | N16: =SUMIFS(COMPRAS!$G$6:$G$500,COMPRAS!$D$6:$D$500,Q16,COMPRAS!$J$6:$J$500,"<>Cancelado")+SUMIFS(LOCACOES!$I$6:$I$200,LOCACOES!$J$6:$J$200,Q16) -> 0 | O16: =K16-N16 -> 0 | Q16: =IF(LEFT(A16,4)="Estr","REV","LPU")&"|"&B16 -> REV|3.3
... A44: Estrutural REV_04 | B44: 9.3 | C44: Outros custos operacionais (hospedagem/alimentação equipe – Macaé) | D44: vb | E44: 1 | F44: 9000 | G44: =E44*F44 -> 9000 | H44: 0 | I44: =IF(H44=0,"Indireto / imposto",IFERROR(INDEX(CRONOGRAMA!$D$5:$D$32,MATCH(H44,CRONOGRAMA!$A$5:$A$32,0)),"nº inexistente")) -> Indireto / imposto | K44: =G44*N(J44) -> 0 | L44: =G44-K44 -> 9000 | N44: =SUMIFS(COMPRAS!$G$6:$G$500,COMPRAS!$D$6:$D$500,Q44,COMPRAS!$J$6:$J$500,"<>Cancelado")+SUMIFS(LOCACOES!$I$6:$I$200,LOCACOES!$J$6:$J$200,Q44) -> 0 | O44: =K44-N44 -> 0 | Q44: =IF(LEFT(A44,4)="Estr","REV","LPU")&"|"&B44 -> REV|9.3
A45: Estrutural REV_04 | B45: 9.4 | C45: Alíquota de imposto sobre os serviços (base = itens 1.1 a 9.3) | D45: % | E45: 0.17 | F45: =SUM(G5:G44) -> 250400 | G45: =E45*F45 -> 42568 | H45: 0 | I45: =IF(H45=0,"Indireto / imposto",IFERROR(INDEX(CRONOGRAMA!$D$5:$D$32,MATCH(H45,CRONOGRAMA!$A$5:$A$32,0)),"nº inexistente")) -> Indireto / imposto | K45: =G45*N(J45) -> 0 | L45: =G45-K45 -> 42568 | N45: =SUMIFS(COMPRAS!$G$6:$G$500,COMPRAS!$D$6:$D$500,Q45,COMPRAS!$J$6:$J$500,"<>Cancelado")+SUMIFS(LOCACOES!$I$6:$I$200,LOCACOES!$J$6:$J$200,Q45) -> 0 | O45: =K45-N45 -> 0 | Q45: =IF(LEFT(A45,4)="Estr","REV","LPU")&"|"&B45 -> REV|9.4
A46: Reforma light LPU | B46: 1.4 | C46: LAUDO TÉCNICO ESTRUTURAL | D46: unit. | E46: 2 | F46: 2000 | G46: =E46*F46 -> 4000 | H46: 9 | I46: =IF(H46=0,"Indireto / imposto",IFERROR(INDEX(CRONOGRAMA!$D$5:$D$32,MATCH(H46,CRONOGRAMA!$A$5:$A$32,0)),"nº inexistente")) -> Projeto estrutural de reforço (treliça, apoios e fundações) + ART | K46: =G46*N(J46) -> 0 | L46: =G46-K46 -> 4000 | N46: =SUMIFS(COMPRAS!$G$6:$G$500,COMPRAS!$D$6:$D$500,Q46,COMPRAS!$J$6:$J$500,"<>Cancelado")+SUMIFS(LOCACOES!$I$6:$I$200,LOCACOES!$J$6:$J$200,Q46) -> 0 | O46: =K46-N46 -> 0 | Q46: =IF(LEFT(A46,4)="Estr","REV","LPU")&"|"&B46 -> LPU|1.4
A47: Reforma light LPU | B47: 2.1 | C47: MOBILIZAÇÃO DE OBRA | D47: unit. | E47: 1 | F47: 500 | G47: =E47*F47 -> 500 | H47: 1 | I47: =IF(H47=0,"Indireto / imposto",IFERROR(INDEX(CRONOGRAMA!$D$5:$D$32,MATCH(H47,CRONOGRAMA!$A$5:$A$32,0)),"nº inexistente")) -> Reunião de partida no local: identificar P1–P4, treliça e faixa de piso afetada | K47: =G47*N(J47) -> 0 | L47: =G47-K47 -> 500 | N47: =SUMIFS(COMPRAS!$G$6:$G$500,COMPRAS!$D$6:$D$500,Q47,COMPRAS!$J$6:$J$500,"<>Cancelado")+SUMIFS(LOCACOES!$I$6:$I$200,LOCACOES!$J$6:$J$200,Q47) -> 0 | O47: =K47-N47 -> 0 | Q47: =IF(LEFT(A47,4)="Estr","REV","LPU")&"|"&B47 -> LPU|2.1
A48: Reforma light LPU | B48: 2.2 | C48: DESMOBILIZAÇÃO DE OBRA | D48: unit. | E48: 1 | F48: 400 | G48: =E48*F48 -> 400 | H48: 1 | I48: =IF(H48=0,"Indireto / imposto",IFERROR(INDEX(CRONOGRAMA!$D$5:$D$32,MATCH(H48,CRONOGRAMA!$A$5:$A$32,0)),"nº inexistente")) -> Reunião de partida no local: identificar P1–P4, treliça e faixa de piso afetada | K48: =G48*N(J48) -> 0 | L48: =G48-K48 -> 400 | N48: =SUMIFS(COMPRAS!$G$6:$G$500,COMPRAS!$D$6:$D$500,Q48,COMPRAS!$J$6:$J$500,"<>Cancelado")+SUMIFS(LOCACOES!$I$6:$I$200,LOCACOES!$J$6:$J$200,Q48) -> 0 | O48: =K48-N48 -> 0 | Q48: =IF(LEFT(A48,4)="Estr","REV","LPU")&"|"&B48 -> LPU|2.2
A49: Reforma light LPU | B49: 2.3 | C49: DESLOCAMENTO DE EQUIPE - SOMENTE ACIMA DE 50 KM DA BASE. | D49: km | E49: 500 | F49: 2.5 | G49: =E49*F49 -> 1250 | H49: 1 | I49: =IF(H49=0,"Indireto / imposto",IFERROR(INDEX(CRONOGRAMA!$D$5:$D$32,MATCH(H49,CRONOGRAMA!$A$5:$A$32,0)),"nº inexistente")) -> Reunião de partida no local: identificar P1–P4, treliça e faixa de piso afetada | K49: =G49*N(J49) -> 0 | L49: =G49-K49 -> 1250 | N49: =SUMIFS(COMPRAS!$G$6:$G$500,COMPRAS!$D$6:$D$500,Q49,COMPRAS!$J$6:$J$500,"<>Cancelado")+SUMIFS(LOCACOES!$I$6:$I$200,LOCACOES!$J$6:$J$200,Q49) -> 0 | O49: =K49-N49 -> 0 | Q49: =IF(LEFT(A49,4)="Estr","REV","LPU")&"|"&B49 -> LPU|2.3
A50: Reforma light LPU | B50: 3.40 | C50: LOCAÇÃO DE ANDAIME METÁLICO TUBULAR DE ENCAIXE, TIPO DE TORRE, COM LARGURA DE 1 ATÉ 1,5 M E ALTURA DE *1,00* M, INCLUSIVE MONTAGEM | D50: M²/MÊS | E50: 25 | F50: 33.72 | G50: =E50*F50 -> 843 | H50: 25 | I50: =IF(H50=0,"Indireto / imposto",IFERROR(INDEX(CRONOGRAMA!$D$5:$D$32,MATCH(H50,CRONOGRAMA!$A$5:$A$32,0)),"nº inexistente")) -> Forro mineral (250 m²) e abertura de luminárias | K50: =G50*N(J50) -> 0 | L50: =G50-K50 -> 843 | N50: =SUMIFS(COMPRAS!$G$6:$G$500,COMPRAS!$D$6:$D$500,Q50,COMPRAS!$J$6:$J$500,"<>Cancelado")+SUMIFS(LOCACOES!$I$6:$I$200,LOCACOES!$J$6:$J$200,Q50) -> 0 | O50: =K50-N50 -> 0 | Q50: =IF(LEFT(A50,4)="Estr","REV","LPU")&"|"&B50 -> LPU|3.40
A51: Reforma light LPU | B51: 4.6 | C51: PINTURA - FACHADA | D51: m² | E51: 30 | F51: 26.4 | G51: =E51*F51 -> 792 | H51: 28 | I51: =IF(H51=0,"Indireto / imposto",IFERROR(INDEX(CRONOGRAMA!$D$5:$D$32,MATCH(H51,CRONOGRAMA!$A$5:$A$32,0)),"nº inexistente")) -> Fachada: fixação de vidros e pintura | K51: =G51*N(J51) -> 0 | L51: =G51-K51 -> 792 | N51: =SUMIFS(COMPRAS!$G$6:$G$500,COMPRAS!$D$6:$D$500,Q51,COMPRAS!$J$6:$J$500,"<>Cancelado")+SUMIFS(LOCACOES!$I$6:$I$200,LOCACOES!$J$6:$J$200,Q51) -> 0 | O51: =K51-N51 -> 0 | Q51: =IF(LEFT(A51,4)="Estr","REV","LPU")&"|"&B51 -> LPU|4.6
A52: Reforma light LPU | B52: 5.1 | C52: DEMOLIÇÃO DE FORRO DE ESTUQUE OU GESSO EM PLACAS (COM BOTA FORA E TRANSPORTE) | D52: m² | E52: 250 | F52: 4.23 | G52: =E52*F52 -> 1057.5 | H52: 21 | I52: =IF(H52=0,"Indireto / imposto",IFERROR(INDEX(CRONOGRAMA!$D$5:$D$32,MATCH(H52,CRONOGRAMA!$A$5:$A$32,0)),"nº inexistente")) -> Demolição de forro (250 m²) e drywall (100 m²) | K52: =G52*N(J52) -> 0 | L52: =G52-K52 -> 1057.5 | N52: =SUMIFS(COMPRAS!$G$6:$G$500,COMPRAS!$D$6:$D$500,Q52,COMPRAS!$J$6:$J$500,"<>Cancelado")+SUMIFS(LOCACOES!$I$6:$I$200,LOCACOES!$J$6:$J$200,Q52) -> 0 | O52: =K52-N52 -> 0 | Q52: =IF(LEFT(A52,4)="Estr","REV","LPU")&"|"&B52 -> LPU|5.1
A53: Reforma light LPU | B53: 5.22 | C53: DEMOLIÇÃO DE PAREDES EM DRYWALL E DIVISÓRIAS (COM BOTA FORA E TRANSPORTE) | D53: m² | E53: 100 | F53: 10.65 | G53: =E53*F53 -> 1065 | H53: 21 | I53: =IF(H53=0,"Indireto / imposto",IFERROR(INDEX(CRONOGRAMA!$D$5:$D$32,MATCH(H53,CRONOGRAMA!$A$5:$A$32,0)),"nº inexistente")) -> Demolição de forro (250 m²) e drywall (100 m²) | K53: =G53*N(J53) -> 0 | L53: =G53-K53 -> 1065 | N53: =SUMIFS(COMPRAS!$G$6:$G$500,COMPRAS!$D$6:$D$500,Q53,COMPRAS!$J$6:$J$500,"<>Cancelado")+SUMIFS(LOCACOES!$I$6:$I$200,LOCACOES!$J$6:$J$200,Q53) -> 0 | O53: =K53-N53 -> 0 | Q53: =IF(LEFT(A53,4)="Estr","REV","LPU")&"|"&B53 -> LPU|5.22
A54: Reforma light LPU | B54: 5.32 | C54: DESMONTAGEM DE MOBILIÁRIO | D54: m² | E54: 250 | F54: 10 | G54: =E54*F54 -> 2500 | H54: 4 | I54: =IF(H54=0,"Indireto / imposto",IFERROR(INDEX(CRONOGRAMA!$D$5:$D$32,MATCH(H54,CRONOGRAMA!$A$5:$A$32,0)),"nº inexistente")) -> Remover produtos, virar o balcão e mudar o mobiliário da área afetada | K54: =G54*N(J54) -> 0 | L54: =G54-K54 -> 2500 | N54: =SUMIFS(COMPRAS!$G$6:$G$500,COMPRAS!$D$6:$D$500,Q54,COMPRAS!$J$6:$J$500,"<>Cancelado")+SUMIFS(LOCACOES!$I$6:$I$200,LOCACOES!$J$6:$J$200,Q54) -> 0 | O54: =K54-N54 -> 0 | Q54: =IF(LEFT(A54,4)="Estr","REV","LPU")&"|"&B54 -> LPU|5.32
A55: Reforma light LPU | B55: 5.33 | C55: RETIRADA DE LOUÇAS E METAIS - CONSIDERANDO 2 PROFISSIONAIS | D55: diária | E55: 1 | F55: 424.76 | G55: =E55*F55 -> 424.76 | H55: 13 | I55: =IF(H55=0,"Indireto / imposto",IFERROR(INDEX(CRONOGRAMA!$D$5:$D$32,MATCH(H55,CRONOGRAMA!$A$5:$A$32,0)),"nº inexistente")) -> Desmobilização do banheiro | K55: =G55*N(J55) -> 0 | L55: =G55-K55 -> 424.76 | N55: =SUMIFS(COMPRAS!$G$6:$G$500,COMPRAS!$D$6:$D$500,Q55,COMPRAS!$J$6:$J$500,"<>Cancelado")+SUMIFS(LOCACOES!$I$6:$I$200,LOCACOES!$J$6:$J$200,Q55) -> 0 | O55: =K55-N55 -> 0 | Q55: =IF(LEFT(A55,4)="Estr","REV","LPU")&"|"&B55 -> LPU|5.33
A56: Reforma light LPU | B56: 5.34 | C56: RETIRADA DE APARELHOS SANITÁRIOS | D56: unit. | E56: 1 | F56: 13.92 | G56: =E56*F56 -> 13.92 | H56: 13 | I56: =IF(H56=0,"Indireto / imposto",IFERROR(INDEX(CRONOGRAMA!$D$5:$D$32,MATCH(H56,CRONOGRAMA!$A$5:$A$32,0)),"nº inexistente")) -> Desmobilização do banheiro | K56: =G56*N(J56) -> 0 | L56: =G56-K56 -> 13.92 | N56: =SUMIFS(COMPRAS!$G$6:$G$500,COMPRAS!$D$6:$D$500,Q56,COMPRAS!$J$6:$J$500,"<>Cancelado")+SUMIFS(LOCACOES!$I$6:$I$200,LOCACOES!$J$6:$J$200,Q56) -> 0 | O56: =K56-N56 -> 0 | Q56: =IF(LEFT(A56,4)="Estr","REV","LPU")&"|"&B56 -> LPU|5.34
A57: Reforma light LPU | B57: 5.41 | C57: RETIRADA DE PISOS DE MADEIRA, CERÂMICO, PORCELANATO, VINÍLICO, FORMICA COM BOTA FORA | D57: m² | E57: 200 | F57: 13 | G57: =E57*F57 -> 2600 | H57: 14 | I57: =IF(H57=0,"Indireto / imposto",IFERROR(INDEX(CRONOGRAMA!$D$5:$D$32,MATCH(H57,CRONOGRAMA!$A$5:$A$32,0)),"nº inexistente")) -> Demolição do piso (revestimento, contrapiso e laje) + descarte com CTR | K57: =G57*N(J57) -> 0 | L57: =G57-K57 -> 2600 | N57: =SUMIFS(COMPRAS!$G$6:$G$500,COMPRAS!$D$6:$D$500,Q57,COMPRAS!$J$6:$J$500,"<>Cancelado")+SUMIFS(LOCACOES!$I$6:$I$200,LOCACOES!$J$6:$J$200,Q57) -> 0 | O57: =K57-N57 -> 0 | Q57: =IF(LEFT(A57,4)="Estr","REV","LPU")&"|"&B57 -> LPU|5.41
... A110: Reforma light LPU | B110: S/N-2 | C110: FORNECIMENTO E INSTALAÇÃO DE FECHADURA ELETRONICA | D110: unit. | E110: 1 | F110: 850 | G110: =E110*F110 -> 850 | H110: 26 | I110: =IF(H110=0,"Indireto / imposto",IFERROR(INDEX(CRONOGRAMA!$D$5:$D$32,MATCH(H110,CRONOGRAMA!$A$5:$A$32,0)),"nº inexistente")) -> Portas, molas, grelhas, guia de porta de enrolar e fechadura | K110: =G110*N(J110) -> 0 | L110: =G110-K110 -> 850 | N110: =SUMIFS(COMPRAS!$G$6:$G$500,COMPRAS!$D$6:$D$500,Q110,COMPRAS!$J$6:$J$500,"<>Cancelado")+SUMIFS(LOCACOES!$I$6:$I$200,LOCACOES!$J$6:$J$200,Q110) -> 0 | O110: =K110-N110 -> 0 | Q110: =IF(LEFT(A110,4)="Estr","REV","LPU")&"|"&B110 -> LPU|S/N-2
C112: TOTAL | G112: =SUM(G5:G110) -> 506340.41 | K112: =SUM(K5:K110) -> 0 | L112: =SUM(L5:L110) -> 506340.41 | M112: =SUM(M5:M110) -> 0 | N112: =SUM(N5:N110) -> 0 | O112: =SUM(O5:O110) -> 0

Sheet CONFLITOS
A1: Sobreposição de escopo – REV_04 x LPU
A2: Mesmo serviço nos dois pedidos = risco de glosa ou cobrança em duplicidade. Definir a fronteira por área antes da 1ª medição.
A4: Tema | B4: Itens REV_04 | C4: Valor REV_04 | D4: Itens LPU | E4: Valor LPU | F4: Risco | G4: Ação recomendada | H4: Decisão registrada | I4: Status | J4: Exposição (menor valor)
A5: Isolamento da área | B5: 1.1 | C5: =SUMIFS(ORCAMENTO!$G$5:$G$200,ORCAMENTO!$Q$5:$Q$200,"REV|1.1") -> 9500 | D5: S/N-1 | E5: =SUMIFS(ORCAMENTO!$G$5:$G$200,ORCAMENTO!$Q$5:$Q$200,"LPU|S/N-1") -> 7369.2 | F5: Malha lycra (LPU) e isolamento (REV_04) cobrem o mesmo fechamento. | G5: Separar: LPU para a loja inteira, REV_04 só para a faixa estrutural e o mezanino. | I5: Aberto | J5: =MIN(C5,E5) -> 7369.2
A6: Mobilização | B6: 1.2 | C6: =SUMIFS(ORCAMENTO!$G$5:$G$200,ORCAMENTO!$Q$5:$Q$200,"REV|1.2") -> 4500 | D6: 2.1, 2.2, 2.3 | E6: =SUMIFS(ORCAMENTO!$G$5:$G$200,ORCAMENTO!$Q$5:$Q$200,"LPU|2.1")+SUMIFS(ORCAMENTO!$G$5:$G$200,ORCAMENTO!$Q$5:$Q$200,"LPU|2.2")+SUMIFS(ORCAMENTO!$G$5:$G$200,ORCAMENTO!$Q$5:$Q$200,"LPU|2.3") -> 2150 | F6: Duas mobilizações para a mesma obra. | G6: Manter uma só por pedido e declarar qual cobre o deslocamento para Macaé. | I6: Aberto | J6: =MIN(C6,E6) -> 2150
A7: Mobiliário | B7: 1.4 | C7: =SUMIFS(ORCAMENTO!$G$5:$G$200,ORCAMENTO!$Q$5:$Q$200,"REV|1.4") -> 2500 | D7: 5.32, 6.11, 6.19 | E7: =SUMIFS(ORCAMENTO!$G$5:$G$200,ORCAMENTO!$Q$5:$Q$200,"LPU|5.32")+SUMIFS(ORCAMENTO!$G$5:$G$200,ORCAMENTO!$Q$5:$Q$200,"LPU|6.11")+SUMIFS(ORCAMENTO!$G$5:$G$200,ORCAMENTO!$Q$5:$Q$200,"LPU|6.19") -> 5080 | F7: Remanejamento cobrado nos dois pedidos. | G7: Vincular cada pedido a ambientes distintos no layout. | I7: Aberto | J7: =MIN(C7,E7) -> 2500
A8: Demolição de piso | B8: 3.2 | C8: =SUMIFS(ORCAMENTO!$G$5:$G$200,ORCAMENTO!$Q$5:$Q$200,"REV|3.2") -> 6500 | D8: 5.41 | E8: =SUMIFS(ORCAMENTO!$G$5:$G$200,ORCAMENTO!$Q$5:$Q$200,"LPU|5.41") -> 2600 | F8: Retirada de revestimento em área sobreposta. | G8: REV_04 = faixa da divisa esquerda (fig. B do laudo); LPU = restante. | I8: Aberto | J8: =MIN(C8,E8) -> 2600
A9: Entulho e caçambas | B9: 3.3 | C9: =SUMIFS(ORCAMENTO!$G$5:$G$200,ORCAMENTO!$Q$5:$Q$200,"REV|3.3") -> 4500 | D9: 5.47, 6.16 | E9: =SUMIFS(ORCAMENTO!$G$5:$G$200,ORCAMENTO!$Q$5:$Q$200,"LPU|5.47")+SUMIFS(ORCAMENTO!$G$5:$G$200,ORCAMENTO!$Q$5:$Q$200,"LPU|6.16") -> 8615.86 | F9: Descarte cobrado em dobro. | G9: Ratear caçambas por frente e registrar CTR por pedido. | I9: Aberto | J9: =MIN(C9,E9) -> 4500
A10: Porcelanato do salão | B10: 7.2 | C10: =SUMIFS(ORCAMENTO!$G$5:$G$200,ORCAMENTO!$Q$5:$Q$200,"REV|7.2") -> 5000 | D10: 18.4 | E10: =SUMIFS(ORCAMENTO!$G$5:$G$200,ORCAMENTO!$Q$5:$Q$200,"LPU|18.4") -> 11000 | F10: Mão de obra de assentamento nos dois pedidos. | G10: REV_04 só na faixa reconstruída; LPU no restante. Conferir m² com o layout. | I10: Aberto | J10: =MIN(C10,E10) -> 5000
A11: Projeto, ART e laudo | B11: 4.5, 4.6 | C11: =SUMIFS(ORCAMENTO!$G$5:$G$200,ORCAMENTO!$Q$5:$Q$200,"REV|4.5")+SUMIFS(ORCAMENTO!$G$5:$G$200,ORCAMENTO!$Q$5:$Q$200,"REV|4.6") -> 11000 | D11: 1.4, 41.4 | E11: =SUMIFS(ORCAMENTO!$G$5:$G$200,ORCAMENTO!$Q$5:$Q$200,"LPU|1.4")+SUMIFS(ORCAMENTO!$G$5:$G$200,ORCAMENTO!$Q$5:$Q$200,"LPU|41.4") -> 5293.44 | F11: LPU já prevê 2 laudos estruturais e ART de projeto. | G11: Confirmar se o laudo EGUTI foi pago pela LPU 1.4 e não repetir ART. | I11: Aberto | J11: =MIN(C11,E11) -> 5293.44
A12: Limpeza final | B12: 7.4 | C12: =SUMIFS(ORCAMENTO!$G$5:$G$200,ORCAMENTO!$Q$5:$Q$200,"REV|7.4") -> 6000 | D12: 38.1 | E12: =SUMIFS(ORCAMENTO!$G$5:$G$200,ORCAMENTO!$Q$5:$Q$200,"LPU|38.1") -> 7656 | F12: Limpeza na entrega duplicada. | G12: Manter só a LPU 38.1, com m² corrigido. | I12: Aberto | J12: =MIN(C12,E12) -> 6000
A13: Retirada de vidro (interno à LPU) | B13: — | C13: 0 | D13: 5.42, 48.68 | E13: =SUMIFS(ORCAMENTO!$G$5:$G$200,ORCAMENTO!$Q$5:$Q$200,"LPU|5.42")+SUMIFS(ORCAMENTO!$G$5:$G$200,ORCAMENTO!$Q$5:$Q$200,"LPU|48.68") -> 2100 | F13: Dois itens da LPU para retirar vidro (20 m² cada). | G13: Confirmar com a DPSP se são vidros diferentes; senão excluir um. | I13: Aberto | J13: =MIN(SUMIFS(ORCAMENTO!$G$5:$G$200,ORCAMENTO!$Q$5:$Q$200,"LPU|5.42"),SUMIFS(ORCAMENTO!$G$5:$G$200,ORCAMENTO!$Q$5:$Q$200,"LPU|48.68")) -> 500
A15: Total | C15: =SUM(C5:C13) -> 49500 | E15: =SUM(E5:E13) -> 51864.5 | J15: =SUM(J5:J13) -> 35912.64

Sheet RDO
A1: Registro Diário de Obra (RDO)
A2: Encarregado registra ao fim do expediente; engenheiro valida; COP envia o informe diário. Linha cinza = exemplo (não é somada).
A4: Data | B4: Dia | C4: Clima | D4: Ativ. nº | E4: Atividade | F4: Serviços executados | G4: Qtd. | H4: Un. | I4: Efetivo | J4: Empresa / equipe | K4: Equipamentos | L4: Link das fotos | M4: Ocorrências / impedimentos | N4: Programação para amanhã | O4: Registrado por | P4: Validado por | Q4: Enviado?
A5: EXEMPLO | B5: sex | C5: Sol | D5: 6 | E5: Escoramento provisório… | F5: Montagem de 4 escoras sob a treliça entre P3 e P4 | G5: 4 | H5: un | I5: 5 | J5: Equipe MANFAC | K5: Escoras metálicas, macaco 10 t | L5: pasta/2026-10-30 | M5: Sem impedimentos | N5: Concluir escoramento da viga principal | O5: Encarregado | P5: Engenheiro | Q5: Sim
B6: =IF(A6="","",CHOOSE(WEEKDAY(A6,2),"seg","ter","qua","qui","sex","sáb","dom")) | E6: =IF(D6="","",IFERROR(INDEX(CRONOGRAMA!$D$5:$D$32,MATCH(D6,CRONOGRAMA!$A$5:$A$32,0)),"nº inexistente"))
B7: =IF(A7="","",CHOOSE(WEEKDAY(A7,2),"seg","ter","qua","qui","sex","sáb","dom")) | E7: =IF(D7="","",IFERROR(INDEX(CRONOGRAMA!$D$5:$D$32,MATCH(D7,CRONOGRAMA!$A$5:$A$32,0)),"nº inexistente"))
B8: =IF(A8="","",CHOOSE(WEEKDAY(A8,2),"seg","ter","qua","qui","sex","sáb","dom")) | E8: =IF(D8="","",IFERROR(INDEX(CRONOGRAMA!$D$5:$D$32,MATCH(D8,CRONOGRAMA!$A$5:$A$32,0)),"nº inexistente"))
B9: =IF(A9="","",CHOOSE(WEEKDAY(A9,2),"seg","ter","qua","qui","sex","sáb","dom")) | E9: =IF(D9="","",IFERROR(INDEX(CRONOGRAMA!$D$5:$D$32,MATCH(D9,CRONOGRAMA!$A$5:$A$32,0)),"nº inexistente"))
B10: =IF(A10="","",CHOOSE(WEEKDAY(A10,2),"seg","ter","qua","qui","sex","sáb","dom")) | E10: =IF(D10="","",IFERROR(INDEX(CRONOGRAMA!$D$5:$D$32,MATCH(D10,CRONOGRAMA!$A$5:$A$32,0)),"nº inexistente"))
B11: =IF(A11="","",CHOOSE(WEEKDAY(A11,2),"seg","ter","qua","qui","sex","sáb","dom")) | E11: =IF(D11="","",IFERROR(INDEX(CRONOGRAMA!$D$5:$D$32,MATCH(D11,CRONOGRAMA!$A$5:$A$32,0)),"nº inexistente"))
B12: =IF(A12="","",CHOOSE(WEEKDAY(A12,2),"seg","ter","qua","qui","sex","sáb","dom")) | E12: =IF(D12="","",IFERROR(INDEX(CRONOGRAMA!$D$5:$D$32,MATCH(D12,CRONOGRAMA!$A$5:$A$32,0)),"nº inexistente"))
B13: =IF(A13="","",CHOOSE(WEEKDAY(A13,2),"seg","ter","qua","qui","sex","sáb","dom")) | E13: =IF(D13="","",IFERROR(INDEX(CRONOGRAMA!$D$5:$D$32,MATCH(D13,CRONOGRAMA!$A$5:$A$32,0)),"nº inexistente"))
B14: =IF(A14="","",CHOOSE(WEEKDAY(A14,2),"seg","ter","qua","qui","sex","sáb","dom")) | E14: =IF(D14="","",IFERROR(INDEX(CRONOGRAMA!$D$5:$D$32,MATCH(D14,CRONOGRAMA!$A$5:$A$32,0)),"nº inexistente"))
B15: =IF(A15="","",CHOOSE(WEEKDAY(A15,2),"seg","ter","qua","qui","sex","sáb","dom")) | E15: =IF(D15="","",IFERROR(INDEX(CRONOGRAMA!$D$5:$D$32,MATCH(D15,CRONOGRAMA!$A$5:$A$32,0)),"nº inexistente"))
B16: =IF(A16="","",CHOOSE(WEEKDAY(A16,2),"seg","ter","qua","qui","sex","sáb","dom")) | E16: =IF(D16="","",IFERROR(INDEX(CRONOGRAMA!$D$5:$D$32,MATCH(D16,CRONOGRAMA!$A$5:$A$32,0)),"nº inexistente"))
B17: =IF(A17="","",CHOOSE(WEEKDAY(A17,2),"seg","ter","qua","qui","sex","sáb","dom")) | E17: =IF(D17="","",IFERROR(INDEX(CRONOGRAMA!$D$5:$D$32,MATCH(D17,CRONOGRAMA!$A$5:$A$32,0)),"nº inexistente"))
... B300: =IF(A300="","",CHOOSE(WEEKDAY(A300,2),"seg","ter","qua","qui","sex","sáb","dom")) | E300: =IF(D300="","",IFERROR(INDEX(CRONOGRAMA!$D$5:$D$32,MATCH(D300,CRONOGRAMA!$A$5:$A$32,0)),"nº inexistente"))

Sheet COMPRAS
A1: Compras e materiais
A2: Cada pedido vinculado a um item do orçamento (chave) para custo real por item. Cancelados não entram no custo.
A4: Data pedido | B4: Fornecedor | C4: Descrição | D4: Chave orçamento | E4: Atividade | F4: Qtd. | G4: Valor total (R$) | H4: Previsão entrega | I4: Entrega real | J4: Status | K4: NF | L4: Situação | M4: Observação
A5: EXEMPLO | B5: Fornecedor X | C5: Brita graduada 10 m³ | D5: REV|5.2 | E5: Remoção do solo… | F5: 10 | G5: 1800 | H5: dd/mm | J5: Pedido emitido | L5: No prazo
E6: =IF(D6="","",IFERROR(INDEX(ORCAMENTO!$I$5:$I$200,MATCH(D6,ORCAMENTO!$Q$5:$Q$200,0)),"chave inexistente")) | L6: =IF(A6="","",IF(J6="Entregue","Entregue",IF(J6="Cancelado","Cancelado",IF(AND(H6<>"",DataRef>H6),"ATRASADA","No prazo"))))
E7: =IF(D7="","",IFERROR(INDEX(ORCAMENTO!$I$5:$I$200,MATCH(D7,ORCAMENTO!$Q$5:$Q$200,0)),"chave inexistente")) | L7: =IF(A7="","",IF(J7="Entregue","Entregue",IF(J7="Cancelado","Cancelado",IF(AND(H7<>"",DataRef>H7),"ATRASADA","No prazo"))))
E8: =IF(D8="","",IFERROR(INDEX(ORCAMENTO!$I$5:$I$200,MATCH(D8,ORCAMENTO!$Q$5:$Q$200,0)),"chave inexistente")) | L8: =IF(A8="","",IF(J8="Entregue","Entregue",IF(J8="Cancelado","Cancelado",IF(AND(H8<>"",DataRef>H8),"ATRASADA","No prazo"))))
E9: =IF(D9="","",IFERROR(INDEX(ORCAMENTO!$I$5:$I$200,MATCH(D9,ORCAMENTO!$Q$5:$Q$200,0)),"chave inexistente")) | L9: =IF(A9="","",IF(J9="Entregue","Entregue",IF(J9="Cancelado","Cancelado",IF(AND(H9<>"",DataRef>H9),"ATRASADA","No prazo"))))
E10: =IF(D10="","",IFERROR(INDEX(ORCAMENTO!$I$5:$I$200,MATCH(D10,ORCAMENTO!$Q$5:$Q$200,0)),"chave inexistente")) | L10: =IF(A10="","",IF(J10="Entregue","Entregue",IF(J10="Cancelado","Cancelado",IF(AND(H10<>"",DataRef>H10),"ATRASADA","No prazo"))))
E11: =IF(D11="","",IFERROR(INDEX(ORCAMENTO!$I$5:$I$200,MATCH(D11,ORCAMENTO!$Q$5:$Q$200,0)),"chave inexistente")) | L11: =IF(A11="","",IF(J11="Entregue","Entregue",IF(J11="Cancelado","Cancelado",IF(AND(H11<>"",DataRef>H11),"ATRASADA","No prazo"))))
E12: =IF(D12="","",IFERROR(INDEX(ORCAMENTO!$I$5:$I$200,MATCH(D12,ORCAMENTO!$Q$5:$Q$200,0)),"chave inexistente")) | L12: =IF(A12="","",IF(J12="Entregue","Entregue",IF(J12="Cancelado","Cancelado",IF(AND(H12<>"",DataRef>H12),"ATRASADA","No prazo"))))
E13: =IF(D13="","",IFERROR(INDEX(ORCAMENTO!$I$5:$I$200,MATCH(D13,ORCAMENTO!$Q$5:$Q$200,0)),"chave inexistente")) | L13: =IF(A13="","",IF(J13="Entregue","Entregue",IF(J13="Cancelado","Cancelado",IF(AND(H13<>"",DataRef>H13),"ATRASADA","No prazo"))))
E14: =IF(D14="","",IFERROR(INDEX(ORCAMENTO!$I$5:$I$200,MATCH(D14,ORCAMENTO!$Q$5:$Q$200,0)),"chave inexistente")) | L14: =IF(A14="","",IF(J14="Entregue","Entregue",IF(J14="Cancelado","Cancelado",IF(AND(H14<>"",DataRef>H14),"ATRASADA","No prazo"))))
E15: =IF(D15="","",IFERROR(INDEX(ORCAMENTO!$I$5:$I$200,MATCH(D15,ORCAMENTO!$Q$5:$Q$200,0)),"chave inexistente")) | L15: =IF(A15="","",IF(J15="Entregue","Entregue",IF(J15="Cancelado","Cancelado",IF(AND(H15<>"",DataRef>H15),"ATRASADA","No prazo"))))
E16: =IF(D16="","",IFERROR(INDEX(ORCAMENTO!$I$5:$I$200,MATCH(D16,ORCAMENTO!$Q$5:$Q$200,0)),"chave inexistente")) | L16: =IF(A16="","",IF(J16="Entregue","Entregue",IF(J16="Cancelado","Cancelado",IF(AND(H16<>"",DataRef>H16),"ATRASADA","No prazo"))))
E17: =IF(D17="","",IFERROR(INDEX(ORCAMENTO!$I$5:$I$200,MATCH(D17,ORCAMENTO!$Q$5:$Q$200,0)),"chave inexistente")) | L17: =IF(A17="","",IF(J17="Entregue","Entregue",IF(J17="Cancelado","Cancelado",IF(AND(H17<>"",DataRef>H17),"ATRASADA","No prazo"))))
... E500: =IF(D500="","",IFERROR(INDEX(ORCAMENTO!$I$5:$I$200,MATCH(D500,ORCAMENTO!$Q$5:$Q$200,0)),"chave inexistente")) | L500: =IF(A500="","",IF(J500="Entregue","Entregue",IF(J500="Cancelado","Cancelado",IF(AND(H500<>"",DataRef>H500),"ATRASADA","No prazo"))))

Sheet LOCACOES
A1: Locações de equipamentos
A2: Custo corre por dia até a devolução. Situação avisa quando o prazo contratado vence.
A4: Equipamento | B4: Fornecedor | C4: Qtd. | D4: Início | E4: Fim previsto | F4: Devolução real | G4: R$/dia por un. | H4: Dias cobrados | I4: Custo acumulado | J4: Chave orçamento | K4: Situação | L4: Observação
A5: EXEMPLO – escoras metálicas | B5: Locadora X | C5: 12 | D5: dd/mm | E5: dd/mm | G5: 3.5 | H5: 30 | I5: 1260 | J5: REV|2.2 | K5: Ativa | L5: Manter até o reforço (nº 15)
H6: =IF(D6="","",IF(F6<>"",F6,DataRef)-D6+1) | I6: =IF(D6="","",N(C6)*N(G6)*H6) | K6: =IF(D6="","",IF(F6<>"","Devolvido",IF(AND(E6<>"",DataRef>E6),"VENCIDA – renovar ou devolver","Ativa")))
H7: =IF(D7="","",IF(F7<>"",F7,DataRef)-D7+1) | I7: =IF(D7="","",N(C7)*N(G7)*H7) | K7: =IF(D7="","",IF(F7<>"","Devolvido",IF(AND(E7<>"",DataRef>E7),"VENCIDA – renovar ou devolver","Ativa")))
H8: =IF(D8="","",IF(F8<>"",F8,DataRef)-D8+1) | I8: =IF(D8="","",N(C8)*N(G8)*H8) | K8: =IF(D8="","",IF(F8<>"","Devolvido",IF(AND(E8<>"",DataRef>E8),"VENCIDA – renovar ou devolver","Ativa")))
H9: =IF(D9="","",IF(F9<>"",F9,DataRef)-D9+1) | I9: =IF(D9="","",N(C9)*N(G9)*H9) | K9: =IF(D9="","",IF(F9<>"","Devolvido",IF(AND(E9<>"",DataRef>E9),"VENCIDA – renovar ou devolver","Ativa")))
H10: =IF(D10="","",IF(F10<>"",F10,DataRef)-D10+1) | I10: =IF(D10="","",N(C10)*N(G10)*H10) | K10: =IF(D10="","",IF(F10<>"","Devolvido",IF(AND(E10<>"",DataRef>E10),"VENCIDA – renovar ou devolver","Ativa")))
H11: =IF(D11="","",IF(F11<>"",F11,DataRef)-D11+1) | I11: =IF(D11="","",N(C11)*N(G11)*H11) | K11: =IF(D11="","",IF(F11<>"","Devolvido",IF(AND(E11<>"",DataRef>E11),"VENCIDA – renovar ou devolver","Ativa")))
H12: =IF(D12="","",IF(F12<>"",F12,DataRef)-D12+1) | I12: =IF(D12="","",N(C12)*N(G12)*H12) | K12: =IF(D12="","",IF(F12<>"","Devolvido",IF(AND(E12<>"",DataRef>E12),"VENCIDA – renovar ou devolver","Ativa")))
H13: =IF(D13="","",IF(F13<>"",F13,DataRef)-D13+1) | I13: =IF(D13="","",N(C13)*N(G13)*H13) | K13: =IF(D13="","",IF(F13<>"","Devolvido",IF(AND(E13<>"",DataRef>E13),"VENCIDA – renovar ou devolver","Ativa")))
H14: =IF(D14="","",IF(F14<>"",F14,DataRef)-D14+1) | I14: =IF(D14="","",N(C14)*N(G14)*H14) | K14: =IF(D14="","",IF(F14<>"","Devolvido",IF(AND(E14<>"",DataRef>E14),"VENCIDA – renovar ou devolver","Ativa")))
H15: =IF(D15="","",IF(F15<>"",F15,DataRef)-D15+1) | I15: =IF(D15="","",N(C15)*N(G15)*H15) | K15: =IF(D15="","",IF(F15<>"","Devolvido",IF(AND(E15<>"",DataRef>E15),"VENCIDA – renovar ou devolver","Ativa")))
H16: =IF(D16="","",IF(F16<>"",F16,DataRef)-D16+1) | I16: =IF(D16="","",N(C16)*N(G16)*H16) | K16: =IF(D16="","",IF(F16<>"","Devolvido",IF(AND(E16<>"",DataRef>E16),"VENCIDA – renovar ou devolver","Ativa")))
H17: =IF(D17="","",IF(F17<>"",F17,DataRef)-D17+1) | I17: =IF(D17="","",N(C17)*N(G17)*H17) | K17: =IF(D17="","",IF(F17<>"","Devolvido",IF(AND(E17<>"",DataRef>E17),"VENCIDA – renovar ou devolver","Ativa")))
... H200: =IF(D200="","",IF(F200<>"",F200,DataRef)-D200+1) | I200: =IF(D200="","",N(C200)*N(G200)*H200) | K200: =IF(D200="","",IF(F200<>"","Devolvido",IF(AND(E200<>"",DataRef>E200),"VENCIDA – renovar ou devolver","Ativa")))

Sheet MEDICOES
A1: Medições e faturamento
A2: Do envio da medição ao recebimento. Situação calculada pelas datas preenchidas.
A4: Nº | B4: Pedido | C4: Período de | D4: Período até | E4: Valor medido (R$) | F4: Data envio | G4: Aprovador DPSP | H4: Data aprovação | I4: Nº OS / pedido | J4: NF nº | K4: Data NF | L4: Valor NF (R$) | M4: Recebido em | N4: Situação | O4: Dias em aprovação
A5: EX | B5: Estrutural REV_04 | C5: dd/mm | D5: dd/mm | E5: 25000 | F5: dd/mm | G5: Analista DPSP | N5: Em aprovação | O5: 4
N6: =IF(A6="","",IF(M6<>"","Recebida",IF(K6<>"","Faturada – a receber",IF(H6<>"","Aprovada – faturar",IF(F6<>"","Em aprovação","Em preparação"))))) | O6: =IF(AND(F6<>"",H6=""),DataRef-F6,"")
N7: =IF(A7="","",IF(M7<>"","Recebida",IF(K7<>"","Faturada – a receber",IF(H7<>"","Aprovada – faturar",IF(F7<>"","Em aprovação","Em preparação"))))) | O7: =IF(AND(F7<>"",H7=""),DataRef-F7,"")
N8: =IF(A8="","",IF(M8<>"","Recebida",IF(K8<>"","Faturada – a receber",IF(H8<>"","Aprovada – faturar",IF(F8<>"","Em aprovação","Em preparação"))))) | O8: =IF(AND(F8<>"",H8=""),DataRef-F8,"")
N9: =IF(A9="","",IF(M9<>"","Recebida",IF(K9<>"","Faturada – a receber",IF(H9<>"","Aprovada – faturar",IF(F9<>"","Em aprovação","Em preparação"))))) | O9: =IF(AND(F9<>"",H9=""),DataRef-F9,"")
N10: =IF(A10="","",IF(M10<>"","Recebida",IF(K10<>"","Faturada – a receber",IF(H10<>"","Aprovada – faturar",IF(F10<>"","Em aprovação","Em preparação"))))) | O10: =IF(AND(F10<>"",H10=""),DataRef-F10,"")
N11: =IF(A11="","",IF(M11<>"","Recebida",IF(K11<>"","Faturada – a receber",IF(H11<>"","Aprovada – faturar",IF(F11<>"","Em aprovação","Em preparação"))))) | O11: =IF(AND(F11<>"",H11=""),DataRef-F11,"")
N12: =IF(A12="","",IF(M12<>"","Recebida",IF(K12<>"","Faturada – a receber",IF(H12<>"","Aprovada – faturar",IF(F12<>"","Em aprovação","Em preparação"))))) | O12: =IF(AND(F12<>"",H12=""),DataRef-F12,"")
N13: =IF(A13="","",IF(M13<>"","Recebida",IF(K13<>"","Faturada – a receber",IF(H13<>"","Aprovada – faturar",IF(F13<>"","Em aprovação","Em preparação"))))) | O13: =IF(AND(F13<>"",H13=""),DataRef-F13,"")
N14: =IF(A14="","",IF(M14<>"","Recebida",IF(K14<>"","Faturada – a receber",IF(H14<>"","Aprovada – faturar",IF(F14<>"","Em aprovação","Em preparação"))))) | O14: =IF(AND(F14<>"",H14=""),DataRef-F14,"")
N15: =IF(A15="","",IF(M15<>"","Recebida",IF(K15<>"","Faturada – a receber",IF(H15<>"","Aprovada – faturar",IF(F15<>"","Em aprovação","Em preparação"))))) | O15: =IF(AND(F15<>"",H15=""),DataRef-F15,"")
N16: =IF(A16="","",IF(M16<>"","Recebida",IF(K16<>"","Faturada – a receber",IF(H16<>"","Aprovada – faturar",IF(F16<>"","Em aprovação","Em preparação"))))) | O16: =IF(AND(F16<>"",H16=""),DataRef-F16,"")
N17: =IF(A17="","",IF(M17<>"","Recebida",IF(K17<>"","Faturada – a receber",IF(H17<>"","Aprovada – faturar",IF(F17<>"","Em aprovação","Em preparação"))))) | O17: =IF(AND(F17<>"",H17=""),DataRef-F17,"")
... N200: =IF(A200="","",IF(M200<>"","Recebida",IF(K200<>"","Faturada – a receber",IF(H200<>"","Aprovada – faturar",IF(F200<>"","Em aprovação","Em preparação"))))) | O200: =IF(AND(F200<>"",H200=""),DataRef-F200,"")

Sheet PENDENCIAS
A1: Pendências, riscos e decisões do cliente
A2: Inclui as travas da obra e os pontos levantados na conferência de laudo, layout, REV_04 e LPU (23/10/2026).
A4: Nº | B4: Tipo | C4: Descrição | D4: Impacto | E4: Ativ. nº | F4: Responsável | G4: Cliente? | H4: Abertura | I4: Prazo | J4: Status | K4: Fechamento | L4: Dias em aberto | M4: Situação | N4: aux | O4: No relatório do cliente?
A5: 1 | B5: Trava | C5: Escorar a viga principal (treliça P3–P4, 10,00 m) conforme definição do RT | D5: Bloqueia todas as demolições (nº 11 a 14 e 21) | E5: 6 | F5: Engenheiro de obras | G5: Não | H5: 46318 | J5: Aberta | L5: =IF(OR(C5="",H5=""),"",IF(K5<>"",K5,DataRef)-H5) -> 0 | M5: =IF(C5="","",IF(J5="Concluída","Concluída",IF(AND(I5<>"",DataRef>I5),"VENCIDA","Em aberto"))) -> Em aberto | N5: =IF(AND(G5="Sim",O5<>"Não",J5<>"Concluída",C5<>""),COUNTIFS($G$5:G5,"Sim",$O$5:O5,"<>Não",$J$5:J5,"<>Concluída",$C$5:C5,"<>"),"")
A6: 2 | B6: Risco | C6: Iniciar leituras periódicas dos marcos de nível para confirmar que o escoramento estabilizou os recalques | D6: Recalque ativo = risco de colapso localizado (laudo 7.4.a) | E6: 2 | F6: Engenheiro de obras | G6: Não | H6: 46318 | J6: Aberta | L6: =IF(OR(C6="",H6=""),"",IF(K6<>"",K6,DataRef)-H6) -> 0 | M6: =IF(C6="","",IF(J6="Concluída","Concluída",IF(AND(I6<>"",DataRef>I6),"VENCIDA","Em aberto"))) -> Em aberto | N6: =IF(AND(G6="Sim",O6<>"Não",J6<>"Concluída",C6<>""),COUNTIFS($G$5:G6,"Sim",$O$5:O6,"<>Não",$J$5:J6,"<>Concluída",$C$5:C6,"<>"),"")
A7: 3 | B7: Decisão do cliente | C7: Autorização formal de baixa de patrimônio para descarte de gôndolas e geladeira | D7: Sem autorização, nº 12 não pode ser executada | E7: 12 | F7: Analista de obras / COP | G7: Sim | H7: 46318 | J7: Aberta | L7: =IF(OR(C7="",H7=""),"",IF(K7<>"",K7,DataRef)-H7) -> 0 | M7: =IF(C7="","",IF(J7="Concluída","Concluída",IF(AND(I7<>"",DataRef>I7),"VENCIDA","Em aberto"))) -> Em aberto | N7: =IF(AND(G7="Sim",O7<>"Não",J7<>"Concluída",C7<>""),COUNTIFS($G$5:G7,"Sim",$O$5:O7,"<>Não",$J$5:J7,"<>Concluída",$C$5:C7,"<>"),"") -> 1 | O7: Sim
A8: 4 | B8: Decisão do cliente | C8: Confirmar se o vidro a retirar é de fachada; se for, obter autorização do Best Center / condomínio | D8: Bloqueia nº 11 e 28 | E8: 11 | F8: Analista de obras / COP | G8: Sim | H8: 46318 | J8: Aberta | L8: =IF(OR(C8="",H8=""),"",IF(K8<>"",K8,DataRef)-H8) -> 0 | M8: =IF(C8="","",IF(J8="Concluída","Concluída",IF(AND(I8<>"",DataRef>I8),"VENCIDA","Em aberto"))) -> Em aberto | N8: =IF(AND(G8="Sim",O8<>"Não",J8<>"Concluída",C8<>""),COUNTIFS($G$5:G8,"Sim",$O$5:O8,"<>Não",$J$5:J8,"<>Concluída",$C$5:C8,"<>"),"") -> 2 | O8: Sim
A9: 5 | B9: Decisão do cliente | C9: Registrar formalmente que Mall, estacionamento e drenagem do centro comercial estão fora do escopo | D9: Evita assumir passivo classificado como alto risco (laudo 7.2) | F9: GO | G9: Sim | H9: 46318 | J9: Aberta | L9: =IF(OR(C9="",H9=""),"",IF(K9<>"",K9,DataRef)-H9) -> 0 | M9: =IF(C9="","",IF(J9="Concluída","Concluída",IF(AND(I9<>"",DataRef>I9),"VENCIDA","Em aberto"))) -> Em aberto | N9: =IF(AND(G9="Sim",O9<>"Não",J9<>"Concluída",C9<>""),COUNTIFS($G$5:G9,"Sim",$O$5:O9,"<>Não",$J$5:J9,"<>Concluída",$C$5:C9,"<>"),"") -> 3 | O9: Sim
A10: 6 | B10: Decisão do cliente | C10: Definir qual banheiro será desmobilizado: térreo ou WC do mezanino | D10: Define escopo de nº 13 e 18 | E10: 13 | F10: Engenheiro de obras | G10: Sim | H10: 46318 | J10: Aberta | L10: =IF(OR(C10="",H10=""),"",IF(K10<>"",K10,DataRef)-H10) -> 0 | M10: =IF(C10="","",IF(J10="Concluída","Concluída",IF(AND(I10<>"",DataRef>I10),"VENCIDA","Em aberto"))) -> Em aberto | N10: =IF(AND(G10="Sim",O10<>"Não",J10<>"Concluída",C10<>""),COUNTIFS($G$5:G10,"Sim",$O$5:O10,"<>Não",$J$5:J10,"<>Concluída",$C$5:C10,"<>"),"") -> 4 | O10: Sim
A11: 7 | B11: Escopo | C11: Precificar itens sem cobertura: descarte de gôndolas/geladeira, reexecução do banheiro e relatório fotográfico. Retirada de louças e de vidro já consta na LPU (5.33, 5.34, 5.42, 48.68) | D11: Execução sem receita | F11: Orçamentos | G11: Não | H11: 46318 | J11: Aberta | L11: =IF(OR(C11="",H11=""),"",IF(K11<>"",K11,DataRef)-H11) -> 0 | M11: =IF(C11="","",IF(J11="Concluída","Concluída",IF(AND(I11<>"",DataRef>I11),"VENCIDA","Em aberto"))) -> Em aberto | N11: =IF(AND(G11="Sim",O11<>"Não",J11<>"Concluída",C11<>""),COUNTIFS($G$5:G11,"Sim",$O$5:O11,"<>Não",$J$5:J11,"<>Concluída",$C$5:C11,"<>"),"")
A12: 8 | B12: Conflito | C12: Resolver as 9 sobreposições REV_04 x LPU (aba CONFLITOS) e registrar a fronteira por área | D12: Glosa na medição ou cobrança em duplicidade | F12: GO | G12: Sim | H12: 46318 | J12: Aberta | L12: =IF(OR(C12="",H12=""),"",IF(K12<>"",K12,DataRef)-H12) -> 0 | M12: =IF(C12="","",IF(J12="Concluída","Concluída",IF(AND(I12<>"",DataRef>I12),"VENCIDA","Em aberto"))) -> Em aberto | N12: =IF(AND(G12="Sim",O12<>"Não",J12<>"Concluída",C12<>""),COUNTIFS($G$5:G12,"Sim",$O$5:O12,"<>Não",$J$5:J12,"<>Concluída",$C$5:C12,"<>"),"") | O12: Não
A13: 9 | B13: Quantitativo | C13: LPU 38.1 – limpeza final de 1.200 m², contra ≈ 224 m² somando as áreas do layout aprovado | D13: Glosa provável de ≈ R$ 6.200 na conferência DPSP | E13: 20 | F13: Orçamentos | G13: Não | H13: 46318 | J13: Aberta | L13: =IF(OR(C13="",H13=""),"",IF(K13<>"",K13,DataRef)-H13) -> 0 | M13: =IF(C13="","",IF(J13="Concluída","Concluída",IF(AND(I13<>"",DataRef>I13),"VENCIDA","Em aberto"))) -> Em aberto | N13: =IF(AND(G13="Sim",O13<>"Não",J13<>"Concluída",C13<>""),COUNTIFS($G$5:G13,"Sim",$O$5:O13,"<>Não",$J$5:J13,"<>Concluída",$C$5:C13,"<>"),"")
A14: 10 | B14: Quantitativo | C14: LPU 18.4 + 18.6 – porcelanato de 250 m², contra 142,93 m² de área de vendas + medicamentos no térreo | D14: Compra ou medição acima do real | E14: 18 | F14: Orçamentos | G14: Não | H14: 46318 | J14: Aberta | L14: =IF(OR(C14="",H14=""),"",IF(K14<>"",K14,DataRef)-H14) -> 0 | M14: =IF(C14="","",IF(J14="Concluída","Concluída",IF(AND(I14<>"",DataRef>I14),"VENCIDA","Em aberto"))) -> Em aberto | N14: =IF(AND(G14="Sim",O14<>"Não",J14<>"Concluída",C14<>""),COUNTIFS($G$5:G14,"Sim",$O$5:O14,"<>Não",$J$5:J14,"<>Concluída",$C$5:C14,"<>"),"")
A15: 11 | B15: Quantitativo | C15: LPU 21.1 – fundo preparador em 400 m², enquanto massa e pintura somam 260 m² | D15: Ajustar quantidade ou justificar | E15: 27 | F15: Orçamentos | G15: Não | H15: 46318 | J15: Aberta | L15: =IF(OR(C15="",H15=""),"",IF(K15<>"",K15,DataRef)-H15) -> 0 | M15: =IF(C15="","",IF(J15="Concluída","Concluída",IF(AND(I15<>"",DataRef>I15),"VENCIDA","Em aberto"))) -> Em aberto | N15: =IF(AND(G15="Sim",O15<>"Não",J15<>"Concluída",C15<>""),COUNTIFS($G$5:G15,"Sim",$O$5:O15,"<>Não",$J$5:J15,"<>Concluída",$C$5:C15,"<>"),"")
A16: 12 | B16: Comercial | C16: Definir com a DPSP o critério do imposto no REV_04: 17% por fora (R$ 42.568) ou por dentro (≈ R$ 51.287) | D16: Diferença de ≈ R$ 8.700 na margem | F16: Financeiro | G16: Sim | H16: 46318 | J16: Aberta | L16: =IF(OR(C16="",H16=""),"",IF(K16<>"",K16,DataRef)-H16) -> 0 | M16: =IF(C16="","",IF(J16="Concluída","Concluída",IF(AND(I16<>"",DataRef>I16),"VENCIDA","Em aberto"))) -> Em aberto | N16: =IF(AND(G16="Sim",O16<>"Não",J16<>"Concluída",C16<>""),COUNTIFS($G$5:G16,"Sim",$O$5:O16,"<>Não",$J$5:J16,"<>Concluída",$C$5:C16,"<>"),"") | O16: Não
A17: 13 | B17: Comercial | C17: Recolocar no REV_04 a observação do item 7.2: "mesmo padrão existente, sujeito a disponibilidade" | D17: Proteção caso o porcelanato esteja fora de linha | E17: 18 | F17: Orçamentos | G17: Não | H17: 46318 | J17: Aberta | L17: =IF(OR(C17="",H17=""),"",IF(K17<>"",K17,DataRef)-H17) -> 0 | M17: =IF(C17="","",IF(J17="Concluída","Concluída",IF(AND(I17<>"",DataRef>I17),"VENCIDA","Em aberto"))) -> Em aberto | N17: =IF(AND(G17="Sim",O17<>"Não",J17<>"Concluída",C17<>""),COUNTIFS($G$5:G17,"Sim",$O$5:O17,"<>Não",$J$5:J17,"<>Concluída",$C$5:C17,"<>"),"") | O17: Não
A18: 14 | B18: Dados | C18: LPU: dois itens sem código (malha lycra e fechadura) e fechadura sem parcela de mão de obra (regra 40/60) | D18: Questionamento na conferência DPSP | F18: Orçamentos | G18: Não | H18: 46318 | J18: Aberta | L18: =IF(OR(C18="",H18=""),"",IF(K18<>"",K18,DataRef)-H18) -> 0 | M18: =IF(C18="","",IF(J18="Concluída","Concluída",IF(AND(I18<>"",DataRef>I18),"VENCIDA","Em aberto"))) -> Em aberto | N18: =IF(AND(G18="Sim",O18<>"Não",J18<>"Concluída",C18<>""),COUNTIFS($G$5:G18,"Sim",$O$5:O18,"<>Não",$J$5:J18,"<>Concluída",$C$5:C18,"<>"),"")
A19: =IF(C19="","",ROW()-4) | L19: =IF(OR(C19="",H19=""),"",IF(K19<>"",K19,DataRef)-H19) | M19: =IF(C19="","",IF(J19="Concluída","Concluída",IF(AND(I19<>"",DataRef>I19),"VENCIDA","Em aberto"))) | N19: =IF(AND(G19="Sim",O19<>"Não",J19<>"Concluída",C19<>""),COUNTIFS($G$5:G19,"Sim",$O$5:O19,"<>Não",$J$5:J19,"<>Concluída",$C$5:C19,"<>"),"")
A20: =IF(C20="","",ROW()-4) | L20: =IF(OR(C20="",H20=""),"",IF(K20<>"",K20,DataRef)-H20) | M20: =IF(C20="","",IF(J20="Concluída","Concluída",IF(AND(I20<>"",DataRef>I20),"VENCIDA","Em aberto"))) | N20: =IF(AND(G20="Sim",O20<>"Não",J20<>"Concluída",C20<>""),COUNTIFS($G$5:G20,"Sim",$O$5:O20,"<>Não",$J$5:J20,"<>Concluída",$C$5:C20,"<>"),"")
A21: =IF(C21="","",ROW()-4) | L21: =IF(OR(C21="",H21=""),"",IF(K21<>"",K21,DataRef)-H21) | M21: =IF(C21="","",IF(J21="Concluída","Concluída",IF(AND(I21<>"",DataRef>I21),"VENCIDA","Em aberto"))) | N21: =IF(AND(G21="Sim",O21<>"Não",J21<>"Concluída",C21<>""),COUNTIFS($G$5:G21,"Sim",$O$5:O21,"<>Não",$J$5:J21,"<>Concluída",$C$5:C21,"<>"),"")
A22: =IF(C22="","",ROW()-4) | L22: =IF(OR(C22="",H22=""),"",IF(K22<>"",K22,DataRef)-H22) | M22: =IF(C22="","",IF(J22="Concluída","Concluída",IF(AND(I22<>"",DataRef>I22),"VENCIDA","Em aberto"))) | N22: =IF(AND(G22="Sim",O22<>"Não",J22<>"Concluída",C22<>""),COUNTIFS($G$5:G22,"Sim",$O$5:O22,"<>Não",$J$5:J22,"<>Concluída",$C$5:C22,"<>"),"")
A23: =IF(C23="","",ROW()-4) | L23: =IF(OR(C23="",H23=""),"",IF(K23<>"",K23,DataRef)-H23) | M23: =IF(C23="","",IF(J23="Concluída","Concluída",IF(AND(I23<>"",DataRef>I23),"VENCIDA","Em aberto"))) | N23: =IF(AND(G23="Sim",O23<>"Não",J23<>"Concluída",C23<>""),COUNTIFS($G$5:G23,"Sim",$O$5:O23,"<>Não",$J$5:J23,"<>Concluída",$C$5:C23,"<>"),"")
A24: =IF(C24="","",ROW()-4) | L24: =IF(OR(C24="",H24=""),"",IF(K24<>"",K24,DataRef)-H24) | M24: =IF(C24="","",IF(J24="Concluída","Concluída",IF(AND(I24<>"",DataRef>I24),"VENCIDA","Em aberto"))) | N24: =IF(AND(G24="Sim",O24<>"Não",J24<>"Concluída",C24<>""),COUNTIFS($G$5:G24,"Sim",$O$5:O24,"<>Não",$J$5:J24,"<>Concluída",$C$5:C24,"<>"),"")
A25: =IF(C25="","",ROW()-4) | L25: =IF(OR(C25="",H25=""),"",IF(K25<>"",K25,DataRef)-H25) | M25: =IF(C25="","",IF(J25="Concluída","Concluída",IF(AND(I25<>"",DataRef>I25),"VENCIDA","Em aberto"))) | N25: =IF(AND(G25="Sim",O25<>"Não",J25<>"Concluída",C25<>""),COUNTIFS($G$5:G25,"Sim",$O$5:O25,"<>Não",$J$5:J25,"<>Concluída",$C$5:C25,"<>"),"")
A26: =IF(C26="","",ROW()-4) | L26: =IF(OR(C26="",H26=""),"",IF(K26<>"",K26,DataRef)-H26) | M26: =IF(C26="","",IF(J26="Concluída","Concluída",IF(AND(I26<>"",DataRef>I26),"VENCIDA","Em aberto"))) | N26: =IF(AND(G26="Sim",O26<>"Não",J26<>"Concluída",C26<>""),COUNTIFS($G$5:G26,"Sim",$O$5:O26,"<>Não",$J$5:J26,"<>Concluída",$C$5:C26,"<>"),"")
A27: =IF(C27="","",ROW()-4) | L27: =IF(OR(C27="",H27=""),"",IF(K27<>"",K27,DataRef)-H27) | M27: =IF(C27="","",IF(J27="Concluída","Concluída",IF(AND(I27<>"",DataRef>I27),"VENCIDA","Em aberto"))) | N27: =IF(AND(G27="Sim",O27<>"Não",J27<>"Concluída",C27<>""),COUNTIFS($G$5:G27,"Sim",$O$5:O27,"<>Não",$J$5:J27,"<>Concluída",$C$5:C27,"<>"),"")
A28: =IF(C28="","",ROW()-4) | L28: =IF(OR(C28="",H28=""),"",IF(K28<>"",K28,DataRef)-H28) | M28: =IF(C28="","",IF(J28="Concluída","Concluída",IF(AND(I28<>"",DataRef>I28),"VENCIDA","Em aberto"))) | N28: =IF(AND(G28="Sim",O28<>"Não",J28<>"Concluída",C28<>""),COUNTIFS($G$5:G28,"Sim",$O$5:O28,"<>Não",$J$5:J28,"<>Concluída",$C$5:C28,"<>"),"")
A29: =IF(C29="","",ROW()-4) | L29: =IF(OR(C29="",H29=""),"",IF(K29<>"",K29,DataRef)-H29) | M29: =IF(C29="","",IF(J29="Concluída","Concluída",IF(AND(I29<>"",DataRef>I29),"VENCIDA","Em aberto"))) | N29: =IF(AND(G29="Sim",O29<>"Não",J29<>"Concluída",C29<>""),COUNTIFS($G$5:G29,"Sim",$O$5:O29,"<>Não",$J$5:J29,"<>Concluída",$C$5:C29,"<>"),"")
A30: =IF(C30="","",ROW()-4) | L30: =IF(OR(C30="",H30=""),"",IF(K30<>"",K30,DataRef)-H30) | M30: =IF(C30="","",IF(J30="Concluída","Concluída",IF(AND(I30<>"",DataRef>I30),"VENCIDA","Em aberto"))) | N30: =IF(AND(G30="Sim",O30<>"Não",J30<>"Concluída",C30<>""),COUNTIFS($G$5:G30,"Sim",$O$5:O30,"<>Não",$J$5:J30,"<>Concluída",$C$5:C30,"<>"),"")
... A200: =IF(C200="","",ROW()-4) | L200: =IF(OR(C200="",H200=""),"",IF(K200<>"",K200,DataRef)-H200) | M200: =IF(C200="","",IF(J200="Concluída","Concluída",IF(AND(I200<>"",DataRef>I200),"VENCIDA","Em aberto"))) | N200: =IF(AND(G200="Sim",O200<>"Não",J200<>"Concluída",C200<>""),COUNTIFS($G$5:G200,"Sim",$O$5:O200,"<>Não",$J$5:J200,"<>Concluída",$C$5:C200,"<>"),"")

Sheet COMUNICACAO
A1: Comunicação com o cliente – programação e histórico de envios
A2: Datas previstas geradas pelo cronograma. Preencha data real, destinatários e link do PDF a cada envio. Risco relevante = comunicação imediata (incluir linha).
A4: Nº | B4: Tipo | C4: Referência | D4: Responsável | E4: Data prevista | F4: Data real | G4: Destinatários | H4: Link do PDF | I4: Confirmação | J4: Comentários do cliente | K4: Respostas pendentes | L4: Situação
A5: 1 | B5: Relatório semanal | C5: Semana 1 | D5: Engenharia (atualiza) / GO (valida) | E5: =IF(DataBase+MOD(5-WEEKDAY(DataBase,2),7)+0>FimObra+7,"",WORKDAY(DataBase+MOD(5-WEEKDAY(DataBase,2),7)+0+1,-1,Feriados)) -> 46325 | L5: =IF(E5="","",IF(F5<>"",IF(F5>E5,"Enviado com atraso","Enviado no prazo"),IF(DataRef>E5,"ATRASADO",IF(DataRef=E5,"ENVIAR HOJE","Programado")))) -> Programado
A6: 2 | B6: Relatório semanal | C6: Semana 2 | D6: Engenharia (atualiza) / GO (valida) | E6: =IF(DataBase+MOD(5-WEEKDAY(DataBase,2),7)+7>FimObra+7,"",WORKDAY(DataBase+MOD(5-WEEKDAY(DataBase,2),7)+7+1,-1,Feriados)) -> 46332 | L6: =IF(E6="","",IF(F6<>"",IF(F6>E6,"Enviado com atraso","Enviado no prazo"),IF(DataRef>E6,"ATRASADO",IF(DataRef=E6,"ENVIAR HOJE","Programado")))) -> Programado
A7: 3 | B7: Relatório semanal | C7: Semana 3 | D7: Engenharia (atualiza) / GO (valida) | E7: =IF(DataBase+MOD(5-WEEKDAY(DataBase,2),7)+14>FimObra+7,"",WORKDAY(DataBase+MOD(5-WEEKDAY(DataBase,2),7)+14+1,-1,Feriados)) -> 46339 | L7: =IF(E7="","",IF(F7<>"",IF(F7>E7,"Enviado com atraso","Enviado no prazo"),IF(DataRef>E7,"ATRASADO",IF(DataRef=E7,"ENVIAR HOJE","Programado")))) -> Programado
A8: 4 | B8: Relatório semanal | C8: Semana 4 | D8: Engenharia (atualiza) / GO (valida) | E8: =IF(DataBase+MOD(5-WEEKDAY(DataBase,2),7)+21>FimObra+7,"",WORKDAY(DataBase+MOD(5-WEEKDAY(DataBase,2),7)+21+1,-1,Feriados)) -> 46345 | L8: =IF(E8="","",IF(F8<>"",IF(F8>E8,"Enviado com atraso","Enviado no prazo"),IF(DataRef>E8,"ATRASADO",IF(DataRef=E8,"ENVIAR HOJE","Programado")))) -> Programado
A9: 5 | B9: Relatório semanal | C9: Semana 5 | D9: Engenharia (atualiza) / GO (valida) | E9: =IF(DataBase+MOD(5-WEEKDAY(DataBase,2),7)+28>FimObra+7,"",WORKDAY(DataBase+MOD(5-WEEKDAY(DataBase,2),7)+28+1,-1,Feriados)) -> 46353 | L9: =IF(E9="","",IF(F9<>"",IF(F9>E9,"Enviado com atraso","Enviado no prazo"),IF(DataRef>E9,"ATRASADO",IF(DataRef=E9,"ENVIAR HOJE","Programado")))) -> Programado
A10: 6 | B10: Relatório semanal | C10: Semana 6 | D10: Engenharia (atualiza) / GO (valida) | E10: =IF(DataBase+MOD(5-WEEKDAY(DataBase,2),7)+35>FimObra+7,"",WORKDAY(DataBase+MOD(5-WEEKDAY(DataBase,2),7)+35+1,-1,Feriados)) -> 46360 | L10: =IF(E10="","",IF(F10<>"",IF(F10>E10,"Enviado com atraso","Enviado no prazo"),IF(DataRef>E10,"ATRASADO",IF(DataRef=E10,"ENVIAR HOJE","Programado")))) -> Programado
A11: 7 | B11: Relatório semanal | C11: Semana 7 | D11: Engenharia (atualiza) / GO (valida) | E11: =IF(DataBase+MOD(5-WEEKDAY(DataBase,2),7)+42>FimObra+7,"",WORKDAY(DataBase+MOD(5-WEEKDAY(DataBase,2),7)+42+1,-1,Feriados)) -> 46367 | L11: =IF(E11="","",IF(F11<>"",IF(F11>E11,"Enviado com atraso","Enviado no prazo"),IF(DataRef>E11,"ATRASADO",IF(DataRef=E11,"ENVIAR HOJE","Programado")))) -> Programado
A12: 8 | B12: Relatório semanal | C12: Semana 8 | D12: Engenharia (atualiza) / GO (valida) | E12: =IF(DataBase+MOD(5-WEEKDAY(DataBase,2),7)+49>FimObra+7,"",WORKDAY(DataBase+MOD(5-WEEKDAY(DataBase,2),7)+49+1,-1,Feriados)) -> 46374 | L12: =IF(E12="","",IF(F12<>"",IF(F12>E12,"Enviado com atraso","Enviado no prazo"),IF(DataRef>E12,"ATRASADO",IF(DataRef=E12,"ENVIAR HOJE","Programado")))) -> Programado
A13: 9 | B13: Relatório semanal | C13: Semana 9 | D13: Engenharia (atualiza) / GO (valida) | E13: =IF(DataBase+MOD(5-WEEKDAY(DataBase,2),7)+56>FimObra+7,"",WORKDAY(DataBase+MOD(5-WEEKDAY(DataBase,2),7)+56+1,-1,Feriados)) -> 46380 | L13: =IF(E13="","",IF(F13<>"",IF(F13>E13,"Enviado com atraso","Enviado no prazo"),IF(DataRef>E13,"ATRASADO",IF(DataRef=E13,"ENVIAR HOJE","Programado")))) -> Programado
A14: 10 | B14: Relatório semanal | C14: Semana 10 | D14: Engenharia (atualiza) / GO (valida) | E14: =IF(DataBase+MOD(5-WEEKDAY(DataBase,2),7)+63>FimObra+7,"",WORKDAY(DataBase+MOD(5-WEEKDAY(DataBase,2),7)+63+1,-1,Feriados)) -> 46387 | L14: =IF(E14="","",IF(F14<>"",IF(F14>E14,"Enviado com atraso","Enviado no prazo"),IF(DataRef>E14,"ATRASADO",IF(DataRef=E14,"ENVIAR HOJE","Programado")))) -> Programado
A15: 11 | B15: Relatório semanal | C15: Semana 11 | D15: Engenharia (atualiza) / GO (valida) | E15: =IF(DataBase+MOD(5-WEEKDAY(DataBase,2),7)+70>FimObra+7,"",WORKDAY(DataBase+MOD(5-WEEKDAY(DataBase,2),7)+70+1,-1,Feriados)) -> 46395 | L15: =IF(E15="","",IF(F15<>"",IF(F15>E15,"Enviado com atraso","Enviado no prazo"),IF(DataRef>E15,"ATRASADO",IF(DataRef=E15,"ENVIAR HOJE","Programado")))) -> Programado
A16: 12 | B16: Relatório semanal | C16: Semana 12 | D16: Engenharia (atualiza) / GO (valida) | E16: =IF(DataBase+MOD(5-WEEKDAY(DataBase,2),7)+77>FimObra+7,"",WORKDAY(DataBase+MOD(5-WEEKDAY(DataBase,2),7)+77+1,-1,Feriados)) -> 46402 | L16: =IF(E16="","",IF(F16<>"",IF(F16>E16,"Enviado com atraso","Enviado no prazo"),IF(DataRef>E16,"ATRASADO",IF(DataRef=E16,"ENVIAR HOJE","Programado")))) -> Programado
A17: 13 | B17: Relatório semanal | C17: Semana 13 | D17: Engenharia (atualiza) / GO (valida) | E17: =IF(DataBase+MOD(5-WEEKDAY(DataBase,2),7)+84>FimObra+7,"",WORKDAY(DataBase+MOD(5-WEEKDAY(DataBase,2),7)+84+1,-1,Feriados)) -> 46409 | L17: =IF(E17="","",IF(F17<>"",IF(F17>E17,"Enviado com atraso","Enviado no prazo"),IF(DataRef>E17,"ATRASADO",IF(DataRef=E17,"ENVIAR HOJE","Programado")))) -> Programado
A18: 14 | B18: Relatório semanal | C18: Semana 14 | D18: Engenharia (atualiza) / GO (valida) | E18: =IF(DataBase+MOD(5-WEEKDAY(DataBase,2),7)+91>FimObra+7,"",WORKDAY(DataBase+MOD(5-WEEKDAY(DataBase,2),7)+91+1,-1,Feriados)) -> 46416 | L18: =IF(E18="","",IF(F18<>"",IF(F18>E18,"Enviado com atraso","Enviado no prazo"),IF(DataRef>E18,"ATRASADO",IF(DataRef=E18,"ENVIAR HOJE","Programado")))) -> Programado
A19: 15 | B19: Relatório semanal | C19: Semana 15 | D19: Engenharia (atualiza) / GO (valida) | E19: =IF(DataBase+MOD(5-WEEKDAY(DataBase,2),7)+98>FimObra+7,"",WORKDAY(DataBase+MOD(5-WEEKDAY(DataBase,2),7)+98+1,-1,Feriados)) | L19: =IF(E19="","",IF(F19<>"",IF(F19>E19,"Enviado com atraso","Enviado no prazo"),IF(DataRef>E19,"ATRASADO",IF(DataRef=E19,"ENVIAR HOJE","Programado"))))
A20: 16 | B20: Relatório semanal | C20: Semana 16 | D20: Engenharia (atualiza) / GO (valida) | E20: =IF(DataBase+MOD(5-WEEKDAY(DataBase,2),7)+105>FimObra+7,"",WORKDAY(DataBase+MOD(5-WEEKDAY(DataBase,2),7)+105+1,-1,Feriados)) | L20: =IF(E20="","",IF(F20<>"",IF(F20>E20,"Enviado com atraso","Enviado no prazo"),IF(DataRef>E20,"ATRASADO",IF(DataRef=E20,"ENVIAR HOJE","Programado"))))
A21: 17 | B21: Relatório mensal | C21: Mês 1 | D21: Engenharia + Financeiro / GO valida | E21: =IF(EOMONTH(DataBase,0)>EOMONTH(FimObra,0),"",WORKDAY(EOMONTH(DataBase,0)+1,-1,Feriados)) -> 46325 | L21: =IF(E21="","",IF(F21<>"",IF(F21>E21,"Enviado com atraso","Enviado no prazo"),IF(DataRef>E21,"ATRASADO",IF(DataRef=E21,"ENVIAR HOJE","Programado")))) -> Programado
A22: 18 | B22: Relatório mensal | C22: Mês 2 | D22: Engenharia + Financeiro / GO valida | E22: =IF(EOMONTH(DataBase,1)>EOMONTH(FimObra,0),"",WORKDAY(EOMONTH(DataBase,1)+1,-1,Feriados)) -> 46356 | L22: =IF(E22="","",IF(F22<>"",IF(F22>E22,"Enviado com atraso","Enviado no prazo"),IF(DataRef>E22,"ATRASADO",IF(DataRef=E22,"ENVIAR HOJE","Programado")))) -> Programado
A23: 19 | B23: Relatório mensal | C23: Mês 3 | D23: Engenharia + Financeiro / GO valida | E23: =IF(EOMONTH(DataBase,2)>EOMONTH(FimObra,0),"",WORKDAY(EOMONTH(DataBase,2)+1,-1,Feriados)) -> 46387 | L23: =IF(E23="","",IF(F23<>"",IF(F23>E23,"Enviado com atraso","Enviado no prazo"),IF(DataRef>E23,"ATRASADO",IF(DataRef=E23,"ENVIAR HOJE","Programado")))) -> Programado
A24: 20 | B24: Relatório mensal | C24: Mês 4 | D24: Engenharia + Financeiro / GO valida | E24: =IF(EOMONTH(DataBase,3)>EOMONTH(FimObra,0),"",WORKDAY(EOMONTH(DataBase,3)+1,-1,Feriados)) -> 46416 | L24: =IF(E24="","",IF(F24<>"",IF(F24>E24,"Enviado com atraso","Enviado no prazo"),IF(DataRef>E24,"ATRASADO",IF(DataRef=E24,"ENVIAR HOJE","Programado")))) -> Programado
A25: 21 | B25: Relatório mensal | C25: Mês 5 | D25: Engenharia + Financeiro / GO valida | E25: =IF(EOMONTH(DataBase,4)>EOMONTH(FimObra,0),"",WORKDAY(EOMONTH(DataBase,4)+1,-1,Feriados)) | L25: =IF(E25="","",IF(F25<>"",IF(F25>E25,"Enviado com atraso","Enviado no prazo"),IF(DataRef>E25,"ATRASADO",IF(DataRef=E25,"ENVIAR HOJE","Programado"))))
A26: 22 | B26: Relatório de fase | C26: Conclusão da etapa 1 – Mobilização e isolamento | D26: Engenheiro de obras | E26: =_xlfn.MAXIFS(CRONOGRAMA!$K$5:$K$32,CRONOGRAMA!$C$5:$C$32,"1 – Mobilização e isolamento") -> 46329 | L26: =IF(E26="","",IF(F26<>"",IF(F26>E26,"Enviado com atraso","Enviado no prazo"),IF(DataRef>E26,"ATRASADO",IF(DataRef=E26,"ENVIAR HOJE","Programado")))) -> Programado
A27: 23 | B27: Relatório de fase | C27: Conclusão da etapa 2 – Estabilização | D27: Engenheiro de obras | E27: =_xlfn.MAXIFS(CRONOGRAMA!$K$5:$K$32,CRONOGRAMA!$C$5:$C$32,"2 – Estabilização") -> 46330 | L27: =IF(E27="","",IF(F27<>"",IF(F27>E27,"Enviado com atraso","Enviado no prazo"),IF(DataRef>E27,"ATRASADO",IF(DataRef=E27,"ENVIAR HOJE","Programado")))) -> Programado
A28: 24 | B28: Relatório de fase | C28: Conclusão da etapa 3 – Investigação e projeto | D28: Engenheiro de obras | E28: =_xlfn.MAXIFS(CRONOGRAMA!$K$5:$K$32,CRONOGRAMA!$C$5:$C$32,"3 – Investigação e projeto") -> 46359 | L28: =IF(E28="","",IF(F28<>"",IF(F28>E28,"Enviado com atraso","Enviado no prazo"),IF(DataRef>E28,"ATRASADO",IF(DataRef=E28,"ENVIAR HOJE","Programado")))) -> Programado
A29: 25 | B29: Relatório de fase | C29: Conclusão da etapa 4 – Desmobilização e demolição | D29: Engenheiro de obras | E29: =_xlfn.MAXIFS(CRONOGRAMA!$K$5:$K$32,CRONOGRAMA!$C$5:$C$32,"4 – Desmobilização e demolição") -> 46370 | L29: =IF(E29="","",IF(F29<>"",IF(F29>E29,"Enviado com atraso","Enviado no prazo"),IF(DataRef>E29,"ATRASADO",IF(DataRef=E29,"ENVIAR HOJE","Programado")))) -> Programado
A30: 26 | B30: Relatório de fase | C30: Conclusão da etapa 5 – Reforço e reconstrução | D30: Engenheiro de obras | E30: =_xlfn.MAXIFS(CRONOGRAMA!$K$5:$K$32,CRONOGRAMA!$C$5:$C$32,"5 – Reforço e reconstrução") -> 46412 | L30: =IF(E30="","",IF(F30<>"",IF(F30>E30,"Enviado com atraso","Enviado no prazo"),IF(DataRef>E30,"ATRASADO",IF(DataRef=E30,"ENVIAR HOJE","Programado")))) -> Programado
A31: 27 | B31: Relatório de fase | C31: Conclusão da etapa 6 – Acabamentos e entrega | D31: Engenheiro de obras | E31: =_xlfn.MAXIFS(CRONOGRAMA!$K$5:$K$32,CRONOGRAMA!$C$5:$C$32,"6 – Acabamentos e entrega") -> 46415 | L31: =IF(E31="","",IF(F31<>"",IF(F31>E31,"Enviado com atraso","Enviado no prazo"),IF(DataRef>E31,"ATRASADO",IF(DataRef=E31,"ENVIAR HOJE","Programado")))) -> Programado
A32: 28 | B32: Relatório de fase | C32: Conclusão da etapa R – Reforma light | D32: Engenheiro de obras | E32: =_xlfn.MAXIFS(CRONOGRAMA!$K$5:$K$32,CRONOGRAMA!$C$5:$C$32,"R – Reforma light") -> 46406 | L32: =IF(E32="","",IF(F32<>"",IF(F32>E32,"Enviado com atraso","Enviado no prazo"),IF(DataRef>E32,"ATRASADO",IF(DataRef=E32,"ENVIAR HOJE","Programado")))) -> Programado
A33: 29 | B33: Relatório de entrega | C33: Antes e depois, documentação e aceite final | D33: Engenheiro de obras / GO | E33: =FimObra -> 46415 | L33: =IF(E33="","",IF(F33<>"",IF(F33>E33,"Enviado com atraso","Enviado no prazo"),IF(DataRef>E33,"ATRASADO",IF(DataRef=E33,"ENVIAR HOJE","Programado")))) -> Programado
A34: 30 | B34: Informe diário | C34: RDO nº 1 | D34: Engenheiro valida / COP envia | E34: =IF(WORKDAY(DataBase-1,1,Feriados)>FimObra,"",WORKDAY(DataBase-1,1,Feriados)) -> 46321 | L34: =IF(E34="","",IF(F34<>"",IF(F34>E34,"Enviado com atraso","Enviado no prazo"),IF(DataRef>E34,"ATRASADO",IF(DataRef=E34,"ENVIAR HOJE","Programado")))) -> Programado
A35: 31 | B35: Informe diário | C35: RDO nº 2 | D35: Engenheiro valida / COP envia | E35: =IF(WORKDAY(DataBase-1,2,Feriados)>FimObra,"",WORKDAY(DataBase-1,2,Feriados)) -> 46322 | L35: =IF(E35="","",IF(F35<>"",IF(F35>E35,"Enviado com atraso","Enviado no prazo"),IF(DataRef>E35,"ATRASADO",IF(DataRef=E35,"ENVIAR HOJE","Programado")))) -> Programado
A36: 32 | B36: Informe diário | C36: RDO nº 3 | D36: Engenheiro valida / COP envia | E36: =IF(WORKDAY(DataBase-1,3,Feriados)>FimObra,"",WORKDAY(DataBase-1,3,Feriados)) -> 46323 | L36: =IF(E36="","",IF(F36<>"",IF(F36>E36,"Enviado com atraso","Enviado no prazo"),IF(DataRef>E36,"ATRASADO",IF(DataRef=E36,"ENVIAR HOJE","Programado")))) -> Programado
A37: 33 | B37: Informe diário | C37: RDO nº 4 | D37: Engenheiro valida / COP envia | E37: =IF(WORKDAY(DataBase-1,4,Feriados)>FimObra,"",WORKDAY(DataBase-1,4,Feriados)) -> 46324 | L37: =IF(E37="","",IF(F37<>"",IF(F37>E37,"Enviado com atraso","Enviado no prazo"),IF(DataRef>E37,"ATRASADO",IF(DataRef=E37,"ENVIAR HOJE","Programado")))) -> Programado
A38: 34 | B38: Informe diário | C38: RDO nº 5 | D38: Engenheiro valida / COP envia | E38: =IF(WORKDAY(DataBase-1,5,Feriados)>FimObra,"",WORKDAY(DataBase-1,5,Feriados)) -> 46325 | L38: =IF(E38="","",IF(F38<>"",IF(F38>E38,"Enviado com atraso","Enviado no prazo"),IF(DataRef>E38,"ATRASADO",IF(DataRef=E38,"ENVIAR HOJE","Programado")))) -> Programado
A39: 35 | B39: Informe diário | C39: RDO nº 6 | D39: Engenheiro valida / COP envia | E39: =IF(WORKDAY(DataBase-1,6,Feriados)>FimObra,"",WORKDAY(DataBase-1,6,Feriados)) -> 46329 | L39: =IF(E39="","",IF(F39<>"",IF(F39>E39,"Enviado com atraso","Enviado no prazo"),IF(DataRef>E39,"ATRASADO",IF(DataRef=E39,"ENVIAR HOJE","Programado")))) -> Programado
A40: 36 | B40: Informe diário | C40: RDO nº 7 | D40: Engenheiro valida / COP envia | E40: =IF(WORKDAY(DataBase-1,7,Feriados)>FimObra,"",WORKDAY(DataBase-1,7,Feriados)) -> 46330 | L40: =IF(E40="","",IF(F40<>"",IF(F40>E40,"Enviado com atraso","Enviado no prazo"),IF(DataRef>E40,"ATRASADO",IF(DataRef=E40,"ENVIAR HOJE","Programado")))) -> Programado
A41: 37 | B41: Informe diário | C41: RDO nº 8 | D41: Engenheiro valida / COP envia | E41: =IF(WORKDAY(DataBase-1,8,Feriados)>FimObra,"",WORKDAY(DataBase-1,8,Feriados)) -> 46331 | L41: =IF(E41="","",IF(F41<>"",IF(F41>E41,"Enviado com atraso","Enviado no prazo"),IF(DataRef>E41,"ATRASADO",IF(DataRef=E41,"ENVIAR HOJE","Programado")))) -> Programado
A42: 38 | B42: Informe diário | C42: RDO nº 9 | D42: Engenheiro valida / COP envia | E42: =IF(WORKDAY(DataBase-1,9,Feriados)>FimObra,"",WORKDAY(DataBase-1,9,Feriados)) -> 46332 | L42: =IF(E42="","",IF(F42<>"",IF(F42>E42,"Enviado com atraso","Enviado no prazo"),IF(DataRef>E42,"ATRASADO",IF(DataRef=E42,"ENVIAR HOJE","Programado")))) -> Programado
A43: 39 | B43: Informe diário | C43: RDO nº 10 | D43: Engenheiro valida / COP envia | E43: =IF(WORKDAY(DataBase-1,10,Feriados)>FimObra,"",WORKDAY(DataBase-1,10,Feriados)) -> 46335 | L43: =IF(E43="","",IF(F43<>"",IF(F43>E43,"Enviado com atraso","Enviado no prazo"),IF(DataRef>E43,"ATRASADO",IF(DataRef=E43,"ENVIAR HOJE","Programado")))) -> Programado
A44: 40 | B44: Informe diário | C44: RDO nº 11 | D44: Engenheiro valida / COP envia | E44: =IF(WORKDAY(DataBase-1,11,Feriados)>FimObra,"",WORKDAY(DataBase-1,11,Feriados)) -> 46336 | L44: =IF(E44="","",IF(F44<>"",IF(F44>E44,"Enviado com atraso","Enviado no prazo"),IF(DataRef>E44,"ATRASADO",IF(DataRef=E44,"ENVIAR HOJE","Programado")))) -> Programado
A45: 41 | B45: Informe diário | C45: RDO nº 12 | D45: Engenheiro valida / COP envia | E45: =IF(WORKDAY(DataBase-1,12,Feriados)>FimObra,"",WORKDAY(DataBase-1,12,Feriados)) -> 46337 | L45: =IF(E45="","",IF(F45<>"",IF(F45>E45,"Enviado com atraso","Enviado no prazo"),IF(DataRef>E45,"ATRASADO",IF(DataRef=E45,"ENVIAR HOJE","Programado")))) -> Programado
A46: 42 | B46: Informe diário | C46: RDO nº 13 | D46: Engenheiro valida / COP envia | E46: =IF(WORKDAY(DataBase-1,13,Feriados)>FimObra,"",WORKDAY(DataBase-1,13,Feriados)) -> 46338 | L46: =IF(E46="","",IF(F46<>"",IF(F46>E46,"Enviado com atraso","Enviado no prazo"),IF(DataRef>E46,"ATRASADO",IF(DataRef=E46,"ENVIAR HOJE","Programado")))) -> Programado
A47: 43 | B47: Informe diário | C47: RDO nº 14 | D47: Engenheiro valida / COP envia | E47: =IF(WORKDAY(DataBase-1,14,Feriados)>FimObra,"",WORKDAY(DataBase-1,14,Feriados)) -> 46339 | L47: =IF(E47="","",IF(F47<>"",IF(F47>E47,"Enviado com atraso","Enviado no prazo"),IF(DataRef>E47,"ATRASADO",IF(DataRef=E47,"ENVIAR HOJE","Programado")))) -> Programado
A48: 44 | B48: Informe diário | C48: RDO nº 15 | D48: Engenheiro valida / COP envia | E48: =IF(WORKDAY(DataBase-1,15,Feriados)>FimObra,"",WORKDAY(DataBase-1,15,Feriados)) -> 46342 | L48: =IF(E48="","",IF(F48<>"",IF(F48>E48,"Enviado com atraso","Enviado no prazo"),IF(DataRef>E48,"ATRASADO",IF(DataRef=E48,"ENVIAR HOJE","Programado")))) -> Programado
A49: 45 | B49: Informe diário | C49: RDO nº 16 | D49: Engenheiro valida / COP envia | E49: =IF(WORKDAY(DataBase-1,16,Feriados)>FimObra,"",WORKDAY(DataBase-1,16,Feriados)) -> 46343 | L49: =IF(E49="","",IF(F49<>"",IF(F49>E49,"Enviado com atraso","Enviado no prazo"),IF(DataRef>E49,"ATRASADO",IF(DataRef=E49,"ENVIAR HOJE","Programado")))) -> Programado
A50: 46 | B50: Informe diário | C50: RDO nº 17 | D50: Engenheiro valida / COP envia | E50: =IF(WORKDAY(DataBase-1,17,Feriados)>FimObra,"",WORKDAY(DataBase-1,17,Feriados)) -> 46344 | L50: =IF(E50="","",IF(F50<>"",IF(F50>E50,"Enviado com atraso","Enviado no prazo"),IF(DataRef>E50,"ATRASADO",IF(DataRef=E50,"ENVIAR HOJE","Programado")))) -> Programado
A51: 47 | B51: Informe diário | C51: RDO nº 18 | D51: Engenheiro valida / COP envia | E51: =IF(WORKDAY(DataBase-1,18,Feriados)>FimObra,"",WORKDAY(DataBase-1,18,Feriados)) -> 46345 | L51: =IF(E51="","",IF(F51<>"",IF(F51>E51,"Enviado com atraso","Enviado no prazo"),IF(DataRef>E51,"ATRASADO",IF(DataRef=E51,"ENVIAR HOJE","Programado")))) -> Programado
A52: 48 | B52: Informe diário | C52: RDO nº 19 | D52: Engenheiro valida / COP envia | E52: =IF(WORKDAY(DataBase-1,19,Feriados)>FimObra,"",WORKDAY(DataBase-1,19,Feriados)) -> 46349 | L52: =IF(E52="","",IF(F52<>"",IF(F52>E52,"Enviado com atraso","Enviado no prazo"),IF(DataRef>E52,"ATRASADO",IF(DataRef=E52,"ENVIAR HOJE","Programado")))) -> Programado
A53: 49 | B53: Informe diário | C53: RDO nº 20 | D53: Engenheiro valida / COP envia | E53: =IF(WORKDAY(DataBase-1,20,Feriados)>FimObra,"",WORKDAY(DataBase-1,20,Feriados)) -> 46350 | L53: =IF(E53="","",IF(F53<>"",IF(F53>E53,"Enviado com atraso","Enviado no prazo"),IF(DataRef>E53,"ATRASADO",IF(DataRef=E53,"ENVIAR HOJE","Programado")))) -> Programado
A54: 50 | B54: Informe diário | C54: RDO nº 21 | D54: Engenheiro valida / COP envia | E54: =IF(WORKDAY(DataBase-1,21,Feriados)>FimObra,"",WORKDAY(DataBase-1,21,Feriados)) -> 46351 | L54: =IF(E54="","",IF(F54<>"",IF(F54>E54,"Enviado com atraso","Enviado no prazo"),IF(DataRef>E54,"ATRASADO",IF(DataRef=E54,"ENVIAR HOJE","Programado")))) -> Programado
A55: 51 | B55: Informe diário | C55: RDO nº 22 | D55: Engenheiro valida / COP envia | E55: =IF(WORKDAY(DataBase-1,22,Feriados)>FimObra,"",WORKDAY(DataBase-1,22,Feriados)) -> 46352 | L55: =IF(E55="","",IF(F55<>"",IF(F55>E55,"Enviado com atraso","Enviado no prazo"),IF(DataRef>E55,"ATRASADO",IF(DataRef=E55,"ENVIAR HOJE","Programado")))) -> Programado
A56: 52 | B56: Informe diário | C56: RDO nº 23 | D56: Engenheiro valida / COP envia | E56: =IF(WORKDAY(DataBase-1,23,Feriados)>FimObra,"",WORKDAY(DataBase-1,23,Feriados)) -> 46353 | L56: =IF(E56="","",IF(F56<>"",IF(F56>E56,"Enviado com atraso","Enviado no prazo"),IF(DataRef>E56,"ATRASADO",IF(DataRef=E56,"ENVIAR HOJE","Programado")))) -> Programado
A57: 53 | B57: Informe diário | C57: RDO nº 24 | D57: Engenheiro valida / COP envia | E57: =IF(WORKDAY(DataBase-1,24,Feriados)>FimObra,"",WORKDAY(DataBase-1,24,Feriados)) -> 46356 | L57: =IF(E57="","",IF(F57<>"",IF(F57>E57,"Enviado com atraso","Enviado no prazo"),IF(DataRef>E57,"ATRASADO",IF(DataRef=E57,"ENVIAR HOJE","Programado")))) -> Programado
A58: 54 | B58: Informe diário | C58: RDO nº 25 | D58: Engenheiro valida / COP envia | E58: =IF(WORKDAY(DataBase-1,25,Feriados)>FimObra,"",WORKDAY(DataBase-1,25,Feriados)) -> 46357 | L58: =IF(E58="","",IF(F58<>"",IF(F58>E58,"Enviado com atraso","Enviado no prazo"),IF(DataRef>E58,"ATRASADO",IF(DataRef=E58,"ENVIAR HOJE","Programado")))) -> Programado
A59: 55 | B59: Informe diário | C59: RDO nº 26 | D59: Engenheiro valida / COP envia | E59: =IF(WORKDAY(DataBase-1,26,Feriados)>FimObra,"",WORKDAY(DataBase-1,26,Feriados)) -> 46358 | L59: =IF(E59="","",IF(F59<>"",IF(F59>E59,"Enviado com atraso","Enviado no prazo"),IF(DataRef>E59,"ATRASADO",IF(DataRef=E59,"ENVIAR HOJE","Programado")))) -> Programado
A60: 56 | B60: Informe diário | C60: RDO nº 27 | D60: Engenheiro valida / COP envia | E60: =IF(WORKDAY(DataBase-1,27,Feriados)>FimObra,"",WORKDAY(DataBase-1,27,Feriados)) -> 46359 | L60: =IF(E60="","",IF(F60<>"",IF(F60>E60,"Enviado com atraso","Enviado no prazo"),IF(DataRef>E60,"ATRASADO",IF(DataRef=E60,"ENVIAR HOJE","Programado")))) -> Programado
A61: 57 | B61: Informe diário | C61: RDO nº 28 | D61: Engenheiro valida / COP envia | E61: =IF(WORKDAY(DataBase-1,28,Feriados)>FimObra,"",WORKDAY(DataBase-1,28,Feriados)) -> 46360 | L61: =IF(E61="","",IF(F61<>"",IF(F61>E61,"Enviado com atraso","Enviado no prazo"),IF(DataRef>E61,"ATRASADO",IF(DataRef=E61,"ENVIAR HOJE","Programado")))) -> Programado
A62: 58 | B62: Informe diário | C62: RDO nº 29 | D62: Engenheiro valida / COP envia | E62: =IF(WORKDAY(DataBase-1,29,Feriados)>FimObra,"",WORKDAY(DataBase-1,29,Feriados)) -> 46363 | L62: =IF(E62="","",IF(F62<>"",IF(F62>E62,"Enviado com atraso","Enviado no prazo"),IF(DataRef>E62,"ATRASADO",IF(DataRef=E62,"ENVIAR HOJE","Programado")))) -> Programado
A63: 59 | B63: Informe diário | C63: RDO nº 30 | D63: Engenheiro valida / COP envia | E63: =IF(WORKDAY(DataBase-1,30,Feriados)>FimObra,"",WORKDAY(DataBase-1,30,Feriados)) -> 46364 | L63: =IF(E63="","",IF(F63<>"",IF(F63>E63,"Enviado com atraso","Enviado no prazo"),IF(DataRef>E63,"ATRASADO",IF(DataRef=E63,"ENVIAR HOJE","Programado")))) -> Programado
A64: 60 | B64: Informe diário | C64: RDO nº 31 | D64: Engenheiro valida / COP envia | E64: =IF(WORKDAY(DataBase-1,31,Feriados)>FimObra,"",WORKDAY(DataBase-1,31,Feriados)) -> 46365 | L64: =IF(E64="","",IF(F64<>"",IF(F64>E64,"Enviado com atraso","Enviado no prazo"),IF(DataRef>E64,"ATRASADO",IF(DataRef=E64,"ENVIAR HOJE","Programado")))) -> Programado
A65: 61 | B65: Informe diário | C65: RDO nº 32 | D65: Engenheiro valida / COP envia | E65: =IF(WORKDAY(DataBase-1,32,Feriados)>FimObra,"",WORKDAY(DataBase-1,32,Feriados)) -> 46366 | L65: =IF(E65="","",IF(F65<>"",IF(F65>E65,"Enviado com atraso","Enviado no prazo"),IF(DataRef>E65,"ATRASADO",IF(DataRef=E65,"ENVIAR HOJE","Programado")))) -> Programado
A66: 62 | B66: Informe diário | C66: RDO nº 33 | D66: Engenheiro valida / COP envia | E66: =IF(WORKDAY(DataBase-1,33,Feriados)>FimObra,"",WORKDAY(DataBase-1,33,Feriados)) -> 46367 | L66: =IF(E66="","",IF(F66<>"",IF(F66>E66,"Enviado com atraso","Enviado no prazo"),IF(DataRef>E66,"ATRASADO",IF(DataRef=E66,"ENVIAR HOJE","Programado")))) -> Programado
A67: 63 | B67: Informe diário | C67: RDO nº 34 | D67: Engenheiro valida / COP envia | E67: =IF(WORKDAY(DataBase-1,34,Feriados)>FimObra,"",WORKDAY(DataBase-1,34,Feriados)) -> 46370 | L67: =IF(E67="","",IF(F67<>"",IF(F67>E67,"Enviado com atraso","Enviado no prazo"),IF(DataRef>E67,"ATRASADO",IF(DataRef=E67,"ENVIAR HOJE","Programado")))) -> Programado
A68: 64 | B68: Informe diário | C68: RDO nº 35 | D68: Engenheiro valida / COP envia | E68: =IF(WORKDAY(DataBase-1,35,Feriados)>FimObra,"",WORKDAY(DataBase-1,35,Feriados)) -> 46371 | L68: =IF(E68="","",IF(F68<>"",IF(F68>E68,"Enviado com atraso","Enviado no prazo"),IF(DataRef>E68,"ATRASADO",IF(DataRef=E68,"ENVIAR HOJE","Programado")))) -> Programado
A69: 65 | B69: Informe diário | C69: RDO nº 36 | D69: Engenheiro valida / COP envia | E69: =IF(WORKDAY(DataBase-1,36,Feriados)>FimObra,"",WORKDAY(DataBase-1,36,Feriados)) -> 46372 | L69: =IF(E69="","",IF(F69<>"",IF(F69>E69,"Enviado com atraso","Enviado no prazo"),IF(DataRef>E69,"ATRASADO",IF(DataRef=E69,"ENVIAR HOJE","Programado")))) -> Programado
A70: 66 | B70: Informe diário | C70: RDO nº 37 | D70: Engenheiro valida / COP envia | E70: =IF(WORKDAY(DataBase-1,37,Feriados)>FimObra,"",WORKDAY(DataBase-1,37,Feriados)) -> 46373 | L70: =IF(E70="","",IF(F70<>"",IF(F70>E70,"Enviado com atraso","Enviado no prazo"),IF(DataRef>E70,"ATRASADO",IF(DataRef=E70,"ENVIAR HOJE","Programado")))) -> Programado
A71: 67 | B71: Informe diário | C71: RDO nº 38 | D71: Engenheiro valida / COP envia | E71: =IF(WORKDAY(DataBase-1,38,Feriados)>FimObra,"",WORKDAY(DataBase-1,38,Feriados)) -> 46374 | L71: =IF(E71="","",IF(F71<>"",IF(F71>E71,"Enviado com atraso","Enviado no prazo"),IF(DataRef>E71,"ATRASADO",IF(DataRef=E71,"ENVIAR HOJE","Programado")))) -> Programado
A72: 68 | B72: Informe diário | C72: RDO nº 39 | D72: Engenheiro valida / COP envia | E72: =IF(WORKDAY(DataBase-1,39,Feriados)>FimObra,"",WORKDAY(DataBase-1,39,Feriados)) -> 46377 | L72: =IF(E72="","",IF(F72<>"",IF(F72>E72,"Enviado com atraso","Enviado no prazo"),IF(DataRef>E72,"ATRASADO",IF(DataRef=E72,"ENVIAR HOJE","Programado")))) -> Programado
A73: 69 | B73: Informe diário | C73: RDO nº 40 | D73: Engenheiro valida / COP envia | E73: =IF(WORKDAY(DataBase-1,40,Feriados)>FimObra,"",WORKDAY(DataBase-1,40,Feriados)) -> 46378 | L73: =IF(E73="","",IF(F73<>"",IF(F73>E73,"Enviado com atraso","Enviado no prazo"),IF(DataRef>E73,"ATRASADO",IF(DataRef=E73,"ENVIAR HOJE","Programado")))) -> Programado
A74: 70 | B74: Informe diário | C74: RDO nº 41 | D74: Engenheiro valida / COP envia | E74: =IF(WORKDAY(DataBase-1,41,Feriados)>FimObra,"",WORKDAY(DataBase-1,41,Feriados)) -> 46379 | L74: =IF(E74="","",IF(F74<>"",IF(F74>E74,"Enviado com atraso","Enviado no prazo"),IF(DataRef>E74,"ATRASADO",IF(DataRef=E74,"ENVIAR HOJE","Programado")))) -> Programado
A75: 71 | B75: Informe diário | C75: RDO nº 42 | D75: Engenheiro valida / COP envia | E75: =IF(WORKDAY(DataBase-1,42,Feriados)>FimObra,"",WORKDAY(DataBase-1,42,Feriados)) -> 46380 | L75: =IF(E75="","",IF(F75<>"",IF(F75>E75,"Enviado com atraso","Enviado no prazo"),IF(DataRef>E75,"ATRASADO",IF(DataRef=E75,"ENVIAR HOJE","Programado")))) -> Programado
A76: 72 | B76: Informe diário | C76: RDO nº 43 | D76: Engenheiro valida / COP envia | E76: =IF(WORKDAY(DataBase-1,43,Feriados)>FimObra,"",WORKDAY(DataBase-1,43,Feriados)) -> 46384 | L76: =IF(E76="","",IF(F76<>"",IF(F76>E76,"Enviado com atraso","Enviado no prazo"),IF(DataRef>E76,"ATRASADO",IF(DataRef=E76,"ENVIAR HOJE","Programado")))) -> Programado
A77: 73 | B77: Informe diário | C77: RDO nº 44 | D77: Engenheiro valida / COP envia | E77: =IF(WORKDAY(DataBase-1,44,Feriados)>FimObra,"",WORKDAY(DataBase-1,44,Feriados)) -> 46385 | L77: =IF(E77="","",IF(F77<>"",IF(F77>E77,"Enviado com atraso","Enviado no prazo"),IF(DataRef>E77,"ATRASADO",IF(DataRef=E77,"ENVIAR HOJE","Programado")))) -> Programado
A78: 74 | B78: Informe diário | C78: RDO nº 45 | D78: Engenheiro valida / COP envia | E78: =IF(WORKDAY(DataBase-1,45,Feriados)>FimObra,"",WORKDAY(DataBase-1,45,Feriados)) -> 46386 | L78: =IF(E78="","",IF(F78<>"",IF(F78>E78,"Enviado com atraso","Enviado no prazo"),IF(DataRef>E78,"ATRASADO",IF(DataRef=E78,"ENVIAR HOJE","Programado")))) -> Programado
A79: 75 | B79: Informe diário | C79: RDO nº 46 | D79: Engenheiro valida / COP envia | E79: =IF(WORKDAY(DataBase-1,46,Feriados)>FimObra,"",WORKDAY(DataBase-1,46,Feriados)) -> 46387 | L79: =IF(E79="","",IF(F79<>"",IF(F79>E79,"Enviado com atraso","Enviado no prazo"),IF(DataRef>E79,"ATRASADO",IF(DataRef=E79,"ENVIAR HOJE","Programado")))) -> Programado
A80: 76 | B80: Informe diário | C80: RDO nº 47 | D80: Engenheiro valida / COP envia | E80: =IF(WORKDAY(DataBase-1,47,Feriados)>FimObra,"",WORKDAY(DataBase-1,47,Feriados)) -> 46391 | L80: =IF(E80="","",IF(F80<>"",IF(F80>E80,"Enviado com atraso","Enviado no prazo"),IF(DataRef>E80,"ATRASADO",IF(DataRef=E80,"ENVIAR HOJE","Programado")))) -> Programado
A81: 77 | B81: Informe diário | C81: RDO nº 48 | D81: Engenheiro valida / COP envia | E81: =IF(WORKDAY(DataBase-1,48,Feriados)>FimObra,"",WORKDAY(DataBase-1,48,Feriados)) -> 46392 | L81: =IF(E81="","",IF(F81<>"",IF(F81>E81,"Enviado com atraso","Enviado no prazo"),IF(DataRef>E81,"ATRASADO",IF(DataRef=E81,"ENVIAR HOJE","Programado")))) -> Programado
A82: 78 | B82: Informe diário | C82: RDO nº 49 | D82: Engenheiro valida / COP envia | E82: =IF(WORKDAY(DataBase-1,49,Feriados)>FimObra,"",WORKDAY(DataBase-1,49,Feriados)) -> 46393 | L82: =IF(E82="","",IF(F82<>"",IF(F82>E82,"Enviado com atraso","Enviado no prazo"),IF(DataRef>E82,"ATRASADO",IF(DataRef=E82,"ENVIAR HOJE","Programado")))) -> Programado
A83: 79 | B83: Informe diário | C83: RDO nº 50 | D83: Engenheiro valida / COP envia | E83: =IF(WORKDAY(DataBase-1,50,Feriados)>FimObra,"",WORKDAY(DataBase-1,50,Feriados)) -> 46394 | L83: =IF(E83="","",IF(F83<>"",IF(F83>E83,"Enviado com atraso","Enviado no prazo"),IF(DataRef>E83,"ATRASADO",IF(DataRef=E83,"ENVIAR HOJE","Programado")))) -> Programado
A84: 80 | B84: Informe diário | C84: RDO nº 51 | D84: Engenheiro valida / COP envia | E84: =IF(WORKDAY(DataBase-1,51,Feriados)>FimObra,"",WORKDAY(DataBase-1,51,Feriados)) -> 46395 | L84: =IF(E84="","",IF(F84<>"",IF(F84>E84,"Enviado com atraso","Enviado no prazo"),IF(DataRef>E84,"ATRASADO",IF(DataRef=E84,"ENVIAR HOJE","Programado")))) -> Programado
A85: 81 | B85: Informe diário | C85: RDO nº 52 | D85: Engenheiro valida / COP envia | E85: =IF(WORKDAY(DataBase-1,52,Feriados)>FimObra,"",WORKDAY(DataBase-1,52,Feriados)) -> 46398 | L85: =IF(E85="","",IF(F85<>"",IF(F85>E85,"Enviado com atraso","Enviado no prazo"),IF(DataRef>E85,"ATRASADO",IF(DataRef=E85,"ENVIAR HOJE","Programado")))) -> Programado
A86: 82 | B86: Informe diário | C86: RDO nº 53 | D86: Engenheiro valida / COP envia | E86: =IF(WORKDAY(DataBase-1,53,Feriados)>FimObra,"",WORKDAY(DataBase-1,53,Feriados)) -> 46399 | L86: =IF(E86="","",IF(F86<>"",IF(F86>E86,"Enviado com atraso","Enviado no prazo"),IF(DataRef>E86,"ATRASADO",IF(DataRef=E86,"ENVIAR HOJE","Programado")))) -> Programado
A87: 83 | B87: Informe diário | C87: RDO nº 54 | D87: Engenheiro valida / COP envia | E87: =IF(WORKDAY(DataBase-1,54,Feriados)>FimObra,"",WORKDAY(DataBase-1,54,Feriados)) -> 46400 | L87: =IF(E87="","",IF(F87<>"",IF(F87>E87,"Enviado com atraso","Enviado no prazo"),IF(DataRef>E87,"ATRASADO",IF(DataRef=E87,"ENVIAR HOJE","Programado")))) -> Programado
A88: 84 | B88: Informe diário | C88: RDO nº 55 | D88: Engenheiro valida / COP envia | E88: =IF(WORKDAY(DataBase-1,55,Feriados)>FimObra,"",WORKDAY(DataBase-1,55,Feriados)) -> 46401 | L88: =IF(E88="","",IF(F88<>"",IF(F88>E88,"Enviado com atraso","Enviado no prazo"),IF(DataRef>E88,"ATRASADO",IF(DataRef=E88,"ENVIAR HOJE","Programado")))) -> Programado
A89: 85 | B89: Informe diário | C89: RDO nº 56 | D89: Engenheiro valida / COP envia | E89: =IF(WORKDAY(DataBase-1,56,Feriados)>FimObra,"",WORKDAY(DataBase-1,56,Feriados)) -> 46402 | L89: =IF(E89="","",IF(F89<>"",IF(F89>E89,"Enviado com atraso","Enviado no prazo"),IF(DataRef>E89,"ATRASADO",IF(DataRef=E89,"ENVIAR HOJE","Programado")))) -> Programado
A90: 86 | B90: Informe diário | C90: RDO nº 57 | D90: Engenheiro valida / COP envia | E90: =IF(WORKDAY(DataBase-1,57,Feriados)>FimObra,"",WORKDAY(DataBase-1,57,Feriados)) -> 46405 | L90: =IF(E90="","",IF(F90<>"",IF(F90>E90,"Enviado com atraso","Enviado no prazo"),IF(DataRef>E90,"ATRASADO",IF(DataRef=E90,"ENVIAR HOJE","Programado")))) -> Programado
A91: 87 | B91: Informe diário | C91: RDO nº 58 | D91: Engenheiro valida / COP envia | E91: =IF(WORKDAY(DataBase-1,58,Feriados)>FimObra,"",WORKDAY(DataBase-1,58,Feriados)) -> 46406 | L91: =IF(E91="","",IF(F91<>"",IF(F91>E91,"Enviado com atraso","Enviado no prazo"),IF(DataRef>E91,"ATRASADO",IF(DataRef=E91,"ENVIAR HOJE","Programado")))) -> Programado
A92: 88 | B92: Informe diário | C92: RDO nº 59 | D92: Engenheiro valida / COP envia | E92: =IF(WORKDAY(DataBase-1,59,Feriados)>FimObra,"",WORKDAY(DataBase-1,59,Feriados)) -> 46407 | L92: =IF(E92="","",IF(F92<>"",IF(F92>E92,"Enviado com atraso","Enviado no prazo"),IF(DataRef>E92,"ATRASADO",IF(DataRef=E92,"ENVIAR HOJE","Programado")))) -> Programado
A93: 89 | B93: Informe diário | C93: RDO nº 60 | D93: Engenheiro valida / COP envia | E93: =IF(WORKDAY(DataBase-1,60,Feriados)>FimObra,"",WORKDAY(DataBase-1,60,Feriados)) -> 46408 | L93: =IF(E93="","",IF(F93<>"",IF(F93>E93,"Enviado com atraso","Enviado no prazo"),IF(DataRef>E93,"ATRASADO",IF(DataRef=E93,"ENVIAR HOJE","Programado")))) -> Programado
A94: 90 | B94: Informe diário | C94: RDO nº 61 | D94: Engenheiro valida / COP envia | E94: =IF(WORKDAY(DataBase-1,61,Feriados)>FimObra,"",WORKDAY(DataBase-1,61,Feriados)) -> 46409 | L94: =IF(E94="","",IF(F94<>"",IF(F94>E94,"Enviado com atraso","Enviado no prazo"),IF(DataRef>E94,"ATRASADO",IF(DataRef=E94,"ENVIAR HOJE","Programado")))) -> Programado
A95: 91 | B95: Informe diário | C95: RDO nº 62 | D95: Engenheiro valida / COP envia | E95: =IF(WORKDAY(DataBase-1,62,Feriados)>FimObra,"",WORKDAY(DataBase-1,62,Feriados)) -> 46412 | L95: =IF(E95="","",IF(F95<>"",IF(F95>E95,"Enviado com atraso","Enviado no prazo"),IF(DataRef>E95,"ATRASADO",IF(DataRef=E95,"ENVIAR HOJE","Programado")))) -> Programado
A96: 92 | B96: Informe diário | C96: RDO nº 63 | D96: Engenheiro valida / COP envia | E96: =IF(WORKDAY(DataBase-1,63,Feriados)>FimObra,"",WORKDAY(DataBase-1,63,Feriados)) -> 46413 | L96: =IF(E96="","",IF(F96<>"",IF(F96>E96,"Enviado com atraso","Enviado no prazo"),IF(DataRef>E96,"ATRASADO",IF(DataRef=E96,"ENVIAR HOJE","Programado")))) -> Programado
A97: 93 | B97: Informe diário | C97: RDO nº 64 | D97: Engenheiro valida / COP envia | E97: =IF(WORKDAY(DataBase-1,64,Feriados)>FimObra,"",WORKDAY(DataBase-1,64,Feriados)) -> 46414 | L97: =IF(E97="","",IF(F97<>"",IF(F97>E97,"Enviado com atraso","Enviado no prazo"),IF(DataRef>E97,"ATRASADO",IF(DataRef=E97,"ENVIAR HOJE","Programado")))) -> Programado
A98: 94 | B98: Informe diário | C98: RDO nº 65 | D98: Engenheiro valida / COP envia | E98: =IF(WORKDAY(DataBase-1,65,Feriados)>FimObra,"",WORKDAY(DataBase-1,65,Feriados)) -> 46415 | L98: =IF(E98="","",IF(F98<>"",IF(F98>E98,"Enviado com atraso","Enviado no prazo"),IF(DataRef>E98,"ATRASADO",IF(DataRef=E98,"ENVIAR HOJE","Programado")))) -> Programado
A99: 95 | B99: Informe diário | C99: RDO nº 66 | D99: Engenheiro valida / COP envia | E99: =IF(WORKDAY(DataBase-1,66,Feriados)>FimObra,"",WORKDAY(DataBase-1,66,Feriados)) | L99: =IF(E99="","",IF(F99<>"",IF(F99>E99,"Enviado com atraso","Enviado no prazo"),IF(DataRef>E99,"ATRASADO",IF(DataRef=E99,"ENVIAR HOJE","Programado"))))
A100: 96 | B100: Informe diário | C100: RDO nº 67 | D100: Engenheiro valida / COP envia | E100: =IF(WORKDAY(DataBase-1,67,Feriados)>FimObra,"",WORKDAY(DataBase-1,67,Feriados)) | L100: =IF(E100="","",IF(F100<>"",IF(F100>E100,"Enviado com atraso","Enviado no prazo"),IF(DataRef>E100,"ATRASADO",IF(DataRef=E100,"ENVIAR HOJE","Programado"))))
A101: 97 | B101: Informe diário | C101: RDO nº 68 | D101: Engenheiro valida / COP envia | E101: =IF(WORKDAY(DataBase-1,68,Feriados)>FimObra,"",WORKDAY(DataBase-1,68,Feriados)) | L101: =IF(E101="","",IF(F101<>"",IF(F101>E101,"Enviado com atraso","Enviado no prazo"),IF(DataRef>E101,"ATRASADO",IF(DataRef=E101,"ENVIAR HOJE","Programado"))))
...

Sheet RELATORIO_CLIENTE
A1: MANFAC | Relatório Semanal de Obra
A2: Visão do cliente: sem custos, margem ou fornecedores. Imprimir ou salvar em PDF para envio na sexta-feira.
B4: Obra | C4: =PAINEL!C5 -> DP Macaé 3 – Intervenção estrutural + reforma light
B5: Data de referência (qualquer dia da semana) | C5: =DataRef -> 46318
B6: Semana de | C6: =C5-WEEKDAY(C5,2)+1 -> 46314
B7: até | C7: =C6+4 -> 46318
B9: INDICADORES DA SEMANA
B10: Avanço planejado até a sexta-feira | C10: =SUMPRODUCT(CRONOGRAMA!M5:M32,CRONOGRAMA!U5:U32) -> 0
B11: Avanço realizado (posição atual) | C11: =SUMPRODUCT(CRONOGRAMA!M5:M32,CRONOGRAMA!O5:O32) -> 0
B12: Desvio | C12: =(C11-C10)*100 -> 0
B13: Etapas da obra concluídas | C13: =COUNTIF(CRONOGRAMA!N5:N32,"Concluído")&" de "&COUNTA(CRONOGRAMA!A5:A32)&" atividades" -> 0 de 28 atividades
B14: Data prevista de entrega | C14: =FimObra -> 46415
B15: Principal impedimento | C15: =IF(CRONOGRAMA!N10<>"Concluído","Escoramento da viga principal em execução – demolições aguardando",IFERROR(INDEX(PENDENCIAS!C5:C200,MATCH(1,PENDENCIAS!N5:N200,0)),"Nenhum")) -> Escoramento da viga principal em execução – demolições aguardando
B17: ATIVIDADES CONCLUÍDAS | C17: Concluída em
A18: 1 | B18: =IFERROR(INDEX(CRONOGRAMA!$D$5:$D$32,MATCH(A18,CRONOGRAMA!$V$5:$V$32,0)),"") | C18: =IF(B18="","",INDEX(CRONOGRAMA!$Q$5:$Q$32,MATCH(A18,CRONOGRAMA!$V$5:$V$32,0)))
A19: 2 | B19: =IFERROR(INDEX(CRONOGRAMA!$D$5:$D$32,MATCH(A19,CRONOGRAMA!$V$5:$V$32,0)),"") | C19: =IF(B19="","",INDEX(CRONOGRAMA!$Q$5:$Q$32,MATCH(A19,CRONOGRAMA!$V$5:$V$32,0)))
A20: 3 | B20: =IFERROR(INDEX(CRONOGRAMA!$D$5:$D$32,MATCH(A20,CRONOGRAMA!$V$5:$V$32,0)),"") | C20: =IF(B20="","",INDEX(CRONOGRAMA!$Q$5:$Q$32,MATCH(A20,CRONOGRAMA!$V$5:$V$32,0)))
A21: 4 | B21: =IFERROR(INDEX(CRONOGRAMA!$D$5:$D$32,MATCH(A21,CRONOGRAMA!$V$5:$V$32,0)),"") | C21: =IF(B21="","",INDEX(CRONOGRAMA!$Q$5:$Q$32,MATCH(A21,CRONOGRAMA!$V$5:$V$32,0)))
A22: 5 | B22: =IFERROR(INDEX(CRONOGRAMA!$D$5:$D$32,MATCH(A22,CRONOGRAMA!$V$5:$V$32,0)),"") | C22: =IF(B22="","",INDEX(CRONOGRAMA!$Q$5:$Q$32,MATCH(A22,CRONOGRAMA!$V$5:$V$32,0)))
A23: 6 | B23: =IFERROR(INDEX(CRONOGRAMA!$D$5:$D$32,MATCH(A23,CRONOGRAMA!$V$5:$V$32,0)),"") | C23: =IF(B23="","",INDEX(CRONOGRAMA!$Q$5:$Q$32,MATCH(A23,CRONOGRAMA!$V$5:$V$32,0)))
A24: 7 | B24: =IFERROR(INDEX(CRONOGRAMA!$D$5:$D$32,MATCH(A24,CRONOGRAMA!$V$5:$V$32,0)),"") | C24: =IF(B24="","",INDEX(CRONOGRAMA!$Q$5:$Q$32,MATCH(A24,CRONOGRAMA!$V$5:$V$32,0)))
A25: 8 | B25: =IFERROR(INDEX(CRONOGRAMA!$D$5:$D$32,MATCH(A25,CRONOGRAMA!$V$5:$V$32,0)),"") | C25: =IF(B25="","",INDEX(CRONOGRAMA!$Q$5:$Q$32,MATCH(A25,CRONOGRAMA!$V$5:$V$32,0)))
B27: EM ANDAMENTO | C27: % realizado | D27: Término previsto
A28: 1 | B28: =IFERROR(INDEX(CRONOGRAMA!$D$5:$D$32,MATCH(A28,CRONOGRAMA!$W$5:$W$32,0)),"") -> Escoramento provisório sob a treliça (P2/P3 e vão P3–P4); macaco só para encunhar | C28: =IF(B28="","",INDEX(CRONOGRAMA!$O$5:$O$32,MATCH(A28,CRONOGRAMA!$W$5:$W$32,0))) -> 0 | D28: =IF(B28="","",INDEX(CRONOGRAMA!$K$5:$K$32,MATCH(A28,CRONOGRAMA!$W$5:$W$32,0))) -> 46330
A29: 2 | B29: =IFERROR(INDEX(CRONOGRAMA!$D$5:$D$32,MATCH(A29,CRONOGRAMA!$W$5:$W$32,0)),"") | C29: =IF(B29="","",INDEX(CRONOGRAMA!$O$5:$O$32,MATCH(A29,CRONOGRAMA!$W$5:$W$32,0))) | D29: =IF(B29="","",INDEX(CRONOGRAMA!$K$5:$K$32,MATCH(A29,CRONOGRAMA!$W$5:$W$32,0)))
A30: 3 | B30: =IFERROR(INDEX(CRONOGRAMA!$D$5:$D$32,MATCH(A30,CRONOGRAMA!$W$5:$W$32,0)),"") | C30: =IF(B30="","",INDEX(CRONOGRAMA!$O$5:$O$32,MATCH(A30,CRONOGRAMA!$W$5:$W$32,0))) | D30: =IF(B30="","",INDEX(CRONOGRAMA!$K$5:$K$32,MATCH(A30,CRONOGRAMA!$W$5:$W$32,0)))
A31: 4 | B31: =IFERROR(INDEX(CRONOGRAMA!$D$5:$D$32,MATCH(A31,CRONOGRAMA!$W$5:$W$32,0)),"") | C31: =IF(B31="","",INDEX(CRONOGRAMA!$O$5:$O$32,MATCH(A31,CRONOGRAMA!$W$5:$W$32,0))) | D31: =IF(B31="","",INDEX(CRONOGRAMA!$K$5:$K$32,MATCH(A31,CRONOGRAMA!$W$5:$W$32,0)))
A32: 5 | B32: =IFERROR(INDEX(CRONOGRAMA!$D$5:$D$32,MATCH(A32,CRONOGRAMA!$W$5:$W$32,0)),"") | C32: =IF(B32="","",INDEX(CRONOGRAMA!$O$5:$O$32,MATCH(A32,CRONOGRAMA!$W$5:$W$32,0))) | D32: =IF(B32="","",INDEX(CRONOGRAMA!$K$5:$K$32,MATCH(A32,CRONOGRAMA!$W$5:$W$32,0)))
A33: 6 | B33: =IFERROR(INDEX(CRONOGRAMA!$D$5:$D$32,MATCH(A33,CRONOGRAMA!$W$5:$W$32,0)),"") | C33: =IF(B33="","",INDEX(CRONOGRAMA!$O$5:$O$32,MATCH(A33,CRONOGRAMA!$W$5:$W$32,0))) | D33: =IF(B33="","",INDEX(CRONOGRAMA!$K$5:$K$32,MATCH(A33,CRONOGRAMA!$W$5:$W$32,0)))
A34: 7 | B34: =IFERROR(INDEX(CRONOGRAMA!$D$5:$D$32,MATCH(A34,CRONOGRAMA!$W$5:$W$32,0)),"") | C34: =IF(B34="","",INDEX(CRONOGRAMA!$O$5:$O$32,MATCH(A34,CRONOGRAMA!$W$5:$W$32,0))) | D34: =IF(B34="","",INDEX(CRONOGRAMA!$K$5:$K$32,MATCH(A34,CRONOGRAMA!$W$5:$W$32,0)))
A35: 8 | B35: =IFERROR(INDEX(CRONOGRAMA!$D$5:$D$32,MATCH(A35,CRONOGRAMA!$W$5:$W$32,0)),"") | C35: =IF(B35="","",INDEX(CRONOGRAMA!$O$5:$O$32,MATCH(A35,CRONOGRAMA!$W$5:$W$32,0))) | D35: =IF(B35="","",INDEX(CRONOGRAMA!$K$5:$K$32,MATCH(A35,CRONOGRAMA!$W$5:$W$32,0)))
B37: PROGRAMAÇÃO DA PRÓXIMA SEMANA | C37: Início | D37: Término
A38: 1 | B38: =IFERROR(INDEX(CRONOGRAMA!$D$5:$D$32,MATCH(A38,CRONOGRAMA!$X$5:$X$32,0)),"") -> Reunião de partida no local: identificar P1–P4, treliça e faixa de piso afetada | C38: =IF(B38="","",INDEX(CRONOGRAMA!$J$5:$J$32,MATCH(A38,CRONOGRAMA!$X$5:$X$32,0))) -> 46321 | D38: =IF(B38="","",INDEX(CRONOGRAMA!$K$5:$K$32,MATCH(A38,CRONOGRAMA!$X$5:$X$32,0))) -> 46321
A39: 2 | B39: =IFERROR(INDEX(CRONOGRAMA!$D$5:$D$32,MATCH(A39,CRONOGRAMA!$X$5:$X$32,0)),"") -> Pontos de acompanhamento fotográfico, relatório "antes da obra" e marcos de nível | C39: =IF(B39="","",INDEX(CRONOGRAMA!$J$5:$J$32,MATCH(A39,CRONOGRAMA!$X$5:$X$32,0))) -> 46322 | D39: =IF(B39="","",INDEX(CRONOGRAMA!$K$5:$K$32,MATCH(A39,CRONOGRAMA!$X$5:$X$32,0))) -> 46323
A40: 3 | B40: =IFERROR(INDEX(CRONOGRAMA!$D$5:$D$32,MATCH(A40,CRONOGRAMA!$X$5:$X$32,0)),"") -> Instalar divisória de fechamento da área | C40: =IF(B40="","",INDEX(CRONOGRAMA!$J$5:$J$32,MATCH(A40,CRONOGRAMA!$X$5:$X$32,0))) -> 46322 | D40: =IF(B40="","",INDEX(CRONOGRAMA!$K$5:$K$32,MATCH(A40,CRONOGRAMA!$X$5:$X$32,0))) -> 46323
A41: 4 | B41: =IFERROR(INDEX(CRONOGRAMA!$D$5:$D$32,MATCH(A41,CRONOGRAMA!$X$5:$X$32,0)),"") -> Remover produtos, virar o balcão e mudar o mobiliário da área afetada | C41: =IF(B41="","",INDEX(CRONOGRAMA!$J$5:$J$32,MATCH(A41,CRONOGRAMA!$X$5:$X$32,0))) -> 46324 | D41: =IF(B41="","",INDEX(CRONOGRAMA!$K$5:$K$32,MATCH(A41,CRONOGRAMA!$X$5:$X$32,0))) -> 46329
A42: 5 | B42: =IFERROR(INDEX(CRONOGRAMA!$D$5:$D$32,MATCH(A42,CRONOGRAMA!$X$5:$X$32,0)),"") -> Aliviar a carga do mezanino (retirar estoque do depósito) | C42: =IF(B42="","",INDEX(CRONOGRAMA!$J$5:$J$32,MATCH(A42,CRONOGRAMA!$X$5:$X$32,0))) -> 46324 | D42: =IF(B42="","",INDEX(CRONOGRAMA!$K$5:$K$32,MATCH(A42,CRONOGRAMA!$X$5:$X$32,0))) -> 46324
A43: 6 | B43: =IFERROR(INDEX(CRONOGRAMA!$D$5:$D$32,MATCH(A43,CRONOGRAMA!$X$5:$X$32,0)),"") -> Escoramento provisório sob a treliça (P2/P3 e vão P3–P4); macaco só para encunhar | C43: =IF(B43="","",INDEX(CRONOGRAMA!$J$5:$J$32,MATCH(A43,CRONOGRAMA!$X$5:$X$32,0))) -> 46325 | D43: =IF(B43="","",INDEX(CRONOGRAMA!$K$5:$K$32,MATCH(A43,CRONOGRAMA!$X$5:$X$32,0))) -> 46330
A44: 7 | B44: =IFERROR(INDEX(CRONOGRAMA!$D$5:$D$32,MATCH(A44,CRONOGRAMA!$X$5:$X$32,0)),"") | C44: =IF(B44="","",INDEX(CRONOGRAMA!$J$5:$J$32,MATCH(A44,CRONOGRAMA!$X$5:$X$32,0))) | D44: =IF(B44="","",INDEX(CRONOGRAMA!$K$5:$K$32,MATCH(A44,CRONOGRAMA!$X$5:$X$32,0)))
A45: 8 | B45: =IFERROR(INDEX(CRONOGRAMA!$D$5:$D$32,MATCH(A45,CRONOGRAMA!$X$5:$X$32,0)),"") | C45: =IF(B45="","",INDEX(CRONOGRAMA!$J$5:$J$32,MATCH(A45,CRONOGRAMA!$X$5:$X$32,0))) | D45: =IF(B45="","",INDEX(CRONOGRAMA!$K$5:$K$32,MATCH(A45,CRONOGRAMA!$X$5:$X$32,0)))
B47: DECISÕES QUE DEPENDEM DO CLIENTE | C47: Prazo | D47: Dias em aberto
A48: 1 | B48: =IFERROR(INDEX(PENDENCIAS!$C$5:$C$200,MATCH(A48,PENDENCIAS!$N$5:$N$200,0)),"") -> Autorização formal de baixa de patrimônio para descarte de gôndolas e geladeira | C48: =IF(B48="","",IF(INDEX(PENDENCIAS!$I$5:$I$200,MATCH(A48,PENDENCIAS!$N$5:$N$200,0))="","a definir",INDEX(PENDENCIAS!$I$5:$I$200,MATCH(A48,PENDENCIAS!$N$5:$N$200,0)))) -> a definir | D48: =IF(B48="","",INDEX(PENDENCIAS!$L$5:$L$200,MATCH(A48,PENDENCIAS!$N$5:$N$200,0))) -> 0
A49: 2 | B49: =IFERROR(INDEX(PENDENCIAS!$C$5:$C$200,MATCH(A49,PENDENCIAS!$N$5:$N$200,0)),"") -> Confirmar se o vidro a retirar é de fachada; se for, obter autorização do Best Center / condomínio | C49: =IF(B49="","",IF(INDEX(PENDENCIAS!$I$5:$I$200,MATCH(A49,PENDENCIAS!$N$5:$N$200,0))="","a definir",INDEX(PENDENCIAS!$I$5:$I$200,MATCH(A49,PENDENCIAS!$N$5:$N$200,0)))) -> a definir | D49: =IF(B49="","",INDEX(PENDENCIAS!$L$5:$L$200,MATCH(A49,PENDENCIAS!$N$5:$N$200,0))) -> 0
A50: 3 | B50: =IFERROR(INDEX(PENDENCIAS!$C$5:$C$200,MATCH(A50,PENDENCIAS!$N$5:$N$200,0)),"") -> Registrar formalmente que Mall, estacionamento e drenagem do centro comercial estão fora do escopo | C50: =IF(B50="","",IF(INDEX(PENDENCIAS!$I$5:$I$200,MATCH(A50,PENDENCIAS!$N$5:$N$200,0))="","a definir",INDEX(PENDENCIAS!$I$5:$I$200,MATCH(A50,PENDENCIAS!$N$5:$N$200,0)))) -> a definir | D50: =IF(B50="","",INDEX(PENDENCIAS!$L$5:$L$200,MATCH(A50,PENDENCIAS!$N$5:$N$200,0))) -> 0
A51: 4 | B51: =IFERROR(INDEX(PENDENCIAS!$C$5:$C$200,MATCH(A51,PENDENCIAS!$N$5:$N$200,0)),"") -> Definir qual banheiro será desmobilizado: térreo ou WC do mezanino | C51: =IF(B51="","",IF(INDEX(PENDENCIAS!$I$5:$I$200,MATCH(A51,PENDENCIAS!$N$5:$N$200,0))="","a definir",INDEX(PENDENCIAS!$I$5:$I$200,MATCH(A51,PENDENCIAS!$N$5:$N$200,0)))) -> a definir | D51: =IF(B51="","",INDEX(PENDENCIAS!$L$5:$L$200,MATCH(A51,PENDENCIAS!$N$5:$N$200,0))) -> 0
A52: 5 | B52: =IFERROR(INDEX(PENDENCIAS!$C$5:$C$200,MATCH(A52,PENDENCIAS!$N$5:$N$200,0)),"") | C52: =IF(B52="","",IF(INDEX(PENDENCIAS!$I$5:$I$200,MATCH(A52,PENDENCIAS!$N$5:$N$200,0))="","a definir",INDEX(PENDENCIAS!$I$5:$I$200,MATCH(A52,PENDENCIAS!$N$5:$N$200,0)))) | D52: =IF(B52="","",INDEX(PENDENCIAS!$L$5:$L$200,MATCH(A52,PENDENCIAS!$N$5:$N$200,0)))
A53: 6 | B53: =IFERROR(INDEX(PENDENCIAS!$C$5:$C$200,MATCH(A53,PENDENCIAS!$N$5:$N$200,0)),"") | C53: =IF(B53="","",IF(INDEX(PENDENCIAS!$I$5:$I$200,MATCH(A53,PENDENCIAS!$N$5:$N$200,0))="","a definir",INDEX(PENDENCIAS!$I$5:$I$200,MATCH(A53,PENDENCIAS!$N$5:$N$200,0)))) | D53: =IF(B53="","",INDEX(PENDENCIAS!$L$5:$L$200,MATCH(A53,PENDENCIAS!$N$5:$N$200,0)))
A54: 7 | B54: =IFERROR(INDEX(PENDENCIAS!$C$5:$C$200,MATCH(A54,PENDENCIAS!$N$5:$N$200,0)),"") | C54: =IF(B54="","",IF(INDEX(PENDENCIAS!$I$5:$I$200,MATCH(A54,PENDENCIAS!$N$5:$N$200,0))="","a definir",INDEX(PENDENCIAS!$I$5:$I$200,MATCH(A54,PENDENCIAS!$N$5:$N$200,0)))) | D54: =IF(B54="","",INDEX(PENDENCIAS!$L$5:$L$200,MATCH(A54,PENDENCIAS!$N$5:$N$200,0)))
A55: 8 | B55: =IFERROR(INDEX(PENDENCIAS!$C$5:$C$200,MATCH(A55,PENDENCIAS!$N$5:$N$200,0)),"") | C55: =IF(B55="","",IF(INDEX(PENDENCIAS!$I$5:$I$200,MATCH(A55,PENDENCIAS!$N$5:$N$200,0))="","a definir",INDEX(PENDENCIAS!$I$5:$I$200,MATCH(A55,PENDENCIAS!$N$5:$N$200,0)))) | D55: =IF(B55="","",INDEX(PENDENCIAS!$L$5:$L$200,MATCH(A55,PENDENCIAS!$N$5:$N$200,0)))
B57: REGISTRO FOTOGRÁFICO DA SEMANA
B58: Link da pasta de fotos datadas e identificadas
B59: Observações da engenharia
B61: MANFAC Engenharia – relatório gerado da base única de controle da obra (SGO).

Sheet LISTAS
A1: Listas e parâmetros de apoio
A2: Valores usados nas listas suspensas e no calendário. Feriados editáveis (amarelo).
A4: Status atividade | B4: Status pendência | C4: Tipo pendência | D4: Sim/Não | E4: Feriados | F4: Descrição | G4: Tipo comunicação | H4: Status compra | I4: Pedido | J4: Funções
A5: Não iniciado | B5: Aberta | C5: Trava | D5: Sim | E5: 46328 | F5: Finados | G5: Informe diário | H5: Cotação | I5: Estrutural REV_04 | J5: Encarregado
A6: Em andamento | B6: Em tratativa | C6: Risco | D6: Não | E6: 46341 | F6: Proclamação da República | G6: Relatório semanal | H6: Pedido emitido | I6: Reforma light LPU | J6: Engenheiro de obras
A7: Concluído | B7: Concluída | C7: Decisão do cliente | E7: 46346 | F7: Consciência Negra | G7: Relatório mensal | H7: Entregue | J7: Analista de obras / COP
A8: Bloqueado | C8: Escopo | E8: 46381 | F8: Natal | G8: Relatório de fase | H8: Cancelado | J8: Compras e Almoxarifado
C9: Conflito | E9: 46388 | F9: Confraternização Universal | G9: Relatório de entrega | J9: Financeiro
C10: Quantitativo | E10: 46426 | F10: Carnaval (ponto facultativo – ajustar) | G10: Comunicação imediata | J10: GO
C11: Comercial | E11: 46427 | F11: Carnaval (ponto facultativo – ajustar) | J11: CEO
C12: Dados | E12: 46472 | F12: Sexta-feira Santa | J12: Segurança do trabalho
E13: 46498 | F13: Tiradentes | J13: Orçamentos
E14: 46500 | F14: São Jorge (estadual RJ)
E26: Conferir feriados municipais de Macaé e recessos do shopping.
